Workbook

Sheet INSTRUÇÕES
A1: CONTROLE FINANCEIRO — ENTRADA, SAÍDA E CARTÃO
A2: Moeda: Guaraní (Gs.) · Ano-base: 2026
B4: AS 3 REGRAS QUE FAZEM A PLANILHA FECHAR
B5: 1) Dinheiro que entra ou sai da sua mão / conta → lança na aba LANÇAMENTOS.
B6: 2) Compra no cartão de crédito → lança SÓ na aba CARTÕES. Não repita em LANÇAMENTOS.
B7: A planilha divide a compra nas parcelas e joga cada parcela no mês certo, sozinha.
B8: 3) Quando você paga a fatura do cartão, NÃO lance nada. A parcela já foi contada no mês dela.
B9: Seguindo essas 3 regras é impossível contar o mesmo gasto duas vezes.
B11: COMO USAR, PASSO A PASSO
B12: 1º Abra a aba LISTAS e escreva o nome dos seus cartões e, se quiser, ajuste as categorias.
B13: 2º Abra a aba LANÇAMENTOS e comece a digitar. Data, Tipo, Status, Categoria, Descrição, Meio, Valor.
B14: 3º Compras parceladas no cartão vão na aba CARTÕES: data, cartão, valor total e nº de parcelas.
B15: 4º Veja o mês na aba RESUMO MENSAL (escolha ano e mês no alto) e o ano na aba RESUMO ANUAL.
B17: REALIZADO x PROJETADO
... B39: O saldo acumulado no RESUMO ANUAL soma o resultado de cada mês, de janeiro em diante.

Sheet LANÇAMENTOS
A1: LANÇAMENTOS
A2: Dinheiro que entra e sai da sua conta ou do seu bolso. Compra no cartão NÃO vem aqui — vai na aba CARTÕES.
A3: Total ENTRADAS | B3: Total SAÍDAS | C3: Saldo (sem cartão) | D3: Lançamentos digitados | E3: Espaço livre para digitar
A4: =SUMIF($B$6:$B$1005,"ENTRADA",$G$6:$G$1005) | B4: =SUMIF($B$6:$B$1005,"SAÍDA",$G$6:$G$1005) | C4: =A4-B4 | D4: =COUNTA($A$6:$A$1005) | E4: =1000-D4
A5: Data | B5: Tipo | C5: Status | D5: Categoria | E5: Descrição | F5: Meio de pagamento | G5: Valor (Gs.) | H5: Mês (auto) | I5: Índice (auto)
H6: =IF($A6="","",MONTH($A6)&"/"&YEAR($A6)) | I6: =IF($A6="",0,YEAR($A6)*12+MONTH($A6))
H7: =IF($A7="","",MONTH($A7)&"/"&YEAR($A7)) | I7: =IF($A7="",0,YEAR($A7)*12+MONTH($A7))
H8: =IF($A8="","",MONTH($A8)&"/"&YEAR($A8)) | I8: =IF($A8="",0,YEAR($A8)*12+MONTH($A8))
H9: =IF($A9="","",MONTH($A9)&"/"&YEAR($A9)) | I9: =IF($A9="",0,YEAR($A9)*12+MONTH($A9))
H10: =IF($A10="","",MONTH($A10)&"/"&YEAR($A10)) | I10: =IF($A10="",0,YEAR($A10)*12+MONTH($A10))
H11: =IF($A11="","",MONTH($A11)&"/"&YEAR($A11)) | I11: =IF($A11="",0,YEAR($A11)*12+MONTH($A11))
H12: =IF($A12="","",MONTH($A12)&"/"&YEAR($A12)) | I12: =IF($A12="",0,YEAR($A12)*12+MONTH($A12))
H13: =IF($A13="","",MONTH($A13)&"/"&YEAR($A13)) | I13: =IF($A13="",0,YEAR($A13)*12+MONTH($A13))
H14: =IF($A14="","",MONTH($A14)&"/"&YEAR($A14)) | I14: =IF($A14="",0,YEAR($A14)*12+MONTH($A14))
H15: =IF($A15="","",MONTH($A15)&"/"&YEAR($A15)) | I15: =IF($A15="",0,YEAR($A15)*12+MONTH($A15))
H16: =IF($A16="","",MONTH($A16)&"/"&YEAR($A16)) | I16: =IF($A16="",0,YEAR($A16)*12+MONTH($A16))
H17: =IF($A17="","",MONTH($A17)&"/"&YEAR($A17)) | I17: =IF($A17="",0,YEAR($A17)*12+MONTH($A17))
... H1005: =IF($A1005="","",MONTH($A1005)&"/"&YEAR($A1005)) | I1005: =IF($A1005="",0,YEAR($A1005)*12+MONTH($A1005))

Sheet CARTÕES
A1: CARTÕES DE CRÉDITO — COMPRAS E PARCELAS
A2: Digite a compra uma vez. A planilha divide nas parcelas e joga cada uma no mês certo. Não lance a fatura em LANÇAMENTOS.
A3: Total comprado | B3: Já pago (até hoje) | C3: Falta pagar (saldo devedor) | D3: Mês de referência de hoje
A4: =SUM($E$6:$E$65) | B4: =SUM($L$6:$L$65) | C4: =SUM($M$6:$M$65) | D4: =MONTH(TODAY())&"/"&YEAR(TODAY())
A5: Data da compra | B5: Cartão | C5: Descrição | D5: Categoria | E5: Valor total (Gs.) | F5: Nº de parcelas | G5: 1ª parcela (opcional) | H5: Início (auto) | I5: Valor da parcela (auto) | J5: Última parcela (auto) | K5: Índice (auto) | L5: Já pago (auto) | M5: Falta pagar (auto)
H6: =IF($A6="","",IF($G6<>"",$G6,DATE(YEAR($A6)+IF(MONTH($A6)=12,1,0),IF(MONTH($A6)=12,1,MONTH($A6)+1),1))) | I6: =IF(OR($E6="",$F6=""),"",ROUND($E6/$F6,0)) | J6: =IF($K6=0,"",($K6+$F6-1-INT(($K6+$F6-2)/12)*12)&"/"&INT(($K6+$F6-2)/12)) | K6: =IF($H6="",0,YEAR($H6)*12+MONTH($H6)) | L6: =IF($K6=0,"",SUMPRODUCT((PARCELAS!$C6:$AL6>0)*(PARCELAS!$C6:$AL6<=YEAR(TODAY())*12+MONTH(TODAY()))*PARCELAS!$AM6:$BV6)) | M6: =IF($K6=0,"",$E6-$L6)
H7: =IF($A7="","",IF($G7<>"",$G7,DATE(YEAR($A7)+IF(MONTH($A7)=12,1,0),IF(MONTH($A7)=12,1,MONTH($A7)+1),1))) | I7: =IF(OR($E7="",$F7=""),"",ROUND($E7/$F7,0)) | J7: =IF($K7=0,"",($K7+$F7-1-INT(($K7+$F7-2)/12)*12)&"/"&INT(($K7+$F7-2)/12)) | K7: =IF($H7="",0,YEAR($H7)*12+MONTH($H7)) | L7: =IF($K7=0,"",SUMPRODUCT((PARCELAS!$C7:$AL7>0)*(PARCELAS!$C7:$AL7<=YEAR(TODAY())*12+MONTH(TODAY()))*PARCELAS!$AM7:$BV7)) | M7: =IF($K7=0,"",$E7-$L7)
H8: =IF($A8="","",IF($G8<>"",$G8,DATE(YEAR($A8)+IF(MONTH($A8)=12,1,0),IF(MONTH($A8)=12,1,MONTH($A8)+1),1))) | I8: =IF(OR($E8="",$F8=""),"",ROUND($E8/$F8,0)) | J8: =IF($K8=0,"",($K8+$F8-1-INT(($K8+$F8-2)/12)*12)&"/"&INT(($K8+$F8-2)/12)) | K8: =IF($H8="",0,YEAR($H8)*12+MONTH($H8)) | L8: =IF($K8=0,"",SUMPRODUCT((PARCELAS!$C8:$AL8>0)*(PARCELAS!$C8:$AL8<=YEAR(TODAY())*12+MONTH(TODAY()))*PARCELAS!$AM8:$BV8)) | M8: =IF($K8=0,"",$E8-$L8)
H9: =IF($A9="","",IF($G9<>"",$G9,DATE(YEAR($A9)+IF(MONTH($A9)=12,1,0),IF(MONTH($A9)=12,1,MONTH($A9)+1),1))) | I9: =IF(OR($E9="",$F9=""),"",ROUND($E9/$F9,0)) | J9: =IF($K9=0,"",($K9+$F9-1-INT(($K9+$F9-2)/12)*12)&"/"&INT(($K9+$F9-2)/12)) | K9: =IF($H9="",0,YEAR($H9)*12+MONTH($H9)) | L9: =IF($K9=0,"",SUMPRODUCT((PARCELAS!$C9:$AL9>0)*(PARCELAS!$C9:$AL9<=YEAR(TODAY())*12+MONTH(TODAY()))*PARCELAS!$AM9:$BV9)) | M9: =IF($K9=0,"",$E9-$L9)
H10: =IF($A10="","",IF($G10<>"",$G10,DATE(YEAR($A10)+IF(MONTH($A10)=12,1,0),IF(MONTH($A10)=12,1,MONTH($A10)+1),1))) | I10: =IF(OR($E10="",$F10=""),"",ROUND($E10/$F10,0)) | J10: =IF($K10=0,"",($K10+$F10-1-INT(($K10+$F10-2)/12)*12)&"/"&INT(($K10+$F10-2)/12)) | K10: =IF($H10="",0,YEAR($H10)*12+MONTH($H10)) | L10: =IF($K10=0,"",SUMPRODUCT((PARCELAS!$C10:$AL10>0)*(PARCELAS!$C10:$AL10<=YEAR(TODAY())*12+MONTH(TODAY()))*PARCELAS!$AM10:$BV10)) | M10: =IF($K10=0,"",$E10-$L10)
H11: =IF($A11="","",IF($G11<>"",$G11,DATE(YEAR($A11)+IF(MONTH($A11)=12,1,0),IF(MONTH($A11)=12,1,MONTH($A11)+1),1))) | I11: =IF(OR($E11="",$F11=""),"",ROUND($E11/$F11,0)) | J11: =IF($K11=0,"",($K11+$F11-1-INT(($K11+$F11-2)/12)*12)&"/"&INT(($K11+$F11-2)/12)) | K11: =IF($H11="",0,YEAR($H11)*12+MONTH($H11)) | L11: =IF($K11=0,"",SUMPRODUCT((PARCELAS!$C11:$AL11>0)*(PARCELAS!$C11:$AL11<=YEAR(TODAY())*12+MONTH(TODAY()))*PARCELAS!$AM11:$BV11)) | M11: =IF($K11=0,"",$E11-$L11)
H12: =IF($A12="","",IF($G12<>"",$G12,DATE(YEAR($A12)+IF(MONTH($A12)=12,1,0),IF(MONTH($A12)=12,1,MONTH($A12)+1),1))) | I12: =IF(OR($E12="",$F12=""),"",ROUND($E12/$F12,0)) | J12: =IF($K12=0,"",($K12+$F12-1-INT(($K12+$F12-2)/12)*12)&"/"&INT(($K12+$F12-2)/12)) | K12: =IF($H12="",0,YEAR($H12)*12+MONTH($H12)) | L12: =IF($K12=0,"",SUMPRODUCT((PARCELAS!$C12:$AL12>0)*(PARCELAS!$C12:$AL12<=YEAR(TODAY())*12+MONTH(TODAY()))*PARCELAS!$AM12:$BV12)) | M12: =IF($K12=0,"",$E12-$L12)
H13: =IF($A13="","",IF($G13<>"",$G13,DATE(YEAR($A13)+IF(MONTH($A13)=12,1,0),IF(MONTH($A13)=12,1,MONTH($A13)+1),1))) | I13: =IF(OR($E13="",$F13=""),"",ROUND($E13/$F13,0)) | J13: =IF($K13=0,"",($K13+$F13-1-INT(($K13+$F13-2)/12)*12)&"/"&INT(($K13+$F13-2)/12)) | K13: =IF($H13="",0,YEAR($H13)*12+MONTH($H13)) | L13: =IF($K13=0,"",SUMPRODUCT((PARCELAS!$C13:$AL13>0)*(PARCELAS!$C13:$AL13<=YEAR(TODAY())*12+MONTH(TODAY()))*PARCELAS!$AM13:$BV13)) | M13: =IF($K13=0,"",$E13-$L13)
H14: =IF($A14="","",IF($G14<>"",$G14,DATE(YEAR($A14)+IF(MONTH($A14)=12,1,0),IF(MONTH($A14)=12,1,MONTH($A14)+1),1))) | I14: =IF(OR($E14="",$F14=""),"",ROUND($E14/$F14,0)) | J14: =IF($K14=0,"",($K14+$F14-1-INT(($K14+$F14-2)/12)*12)&"/"&INT(($K14+$F14-2)/12)) | K14: =IF($H14="",0,YEAR($H14)*12+MONTH($H14)) | L14: =IF($K14=0,"",SUMPRODUCT((PARCELAS!$C14:$AL14>0)*(PARCELAS!$C14:$AL14<=YEAR(TODAY())*12+MONTH(TODAY()))*PARCELAS!$AM14:$BV14)) | M14: =IF($K14=0,"",$E14-$L14)
H15: =IF($A15="","",IF($G15<>"",$G15,DATE(YEAR($A15)+IF(MONTH($A15)=12,1,0),IF(MONTH($A15)=12,1,MONTH($A15)+1),1))) | I15: =IF(OR($E15="",$F15=""),"",ROUND($E15/$F15,0)) | J15: =IF($K15=0,"",($K15+$F15-1-INT(($K15+$F15-2)/12)*12)&"/"&INT(($K15+$F15-2)/12)) | K15: =IF($H15="",0,YEAR($H15)*12+MONTH($H15)) | L15: =IF($K15=0,"",SUMPRODUCT((PARCELAS!$C15:$AL15>0)*(PARCELAS!$C15:$AL15<=YEAR(TODAY())*12+MONTH(TODAY()))*PARCELAS!$AM15:$BV15)) | M15: =IF($K15=0,"",$E15-$L15)
H16: =IF($A16="","",IF($G16<>"",$G16,DATE(YEAR($A16)+IF(MONTH($A16)=12,1,0),IF(MONTH($A16)=12,1,MONTH($A16)+1),1))) | I16: =IF(OR($E16="",$F16=""),"",ROUND($E16/$F16,0)) | J16: =IF($K16=0,"",($K16+$F16-1-INT(($K16+$F16-2)/12)*12)&"/"&INT(($K16+$F16-2)/12)) | K16: =IF($H16="",0,YEAR($H16)*12+MONTH($H16)) | L16: =IF($K16=0,"",SUMPRODUCT((PARCELAS!$C16:$AL16>0)*(PARCELAS!$C16:$AL16<=YEAR(TODAY())*12+MONTH(TODAY()))*PARCELAS!$AM16:$BV16)) | M16: =IF($K16=0,"",$E16-$L16)
H17: =IF($A17="","",IF($G17<>"",$G17,DATE(YEAR($A17)+IF(MONTH($A17)=12,1,0),IF(MONTH($A17)=12,1,MONTH($A17)+1),1))) | I17: =IF(OR($E17="",$F17=""),"",ROUND($E17/$F17,0)) | J17: =IF($K17=0,"",($K17+$F17-1-INT(($K17+$F17-2)/12)*12)&"/"&INT(($K17+$F17-2)/12)) | K17: =IF($H17="",0,YEAR($H17)*12+MONTH($H17)) | L17: =IF($K17=0,"",SUMPRODUCT((PARCELAS!$C17:$AL17>0)*(PARCELAS!$C17:$AL17<=YEAR(TODAY())*12+MONTH(TODAY()))*PARCELAS!$AM17:$BV17)) | M17: =IF($K17=0,"",$E17-$L17)
... H65: =IF($A65="","",IF($G65<>"",$G65,DATE(YEAR($A65)+IF(MONTH($A65)=12,1,0),IF(MONTH($A65)=12,1,MONTH($A65)+1),1))) | I65: =IF(OR($E65="",$F65=""),"",ROUND($E65/$F65,0)) | J65: =IF($K65=0,"",($K65+$F65-1-INT(($K65+$F65-2)/12)*12)&"/"&INT(($K65+$F65-2)/12)) | K65: =IF($H65="",0,YEAR($H65)*12+MONTH($H65)) | L65: =IF($K65=0,"",SUMPRODUCT((PARCELAS!$C65:$AL65>0)*(PARCELAS!$C65:$AL65<=YEAR(TODAY())*12+MONTH(TODAY()))*PARCELAS!$AM65:$BV65)) | M65: =IF($K65=0,"",$E65-$L65)
A68: SALDO POR CARTÃO
A69: Cartão | B69: Total comprado | C69: Já pago | D69: Falta pagar | E69: Parcelas em aberto
A70: =IF(LISTAS!$F6="","",LISTAS!$F6) | B70: =IF($A70="","",SUMIF($B$6:$B$65,$A70,$E$6:$E$65)) | C70: =IF($A70="","",SUMIF($B$6:$B$65,$A70,$L$6:$L$65)) | D70: =IF($A70="","",SUMIF($B$6:$B$65,$A70,$M$6:$M$65)) | E70: =IF($A70="","",SUMPRODUCT((PARCELAS!$C$6:$AL$65>YEAR(TODAY())*12+MONTH(TODAY()))*(PARCELAS!$AM$6:$BV$65>0)*1*(CARTÕES!$B$6:$B$65=$A70)))
A71: =IF(LISTAS!$F7="","",LISTAS!$F7) | B71: =IF($A71="","",SUMIF($B$6:$B$65,$A71,$E$6:$E$65)) | C71: =IF($A71="","",SUMIF($B$6:$B$65,$A71,$L$6:$L$65)) | D71: =IF($A71="","",SUMIF($B$6:$B$65,$A71,$M$6:$M$65)) | E71: =IF($A71="","",SUMPRODUCT((PARCELAS!$C$6:$AL$65>YEAR(TODAY())*12+MONTH(TODAY()))*(PARCELAS!$AM$6:$BV$65>0)*1*(CARTÕES!$B$6:$B$65=$A71)))
A72: =IF(LISTAS!$F8="","",LISTAS!$F8) | B72: =IF($A72="","",SUMIF($B$6:$B$65,$A72,$E$6:$E$65)) | C72: =IF($A72="","",SUMIF($B$6:$B$65,$A72,$L$6:$L$65)) | D72: =IF($A72="","",SUMIF($B$6:$B$65,$A72,$M$6:$M$65)) | E72: =IF($A72="","",SUMPRODUCT((PARCELAS!$C$6:$AL$65>YEAR(TODAY())*12+MONTH(TODAY()))*(PARCELAS!$AM$6:$BV$65>0)*1*(CARTÕES!$B$6:$B$65=$A72)))
A73: =IF(LISTAS!$F9="","",LISTAS!$F9) | B73: =IF($A73="","",SUMIF($B$6:$B$65,$A73,$E$6:$E$65)) | C73: =IF($A73="","",SUMIF($B$6:$B$65,$A73,$L$6:$L$65)) | D73: =IF($A73="","",SUMIF($B$6:$B$65,$A73,$M$6:$M$65)) | E73: =IF($A73="","",SUMPRODUCT((PARCELAS!$C$6:$AL$65>YEAR(TODAY())*12+MONTH(TODAY()))*(PARCELAS!$AM$6:$BV$65>0)*1*(CARTÕES!$B$6:$B$65=$A73)))
A74: =IF(LISTAS!$F10="","",LISTAS!$F10) | B74: =IF($A74="","",SUMIF($B$6:$B$65,$A74,$E$6:$E$65)) | C74: =IF($A74="","",SUMIF($B$6:$B$65,$A74,$L$6:$L$65)) | D74: =IF($A74="","",SUMIF($B$6:$B$65,$A74,$M$6:$M$65)) | E74: =IF($A74="","",SUMPRODUCT((PARCELAS!$C$6:$AL$65>YEAR(TODAY())*12+MONTH(TODAY()))*(PARCELAS!$AM$6:$BV$65>0)*1*(CARTÕES!$B$6:$B$65=$A74)))
A75: =IF(LISTAS!$F11="","",LISTAS!$F11) | B75: =IF($A75="","",SUMIF($B$6:$B$65,$A75,$E$6:$E$65)) | C75: =IF($A75="","",SUMIF($B$6:$B$65,$A75,$L$6:$L$65)) | D75: =IF($A75="","",SUMIF($B$6:$B$65,$A75,$M$6:$M$65)) | E75: =IF($A75="","",SUMPRODUCT((PARCELAS!$C$6:$AL$65>YEAR(TODAY())*12+MONTH(TODAY()))*(PARCELAS!$AM$6:$BV$65>0)*1*(CARTÕES!$B$6:$B$65=$A75)))
A76: =IF(LISTAS!$F12="","",LISTAS!$F12) | B76: =IF($A76="","",SUMIF($B$6:$B$65,$A76,$E$6:$E$65)) | C76: =IF($A76="","",SUMIF($B$6:$B$65,$A76,$L$6:$L$65)) | D76: =IF($A76="","",SUMIF($B$6:$B$65,$A76,$M$6:$M$65)) | E76: =IF($A76="","",SUMPRODUCT((PARCELAS!$C$6:$AL$65>YEAR(TODAY())*12+MONTH(TODAY()))*(PARCELAS!$AM$6:$BV$65>0)*1*(CARTÕES!$B$6:$B$65=$A76)))
A77: =IF(LISTAS!$F13="","",LISTAS!$F13) | B77: =IF($A77="","",SUMIF($B$6:$B$65,$A77,$E$6:$E$65)) | C77: =IF($A77="","",SUMIF($B$6:$B$65,$A77,$L$6:$L$65)) | D77: =IF($A77="","",SUMIF($B$6:$B$65,$A77,$M$6:$M$65)) | E77: =IF($A77="","",SUMPRODUCT((PARCELAS!$C$6:$AL$65>YEAR(TODAY())*12+MONTH(TODAY()))*(PARCELAS!$AM$6:$BV$65>0)*1*(CARTÕES!$B$6:$B$65=$A77)))
A78: TOTAL | B78: =SUM(B70:B77) | C78: =SUM(C70:C77) | D78: =SUM(D70:D77) | E78: =SUM(E70:E77)

Sheet RESUMO MENSAL
A1: RESUMO MENSAL
A2: Escolha o ano e o mês nas células amarelas. Tudo abaixo se recalcula sozinho.
A3: Ano | B3: Mês | C3: Índice (auto)
A4: 2026 | B4: 1 | C4: =$A$4*12+$B$4 | D4: =INDEX(LISTAS!$K$6:$K$17,$B$4)&" de "&$A$4
A6: Entradas REALIZADAS | C6: Entradas PROJETADAS | E6: Saídas REALIZADAS | G6: Saídas PROJETADAS
A7: =SUMIFS('LANÇAMENTOS'!$G$6:$G$1005,'LANÇAMENTOS'!$I$6:$I$1005,$C$4,'LANÇAMENTOS'!$B$6:$B$1005,"ENTRADA",'LANÇAMENTOS'!$C$6:$C$1005,"REALIZADO") | C7: =SUMIFS('LANÇAMENTOS'!$G$6:$G$1005,'LANÇAMENTOS'!$I$6:$I$1005,$C$4,'LANÇAMENTOS'!$B$6:$B$1005,"ENTRADA",'LANÇAMENTOS'!$C$6:$C$1005,"PROJETADO") | E7: =SUMIFS('LANÇAMENTOS'!$G$6:$G$1005,'LANÇAMENTOS'!$I$6:$I$1005,$C$4,'LANÇAMENTOS'!$B$6:$B$1005,"SAÍDA",'LANÇAMENTOS'!$C$6:$C$1005,"REALIZADO") | G7: =SUMIFS('LANÇAMENTOS'!$G$6:$G$1005,'LANÇAMENTOS'!$I$6:$I$1005,$C$4,'LANÇAMENTOS'!$B$6:$B$1005,"SAÍDA",'LANÇAMENTOS'!$C$6:$C$1005,"PROJETADO")
A9: Entradas do mês (realizado + projetado) | B9: =SUMIFS('LANÇAMENTOS'!$G$6:$G$1005,'LANÇAMENTOS'!$I$6:$I$1005,$C$4,'LANÇAMENTOS'!$B$6:$B$1005,"ENTRADA")
A10: Saídas do mês (realizado + projetado) | B10: =SUMIFS('LANÇAMENTOS'!$G$6:$G$1005,'LANÇAMENTOS'!$I$6:$I$1005,$C$4,'LANÇAMENTOS'!$B$6:$B$1005,"SAÍDA")
A11: Parcelas de cartão que vencem no mês | B11: =SUMPRODUCT((PARCELAS!$C$6:$AL$65=$C$4)*PARCELAS!$AM$6:$BV$65)
A12: RESULTADO DO MÊS | B12: =$B$9-$B$10-$B$11
A14: ENTRADAS POR CATEGORIA | F14: SAÍDAS POR CATEGORIA
A15: Categoria | B15: Realizado | C15: Projetado | D15: Total | F15: Categoria | G15: Realizado | H15: Projetado | I15: Total
A16: =IF(LISTAS!$B6="ENTRADA",LISTAS!$A6,"") | B16: =IF($A16="","",SUMIFS('LANÇAMENTOS'!$G$6:$G$1005,'LANÇAMENTOS'!$I$6:$I$1005,$C$4,'LANÇAMENTOS'!$B$6:$B$1005,"ENTRADA",'LANÇAMENTOS'!$C$6:$C$1005,"REALIZADO",'LANÇAMENTOS'!$D$6:$D$1005,$A16)) | C16: =IF($A16="","",SUMIFS('LANÇAMENTOS'!$G$6:$G$1005,'LANÇAMENTOS'!$I$6:$I$1005,$C$4,'LANÇAMENTOS'!$B$6:$B$1005,"ENTRADA",'LANÇAMENTOS'!$C$6:$C$1005,"PROJETADO",'LANÇAMENTOS'!$D$6:$D$1005,$A16)) | D16: =IF($A16="","",SUMIFS('LANÇAMENTOS'!$G$6:$G$1005,'LANÇAMENTOS'!$I$6:$I$1005,$C$4,'LANÇAMENTOS'!$B$6:$B$1005,"ENTRADA",'LANÇAMENTOS'!$D$6:$D$1005,$A16)) | F16: =IF(LISTAS!$B6="SAÍDA",LISTAS!$A6,"") | G16: =IF($F16="","",SUMIFS('LANÇAMENTOS'!$G$6:$G$1005,'LANÇAMENTOS'!$I$6:$I$1005,$C$4,'LANÇAMENTOS'!$B$6:$B$1005,"SAÍDA",'LANÇAMENTOS'!$C$6:$C$1005,"REALIZADO",'LANÇAMENTOS'!$D$6:$D$1005,$F16)) | H16: =IF($F16="","",SUMIFS('LANÇAMENTOS'!$G$6:$G$1005,'LANÇAMENTOS'!$I$6:$I$1005,$C$4,'LANÇAMENTOS'!$B$6:$B$1005,"SAÍDA",'LANÇAMENTOS'!$C$6:$C$1005,"PROJETADO",'LANÇAMENTOS'!$D$6:$D$1005,$F16)) | I16: =IF($F16="","",SUMIFS('LANÇAMENTOS'!$G$6:$G$1005,'LANÇAMENTOS'!$I$6:$I$1005,$C$4,'LANÇAMENTOS'!$B$6:$B$1005,"SAÍDA",'LANÇAMENTOS'!$D$6:$D$1005,$F16))
A17: =IF(LISTAS!$B7="ENTRADA",LISTAS!$A7,"") | B17: =IF($A17="","",SUMIFS('LANÇAMENTOS'!$G$6:$G$1005,'LANÇAMENTOS'!$I$6:$I$1005,$C$4,'LANÇAMENTOS'!$B$6:$B$1005,"ENTRADA",'LANÇAMENTOS'!$C$6:$C$1005,"REALIZADO",'LANÇAMENTOS'!$D$6:$D$1005,$A17)) | C17: =IF($A17="","",SUMIFS('LANÇAMENTOS'!$G$6:$G$1005,'LANÇAMENTOS'!$I$6:$I$1005,$C$4,'LANÇAMENTOS'!$B$6:$B$1005,"ENTRADA",'LANÇAMENTOS'!$C$6:$C$1005,"PROJETADO",'LANÇAMENTOS'!$D$6:$D$1005,$A17)) | D17: =IF($A17="","",SUMIFS('LANÇAMENTOS'!$G$6:$G$1005,'LANÇAMENTOS'!$I$6:$I$1005,$C$4,'LANÇAMENTOS'!$B$6:$B$1005,"ENTRADA",'LANÇAMENTOS'!$D$6:$D$1005,$A17)) | F17: =IF(LISTAS!$B7="SAÍDA",LISTAS!$A7,"") | G17: =IF($F17="","",SUMIFS('LANÇAMENTOS'!$G$6:$G$1005,'LANÇAMENTOS'!$I$6:$I$1005,$C$4,'LANÇAMENTOS'!$B$6:$B$1005,"SAÍDA",'LANÇAMENTOS'!$C$6:$C$1005,"REALIZADO",'LANÇAMENTOS'!$D$6:$D$1005,$F17)) | H17: =IF($F17="","",SUMIFS('LANÇAMENTOS'!$G$6:$G$1005,'LANÇAMENTOS'!$I$6:$I$1005,$C$4,'LANÇAMENTOS'!$B$6:$B$1005,"SAÍDA",'LANÇAMENTOS'!$C$6:$C$1005,"PROJETADO",'LANÇAMENTOS'!$D$6:$D$1005,$F17)) | I17: =IF($F17="","",SUMIFS('LANÇAMENTOS'!$G$6:$G$1005,'LANÇAMENTOS'!$I$6:$I$1005,$C$4,'LANÇAMENTOS'!$B$6:$B$1005,"SAÍDA",'LANÇAMENTOS'!$D$6:$D$1005,$F17))
A18: =IF(LISTAS!$B8="ENTRADA",LISTAS!$A8,"") | B18: =IF($A18="","",SUMIFS('LANÇAMENTOS'!$G$6:$G$1005,'LANÇAMENTOS'!$I$6:$I$1005,$C$4,'LANÇAMENTOS'!$B$6:$B$1005,"ENTRADA",'LANÇAMENTOS'!$C$6:$C$1005,"REALIZADO",'LANÇAMENTOS'!$D$6:$D$1005,$A18)) | C18: =IF($A18="","",SUMIFS('LANÇAMENTOS'!$G$6:$G$1005,'LANÇAMENTOS'!$I$6:$I$1005,$C$4,'LANÇAMENTOS'!$B$6:$B$1005,"ENTRADA",'LANÇAMENTOS'!$C$6:$C$1005,"PROJETADO",'LANÇAMENTOS'!$D$6:$D$1005,$A18)) | D18: =IF($A18="","",SUMIFS('LANÇAMENTOS'!$G$6:$G$1005,'LANÇAMENTOS'!$I$6:$I$1005,$C$4,'LANÇAMENTOS'!$B$6:$B$1005,"ENTRADA",'LANÇAMENTOS'!$D$6:$D$1005,$A18)) | F18: =IF(LISTAS!$B8="SAÍDA",LISTAS!$A8,"") | G18: =IF($F18="","",SUMIFS('LANÇAMENTOS'!$G$6:$G$1005,'LANÇAMENTOS'!$I$6:$I$1005,$C$4,'LANÇAMENTOS'!$B$6:$B$1005,"SAÍDA",'LANÇAMENTOS'!$C$6:$C$1005,"REALIZADO",'LANÇAMENTOS'!$D$6:$D$1005,$F18)) | H18: =IF($F18="","",SUMIFS('LANÇAMENTOS'!$G$6:$G$1005,'LANÇAMENTOS'!$I$6:$I$1005,$C$4,'LANÇAMENTOS'!$B$6:$B$1005,"SAÍDA",'LANÇAMENTOS'!$C$6:$C$1005,"PROJETADO",'LANÇAMENTOS'!$D$6:$D$1005,$F18)) | I18: =IF($F18="","",SUMIFS('LANÇAMENTOS'!$G$6:$G$1005,'LANÇAMENTOS'!$I$6:$I$1005,$C$4,'LANÇAMENTOS'!$B$6:$B$1005,"SAÍDA",'LANÇAMENTOS'!$D$6:$D$1005,$F18))
A19: =IF(LISTAS!$B9="ENTRADA",LISTAS!$A9,"") | B19: =IF($A19="","",SUMIFS('LANÇAMENTOS'!$G$6:$G$1005,'LANÇAMENTOS'!$I$6:$I$1005,$C$4,'LANÇAMENTOS'!$B$6:$B$1005,"ENTRADA",'LANÇAMENTOS'!$C$6:$C$1005,"REALIZADO",'LANÇAMENTOS'!$D$6:$D$1005,$A19)) | C19: =IF($A19="","",SUMIFS('LANÇAMENTOS'!$G$6:$G$1005,'LANÇAMENTOS'!$I$6:$I$1005,$C$4,'LANÇAMENTOS'!$B$6:$B$1005,"ENTRADA",'LANÇAMENTOS'!$C$6:$C$1005,"PROJETADO",'LANÇAMENTOS'!$D$6:$D$1005,$A19)) | D19: =IF($A19="","",SUMIFS('LANÇAMENTOS'!$G$6:$G$1005,'LANÇAMENTOS'!$I$6:$I$1005,$C$4,'LANÇAMENTOS'!$B$6:$B$1005,"ENTRADA",'LANÇAMENTOS'!$D$6:$D$1005,$A19)) | F19: =IF(LISTAS!$B9="SAÍDA",LISTAS!$A9,"") | G19: =IF($F19="","",SUMIFS('LANÇAMENTOS'!$G$6:$G$1005,'LANÇAMENTOS'!$I$6:$I$1005,$C$4,'LANÇAMENTOS'!$B$6:$B$1005,"SAÍDA",'LANÇAMENTOS'!$C$6:$C$1005,"REALIZADO",'LANÇAMENTOS'!$D$6:$D$1005,$F19)) | H19: =IF($F19="","",SUMIFS('LANÇAMENTOS'!$G$6:$G$1005,'LANÇAMENTOS'!$I$6:$I$1005,$C$4,'LANÇAMENTOS'!$B$6:$B$1005,"SAÍDA",'LANÇAMENTOS'!$C$6:$C$1005,"PROJETADO",'LANÇAMENTOS'!$D$6:$D$1005,$F19)) | I19: =IF($F19="","",SUMIFS('LANÇAMENTOS'!$G$6:$G$1005,'LANÇAMENTOS'!$I$6:$I$1005,$C$4,'LANÇAMENTOS'!$B$6:$B$1005,"SAÍDA",'LANÇAMENTOS'!$D$6:$D$1005,$F19))
A20: =IF(LISTAS!$B10="ENTRADA",LISTAS!$A10,"") | B20: =IF($A20="","",SUMIFS('LANÇAMENTOS'!$G$6:$G$1005,'LANÇAMENTOS'!$I$6:$I$1005,$C$4,'LANÇAMENTOS'!$B$6:$B$1005,"ENTRADA",'LANÇAMENTOS'!$C$6:$C$1005,"REALIZADO",'LANÇAMENTOS'!$D$6:$D$1005,$A20)) | C20: =IF($A20="","",SUMIFS('LANÇAMENTOS'!$G$6:$G$1005,'LANÇAMENTOS'!$I$6:$I$1005,$C$4,'LANÇAMENTOS'!$B$6:$B$1005,"ENTRADA",'LANÇAMENTOS'!$C$6:$C$1005,"PROJETADO",'LANÇAMENTOS'!$D$6:$D$1005,$A20)) | D20: =IF($A20="","",SUMIFS('LANÇAMENTOS'!$G$6:$G$1005,'LANÇAMENTOS'!$I$6:$I$1005,$C$4,'LANÇAMENTOS'!$B$6:$B$1005,"ENTRADA",'LANÇAMENTOS'!$D$6:$D$1005,$A20)) | F20: =IF(LISTAS!$B10="SAÍDA",LISTAS!$A10,"") | G20: =IF($F20="","",SUMIFS('LANÇAMENTOS'!$G$6:$G$1005,'LANÇAMENTOS'!$I$6:$I$1005,$C$4,'LANÇAMENTOS'!$B$6:$B$1005,"SAÍDA",'LANÇAMENTOS'!$C$6:$C$1005,"REALIZADO",'LANÇAMENTOS'!$D$6:$D$1005,$F20)) | H20: =IF($F20="","",SUMIFS('LANÇAMENTOS'!$G$6:$G$1005,'LANÇAMENTOS'!$I$6:$I$1005,$C$4,'LANÇAMENTOS'!$B$6:$B$1005,"SAÍDA",'LANÇAMENTOS'!$C$6:$C$1005,"PROJETADO",'LANÇAMENTOS'!$D$6:$D$1005,$F20)) | I20: =IF($F20="","",SUMIFS('LANÇAMENTOS'!$G$6:$G$1005,'LANÇAMENTOS'!$I$6:$I$1005,$C$4,'LANÇAMENTOS'!$B$6:$B$1005,"SAÍDA",'LANÇAMENTOS'!$D$6:$D$1005,$F20))
A21: =IF(LISTAS!$B11="ENTRADA",LISTAS!$A11,"") | B21: =IF($A21="","",SUMIFS('LANÇAMENTOS'!$G$6:$G$1005,'LANÇAMENTOS'!$I$6:$I$1005,$C$4,'LANÇAMENTOS'!$B$6:$B$1005,"ENTRADA",'LANÇAMENTOS'!$C$6:$C$1005,"REALIZADO",'LANÇAMENTOS'!$D$6:$D$1005,$A21)) | C21: =IF($A21="","",SUMIFS('LANÇAMENTOS'!$G$6:$G$1005,'LANÇAMENTOS'!$I$6:$I$1005,$C$4,'LANÇAMENTOS'!$B$6:$B$1005,"ENTRADA",'LANÇAMENTOS'!$C$6:$C$1005,"PROJETADO",'LANÇAMENTOS'!$D$6:$D$1005,$A21)) | D21: =IF($A21="","",SUMIFS('LANÇAMENTOS'!$G$6:$G$1005,'LANÇAMENTOS'!$I$6:$I$1005,$C$4,'LANÇAMENTOS'!$B$6:$B$1005,"ENTRADA",'LANÇAMENTOS'!$D$6:$D$1005,$A21)) | F21: =IF(LISTAS!$B11="SAÍDA",LISTAS!$A11,"") | G21: =IF($F21="","",SUMIFS('LANÇAMENTOS'!$G$6:$G$1005,'LANÇAMENTOS'!$I$6:$I$1005,$C$4,'LANÇAMENTOS'!$B$6:$B$1005,"SAÍDA",'LANÇAMENTOS'!$C$6:$C$1005,"REALIZADO",'LANÇAMENTOS'!$D$6:$D$1005,$F21)) | H21: =IF($F21="","",SUMIFS('LANÇAMENTOS'!$G$6:$G$1005,'LANÇAMENTOS'!$I$6:$I$1005,$C$4,'LANÇAMENTOS'!$B$6:$B$1005,"SAÍDA",'LANÇAMENTOS'!$C$6:$C$1005,"PROJETADO",'LANÇAMENTOS'!$D$6:$D$1005,$F21)) | I21: =IF($F21="","",SUMIFS('LANÇAMENTOS'!$G$6:$G$1005,'LANÇAMENTOS'!$I$6:$I$1005,$C$4,'LANÇAMENTOS'!$B$6:$B$1005,"SAÍDA",'LANÇAMENTOS'!$D$6:$D$1005,$F21))
A22: =IF(LISTAS!$B12="ENTRADA",LISTAS!$A12,"") | B22: =IF($A22="","",SUMIFS('LANÇAMENTOS'!$G$6:$G$1005,'LANÇAMENTOS'!$I$6:$I$1005,$C$4,'LANÇAMENTOS'!$B$6:$B$1005,"ENTRADA",'LANÇAMENTOS'!$C$6:$C$1005,"REALIZADO",'LANÇAMENTOS'!$D$6:$D$1005,$A22)) | C22: =IF($A22="","",SUMIFS('LANÇAMENTOS'!$G$6:$G$1005,'LANÇAMENTOS'!$I$6:$I$1005,$C$4,'LANÇAMENTOS'!$B$6:$B$1005,"ENTRADA",'LANÇAMENTOS'!$C$6:$C$1005,"PROJETADO",'LANÇAMENTOS'!$D$6:$D$1005,$A22)) | D22: =IF($A22="","",SUMIFS('LANÇAMENTOS'!$G$6:$G$1005,'LANÇAMENTOS'!$I$6:$I$1005,$C$4,'LANÇAMENTOS'!$B$6:$B$1005,"ENTRADA",'LANÇAMENTOS'!$D$6:$D$1005,$A22)) | F22: =IF(LISTAS!$B12="SAÍDA",LISTAS!$A12,"") | G22: =IF($F22="","",SUMIFS('LANÇAMENTOS'!$G$6:$G$1005,'LANÇAMENTOS'!$I$6:$I$1005,$C$4,'LANÇAMENTOS'!$B$6:$B$1005,"SAÍDA",'LANÇAMENTOS'!$C$6:$C$1005,"REALIZADO",'LANÇAMENTOS'!$D$6:$D$1005,$F22)) | H22: =IF($F22="","",SUMIFS('LANÇAMENTOS'!$G$6:$G$1005,'LANÇAMENTOS'!$I$6:$I$1005,$C$4,'LANÇAMENTOS'!$B$6:$B$1005,"SAÍDA",'LANÇAMENTOS'!$C$6:$C$1005,"PROJETADO",'LANÇAMENTOS'!$D$6:$D$1005,$F22)) | I22: =IF($F22="","",SUMIFS('LANÇAMENTOS'!$G$6:$G$1005,'LANÇAMENTOS'!$I$6:$I$1005,$C$4,'LANÇAMENTOS'!$B$6:$B$1005,"SAÍDA",'LANÇAMENTOS'!$D$6:$D$1005,$F22))
A23: =IF(LISTAS!$B13="ENTRADA",LISTAS!$A13,"") | B23: =IF($A23="","",SUMIFS('LANÇAMENTOS'!$G$6:$G$1005,'LANÇAMENTOS'!$I$6:$I$1005,$C$4,'LANÇAMENTOS'!$B$6:$B$1005,"ENTRADA",'LANÇAMENTOS'!$C$6:$C$1005,"REALIZADO",'LANÇAMENTOS'!$D$6:$D$1005,$A23)) | C23: =IF($A23="","",SUMIFS('LANÇAMENTOS'!$G$6:$G$1005,'LANÇAMENTOS'!$I$6:$I$1005,$C$4,'LANÇAMENTOS'!$B$6:$B$1005,"ENTRADA",'LANÇAMENTOS'!$C$6:$C$1005,"PROJETADO",'LANÇAMENTOS'!$D$6:$D$1005,$A23)) | D23: =IF($A23="","",SUMIFS('LANÇAMENTOS'!$G$6:$G$1005,'LANÇAMENTOS'!$I$6:$I$1005,$C$4,'LANÇAMENTOS'!$B$6:$B$1005,"ENTRADA",'LANÇAMENTOS'!$D$6:$D$1005,$A23)) | F23: =IF(LISTAS!$B13="SAÍDA",LISTAS!$A13,"") | G23: =IF($F23="","",SUMIFS('LANÇAMENTOS'!$G$6:$G$1005,'LANÇAMENTOS'!$I$6:$I$1005,$C$4,'LANÇAMENTOS'!$B$6:$B$1005,"SAÍDA",'LANÇAMENTOS'!$C$6:$C$1005,"REALIZADO",'LANÇAMENTOS'!$D$6:$D$1005,$F23)) | H23: =IF($F23="","",SUMIFS('LANÇAMENTOS'!$G$6:$G$1005,'LANÇAMENTOS'!$I$6:$I$1005,$C$4,'LANÇAMENTOS'!$B$6:$B$1005,"SAÍDA",'LANÇAMENTOS'!$C$6:$C$1005,"PROJETADO",'LANÇAMENTOS'!$D$6:$D$1005,$F23)) | I23: =IF($F23="","",SUMIFS('LANÇAMENTOS'!$G$6:$G$1005,'LANÇAMENTOS'!$I$6:$I$1005,$C$4,'LANÇAMENTOS'!$B$6:$B$1005,"SAÍDA",'LANÇAMENTOS'!$D$6:$D$1005,$F23))
A24: =IF(LISTAS!$B14="ENTRADA",LISTAS!$A14,"") | B24: =IF($A24="","",SUMIFS('LANÇAMENTOS'!$G$6:$G$1005,'LANÇAMENTOS'!$I$6:$I$1005,$C$4,'LANÇAMENTOS'!$B$6:$B$1005,"ENTRADA",'LANÇAMENTOS'!$C$6:$C$1005,"REALIZADO",'LANÇAMENTOS'!$D$6:$D$1005,$A24)) | C24: =IF($A24="","",SUMIFS('LANÇAMENTOS'!$G$6:$G$1005,'LANÇAMENTOS'!$I$6:$I$1005,$C$4,'LANÇAMENTOS'!$B$6:$B$1005,"ENTRADA",'LANÇAMENTOS'!$C$6:$C$1005,"PROJETADO",'LANÇAMENTOS'!$D$6:$D$1005,$A24)) | D24: =IF($A24="","",SUMIFS('LANÇAMENTOS'!$G$6:$G$1005,'LANÇAMENTOS'!$I$6:$I$1005,$C$4,'LANÇAMENTOS'!$B$6:$B$1005,"ENTRADA",'LANÇAMENTOS'!$D$6:$D$1005,$A24)) | F24: =IF(LISTAS!$B14="SAÍDA",LISTAS!$A14,"") | G24: =IF($F24="","",SUMIFS('LANÇAMENTOS'!$G$6:$G$1005,'LANÇAMENTOS'!$I$6:$I$1005,$C$4,'LANÇAMENTOS'!$B$6:$B$1005,"SAÍDA",'LANÇAMENTOS'!$C$6:$C$1005,"REALIZADO",'LANÇAMENTOS'!$D$6:$D$1005,$F24)) | H24: =IF($F24="","",SUMIFS('LANÇAMENTOS'!$G$6:$G$1005,'LANÇAMENTOS'!$I$6:$I$1005,$C$4,'LANÇAMENTOS'!$B$6:$B$1005,"SAÍDA",'LANÇAMENTOS'!$C$6:$C$1005,"PROJETADO",'LANÇAMENTOS'!$D$6:$D$1005,$F24)) | I24: =IF($F24="","",SUMIFS('LANÇAMENTOS'!$G$6:$G$1005,'LANÇAMENTOS'!$I$6:$I$1005,$C$4,'LANÇAMENTOS'!$B$6:$B$1005,"SAÍDA",'LANÇAMENTOS'!$D$6:$D$1005,$F24))
A25: =IF(LISTAS!$B15="ENTRADA",LISTAS!$A15,"") | B25: =IF($A25="","",SUMIFS('LANÇAMENTOS'!$G$6:$G$1005,'LANÇAMENTOS'!$I$6:$I$1005,$C$4,'LANÇAMENTOS'!$B$6:$B$1005,"ENTRADA",'LANÇAMENTOS'!$C$6:$C$1005,"REALIZADO",'LANÇAMENTOS'!$D$6:$D$1005,$A25)) | C25: =IF($A25="","",SUMIFS('LANÇAMENTOS'!$G$6:$G$1005,'LANÇAMENTOS'!$I$6:$I$1005,$C$4,'LANÇAMENTOS'!$B$6:$B$1005,"ENTRADA",'LANÇAMENTOS'!$C$6:$C$1005,"PROJETADO",'LANÇAMENTOS'!$D$6:$D$1005,$A25)) | D25: =IF($A25="","",SUMIFS('LANÇAMENTOS'!$G$6:$G$1005,'LANÇAMENTOS'!$I$6:$I$1005,$C$4,'LANÇAMENTOS'!$B$6:$B$1005,"ENTRADA",'LANÇAMENTOS'!$D$6:$D$1005,$A25)) | F25: =IF(LISTAS!$B15="SAÍDA",LISTAS!$A15,"") | G25: =IF($F25="","",SUMIFS('LANÇAMENTOS'!$G$6:$G$1005,'LANÇAMENTOS'!$I$6:$I$1005,$C$4,'LANÇAMENTOS'!$B$6:$B$1005,"SAÍDA",'LANÇAMENTOS'!$C$6:$C$1005,"REALIZADO",'LANÇAMENTOS'!$D$6:$D$1005,$F25)) | H25: =IF($F25="","",SUMIFS('LANÇAMENTOS'!$G$6:$G$1005,'LANÇAMENTOS'!$I$6:$I$1005,$C$4,'LANÇAMENTOS'!$B$6:$B$1005,"SAÍDA",'LANÇAMENTOS'!$C$6:$C$1005,"PROJETADO",'LANÇAMENTOS'!$D$6:$D$1005,$F25)) | I25: =IF($F25="","",SUMIFS('LANÇAMENTOS'!$G$6:$G$1005,'LANÇAMENTOS'!$I$6:$I$1005,$C$4,'LANÇAMENTOS'!$B$6:$B$1005,"SAÍDA",'LANÇAMENTOS'!$D$6:$D$1005,$F25))
A26: =IF(LISTAS!$B16="ENTRADA",LISTAS!$A16,"") | B26: =IF($A26="","",SUMIFS('LANÇAMENTOS'!$G$6:$G$1005,'LANÇAMENTOS'!$I$6:$I$1005,$C$4,'LANÇAMENTOS'!$B$6:$B$1005,"ENTRADA",'LANÇAMENTOS'!$C$6:$C$1005,"REALIZADO",'LANÇAMENTOS'!$D$6:$D$1005,$A26)) | C26: =IF($A26="","",SUMIFS('LANÇAMENTOS'!$G$6:$G$1005,'LANÇAMENTOS'!$I$6:$I$1005,$C$4,'LANÇAMENTOS'!$B$6:$B$1005,"ENTRADA",'LANÇAMENTOS'!$C$6:$C$1005,"PROJETADO",'LANÇAMENTOS'!$D$6:$D$1005,$A26)) | D26: =IF($A26="","",SUMIFS('LANÇAMENTOS'!$G$6:$G$1005,'LANÇAMENTOS'!$I$6:$I$1005,$C$4,'LANÇAMENTOS'!$B$6:$B$1005,"ENTRADA",'LANÇAMENTOS'!$D$6:$D$1005,$A26)) | F26: =IF(LISTAS!$B16="SAÍDA",LISTAS!$A16,"") | G26: =IF($F26="","",SUMIFS('LANÇAMENTOS'!$G$6:$G$1005,'LANÇAMENTOS'!$I$6:$I$1005,$C$4,'LANÇAMENTOS'!$B$6:$B$1005,"SAÍDA",'LANÇAMENTOS'!$C$6:$C$1005,"REALIZADO",'LANÇAMENTOS'!$D$6:$D$1005,$F26)) | H26: =IF($F26="","",SUMIFS('LANÇAMENTOS'!$G$6:$G$1005,'LANÇAMENTOS'!$I$6:$I$1005,$C$4,'LANÇAMENTOS'!$B$6:$B$1005,"SAÍDA",'LANÇAMENTOS'!$C$6:$C$1005,"PROJETADO",'LANÇAMENTOS'!$D$6:$D$1005,$F26)) | I26: =IF($F26="","",SUMIFS('LANÇAMENTOS'!$G$6:$G$1005,'LANÇAMENTOS'!$I$6:$I$1005,$C$4,'LANÇAMENTOS'!$B$6:$B$1005,"SAÍDA",'LANÇAMENTOS'!$D$6:$D$1005,$F26))
A27: =IF(LISTAS!$B17="ENTRADA",LISTAS!$A17,"") | B27: =IF($A27="","",SUMIFS('LANÇAMENTOS'!$G$6:$G$1005,'LANÇAMENTOS'!$I$6:$I$1005,$C$4,'LANÇAMENTOS'!$B$6:$B$1005,"ENTRADA",'LANÇAMENTOS'!$C$6:$C$1005,"REALIZADO",'LANÇAMENTOS'!$D$6:$D$1005,$A27)) | C27: =IF($A27="","",SUMIFS('LANÇAMENTOS'!$G$6:$G$1005,'LANÇAMENTOS'!$I$6:$I$1005,$C$4,'LANÇAMENTOS'!$B$6:$B$1005,"ENTRADA",'LANÇAMENTOS'!$C$6:$C$1005,"PROJETADO",'LANÇAMENTOS'!$D$6:$D$1005,$A27)) | D27: =IF($A27="","",SUMIFS('LANÇAMENTOS'!$G$6:$G$1005,'LANÇAMENTOS'!$I$6:$I$1005,$C$4,'LANÇAMENTOS'!$B$6:$B$1005,"ENTRADA",'LANÇAMENTOS'!$D$6:$D$1005,$A27)) | F27: =IF(LISTAS!$B17="SAÍDA",LISTAS!$A17,"") | G27: =IF($F27="","",SUMIFS('LANÇAMENTOS'!$G$6:$G$1005,'LANÇAMENTOS'!$I$6:$I$1005,$C$4,'LANÇAMENTOS'!$B$6:$B$1005,"SAÍDA",'LANÇAMENTOS'!$C$6:$C$1005,"REALIZADO",'LANÇAMENTOS'!$D$6:$D$1005,$F27)) | H27: =IF($F27="","",SUMIFS('LANÇAMENTOS'!$G$6:$G$1005,'LANÇAMENTOS'!$I$6:$I$1005,$C$4,'LANÇAMENTOS'!$B$6:$B$1005,"SAÍDA",'LANÇAMENTOS'!$C$6:$C$1005,"PROJETADO",'LANÇAMENTOS'!$D$6:$D$1005,$F27)) | I27: =IF($F27="","",SUMIFS('LANÇAMENTOS'!$G$6:$G$1005,'LANÇAMENTOS'!$I$6:$I$1005,$C$4,'LANÇAMENTOS'!$B$6:$B$1005,"SAÍDA",'LANÇAMENTOS'!$D$6:$D$1005,$F27))
... A55: =IF(LISTAS!$B45="ENTRADA",LISTAS!$A45,"") | B55: =IF($A55="","",SUMIFS('LANÇAMENTOS'!$G$6:$G$1005,'LANÇAMENTOS'!$I$6:$I$1005,$C$4,'LANÇAMENTOS'!$B$6:$B$1005,"ENTRADA",'LANÇAMENTOS'!$C$6:$C$1005,"REALIZADO",'LANÇAMENTOS'!$D$6:$D$1005,$A55)) | C55: =IF($A55="","",SUMIFS('LANÇAMENTOS'!$G$6:$G$1005,'LANÇAMENTOS'!$I$6:$I$1005,$C$4,'LANÇAMENTOS'!$B$6:$B$1005,"ENTRADA",'LANÇAMENTOS'!$C$6:$C$1005,"PROJETADO",'LANÇAMENTOS'!$D$6:$D$1005,$A55)) | D55: =IF($A55="","",SUMIFS('LANÇAMENTOS'!$G$6:$G$1005,'LANÇAMENTOS'!$I$6:$I$1005,$C$4,'LANÇAMENTOS'!$B$6:$B$1005,"ENTRADA",'LANÇAMENTOS'!$D$6:$D$1005,$A55)) | F55: =IF(LISTAS!$B45="SAÍDA",LISTAS!$A45,"") | G55: =IF($F55="","",SUMIFS('LANÇAMENTOS'!$G$6:$G$1005,'LANÇAMENTOS'!$I$6:$I$1005,$C$4,'LANÇAMENTOS'!$B$6:$B$1005,"SAÍDA",'LANÇAMENTOS'!$C$6:$C$1005,"REALIZADO",'LANÇAMENTOS'!$D$6:$D$1005,$F55)) | H55: =IF($F55="","",SUMIFS('LANÇAMENTOS'!$G$6:$G$1005,'LANÇAMENTOS'!$I$6:$I$1005,$C$4,'LANÇAMENTOS'!$B$6:$B$1005,"SAÍDA",'LANÇAMENTOS'!$C$6:$C$1005,"PROJETADO",'LANÇAMENTOS'!$D$6:$D$1005,$F55)) | I55: =IF($F55="","",SUMIFS('LANÇAMENTOS'!$G$6:$G$1005,'LANÇAMENTOS'!$I$6:$I$1005,$C$4,'LANÇAMENTOS'!$B$6:$B$1005,"SAÍDA",'LANÇAMENTOS'!$D$6:$D$1005,$F55))
A56: TOTAL | B56: =SUM(B16:B55) | C56: =SUM(C16:C55) | D56: =SUM(D16:D55) | F56: TOTAL | G56: =SUM(G16:G55) | H56: =SUM(H16:H55) | I56: =SUM(I16:I55)
A58: CONFERÊNCIA
A59: Entradas: KPI menos soma das categorias | D59: =$B$9-$D$56
A60: Saídas: KPI menos soma das categorias | D60: =$B$10-$I$56
A61: Lançamentos sem tipo ou sem status | D61: =SUMPRODUCT(('LANÇAMENTOS'!$A$6:$A$1005<>"")*(('LANÇAMENTOS'!$B$6:$B$1005="")+('LANÇAMENTOS'!$C$6:$C$1005="")>0))
A62: Compras de cartão sem nº de parcelas | D62: =SUMPRODUCT((CARTÕES!$A$6:$A$65<>"")*(CARTÕES!$F$6:$F$65=""))
A63: Parcelas: soma das parcelas menos total comprado | D63: =SUMPRODUCT((PARCELAS!$C$6:$AL$65>0)*PARCELAS!$AM$6:$BV$65)-SUM(CARTÕES!$E$6:$E$65)
A64: Tudo em zero = a planilha está fechando. Qualquer número diferente de zero fica vermelho.

Sheet RESUMO ANUAL
A1: RESUMO ANUAL
A2: Os 12 meses do ano lado a lado. Troque o ano na célula amarela.
A3: Ano
A4: 2026
A5: Mês | B5: Entradas realizadas | C5: Entradas projetadas | D5: Entradas total | E5: Saídas realizadas | F5: Saídas projetadas | G5: Saídas total | H5: Cartão (parcelas) | I5: Resultado do mês | J5: Saldo acumulado
A6: =INDEX(LISTAS!$K$6:$K$17,1) | B6: =SUMIFS('LANÇAMENTOS'!$G$6:$G$1005,'LANÇAMENTOS'!$I$6:$I$1005,($A$4*12+1),'LANÇAMENTOS'!$B$6:$B$1005,"ENTRADA",'LANÇAMENTOS'!$C$6:$C$1005,"REALIZADO") | C6: =SUMIFS('LANÇAMENTOS'!$G$6:$G$1005,'LANÇAMENTOS'!$I$6:$I$1005,($A$4*12+1),'LANÇAMENTOS'!$B$6:$B$1005,"ENTRADA",'LANÇAMENTOS'!$C$6:$C$1005,"PROJETADO") | D6: =B6+C6 | E6: =SUMIFS('LANÇAMENTOS'!$G$6:$G$1005,'LANÇAMENTOS'!$I$6:$I$1005,($A$4*12+1),'LANÇAMENTOS'!$B$6:$B$1005,"SAÍDA",'LANÇAMENTOS'!$C$6:$C$1005,"REALIZADO") | F6: =SUMIFS('LANÇAMENTOS'!$G$6:$G$1005,'LANÇAMENTOS'!$I$6:$I$1005,($A$4*12+1),'LANÇAMENTOS'!$B$6:$B$1005,"SAÍDA",'LANÇAMENTOS'!$C$6:$C$1005,"PROJETADO") | G6: =E6+F6 | H6: =SUMPRODUCT((PARCELAS!$C$6:$AL$65=($A$4*12+1))*PARCELAS!$AM$6:$BV$65) | I6: =D6-G6-H6 | J6: =I6
A7: =INDEX(LISTAS!$K$6:$K$17,2) | B7: =SUMIFS('LANÇAMENTOS'!$G$6:$G$1005,'LANÇAMENTOS'!$I$6:$I$1005,($A$4*12+2),'LANÇAMENTOS'!$B$6:$B$1005,"ENTRADA",'LANÇAMENTOS'!$C$6:$C$1005,"REALIZADO") | C7: =SUMIFS('LANÇAMENTOS'!$G$6:$G$1005,'LANÇAMENTOS'!$I$6:$I$1005,($A$4*12+2),'LANÇAMENTOS'!$B$6:$B$1005,"ENTRADA",'LANÇAMENTOS'!$C$6:$C$1005,"PROJETADO") | D7: =B7+C7 | E7: =SUMIFS('LANÇAMENTOS'!$G$6:$G$1005,'LANÇAMENTOS'!$I$6:$I$1005,($A$4*12+2),'LANÇAMENTOS'!$B$6:$B$1005,"SAÍDA",'LANÇAMENTOS'!$C$6:$C$1005,"REALIZADO") | F7: =SUMIFS('LANÇAMENTOS'!$G$6:$G$1005,'LANÇAMENTOS'!$I$6:$I$1005,($A$4*12+2),'LANÇAMENTOS'!$B$6:$B$1005,"SAÍDA",'LANÇAMENTOS'!$C$6:$C$1005,"PROJETADO") | G7: =E7+F7 | H7: =SUMPRODUCT((PARCELAS!$C$6:$AL$65=($A$4*12+2))*PARCELAS!$AM$6:$BV$65) | I7: =D7-G7-H7 | J7: =J6+I7
A8: =INDEX(LISTAS!$K$6:$K$17,3) | B8: =SUMIFS('LANÇAMENTOS'!$G$6:$G$1005,'LANÇAMENTOS'!$I$6:$I$1005,($A$4*12+3),'LANÇAMENTOS'!$B$6:$B$1005,"ENTRADA",'LANÇAMENTOS'!$C$6:$C$1005,"REALIZADO") | C8: =SUMIFS('LANÇAMENTOS'!$G$6:$G$1005,'LANÇAMENTOS'!$I$6:$I$1005,($A$4*12+3),'LANÇAMENTOS'!$B$6:$B$1005,"ENTRADA",'LANÇAMENTOS'!$C$6:$C$1005,"PROJETADO") | D8: =B8+C8 | E8: =SUMIFS('LANÇAMENTOS'!$G$6:$G$1005,'LANÇAMENTOS'!$I$6:$I$1005,($A$4*12+3),'LANÇAMENTOS'!$B$6:$B$1005,"SAÍDA",'LANÇAMENTOS'!$C$6:$C$1005,"REALIZADO") | F8: =SUMIFS('LANÇAMENTOS'!$G$6:$G$1005,'LANÇAMENTOS'!$I$6:$I$1005,($A$4*12+3),'LANÇAMENTOS'!$B$6:$B$1005,"SAÍDA",'LANÇAMENTOS'!$C$6:$C$1005,"PROJETADO") | G8: =E8+F8 | H8: =SUMPRODUCT((PARCELAS!$C$6:$AL$65=($A$4*12+3))*PARCELAS!$AM$6:$BV$65) | I8: =D8-G8-H8 | J8: =J7+I8
A9: =INDEX(LISTAS!$K$6:$K$17,4) | B9: =SUMIFS('LANÇAMENTOS'!$G$6:$G$1005,'LANÇAMENTOS'!$I$6:$I$1005,($A$4*12+4),'LANÇAMENTOS'!$B$6:$B$1005,"ENTRADA",'LANÇAMENTOS'!$C$6:$C$1005,"REALIZADO") | C9: =SUMIFS('LANÇAMENTOS'!$G$6:$G$1005,'LANÇAMENTOS'!$I$6:$I$1005,($A$4*12+4),'LANÇAMENTOS'!$B$6:$B$1005,"ENTRADA",'LANÇAMENTOS'!$C$6:$C$1005,"PROJETADO") | D9: =B9+C9 | E9: =SUMIFS('LANÇAMENTOS'!$G$6:$G$1005,'LANÇAMENTOS'!$I$6:$I$1005,($A$4*12+4),'LANÇAMENTOS'!$B$6:$B$1005,"SAÍDA",'LANÇAMENTOS'!$C$6:$C$1005,"REALIZADO") | F9: =SUMIFS('LANÇAMENTOS'!$G$6:$G$1005,'LANÇAMENTOS'!$I$6:$I$1005,($A$4*12+4),'LANÇAMENTOS'!$B$6:$B$1005,"SAÍDA",'LANÇAMENTOS'!$C$6:$C$1005,"PROJETADO") | G9: =E9+F9 | H9: =SUMPRODUCT((PARCELAS!$C$6:$AL$65=($A$4*12+4))*PARCELAS!$AM$6:$BV$65) | I9: =D9-G9-H9 | J9: =J8+I9
A10: =INDEX(LISTAS!$K$6:$K$17,5) | B10: =SUMIFS('LANÇAMENTOS'!$G$6:$G$1005,'LANÇAMENTOS'!$I$6:$I$1005,($A$4*12+5),'LANÇAMENTOS'!$B$6:$B$1005,"ENTRADA",'LANÇAMENTOS'!$C$6:$C$1005,"REALIZADO") | C10: =SUMIFS('LANÇAMENTOS'!$G$6:$G$1005,'LANÇAMENTOS'!$I$6:$I$1005,($A$4*12+5),'LANÇAMENTOS'!$B$6:$B$1005,"ENTRADA",'LANÇAMENTOS'!$C$6:$C$1005,"PROJETADO") | D10: =B10+C10 | E10: =SUMIFS('LANÇAMENTOS'!$G$6:$G$1005,'LANÇAMENTOS'!$I$6:$I$1005,($A$4*12+5),'LANÇAMENTOS'!$B$6:$B$1005,"SAÍDA",'LANÇAMENTOS'!$C$6:$C$1005,"REALIZADO") | F10: =SUMIFS('LANÇAMENTOS'!$G$6:$G$1005,'LANÇAMENTOS'!$I$6:$I$1005,($A$4*12+5),'LANÇAMENTOS'!$B$6:$B$1005,"SAÍDA",'LANÇAMENTOS'!$C$6:$C$1005,"PROJETADO") | G10: =E10+F10 | H10: =SUMPRODUCT((PARCELAS!$C$6:$AL$65=($A$4*12+5))*PARCELAS!$AM$6:$BV$65) | I10: =D10-G10-H10 | J10: =J9+I10
A11: =INDEX(LISTAS!$K$6:$K$17,6) | B11: =SUMIFS('LANÇAMENTOS'!$G$6:$G$1005,'LANÇAMENTOS'!$I$6:$I$1005,($A$4*12+6),'LANÇAMENTOS'!$B$6:$B$1005,"ENTRADA",'LANÇAMENTOS'!$C$6:$C$1005,"REALIZADO") | C11: =SUMIFS('LANÇAMENTOS'!$G$6:$G$1005,'LANÇAMENTOS'!$I$6:$I$1005,($A$4*12+6),'LANÇAMENTOS'!$B$6:$B$1005,"ENTRADA",'LANÇAMENTOS'!$C$6:$C$1005,"PROJETADO") | D11: =B11+C11 | E11: =SUMIFS('LANÇAMENTOS'!$G$6:$G$1005,'LANÇAMENTOS'!$I$6:$I$1005,($A$4*12+6),'LANÇAMENTOS'!$B$6:$B$1005,"SAÍDA",'LANÇAMENTOS'!$C$6:$C$1005,"REALIZADO") | F11: =SUMIFS('LANÇAMENTOS'!$G$6:$G$1005,'LANÇAMENTOS'!$I$6:$I$1005,($A$4*12+6),'LANÇAMENTOS'!$B$6:$B$1005,"SAÍDA",'LANÇAMENTOS'!$C$6:$C$1005,"PROJETADO") | G11: =E11+F11 | H11: =SUMPRODUCT((PARCELAS!$C$6:$AL$65=($A$4*12+6))*PARCELAS!$AM$6:$BV$65) | I11: =D11-G11-H11 | J11: =J10+I11
A12: =INDEX(LISTAS!$K$6:$K$17,7) | B12: =SUMIFS('LANÇAMENTOS'!$G$6:$G$1005,'LANÇAMENTOS'!$I$6:$I$1005,($A$4*12+7),'LANÇAMENTOS'!$B$6:$B$1005,"ENTRADA",'LANÇAMENTOS'!$C$6:$C$1005,"REALIZADO") | C12: =SUMIFS('LANÇAMENTOS'!$G$6:$G$1005,'LANÇAMENTOS'!$I$6:$I$1005,($A$4*12+7),'LANÇAMENTOS'!$B$6:$B$1005,"ENTRADA",'LANÇAMENTOS'!$C$6:$C$1005,"PROJETADO") | D12: =B12+C12 | E12: =SUMIFS('LANÇAMENTOS'!$G$6:$G$1005,'LANÇAMENTOS'!$I$6:$I$1005,($A$4*12+7),'LANÇAMENTOS'!$B$6:$B$1005,"SAÍDA",'LANÇAMENTOS'!$C$6:$C$1005,"REALIZADO") | F12: =SUMIFS('LANÇAMENTOS'!$G$6:$G$1005,'LANÇAMENTOS'!$I$6:$I$1005,($A$4*12+7),'LANÇAMENTOS'!$B$6:$B$1005,"SAÍDA",'LANÇAMENTOS'!$C$6:$C$1005,"PROJETADO") | G12: =E12+F12 | H12: =SUMPRODUCT((PARCELAS!$C$6:$AL$65=($A$4*12+7))*PARCELAS!$AM$6:$BV$65) | I12: =D12-G12-H12 | J12: =J11+I12
A13: =INDEX(LISTAS!$K$6:$K$17,8) | B13: =SUMIFS('LANÇAMENTOS'!$G$6:$G$1005,'LANÇAMENTOS'!$I$6:$I$1005,($A$4*12+8),'LANÇAMENTOS'!$B$6:$B$1005,"ENTRADA",'LANÇAMENTOS'!$C$6:$C$1005,"REALIZADO") | C13: =SUMIFS('LANÇAMENTOS'!$G$6:$G$1005,'LANÇAMENTOS'!$I$6:$I$1005,($A$4*12+8),'LANÇAMENTOS'!$B$6:$B$1005,"ENTRADA",'LANÇAMENTOS'!$C$6:$C$1005,"PROJETADO") | D13: =B13+C13 | E13: =SUMIFS('LANÇAMENTOS'!$G$6:$G$1005,'LANÇAMENTOS'!$I$6:$I$1005,($A$4*12+8),'LANÇAMENTOS'!$B$6:$B$1005,"SAÍDA",'LANÇAMENTOS'!$C$6:$C$1005,"REALIZADO") | F13: =SUMIFS('LANÇAMENTOS'!$G$6:$G$1005,'LANÇAMENTOS'!$I$6:$I$1005,($A$4*12+8),'LANÇAMENTOS'!$B$6:$B$1005,"SAÍDA",'LANÇAMENTOS'!$C$6:$C$1005,"PROJETADO") | G13: =E13+F13 | H13: =SUMPRODUCT((PARCELAS!$C$6:$AL$65=($A$4*12+8))*PARCELAS!$AM$6:$BV$65) | I13: =D13-G13-H13 | J13: =J12+I13
A14: =INDEX(LISTAS!$K$6:$K$17,9) | B14: =SUMIFS('LANÇAMENTOS'!$G$6:$G$1005,'LANÇAMENTOS'!$I$6:$I$1005,($A$4*12+9),'LANÇAMENTOS'!$B$6:$B$1005,"ENTRADA",'LANÇAMENTOS'!$C$6:$C$1005,"REALIZADO") | C14: =SUMIFS('LANÇAMENTOS'!$G$6:$G$1005,'LANÇAMENTOS'!$I$6:$I$1005,($A$4*12+9),'LANÇAMENTOS'!$B$6:$B$1005,"ENTRADA",'LANÇAMENTOS'!$C$6:$C$1005,"PROJETADO") | D14: =B14+C14 | E14: =SUMIFS('LANÇAMENTOS'!$G$6:$G$1005,'LANÇAMENTOS'!$I$6:$I$1005,($A$4*12+9),'LANÇAMENTOS'!$B$6:$B$1005,"SAÍDA",'LANÇAMENTOS'!$C$6:$C$1005,"REALIZADO") | F14: =SUMIFS('LANÇAMENTOS'!$G$6:$G$1005,'LANÇAMENTOS'!$I$6:$I$1005,($A$4*12+9),'LANÇAMENTOS'!$B$6:$B$1005,"SAÍDA",'LANÇAMENTOS'!$C$6:$C$1005,"PROJETADO") | G14: =E14+F14 | H14: =SUMPRODUCT((PARCELAS!$C$6:$AL$65=($A$4*12+9))*PARCELAS!$AM$6:$BV$65) | I14: =D14-G14-H14 | J14: =J13+I14
A15: =INDEX(LISTAS!$K$6:$K$17,10) | B15: =SUMIFS('LANÇAMENTOS'!$G$6:$G$1005,'LANÇAMENTOS'!$I$6:$I$1005,($A$4*12+10),'LANÇAMENTOS'!$B$6:$B$1005,"ENTRADA",'LANÇAMENTOS'!$C$6:$C$1005,"REALIZADO") | C15: =SUMIFS('LANÇAMENTOS'!$G$6:$G$1005,'LANÇAMENTOS'!$I$6:$I$1005,($A$4*12+10),'LANÇAMENTOS'!$B$6:$B$1005,"ENTRADA",'LANÇAMENTOS'!$C$6:$C$1005,"PROJETADO") | D15: =B15+C15 | E15: =SUMIFS('LANÇAMENTOS'!$G$6:$G$1005,'LANÇAMENTOS'!$I$6:$I$1005,($A$4*12+10),'LANÇAMENTOS'!$B$6:$B$1005,"SAÍDA",'LANÇAMENTOS'!$C$6:$C$1005,"REALIZADO") | F15: =SUMIFS('LANÇAMENTOS'!$G$6:$G$1005,'LANÇAMENTOS'!$I$6:$I$1005,($A$4*12+10),'LANÇAMENTOS'!$B$6:$B$1005,"SAÍDA",'LANÇAMENTOS'!$C$6:$C$1005,"PROJETADO") | G15: =E15+F15 | H15: =SUMPRODUCT((PARCELAS!$C$6:$AL$65=($A$4*12+10))*PARCELAS!$AM$6:$BV$65) | I15: =D15-G15-H15 | J15: =J14+I15
A16: =INDEX(LISTAS!$K$6:$K$17,11) | B16: =SUMIFS('LANÇAMENTOS'!$G$6:$G$1005,'LANÇAMENTOS'!$I$6:$I$1005,($A$4*12+11),'LANÇAMENTOS'!$B$6:$B$1005,"ENTRADA",'LANÇAMENTOS'!$C$6:$C$1005,"REALIZADO") | C16: =SUMIFS('LANÇAMENTOS'!$G$6:$G$1005,'LANÇAMENTOS'!$I$6:$I$1005,($A$4*12+11),'LANÇAMENTOS'!$B$6:$B$1005,"ENTRADA",'LANÇAMENTOS'!$C$6:$C$1005,"PROJETADO") | D16: =B16+C16 | E16: =SUMIFS('LANÇAMENTOS'!$G$6:$G$1005,'LANÇAMENTOS'!$I$6:$I$1005,($A$4*12+11),'LANÇAMENTOS'!$B$6:$B$1005,"SAÍDA",'LANÇAMENTOS'!$C$6:$C$1005,"REALIZADO") | F16: =SUMIFS('LANÇAMENTOS'!$G$6:$G$1005,'LANÇAMENTOS'!$I$6:$I$1005,($A$4*12+11),'LANÇAMENTOS'!$B$6:$B$1005,"SAÍDA",'LANÇAMENTOS'!$C$6:$C$1005,"PROJETADO") | G16: =E16+F16 | H16: =SUMPRODUCT((PARCELAS!$C$6:$AL$65=($A$4*12+11))*PARCELAS!$AM$6:$BV$65) | I16: =D16-G16-H16 | J16: =J15+I16
A17: =INDEX(LISTAS!$K$6:$K$17,12) | B17: =SUMIFS('LANÇAMENTOS'!$G$6:$G$1005,'LANÇAMENTOS'!$I$6:$I$1005,($A$4*12+12),'LANÇAMENTOS'!$B$6:$B$1005,"ENTRADA",'LANÇAMENTOS'!$C$6:$C$1005,"REALIZADO") | C17: =SUMIFS('LANÇAMENTOS'!$G$6:$G$1005,'LANÇAMENTOS'!$I$6:$I$1005,($A$4*12+12),'LANÇAMENTOS'!$B$6:$B$1005,"ENTRADA",'LANÇAMENTOS'!$C$6:$C$1005,"PROJETADO") | D17: =B17+C17 | E17: =SUMIFS('LANÇAMENTOS'!$G$6:$G$1005,'LANÇAMENTOS'!$I$6:$I$1005,($A$4*12+12),'LANÇAMENTOS'!$B$6:$B$1005,"SAÍDA",'LANÇAMENTOS'!$C$6:$C$1005,"REALIZADO") | F17: =SUMIFS('LANÇAMENTOS'!$G$6:$G$1005,'LANÇAMENTOS'!$I$6:$I$1005,($A$4*12+12),'LANÇAMENTOS'!$B$6:$B$1005,"SAÍDA",'LANÇAMENTOS'!$C$6:$C$1005,"PROJETADO") | G17: =E17+F17 | H17: =SUMPRODUCT((PARCELAS!$C$6:$AL$65=($A$4*12+12))*PARCELAS!$AM$6:$BV$65) | I17: =D17-G17-H17 | J17: =J16+I17
A18: TOTAL DO ANO | B18: =SUM(B6:B17) | C18: =SUM(C6:C17) | D18: =SUM(D6:D17) | E18: =SUM(E6:E17) | F18: =SUM(F6:F17) | G18: =SUM(G6:G17) | H18: =SUM(H6:H17) | I18: =SUM(I6:I17) | J18: =J17
A21: SAÍDAS POR CATEGORIA, MÊS A MÊS
A22: Categoria | B22: Jan | C22: Fev | D22: Mar | E22: Abr | F22: Mai | G22: Jun | H22: Jul | I22: Ago | J22: Set | K22: Out | L22: Nov | M22: Dez | N22: Total do ano
A23: =IF(LISTAS!$B6="SAÍDA",LISTAS!$A6,"") | B23: =IF($A23="","",SUMIFS('LANÇAMENTOS'!$G$6:$G$1005,'LANÇAMENTOS'!$I$6:$I$1005,($A$4*12+1),'LANÇAMENTOS'!$B$6:$B$1005,"SAÍDA",'LANÇAMENTOS'!$D$6:$D$1005,$A23)) | C23: =IF($A23="","",SUMIFS('LANÇAMENTOS'!$G$6:$G$1005,'LANÇAMENTOS'!$I$6:$I$1005,($A$4*12+2),'LANÇAMENTOS'!$B$6:$B$1005,"SAÍDA",'LANÇAMENTOS'!$D$6:$D$1005,$A23)) | D23: =IF($A23="","",SUMIFS('LANÇAMENTOS'!$G$6:$G$1005,'LANÇAMENTOS'!$I$6:$I$1005,($A$4*12+3),'LANÇAMENTOS'!$B$6:$B$1005,"SAÍDA",'LANÇAMENTOS'!$D$6:$D$1005,$A23)) | E23: =IF($A23="","",SUMIFS('LANÇAMENTOS'!$G$6:$G$1005,'LANÇAMENTOS'!$I$6:$I$1005,($A$4*12+4),'LANÇAMENTOS'!$B$6:$B$1005,"SAÍDA",'LANÇAMENTOS'!$D$6:$D$1005,$A23)) | F23: =IF($A23="","",SUMIFS('LANÇAMENTOS'!$G$6:$G$1005,'LANÇAMENTOS'!$I$6:$I$1005,($A$4*12+5),'LANÇAMENTOS'!$B$6:$B$1005,"SAÍDA",'LANÇAMENTOS'!$D$6:$D$1005,$A23)) | G23: =IF($A23="","",SUMIFS('LANÇAMENTOS'!$G$6:$G$1005,'LANÇAMENTOS'!$I$6:$I$1005,($A$4*12+6),'LANÇAMENTOS'!$B$6:$B$1005,"SAÍDA",'LANÇAMENTOS'!$D$6:$D$1005,$A23)) | H23: =IF($A23="","",SUMIFS('LANÇAMENTOS'!$G$6:$G$1005,'LANÇAMENTOS'!$I$6:$I$1005,($A$4*12+7),'LANÇAMENTOS'!$B$6:$B$1005,"SAÍDA",'LANÇAMENTOS'!$D$6:$D$1005,$A23)) | I23: =IF($A23="","",SUMIFS('LANÇAMENTOS'!$G$6:$G$1005,'LANÇAMENTOS'!$I$6:$I$1005,($A$4*12+8),'LANÇAMENTOS'!$B$6:$B$1005,"SAÍDA",'LANÇAMENTOS'!$D$6:$D$1005,$A23)) | J23: =IF($A23="","",SUMIFS('LANÇAMENTOS'!$G$6:$G$1005,'LANÇAMENTOS'!$I$6:$I$1005,($A$4*12+9),'LANÇAMENTOS'!$B$6:$B$1005,"SAÍDA",'LANÇAMENTOS'!$D$6:$D$1005,$A23)) | K23: =IF($A23="","",SUMIFS('LANÇAMENTOS'!$G$6:$G$1005,'LANÇAMENTOS'!$I$6:$I$1005,($A$4*12+10),'LANÇAMENTOS'!$B$6:$B$1005,"SAÍDA",'LANÇAMENTOS'!$D$6:$D$1005,$A23)) | L23: =IF($A23="","",SUMIFS('LANÇAMENTOS'!$G$6:$G$1005,'LANÇAMENTOS'!$I$6:$I$1005,($A$4*12+11),'LANÇAMENTOS'!$B$6:$B$1005,"SAÍDA",'LANÇAMENTOS'!$D$6:$D$1005,$A23)) | M23: =IF($A23="","",SUMIFS('LANÇAMENTOS'!$G$6:$G$1005,'LANÇAMENTOS'!$I$6:$I$1005,($A$4*12+12),'LANÇAMENTOS'!$B$6:$B$1005,"SAÍDA",'LANÇAMENTOS'!$D$6:$D$1005,$A23)) | N23: =IF($A23="","",SUM(B23:M23))
A24: =IF(LISTAS!$B7="SAÍDA",LISTAS!$A7,"") | B24: =IF($A24="","",SUMIFS('LANÇAMENTOS'!$G$6:$G$1005,'LANÇAMENTOS'!$I$6:$I$1005,($A$4*12+1),'LANÇAMENTOS'!$B$6:$B$1005,"SAÍDA",'LANÇAMENTOS'!$D$6:$D$1005,$A24)) | C24: =IF($A24="","",SUMIFS('LANÇAMENTOS'!$G$6:$G$1005,'LANÇAMENTOS'!$I$6:$I$1005,($A$4*12+2),'LANÇAMENTOS'!$B$6:$B$1005,"SAÍDA",'LANÇAMENTOS'!$D$6:$D$1005,$A24)) | D24: =IF($A24="","",SUMIFS('LANÇAMENTOS'!$G$6:$G$1005,'LANÇAMENTOS'!$I$6:$I$1005,($A$4*12+3),'LANÇAMENTOS'!$B$6:$B$1005,"SAÍDA",'LANÇAMENTOS'!$D$6:$D$1005,$A24)) | E24: =IF($A24="","",SUMIFS('LANÇAMENTOS'!$G$6:$G$1005,'LANÇAMENTOS'!$I$6:$I$1005,($A$4*12+4),'LANÇAMENTOS'!$B$6:$B$1005,"SAÍDA",'LANÇAMENTOS'!$D$6:$D$1005,$A24)) | F24: =IF($A24="","",SUMIFS('LANÇAMENTOS'!$G$6:$G$1005,'LANÇAMENTOS'!$I$6:$I$1005,($A$4*12+5),'LANÇAMENTOS'!$B$6:$B$1005,"SAÍDA",'LANÇAMENTOS'!$D$6:$D$1005,$A24)) | G24: =IF($A24="","",SUMIFS('LANÇAMENTOS'!$G$6:$G$1005,'LANÇAMENTOS'!$I$6:$I$1005,($A$4*12+6),'LANÇAMENTOS'!$B$6:$B$1005,"SAÍDA",'LANÇAMENTOS'!$D$6:$D$1005,$A24)) | H24: =IF($A24="","",SUMIFS('LANÇAMENTOS'!$G$6:$G$1005,'LANÇAMENTOS'!$I$6:$I$1005,($A$4*12+7),'LANÇAMENTOS'!$B$6:$B$1005,"SAÍDA",'LANÇAMENTOS'!$D$6:$D$1005,$A24)) | I24: =IF($A24="","",SUMIFS('LANÇAMENTOS'!$G$6:$G$1005,'LANÇAMENTOS'!$I$6:$I$1005,($A$4*12+8),'LANÇAMENTOS'!$B$6:$B$1005,"SAÍDA",'LANÇAMENTOS'!$D$6:$D$1005,$A24)) | J24: =IF($A24="","",SUMIFS('LANÇAMENTOS'!$G$6:$G$1005,'LANÇAMENTOS'!$I$6:$I$1005,($A$4*12+9),'LANÇAMENTOS'!$B$6:$B$1005,"SAÍDA",'LANÇAMENTOS'!$D$6:$D$1005,$A24)) | K24: =IF($A24="","",SUMIFS('LANÇAMENTOS'!$G$6:$G$1005,'LANÇAMENTOS'!$I$6:$I$1005,($A$4*12+10),'LANÇAMENTOS'!$B$6:$B$1005,"SAÍDA",'LANÇAMENTOS'!$D$6:$D$1005,$A24)) | L24: =IF($A24="","",SUMIFS('LANÇAMENTOS'!$G$6:$G$1005,'LANÇAMENTOS'!$I$6:$I$1005,($A$4*12+11),'LANÇAMENTOS'!$B$6:$B$1005,"SAÍDA",'LANÇAMENTOS'!$D$6:$D$1005,$A24)) | M24: =IF($A24="","",SUMIFS('LANÇAMENTOS'!$G$6:$G$1005,'LANÇAMENTOS'!$I$6:$I$1005,($A$4*12+12),'LANÇAMENTOS'!$B$6:$B$1005,"SAÍDA",'LANÇAMENTOS'!$D$6:$D$1005,$A24)) | N24: =IF($A24="","",SUM(B24:M24))
A25: =IF(LISTAS!$B8="SAÍDA",LISTAS!$A8,"") | B25: =IF($A25="","",SUMIFS('LANÇAMENTOS'!$G$6:$G$1005,'LANÇAMENTOS'!$I$6:$I$1005,($A$4*12+1),'LANÇAMENTOS'!$B$6:$B$1005,"SAÍDA",'LANÇAMENTOS'!$D$6:$D$1005,$A25)) | C25: =IF($A25="","",SUMIFS('LANÇAMENTOS'!$G$6:$G$1005,'LANÇAMENTOS'!$I$6:$I$1005,($A$4*12+2),'LANÇAMENTOS'!$B$6:$B$1005,"SAÍDA",'LANÇAMENTOS'!$D$6:$D$1005,$A25)) | D25: =IF($A25="","",SUMIFS('LANÇAMENTOS'!$G$6:$G$1005,'LANÇAMENTOS'!$I$6:$I$1005,($A$4*12+3),'LANÇAMENTOS'!$B$6:$B$1005,"SAÍDA",'LANÇAMENTOS'!$D$6:$D$1005,$A25)) | E25: =IF($A25="","",SUMIFS('LANÇAMENTOS'!$G$6:$G$1005,'LANÇAMENTOS'!$I$6:$I$1005,($A$4*12+4),'LANÇAMENTOS'!$B$6:$B$1005,"SAÍDA",'LANÇAMENTOS'!$D$6:$D$1005,$A25)) | F25: =IF($A25="","",SUMIFS('LANÇAMENTOS'!$G$6:$G$1005,'LANÇAMENTOS'!$I$6:$I$1005,($A$4*12+5),'LANÇAMENTOS'!$B$6:$B$1005,"SAÍDA",'LANÇAMENTOS'!$D$6:$D$1005,$A25)) | G25: =IF($A25="","",SUMIFS('LANÇAMENTOS'!$G$6:$G$1005,'LANÇAMENTOS'!$I$6:$I$1005,($A$4*12+6),'LANÇAMENTOS'!$B$6:$B$1005,"SAÍDA",'LANÇAMENTOS'!$D$6:$D$1005,$A25)) | H25: =IF($A25="","",SUMIFS('LANÇAMENTOS'!$G$6:$G$1005,'LANÇAMENTOS'!$I$6:$I$1005,($A$4*12+7),'LANÇAMENTOS'!$B$6:$B$1005,"SAÍDA",'LANÇAMENTOS'!$D$6:$D$1005,$A25)) | I25: =IF($A25="","",SUMIFS('LANÇAMENTOS'!$G$6:$G$1005,'LANÇAMENTOS'!$I$6:$I$1005,($A$4*12+8),'LANÇAMENTOS'!$B$6:$B$1005,"SAÍDA",'LANÇAMENTOS'!$D$6:$D$1005,$A25)) | J25: =IF($A25="","",SUMIFS('LANÇAMENTOS'!$G$6:$G$1005,'LANÇAMENTOS'!$I$6:$I$1005,($A$4*12+9),'LANÇAMENTOS'!$B$6:$B$1005,"SAÍDA",'LANÇAMENTOS'!$D$6:$D$1005,$A25)) | K25: =IF($A25="","",SUMIFS('LANÇAMENTOS'!$G$6:$G$1005,'LANÇAMENTOS'!$I$6:$I$1005,($A$4*12+10),'LANÇAMENTOS'!$B$6:$B$1005,"SAÍDA",'LANÇAMENTOS'!$D$6:$D$1005,$A25)) | L25: =IF($A25="","",SUMIFS('LANÇAMENTOS'!$G$6:$G$1005,'LANÇAMENTOS'!$I$6:$I$1005,($A$4*12+11),'LANÇAMENTOS'!$B$6:$B$1005,"SAÍDA",'LANÇAMENTOS'!$D$6:$D$1005,$A25)) | M25: =IF($A25="","",SUMIFS('LANÇAMENTOS'!$G$6:$G$1005,'LANÇAMENTOS'!$I$6:$I$1005,($A$4*12+12),'LANÇAMENTOS'!$B$6:$B$1005,"SAÍDA",'LANÇAMENTOS'!$D$6:$D$1005,$A25)) | N25: =IF($A25="","",SUM(B25:M25))
A26: =IF(LISTAS!$B9="SAÍDA",LISTAS!$A9,"") | B26: =IF($A26="","",SUMIFS('LANÇAMENTOS'!$G$6:$G$1005,'LANÇAMENTOS'!$I$6:$I$1005,($A$4*12+1),'LANÇAMENTOS'!$B$6:$B$1005,"SAÍDA",'LANÇAMENTOS'!$D$6:$D$1005,$A26)) | C26: =IF($A26="","",SUMIFS('LANÇAMENTOS'!$G$6:$G$1005,'LANÇAMENTOS'!$I$6:$I$1005,($A$4*12+2),'LANÇAMENTOS'!$B$6:$B$1005,"SAÍDA",'LANÇAMENTOS'!$D$6:$D$1005,$A26)) | D26: =IF($A26="","",SUMIFS('LANÇAMENTOS'!$G$6:$G$1005,'LANÇAMENTOS'!$I$6:$I$1005,($A$4*12+3),'LANÇAMENTOS'!$B$6:$B$1005,"SAÍDA",'LANÇAMENTOS'!$D$6:$D$1005,$A26)) | E26: =IF($A26="","",SUMIFS('LANÇAMENTOS'!$G$6:$G$1005,'LANÇAMENTOS'!$I$6:$I$1005,($A$4*12+4),'LANÇAMENTOS'!$B$6:$B$1005,"SAÍDA",'LANÇAMENTOS'!$D$6:$D$1005,$A26)) | F26: =IF($A26="","",SUMIFS('LANÇAMENTOS'!$G$6:$G$1005,'LANÇAMENTOS'!$I$6:$I$1005,($A$4*12+5),'LANÇAMENTOS'!$B$6:$B$1005,"SAÍDA",'LANÇAMENTOS'!$D$6:$D$1005,$A26)) | G26: =IF($A26="","",SUMIFS('LANÇAMENTOS'!$G$6:$G$1005,'LANÇAMENTOS'!$I$6:$I$1005,($A$4*12+6),'LANÇAMENTOS'!$B$6:$B$1005,"SAÍDA",'LANÇAMENTOS'!$D$6:$D$1005,$A26)) | H26: =IF($A26="","",SUMIFS('LANÇAMENTOS'!$G$6:$G$1005,'LANÇAMENTOS'!$I$6:$I$1005,($A$4*12+7),'LANÇAMENTOS'!$B$6:$B$1005,"SAÍDA",'LANÇAMENTOS'!$D$6:$D$1005,$A26)) | I26: =IF($A26="","",SUMIFS('LANÇAMENTOS'!$G$6:$G$1005,'LANÇAMENTOS'!$I$6:$I$1005,($A$4*12+8),'LANÇAMENTOS'!$B$6:$B$1005,"SAÍDA",'LANÇAMENTOS'!$D$6:$D$1005,$A26)) | J26: =IF($A26="","",SUMIFS('LANÇAMENTOS'!$G$6:$G$1005,'LANÇAMENTOS'!$I$6:$I$1005,($A$4*12+9),'LANÇAMENTOS'!$B$6:$B$1005,"SAÍDA",'LANÇAMENTOS'!$D$6:$D$1005,$A26)) | K26: =IF($A26="","",SUMIFS('LANÇAMENTOS'!$G$6:$G$1005,'LANÇAMENTOS'!$I$6:$I$1005,($A$4*12+10),'LANÇAMENTOS'!$B$6:$B$1005,"SAÍDA",'LANÇAMENTOS'!$D$6:$D$1005,$A26)) | L26: =IF($A26="","",SUMIFS('LANÇAMENTOS'!$G$6:$G$1005,'LANÇAMENTOS'!$I$6:$I$1005,($A$4*12+11),'LANÇAMENTOS'!$B$6:$B$1005,"SAÍDA",'LANÇAMENTOS'!$D$6:$D$1005,$A26)) | M26: =IF($A26="","",SUMIFS('LANÇAMENTOS'!$G$6:$G$1005,'LANÇAMENTOS'!$I$6:$I$1005,($A$4*12+12),'LANÇAMENTOS'!$B$6:$B$1005,"SAÍDA",'LANÇAMENTOS'!$D$6:$D$1005,$A26)) | N26: =IF($A26="","",SUM(B26:M26))
A27: =IF(LISTAS!$B10="SAÍDA",LISTAS!$A10,"") | B27: =IF($A27="","",SUMIFS('LANÇAMENTOS'!$G$6:$G$1005,'LANÇAMENTOS'!$I$6:$I$1005,($A$4*12+1),'LANÇAMENTOS'!$B$6:$B$1005,"SAÍDA",'LANÇAMENTOS'!$D$6:$D$1005,$A27)) | C27: =IF($A27="","",SUMIFS('LANÇAMENTOS'!$G$6:$G$1005,'LANÇAMENTOS'!$I$6:$I$1005,($A$4*12+2),'LANÇAMENTOS'!$B$6:$B$1005,"SAÍDA",'LANÇAMENTOS'!$D$6:$D$1005,$A27)) | D27: =IF($A27="","",SUMIFS('LANÇAMENTOS'!$G$6:$G$1005,'LANÇAMENTOS'!$I$6:$I$1005,($A$4*12+3),'LANÇAMENTOS'!$B$6:$B$1005,"SAÍDA",'LANÇAMENTOS'!$D$6:$D$1005,$A27)) | E27: =IF($A27="","",SUMIFS('LANÇAMENTOS'!$G$6:$G$1005,'LANÇAMENTOS'!$I$6:$I$1005,($A$4*12+4),'LANÇAMENTOS'!$B$6:$B$1005,"SAÍDA",'LANÇAMENTOS'!$D$6:$D$1005,$A27)) | F27: =IF($A27="","",SUMIFS('LANÇAMENTOS'!$G$6:$G$1005,'LANÇAMENTOS'!$I$6:$I$1005,($A$4*12+5),'LANÇAMENTOS'!$B$6:$B$1005,"SAÍDA",'LANÇAMENTOS'!$D$6:$D$1005,$A27)) | G27: =IF($A27="","",SUMIFS('LANÇAMENTOS'!$G$6:$G$1005,'LANÇAMENTOS'!$I$6:$I$1005,($A$4*12+6),'LANÇAMENTOS'!$B$6:$B$1005,"SAÍDA",'LANÇAMENTOS'!$D$6:$D$1005,$A27)) | H27: =IF($A27="","",SUMIFS('LANÇAMENTOS'!$G$6:$G$1005,'LANÇAMENTOS'!$I$6:$I$1005,($A$4*12+7),'LANÇAMENTOS'!$B$6:$B$1005,"SAÍDA",'LANÇAMENTOS'!$D$6:$D$1005,$A27)) | I27: =IF($A27="","",SUMIFS('LANÇAMENTOS'!$G$6:$G$1005,'LANÇAMENTOS'!$I$6:$I$1005,($A$4*12+8),'LANÇAMENTOS'!$B$6:$B$1005,"SAÍDA",'LANÇAMENTOS'!$D$6:$D$1005,$A27)) | J27: =IF($A27="","",SUMIFS('LANÇAMENTOS'!$G$6:$G$1005,'LANÇAMENTOS'!$I$6:$I$1005,($A$4*12+9),'LANÇAMENTOS'!$B$6:$B$1005,"SAÍDA",'LANÇAMENTOS'!$D$6:$D$1005,$A27)) | K27: =IF($A27="","",SUMIFS('LANÇAMENTOS'!$G$6:$G$1005,'LANÇAMENTOS'!$I$6:$I$1005,($A$4*12+10),'LANÇAMENTOS'!$B$6:$B$1005,"SAÍDA",'LANÇAMENTOS'!$D$6:$D$1005,$A27)) | L27: =IF($A27="","",SUMIFS('LANÇAMENTOS'!$G$6:$G$1005,'LANÇAMENTOS'!$I$6:$I$1005,($A$4*12+11),'LANÇAMENTOS'!$B$6:$B$1005,"SAÍDA",'LANÇAMENTOS'!$D$6:$D$1005,$A27)) | M27: =IF($A27="","",SUMIFS('LANÇAMENTOS'!$G$6:$G$1005,'LANÇAMENTOS'!$I$6:$I$1005,($A$4*12+12),'LANÇAMENTOS'!$B$6:$B$1005,"SAÍDA",'LANÇAMENTOS'!$D$6:$D$1005,$A27)) | N27: =IF($A27="","",SUM(B27:M27))
A28: =IF(LISTAS!$B11="SAÍDA",LISTAS!$A11,"") | B28: =IF($A28="","",SUMIFS('LANÇAMENTOS'!$G$6:$G$1005,'LANÇAMENTOS'!$I$6:$I$1005,($A$4*12+1),'LANÇAMENTOS'!$B$6:$B$1005,"SAÍDA",'LANÇAMENTOS'!$D$6:$D$1005,$A28)) | C28: =IF($A28="","",SUMIFS('LANÇAMENTOS'!$G$6:$G$1005,'LANÇAMENTOS'!$I$6:$I$1005,($A$4*12+2),'LANÇAMENTOS'!$B$6:$B$1005,"SAÍDA",'LANÇAMENTOS'!$D$6:$D$1005,$A28)) | D28: =IF($A28="","",SUMIFS('LANÇAMENTOS'!$G$6:$G$1005,'LANÇAMENTOS'!$I$6:$I$1005,($A$4*12+3),'LANÇAMENTOS'!$B$6:$B$1005,"SAÍDA",'LANÇAMENTOS'!$D$6:$D$1005,$A28)) | E28: =IF($A28="","",SUMIFS('LANÇAMENTOS'!$G$6:$G$1005,'LANÇAMENTOS'!$I$6:$I$1005,($A$4*12+4),'LANÇAMENTOS'!$B$6:$B$1005,"SAÍDA",'LANÇAMENTOS'!$D$6:$D$1005,$A28)) | F28: =IF($A28="","",SUMIFS('LANÇAMENTOS'!$G$6:$G$1005,'LANÇAMENTOS'!$I$6:$I$1005,($A$4*12+5),'LANÇAMENTOS'!$B$6:$B$1005,"SAÍDA",'LANÇAMENTOS'!$D$6:$D$1005,$A28)) | G28: =IF($A28="","",SUMIFS('LANÇAMENTOS'!$G$6:$G$1005,'LANÇAMENTOS'!$I$6:$I$1005,($A$4*12+6),'LANÇAMENTOS'!$B$6:$B$1005,"SAÍDA",'LANÇAMENTOS'!$D$6:$D$1005,$A28)) | H28: =IF($A28="","",SUMIFS('LANÇAMENTOS'!$G$6:$G$1005,'LANÇAMENTOS'!$I$6:$I$1005,($A$4*12+7),'LANÇAMENTOS'!$B$6:$B$1005,"SAÍDA",'LANÇAMENTOS'!$D$6:$D$1005,$A28)) | I28: =IF($A28="","",SUMIFS('LANÇAMENTOS'!$G$6:$G$1005,'LANÇAMENTOS'!$I$6:$I$1005,($A$4*12+8),'LANÇAMENTOS'!$B$6:$B$1005,"SAÍDA",'LANÇAMENTOS'!$D$6:$D$1005,$A28)) | J28: =IF($A28="","",SUMIFS('LANÇAMENTOS'!$G$6:$G$1005,'LANÇAMENTOS'!$I$6:$I$1005,($A$4*12+9),'LANÇAMENTOS'!$B$6:$B$1005,"SAÍDA",'LANÇAMENTOS'!$D$6:$D$1005,$A28)) | K28: =IF($A28="","",SUMIFS('LANÇAMENTOS'!$G$6:$G$1005,'LANÇAMENTOS'!$I$6:$I$1005,($A$4*12+10),'LANÇAMENTOS'!$B$6:$B$1005,"SAÍDA",'LANÇAMENTOS'!$D$6:$D$1005,$A28)) | L28: =IF($A28="","",SUMIFS('LANÇAMENTOS'!$G$6:$G$1005,'LANÇAMENTOS'!$I$6:$I$1005,($A$4*12+11),'LANÇAMENTOS'!$B$6:$B$1005,"SAÍDA",'LANÇAMENTOS'!$D$6:$D$1005,$A28)) | M28: =IF($A28="","",SUMIFS('LANÇAMENTOS'!$G$6:$G$1005,'LANÇAMENTOS'!$I$6:$I$1005,($A$4*12+12),'LANÇAMENTOS'!$B$6:$B$1005,"SAÍDA",'LANÇAMENTOS'!$D$6:$D$1005,$A28)) | N28: =IF($A28="","",SUM(B28:M28))
A29: =IF(LISTAS!$B12="SAÍDA",LISTAS!$A12,"") | B29: =IF($A29="","",SUMIFS('LANÇAMENTOS'!$G$6:$G$1005,'LANÇAMENTOS'!$I$6:$I$1005,($A$4*12+1),'LANÇAMENTOS'!$B$6:$B$1005,"SAÍDA",'LANÇAMENTOS'!$D$6:$D$1005,$A29)) | C29: =IF($A29="","",SUMIFS('LANÇAMENTOS'!$G$6:$G$1005,'LANÇAMENTOS'!$I$6:$I$1005,($A$4*12+2),'LANÇAMENTOS'!$B$6:$B$1005,"SAÍDA",'LANÇAMENTOS'!$D$6:$D$1005,$A29)) | D29: =IF($A29="","",SUMIFS('LANÇAMENTOS'!$G$6:$G$1005,'LANÇAMENTOS'!$I$6:$I$1005,($A$4*12+3),'LANÇAMENTOS'!$B$6:$B$1005,"SAÍDA",'LANÇAMENTOS'!$D$6:$D$1005,$A29)) | E29: =IF($A29="","",SUMIFS('LANÇAMENTOS'!$G$6:$G$1005,'LANÇAMENTOS'!$I$6:$I$1005,($A$4*12+4),'LANÇAMENTOS'!$B$6:$B$1005,"SAÍDA",'LANÇAMENTOS'!$D$6:$D$1005,$A29)) | F29: =IF($A29="","",SUMIFS('LANÇAMENTOS'!$G$6:$G$1005,'LANÇAMENTOS'!$I$6:$I$1005,($A$4*12+5),'LANÇAMENTOS'!$B$6:$B$1005,"SAÍDA",'LANÇAMENTOS'!$D$6:$D$1005,$A29)) | G29: =IF($A29="","",SUMIFS('LANÇAMENTOS'!$G$6:$G$1005,'LANÇAMENTOS'!$I$6:$I$1005,($A$4*12+6),'LANÇAMENTOS'!$B$6:$B$1005,"SAÍDA",'LANÇAMENTOS'!$D$6:$D$1005,$A29)) | H29: =IF($A29="","",SUMIFS('LANÇAMENTOS'!$G$6:$G$1005,'LANÇAMENTOS'!$I$6:$I$1005,($A$4*12+7),'LANÇAMENTOS'!$B$6:$B$1005,"SAÍDA",'LANÇAMENTOS'!$D$6:$D$1005,$A29)) | I29: =IF($A29="","",SUMIFS('LANÇAMENTOS'!$G$6:$G$1005,'LANÇAMENTOS'!$I$6:$I$1005,($A$4*12+8),'LANÇAMENTOS'!$B$6:$B$1005,"SAÍDA",'LANÇAMENTOS'!$D$6:$D$1005,$A29)) | J29: =IF($A29="","",SUMIFS('LANÇAMENTOS'!$G$6:$G$1005,'LANÇAMENTOS'!$I$6:$I$1005,($A$4*12+9),'LANÇAMENTOS'!$B$6:$B$1005,"SAÍDA",'LANÇAMENTOS'!$D$6:$D$1005,$A29)) | K29: =IF($A29="","",SUMIFS('LANÇAMENTOS'!$G$6:$G$1005,'LANÇAMENTOS'!$I$6:$I$1005,($A$4*12+10),'LANÇAMENTOS'!$B$6:$B$1005,"SAÍDA",'LANÇAMENTOS'!$D$6:$D$1005,$A29)) | L29: =IF($A29="","",SUMIFS('LANÇAMENTOS'!$G$6:$G$1005,'LANÇAMENTOS'!$I$6:$I$1005,($A$4*12+11),'LANÇAMENTOS'!$B$6:$B$1005,"SAÍDA",'LANÇAMENTOS'!$D$6:$D$1005,$A29)) | M29: =IF($A29="","",SUMIFS('LANÇAMENTOS'!$G$6:$G$1005,'LANÇAMENTOS'!$I$6:$I$1005,($A$4*12+12),'LANÇAMENTOS'!$B$6:$B$1005,"SAÍDA",'LANÇAMENTOS'!$D$6:$D$1005,$A29)) | N29: =IF($A29="","",SUM(B29:M29))
A30: =IF(LISTAS!$B13="SAÍDA",LISTAS!$A13,"") | B30: =IF($A30="","",SUMIFS('LANÇAMENTOS'!$G$6:$G$1005,'LANÇAMENTOS'!$I$6:$I$1005,($A$4*12+1),'LANÇAMENTOS'!$B$6:$B$1005,"SAÍDA",'LANÇAMENTOS'!$D$6:$D$1005,$A30)) | C30: =IF($A30="","",SUMIFS('LANÇAMENTOS'!$G$6:$G$1005,'LANÇAMENTOS'!$I$6:$I$1005,($A$4*12+2),'LANÇAMENTOS'!$B$6:$B$1005,"SAÍDA",'LANÇAMENTOS'!$D$6:$D$1005,$A30)) | D30: =IF($A30="","",SUMIFS('LANÇAMENTOS'!$G$6:$G$1005,'LANÇAMENTOS'!$I$6:$I$1005,($A$4*12+3),'LANÇAMENTOS'!$B$6:$B$1005,"SAÍDA",'LANÇAMENTOS'!$D$6:$D$1005,$A30)) | E30: =IF($A30="","",SUMIFS('LANÇAMENTOS'!$G$6:$G$1005,'LANÇAMENTOS'!$I$6:$I$1005,($A$4*12+4),'LANÇAMENTOS'!$B$6:$B$1005,"SAÍDA",'LANÇAMENTOS'!$D$6:$D$1005,$A30)) | F30: =IF($A30="","",SUMIFS('LANÇAMENTOS'!$G$6:$G$1005,'LANÇAMENTOS'!$I$6:$I$1005,($A$4*12+5),'LANÇAMENTOS'!$B$6:$B$1005,"SAÍDA",'LANÇAMENTOS'!$D$6:$D$1005,$A30)) | G30: =IF($A30="","",SUMIFS('LANÇAMENTOS'!$G$6:$G$1005,'LANÇAMENTOS'!$I$6:$I$1005,($A$4*12+6),'LANÇAMENTOS'!$B$6:$B$1005,"SAÍDA",'LANÇAMENTOS'!$D$6:$D$1005,$A30)) | H30: =IF($A30="","",SUMIFS('LANÇAMENTOS'!$G$6:$G$1005,'LANÇAMENTOS'!$I$6:$I$1005,($A$4*12+7),'LANÇAMENTOS'!$B$6:$B$1005,"SAÍDA",'LANÇAMENTOS'!$D$6:$D$1005,$A30)) | I30: =IF($A30="","",SUMIFS('LANÇAMENTOS'!$G$6:$G$1005,'LANÇAMENTOS'!$I$6:$I$1005,($A$4*12+8),'LANÇAMENTOS'!$B$6:$B$1005,"SAÍDA",'LANÇAMENTOS'!$D$6:$D$1005,$A30)) | J30: =IF($A30="","",SUMIFS('LANÇAMENTOS'!$G$6:$G$1005,'LANÇAMENTOS'!$I$6:$I$1005,($A$4*12+9),'LANÇAMENTOS'!$B$6:$B$1005,"SAÍDA",'LANÇAMENTOS'!$D$6:$D$1005,$A30)) | K30: =IF($A30="","",SUMIFS('LANÇAMENTOS'!$G$6:$G$1005,'LANÇAMENTOS'!$I$6:$I$1005,($A$4*12+10),'LANÇAMENTOS'!$B$6:$B$1005,"SAÍDA",'LANÇAMENTOS'!$D$6:$D$1005,$A30)) | L30: =IF($A30="","",SUMIFS('LANÇAMENTOS'!$G$6:$G$1005,'LANÇAMENTOS'!$I$6:$I$1005,($A$4*12+11),'LANÇAMENTOS'!$B$6:$B$1005,"SAÍDA",'LANÇAMENTOS'!$D$6:$D$1005,$A30)) | M30: =IF($A30="","",SUMIFS('LANÇAMENTOS'!$G$6:$G$1005,'LANÇAMENTOS'!$I$6:$I$1005,($A$4*12+12),'LANÇAMENTOS'!$B$6:$B$1005,"SAÍDA",'LANÇAMENTOS'!$D$6:$D$1005,$A30)) | N30: =IF($A30="","",SUM(B30:M30))
A31: =IF(LISTAS!$B14="SAÍDA",LISTAS!$A14,"") | B31: =IF($A31="","",SUMIFS('LANÇAMENTOS'!$G$6:$G$1005,'LANÇAMENTOS'!$I$6:$I$1005,($A$4*12+1),'LANÇAMENTOS'!$B$6:$B$1005,"SAÍDA",'LANÇAMENTOS'!$D$6:$D$1005,$A31)) | C31: =IF($A31="","",SUMIFS('LANÇAMENTOS'!$G$6:$G$1005,'LANÇAMENTOS'!$I$6:$I$1005,($A$4*12+2),'LANÇAMENTOS'!$B$6:$B$1005,"SAÍDA",'LANÇAMENTOS'!$D$6:$D$1005,$A31)) | D31: =IF($A31="","",SUMIFS('LANÇAMENTOS'!$G$6:$G$1005,'LANÇAMENTOS'!$I$6:$I$1005,($A$4*12+3),'LANÇAMENTOS'!$B$6:$B$1005,"SAÍDA",'LANÇAMENTOS'!$D$6:$D$1005,$A31)) | E31: =IF($A31="","",SUMIFS('LANÇAMENTOS'!$G$6:$G$1005,'LANÇAMENTOS'!$I$6:$I$1005,($A$4*12+4),'LANÇAMENTOS'!$B$6:$B$1005,"SAÍDA",'LANÇAMENTOS'!$D$6:$D$1005,$A31)) | F31: =IF($A31="","",SUMIFS('LANÇAMENTOS'!$G$6:$G$1005,'LANÇAMENTOS'!$I$6:$I$1005,($A$4*12+5),'LANÇAMENTOS'!$B$6:$B$1005,"SAÍDA",'LANÇAMENTOS'!$D$6:$D$1005,$A31)) | G31: =IF($A31="","",SUMIFS('LANÇAMENTOS'!$G$6:$G$1005,'LANÇAMENTOS'!$I$6:$I$1005,($A$4*12+6),'LANÇAMENTOS'!$B$6:$B$1005,"SAÍDA",'LANÇAMENTOS'!$D$6:$D$1005,$A31)) | H31: =IF($A31="","",SUMIFS('LANÇAMENTOS'!$G$6:$G$1005,'LANÇAMENTOS'!$I$6:$I$1005,($A$4*12+7),'LANÇAMENTOS'!$B$6:$B$1005,"SAÍDA",'LANÇAMENTOS'!$D$6:$D$1005,$A31)) | I31: =IF($A31="","",SUMIFS('LANÇAMENTOS'!$G$6:$G$1005,'LANÇAMENTOS'!$I$6:$I$1005,($A$4*12+8),'LANÇAMENTOS'!$B$6:$B$1005,"SAÍDA",'LANÇAMENTOS'!$D$6:$D$1005,$A31)) | J31: =IF($A31="","",SUMIFS('LANÇAMENTOS'!$G$6:$G$1005,'LANÇAMENTOS'!$I$6:$I$1005,($A$4*12+9),'LANÇAMENTOS'!$B$6:$B$1005,"SAÍDA",'LANÇAMENTOS'!$D$6:$D$1005,$A31)) | K31: =IF($A31="","",SUMIFS('LANÇAMENTOS'!$G$6:$G$1005,'LANÇAMENTOS'!$I$6:$I$1005,($A$4*12+10),'LANÇAMENTOS'!$B$6:$B$1005,"SAÍDA",'LANÇAMENTOS'!$D$6:$D$1005,$A31)) | L31: =IF($A31="","",SUMIFS('LANÇAMENTOS'!$G$6:$G$1005,'LANÇAMENTOS'!$I$6:$I$1005,($A$4*12+11),'LANÇAMENTOS'!$B$6:$B$1005,"SAÍDA",'LANÇAMENTOS'!$D$6:$D$1005,$A31)) | M31: =IF($A31="","",SUMIFS('LANÇAMENTOS'!$G$6:$G$1005,'LANÇAMENTOS'!$I$6:$I$1005,($A$4*12+12),'LANÇAMENTOS'!$B$6:$B$1005,"SAÍDA",'LANÇAMENTOS'!$D$6:$D$1005,$A31)) | N31: =IF($A31="","",SUM(B31:M31))
A32: =IF(LISTAS!$B15="SAÍDA",LISTAS!$A15,"") | B32: =IF($A32="","",SUMIFS('LANÇAMENTOS'!$G$6:$G$1005,'LANÇAMENTOS'!$I$6:$I$1005,($A$4*12+1),'LANÇAMENTOS'!$B$6:$B$1005,"SAÍDA",'LANÇAMENTOS'!$D$6:$D$1005,$A32)) | C32: =IF($A32="","",SUMIFS('LANÇAMENTOS'!$G$6:$G$1005,'LANÇAMENTOS'!$I$6:$I$1005,($A$4*12+2),'LANÇAMENTOS'!$B$6:$B$1005,"SAÍDA",'LANÇAMENTOS'!$D$6:$D$1005,$A32)) | D32: =IF($A32="","",SUMIFS('LANÇAMENTOS'!$G$6:$G$1005,'LANÇAMENTOS'!$I$6:$I$1005,($A$4*12+3),'LANÇAMENTOS'!$B$6:$B$1005,"SAÍDA",'LANÇAMENTOS'!$D$6:$D$1005,$A32)) | E32: =IF($A32="","",SUMIFS('LANÇAMENTOS'!$G$6:$G$1005,'LANÇAMENTOS'!$I$6:$I$1005,($A$4*12+4),'LANÇAMENTOS'!$B$6:$B$1005,"SAÍDA",'LANÇAMENTOS'!$D$6:$D$1005,$A32)) | F32: =IF($A32="","",SUMIFS('LANÇAMENTOS'!$G$6:$G$1005,'LANÇAMENTOS'!$I$6:$I$1005,($A$4*12+5),'LANÇAMENTOS'!$B$6:$B$1005,"SAÍDA",'LANÇAMENTOS'!$D$6:$D$1005,$A32)) | G32: =IF($A32="","",SUMIFS('LANÇAMENTOS'!$G$6:$G$1005,'LANÇAMENTOS'!$I$6:$I$1005,($A$4*12+6),'LANÇAMENTOS'!$B$6:$B$1005,"SAÍDA",'LANÇAMENTOS'!$D$6:$D$1005,$A32)) | H32: =IF($A32="","",SUMIFS('LANÇAMENTOS'!$G$6:$G$1005,'LANÇAMENTOS'!$I$6:$I$1005,($A$4*12+7),'LANÇAMENTOS'!$B$6:$B$1005,"SAÍDA",'LANÇAMENTOS'!$D$6:$D$1005,$A32)) | I32: =IF($A32="","",SUMIFS('LANÇAMENTOS'!$G$6:$G$1005,'LANÇAMENTOS'!$I$6:$I$1005,($A$4*12+8),'LANÇAMENTOS'!$B$6:$B$1005,"SAÍDA",'LANÇAMENTOS'!$D$6:$D$1005,$A32)) | J32: =IF($A32="","",SUMIFS('LANÇAMENTOS'!$G$6:$G$1005,'LANÇAMENTOS'!$I$6:$I$1005,($A$4*12+9),'LANÇAMENTOS'!$B$6:$B$1005,"SAÍDA",'LANÇAMENTOS'!$D$6:$D$1005,$A32)) | K32: =IF($A32="","",SUMIFS('LANÇAMENTOS'!$G$6:$G$1005,'LANÇAMENTOS'!$I$6:$I$1005,($A$4*12+10),'LANÇAMENTOS'!$B$6:$B$1005,"SAÍDA",'LANÇAMENTOS'!$D$6:$D$1005,$A32)) | L32: =IF($A32="","",SUMIFS('LANÇAMENTOS'!$G$6:$G$1005,'LANÇAMENTOS'!$I$6:$I$1005,($A$4*12+11),'LANÇAMENTOS'!$B$6:$B$1005,"SAÍDA",'LANÇAMENTOS'!$D$6:$D$1005,$A32)) | M32: =IF($A32="","",SUMIFS('LANÇAMENTOS'!$G$6:$G$1005,'LANÇAMENTOS'!$I$6:$I$1005,($A$4*12+12),'LANÇAMENTOS'!$B$6:$B$1005,"SAÍDA",'LANÇAMENTOS'!$D$6:$D$1005,$A32)) | N32: =IF($A32="","",SUM(B32:M32))
A33: =IF(LISTAS!$B16="SAÍDA",LISTAS!$A16,"") | B33: =IF($A33="","",SUMIFS('LANÇAMENTOS'!$G$6:$G$1005,'LANÇAMENTOS'!$I$6:$I$1005,($A$4*12+1),'LANÇAMENTOS'!$B$6:$B$1005,"SAÍDA",'LANÇAMENTOS'!$D$6:$D$1005,$A33)) | C33: =IF($A33="","",SUMIFS('LANÇAMENTOS'!$G$6:$G$1005,'LANÇAMENTOS'!$I$6:$I$1005,($A$4*12+2),'LANÇAMENTOS'!$B$6:$B$1005,"SAÍDA",'LANÇAMENTOS'!$D$6:$D$1005,$A33)) | D33: =IF($A33="","",SUMIFS('LANÇAMENTOS'!$G$6:$G$1005,'LANÇAMENTOS'!$I$6:$I$1005,($A$4*12+3),'LANÇAMENTOS'!$B$6:$B$1005,"SAÍDA",'LANÇAMENTOS'!$D$6:$D$1005,$A33)) | E33: =IF($A33="","",SUMIFS('LANÇAMENTOS'!$G$6:$G$1005,'LANÇAMENTOS'!$I$6:$I$1005,($A$4*12+4),'LANÇAMENTOS'!$B$6:$B$1005,"SAÍDA",'LANÇAMENTOS'!$D$6:$D$1005,$A33)) | F33: =IF($A33="","",SUMIFS('LANÇAMENTOS'!$G$6:$G$1005,'LANÇAMENTOS'!$I$6:$I$1005,($A$4*12+5),'LANÇAMENTOS'!$B$6:$B$1005,"SAÍDA",'LANÇAMENTOS'!$D$6:$D$1005,$A33)) | G33: =IF($A33="","",SUMIFS('LANÇAMENTOS'!$G$6:$G$1005,'LANÇAMENTOS'!$I$6:$I$1005,($A$4*12+6),'LANÇAMENTOS'!$B$6:$B$1005,"SAÍDA",'LANÇAMENTOS'!$D$6:$D$1005,$A33)) | H33: =IF($A33="","",SUMIFS('LANÇAMENTOS'!$G$6:$G$1005,'LANÇAMENTOS'!$I$6:$I$1005,($A$4*12+7),'LANÇAMENTOS'!$B$6:$B$1005,"SAÍDA",'LANÇAMENTOS'!$D$6:$D$1005,$A33)) | I33: =IF($A33="","",SUMIFS('LANÇAMENTOS'!$G$6:$G$1005,'LANÇAMENTOS'!$I$6:$I$1005,($A$4*12+8),'LANÇAMENTOS'!$B$6:$B$1005,"SAÍDA",'LANÇAMENTOS'!$D$6:$D$1005,$A33)) | J33: =IF($A33="","",SUMIFS('LANÇAMENTOS'!$G$6:$G$1005,'LANÇAMENTOS'!$I$6:$I$1005,($A$4*12+9),'LANÇAMENTOS'!$B$6:$B$1005,"SAÍDA",'LANÇAMENTOS'!$D$6:$D$1005,$A33)) | K33: =IF($A33="","",SUMIFS('LANÇAMENTOS'!$G$6:$G$1005,'LANÇAMENTOS'!$I$6:$I$1005,($A$4*12+10),'LANÇAMENTOS'!$B$6:$B$1005,"SAÍDA",'LANÇAMENTOS'!$D$6:$D$1005,$A33)) | L33: =IF($A33="","",SUMIFS('LANÇAMENTOS'!$G$6:$G$1005,'LANÇAMENTOS'!$I$6:$I$1005,($A$4*12+11),'LANÇAMENTOS'!$B$6:$B$1005,"SAÍDA",'LANÇAMENTOS'!$D$6:$D$1005,$A33)) | M33: =IF($A33="","",SUMIFS('LANÇAMENTOS'!$G$6:$G$1005,'LANÇAMENTOS'!$I$6:$I$1005,($A$4*12+12),'LANÇAMENTOS'!$B$6:$B$1005,"SAÍDA",'LANÇAMENTOS'!$D$6:$D$1005,$A33)) | N33: =IF($A33="","",SUM(B33:M33))
A34: =IF(LISTAS!$B17="SAÍDA",LISTAS!$A17,"") | B34: =IF($A34="","",SUMIFS('LANÇAMENTOS'!$G$6:$G$1005,'LANÇAMENTOS'!$I$6:$I$1005,($A$4*12+1),'LANÇAMENTOS'!$B$6:$B$1005,"SAÍDA",'LANÇAMENTOS'!$D$6:$D$1005,$A34)) | C34: =IF($A34="","",SUMIFS('LANÇAMENTOS'!$G$6:$G$1005,'LANÇAMENTOS'!$I$6:$I$1005,($A$4*12+2),'LANÇAMENTOS'!$B$6:$B$1005,"SAÍDA",'LANÇAMENTOS'!$D$6:$D$1005,$A34)) | D34: =IF($A34="","",SUMIFS('LANÇAMENTOS'!$G$6:$G$1005,'LANÇAMENTOS'!$I$6:$I$1005,($A$4*12+3),'LANÇAMENTOS'!$B$6:$B$1005,"SAÍDA",'LANÇAMENTOS'!$D$6:$D$1005,$A34)) | E34: =IF($A34="","",SUMIFS('LANÇAMENTOS'!$G$6:$G$1005,'LANÇAMENTOS'!$I$6:$I$1005,($A$4*12+4),'LANÇAMENTOS'!$B$6:$B$1005,"SAÍDA",'LANÇAMENTOS'!$D$6:$D$1005,$A34)) | F34: =IF($A34="","",SUMIFS('LANÇAMENTOS'!$G$6:$G$1005,'LANÇAMENTOS'!$I$6:$I$1005,($A$4*12+5),'LANÇAMENTOS'!$B$6:$B$1005,"SAÍDA",'LANÇAMENTOS'!$D$6:$D$1005,$A34)) | G34: =IF($A34="","",SUMIFS('LANÇAMENTOS'!$G$6:$G$1005,'LANÇAMENTOS'!$I$6:$I$1005,($A$4*12+6),'LANÇAMENTOS'!$B$6:$B$1005,"SAÍDA",'LANÇAMENTOS'!$D$6:$D$1005,$A34)) | H34: =IF($A34="","",SUMIFS('LANÇAMENTOS'!$G$6:$G$1005,'LANÇAMENTOS'!$I$6:$I$1005,($A$4*12+7),'LANÇAMENTOS'!$B$6:$B$1005,"SAÍDA",'LANÇAMENTOS'!$D$6:$D$1005,$A34)) | I34: =IF($A34="","",SUMIFS('LANÇAMENTOS'!$G$6:$G$1005,'LANÇAMENTOS'!$I$6:$I$1005,($A$4*12+8),'LANÇAMENTOS'!$B$6:$B$1005,"SAÍDA",'LANÇAMENTOS'!$D$6:$D$1005,$A34)) | J34: =IF($A34="","",SUMIFS('LANÇAMENTOS'!$G$6:$G$1005,'LANÇAMENTOS'!$I$6:$I$1005,($A$4*12+9),'LANÇAMENTOS'!$B$6:$B$1005,"SAÍDA",'LANÇAMENTOS'!$D$6:$D$1005,$A34)) | K34: =IF($A34="","",SUMIFS('LANÇAMENTOS'!$G$6:$G$1005,'LANÇAMENTOS'!$I$6:$I$1005,($A$4*12+10),'LANÇAMENTOS'!$B$6:$B$1005,"SAÍDA",'LANÇAMENTOS'!$D$6:$D$1005,$A34)) | L34: =IF($A34="","",SUMIFS('LANÇAMENTOS'!$G$6:$G$1005,'LANÇAMENTOS'!$I$6:$I$1005,($A$4*12+11),'LANÇAMENTOS'!$B$6:$B$1005,"SAÍDA",'LANÇAMENTOS'!$D$6:$D$1005,$A34)) | M34: =IF($A34="","",SUMIFS('LANÇAMENTOS'!$G$6:$G$1005,'LANÇAMENTOS'!$I$6:$I$1005,($A$4*12+12),'LANÇAMENTOS'!$B$6:$B$1005,"SAÍDA",'LANÇAMENTOS'!$D$6:$D$1005,$A34)) | N34: =IF($A34="","",SUM(B34:M34))
... A62: =IF(LISTAS!$B45="SAÍDA",LISTAS!$A45,"") | B62: =IF($A62="","",SUMIFS('LANÇAMENTOS'!$G$6:$G$1005,'LANÇAMENTOS'!$I$6:$I$1005,($A$4*12+1),'LANÇAMENTOS'!$B$6:$B$1005,"SAÍDA",'LANÇAMENTOS'!$D$6:$D$1005,$A62)) | C62: =IF($A62="","",SUMIFS('LANÇAMENTOS'!$G$6:$G$1005,'LANÇAMENTOS'!$I$6:$I$1005,($A$4*12+2),'LANÇAMENTOS'!$B$6:$B$1005,"SAÍDA",'LANÇAMENTOS'!$D$6:$D$1005,$A62)) | D62: =IF($A62="","",SUMIFS('LANÇAMENTOS'!$G$6:$G$1005,'LANÇAMENTOS'!$I$6:$I$1005,($A$4*12+3),'LANÇAMENTOS'!$B$6:$B$1005,"SAÍDA",'LANÇAMENTOS'!$D$6:$D$1005,$A62)) | E62: =IF($A62="","",SUMIFS('LANÇAMENTOS'!$G$6:$G$1005,'LANÇAMENTOS'!$I$6:$I$1005,($A$4*12+4),'LANÇAMENTOS'!$B$6:$B$1005,"SAÍDA",'LANÇAMENTOS'!$D$6:$D$1005,$A62)) | F62: =IF($A62="","",SUMIFS('LANÇAMENTOS'!$G$6:$G$1005,'LANÇAMENTOS'!$I$6:$I$1005,($A$4*12+5),'LANÇAMENTOS'!$B$6:$B$1005,"SAÍDA",'LANÇAMENTOS'!$D$6:$D$1005,$A62)) | G62: =IF($A62="","",SUMIFS('LANÇAMENTOS'!$G$6:$G$1005,'LANÇAMENTOS'!$I$6:$I$1005,($A$4*12+6),'LANÇAMENTOS'!$B$6:$B$1005,"SAÍDA",'LANÇAMENTOS'!$D$6:$D$1005,$A62)) | H62: =IF($A62="","",SUMIFS('LANÇAMENTOS'!$G$6:$G$1005,'LANÇAMENTOS'!$I$6:$I$1005,($A$4*12+7),'LANÇAMENTOS'!$B$6:$B$1005,"SAÍDA",'LANÇAMENTOS'!$D$6:$D$1005,$A62)) | I62: =IF($A62="","",SUMIFS('LANÇAMENTOS'!$G$6:$G$1005,'LANÇAMENTOS'!$I$6:$I$1005,($A$4*12+8),'LANÇAMENTOS'!$B$6:$B$1005,"SAÍDA",'LANÇAMENTOS'!$D$6:$D$1005,$A62)) | J62: =IF($A62="","",SUMIFS('LANÇAMENTOS'!$G$6:$G$1005,'LANÇAMENTOS'!$I$6:$I$1005,($A$4*12+9),'LANÇAMENTOS'!$B$6:$B$1005,"SAÍDA",'LANÇAMENTOS'!$D$6:$D$1005,$A62)) | K62: =IF($A62="","",SUMIFS('LANÇAMENTOS'!$G$6:$G$1005,'LANÇAMENTOS'!$I$6:$I$1005,($A$4*12+10),'LANÇAMENTOS'!$B$6:$B$1005,"SAÍDA",'LANÇAMENTOS'!$D$6:$D$1005,$A62)) | L62: =IF($A62="","",SUMIFS('LANÇAMENTOS'!$G$6:$G$1005,'LANÇAMENTOS'!$I$6:$I$1005,($A$4*12+11),'LANÇAMENTOS'!$B$6:$B$1005,"SAÍDA",'LANÇAMENTOS'!$D$6:$D$1005,$A62)) | M62: =IF($A62="","",SUMIFS('LANÇAMENTOS'!$G$6:$G$1005,'LANÇAMENTOS'!$I$6:$I$1005,($A$4*12+12),'LANÇAMENTOS'!$B$6:$B$1005,"SAÍDA",'LANÇAMENTOS'!$D$6:$D$1005,$A62)) | N62: =IF($A62="","",SUM(B62:M62))
A63: TOTAL SAÍDAS | B63: =SUM(B23:B62) | C63: =SUM(C23:C62) | D63: =SUM(D23:D62) | E63: =SUM(E23:E62) | F63: =SUM(F23:F62) | G63: =SUM(G23:G62) | H63: =SUM(H23:H62) | I63: =SUM(I23:I62) | ... N63: =SUM(N23:N62)
A66: ENTRADAS POR CATEGORIA, MÊS A MÊS
A67: Categoria | B67: Jan | C67: Fev | D67: Mar | E67: Abr | F67: Mai | G67: Jun | H67: Jul | I67: Ago | J67: Set | K67: Out | L67: Nov | M67: Dez | N67: Total do ano
A68: =IF(LISTAS!$B6="ENTRADA",LISTAS!$A6,"") | B68: =IF($A68="","",SUMIFS('LANÇAMENTOS'!$G$6:$G$1005,'LANÇAMENTOS'!$I$6:$I$1005,($A$4*12+1),'LANÇAMENTOS'!$B$6:$B$1005,"ENTRADA",'LANÇAMENTOS'!$D$6:$D$1005,$A68)) | C68: =IF($A68="","",SUMIFS('LANÇAMENTOS'!$G$6:$G$1005,'LANÇAMENTOS'!$I$6:$I$1005,($A$4*12+2),'LANÇAMENTOS'!$B$6:$B$1005,"ENTRADA",'LANÇAMENTOS'!$D$6:$D$1005,$A68)) | D68: =IF($A68="","",SUMIFS('LANÇAMENTOS'!$G$6:$G$1005,'LANÇAMENTOS'!$I$6:$I$1005,($A$4*12+3),'LANÇAMENTOS'!$B$6:$B$1005,"ENTRADA",'LANÇAMENTOS'!$D$6:$D$1005,$A68)) | E68: =IF($A68="","",SUMIFS('LANÇAMENTOS'!$G$6:$G$1005,'LANÇAMENTOS'!$I$6:$I$1005,($A$4*12+4),'LANÇAMENTOS'!$B$6:$B$1005,"ENTRADA",'LANÇAMENTOS'!$D$6:$D$1005,$A68)) | F68: =IF($A68="","",SUMIFS('LANÇAMENTOS'!$G$6:$G$1005,'LANÇAMENTOS'!$I$6:$I$1005,($A$4*12+5),'LANÇAMENTOS'!$B$6:$B$1005,"ENTRADA",'LANÇAMENTOS'!$D$6:$D$1005,$A68)) | G68: =IF($A68="","",SUMIFS('LANÇAMENTOS'!$G$6:$G$1005,'LANÇAMENTOS'!$I$6:$I$1005,($A$4*12+6),'LANÇAMENTOS'!$B$6:$B$1005,"ENTRADA",'LANÇAMENTOS'!$D$6:$D$1005,$A68)) | H68: =IF($A68="","",SUMIFS('LANÇAMENTOS'!$G$6:$G$1005,'LANÇAMENTOS'!$I$6:$I$1005,($A$4*12+7),'LANÇAMENTOS'!$B$6:$B$1005,"ENTRADA",'LANÇAMENTOS'!$D$6:$D$1005,$A68)) | I68: =IF($A68="","",SUMIFS('LANÇAMENTOS'!$G$6:$G$1005,'LANÇAMENTOS'!$I$6:$I$1005,($A$4*12+8),'LANÇAMENTOS'!$B$6:$B$1005,"ENTRADA",'LANÇAMENTOS'!$D$6:$D$1005,$A68)) | J68: =IF($A68="","",SUMIFS('LANÇAMENTOS'!$G$6:$G$1005,'LANÇAMENTOS'!$I$6:$I$1005,($A$4*12+9),'LANÇAMENTOS'!$B$6:$B$1005,"ENTRADA",'LANÇAMENTOS'!$D$6:$D$1005,$A68)) | K68: =IF($A68="","",SUMIFS('LANÇAMENTOS'!$G$6:$G$1005,'LANÇAMENTOS'!$I$6:$I$1005,($A$4*12+10),'LANÇAMENTOS'!$B$6:$B$1005,"ENTRADA",'LANÇAMENTOS'!$D$6:$D$1005,$A68)) | L68: =IF($A68="","",SUMIFS('LANÇAMENTOS'!$G$6:$G$1005,'LANÇAMENTOS'!$I$6:$I$1005,($A$4*12+11),'LANÇAMENTOS'!$B$6:$B$1005,"ENTRADA",'LANÇAMENTOS'!$D$6:$D$1005,$A68)) | M68: =IF($A68="","",SUMIFS('LANÇAMENTOS'!$G$6:$G$1005,'LANÇAMENTOS'!$I$6:$I$1005,($A$4*12+12),'LANÇAMENTOS'!$B$6:$B$1005,"ENTRADA",'LANÇAMENTOS'!$D$6:$D$1005,$A68)) | N68: =IF($A68="","",SUM(B68:M68))
A69: =IF(LISTAS!$B7="ENTRADA",LISTAS!$A7,"") | B69: =IF($A69="","",SUMIFS('LANÇAMENTOS'!$G$6:$G$1005,'LANÇAMENTOS'!$I$6:$I$1005,($A$4*12+1),'LANÇAMENTOS'!$B$6:$B$1005,"ENTRADA",'LANÇAMENTOS'!$D$6:$D$1005,$A69)) | C69: =IF($A69="","",SUMIFS('LANÇAMENTOS'!$G$6:$G$1005,'LANÇAMENTOS'!$I$6:$I$1005,($A$4*12+2),'LANÇAMENTOS'!$B$6:$B$1005,"ENTRADA",'LANÇAMENTOS'!$D$6:$D$1005,$A69)) | D69: =IF($A69="","",SUMIFS('LANÇAMENTOS'!$G$6:$G$1005,'LANÇAMENTOS'!$I$6:$I$1005,($A$4*12+3),'LANÇAMENTOS'!$B$6:$B$1005,"ENTRADA",'LANÇAMENTOS'!$D$6:$D$1005,$A69)) | E69: =IF($A69="","",SUMIFS('LANÇAMENTOS'!$G$6:$G$1005,'LANÇAMENTOS'!$I$6:$I$1005,($A$4*12+4),'LANÇAMENTOS'!$B$6:$B$1005,"ENTRADA",'LANÇAMENTOS'!$D$6:$D$1005,$A69)) | F69: =IF($A69="","",SUMIFS('LANÇAMENTOS'!$G$6:$G$1005,'LANÇAMENTOS'!$I$6:$I$1005,($A$4*12+5),'LANÇAMENTOS'!$B$6:$B$1005,"ENTRADA",'LANÇAMENTOS'!$D$6:$D$1005,$A69)) | G69: =IF($A69="","",SUMIFS('LANÇAMENTOS'!$G$6:$G$1005,'LANÇAMENTOS'!$I$6:$I$1005,($A$4*12+6),'LANÇAMENTOS'!$B$6:$B$1005,"ENTRADA",'LANÇAMENTOS'!$D$6:$D$1005,$A69)) | H69: =IF($A69="","",SUMIFS('LANÇAMENTOS'!$G$6:$G$1005,'LANÇAMENTOS'!$I$6:$I$1005,($A$4*12+7),'LANÇAMENTOS'!$B$6:$B$1005,"ENTRADA",'LANÇAMENTOS'!$D$6:$D$1005,$A69)) | I69: =IF($A69="","",SUMIFS('LANÇAMENTOS'!$G$6:$G$1005,'LANÇAMENTOS'!$I$6:$I$1005,($A$4*12+8),'LANÇAMENTOS'!$B$6:$B$1005,"ENTRADA",'LANÇAMENTOS'!$D$6:$D$1005,$A69)) | J69: =IF($A69="","",SUMIFS('LANÇAMENTOS'!$G$6:$G$1005,'LANÇAMENTOS'!$I$6:$I$1005,($A$4*12+9),'LANÇAMENTOS'!$B$6:$B$1005,"ENTRADA",'LANÇAMENTOS'!$D$6:$D$1005,$A69)) | K69: =IF($A69="","",SUMIFS('LANÇAMENTOS'!$G$6:$G$1005,'LANÇAMENTOS'!$I$6:$I$1005,($A$4*12+10),'LANÇAMENTOS'!$B$6:$B$1005,"ENTRADA",'LANÇAMENTOS'!$D$6:$D$1005,$A69)) | L69: =IF($A69="","",SUMIFS('LANÇAMENTOS'!$G$6:$G$1005,'LANÇAMENTOS'!$I$6:$I$1005,($A$4*12+11),'LANÇAMENTOS'!$B$6:$B$1005,"ENTRADA",'LANÇAMENTOS'!$D$6:$D$1005,$A69)) | M69: =IF($A69="","",SUMIFS('LANÇAMENTOS'!$G$6:$G$1005,'LANÇAMENTOS'!$I$6:$I$1005,($A$4*12+12),'LANÇAMENTOS'!$B$6:$B$1005,"ENTRADA",'LANÇAMENTOS'!$D$6:$D$1005,$A69)) | N69: =IF($A69="","",SUM(B69:M69))
A70: =IF(LISTAS!$B8="ENTRADA",LISTAS!$A8,"") | B70: =IF($A70="","",SUMIFS('LANÇAMENTOS'!$G$6:$G$1005,'LANÇAMENTOS'!$I$6:$I$1005,($A$4*12+1),'LANÇAMENTOS'!$B$6:$B$1005,"ENTRADA",'LANÇAMENTOS'!$D$6:$D$1005,$A70)) | C70: =IF($A70="","",SUMIFS('LANÇAMENTOS'!$G$6:$G$1005,'LANÇAMENTOS'!$I$6:$I$1005,($A$4*12+2),'LANÇAMENTOS'!$B$6:$B$1005,"ENTRADA",'LANÇAMENTOS'!$D$6:$D$1005,$A70)) | D70: =IF($A70="","",SUMIFS('LANÇAMENTOS'!$G$6:$G$1005,'LANÇAMENTOS'!$I$6:$I$1005,($A$4*12+3),'LANÇAMENTOS'!$B$6:$B$1005,"ENTRADA",'LANÇAMENTOS'!$D$6:$D$1005,$A70)) | E70: =IF($A70="","",SUMIFS('LANÇAMENTOS'!$G$6:$G$1005,'LANÇAMENTOS'!$I$6:$I$1005,($A$4*12+4),'LANÇAMENTOS'!$B$6:$B$1005,"ENTRADA",'LANÇAMENTOS'!$D$6:$D$1005,$A70)) | F70: =IF($A70="","",SUMIFS('LANÇAMENTOS'!$G$6:$G$1005,'LANÇAMENTOS'!$I$6:$I$1005,($A$4*12+5),'LANÇAMENTOS'!$B$6:$B$1005,"ENTRADA",'LANÇAMENTOS'!$D$6:$D$1005,$A70)) | G70: =IF($A70="","",SUMIFS('LANÇAMENTOS'!$G$6:$G$1005,'LANÇAMENTOS'!$I$6:$I$1005,($A$4*12+6),'LANÇAMENTOS'!$B$6:$B$1005,"ENTRADA",'LANÇAMENTOS'!$D$6:$D$1005,$A70)) | H70: =IF($A70="","",SUMIFS('LANÇAMENTOS'!$G$6:$G$1005,'LANÇAMENTOS'!$I$6:$I$1005,($A$4*12+7),'LANÇAMENTOS'!$B$6:$B$1005,"ENTRADA",'LANÇAMENTOS'!$D$6:$D$1005,$A70)) | I70: =IF($A70="","",SUMIFS('LANÇAMENTOS'!$G$6:$G$1005,'LANÇAMENTOS'!$I$6:$I$1005,($A$4*12+8),'LANÇAMENTOS'!$B$6:$B$1005,"ENTRADA",'LANÇAMENTOS'!$D$6:$D$1005,$A70)) | J70: =IF($A70="","",SUMIFS('LANÇAMENTOS'!$G$6:$G$1005,'LANÇAMENTOS'!$I$6:$I$1005,($A$4*12+9),'LANÇAMENTOS'!$B$6:$B$1005,"ENTRADA",'LANÇAMENTOS'!$D$6:$D$1005,$A70)) | K70: =IF($A70="","",SUMIFS('LANÇAMENTOS'!$G$6:$G$1005,'LANÇAMENTOS'!$I$6:$I$1005,($A$4*12+10),'LANÇAMENTOS'!$B$6:$B$1005,"ENTRADA",'LANÇAMENTOS'!$D$6:$D$1005,$A70)) | L70: =IF($A70="","",SUMIFS('LANÇAMENTOS'!$G$6:$G$1005,'LANÇAMENTOS'!$I$6:$I$1005,($A$4*12+11),'LANÇAMENTOS'!$B$6:$B$1005,"ENTRADA",'LANÇAMENTOS'!$D$6:$D$1005,$A70)) | M70: =IF($A70="","",SUMIFS('LANÇAMENTOS'!$G$6:$G$1005,'LANÇAMENTOS'!$I$6:$I$1005,($A$4*12+12),'LANÇAMENTOS'!$B$6:$B$1005,"ENTRADA",'LANÇAMENTOS'!$D$6:$D$1005,$A70)) | N70: =IF($A70="","",SUM(B70:M70))
A71: =IF(LISTAS!$B9="ENTRADA",LISTAS!$A9,"") | B71: =IF($A71="","",SUMIFS('LANÇAMENTOS'!$G$6:$G$1005,'LANÇAMENTOS'!$I$6:$I$1005,($A$4*12+1),'LANÇAMENTOS'!$B$6:$B$1005,"ENTRADA",'LANÇAMENTOS'!$D$6:$D$1005,$A71)) | C71: =IF($A71="","",SUMIFS('LANÇAMENTOS'!$G$6:$G$1005,'LANÇAMENTOS'!$I$6:$I$1005,($A$4*12+2),'LANÇAMENTOS'!$B$6:$B$1005,"ENTRADA",'LANÇAMENTOS'!$D$6:$D$1005,$A71)) | D71: =IF($A71="","",SUMIFS('LANÇAMENTOS'!$G$6:$G$1005,'LANÇAMENTOS'!$I$6:$I$1005,($A$4*12+3),'LANÇAMENTOS'!$B$6:$B$1005,"ENTRADA",'LANÇAMENTOS'!$D$6:$D$1005,$A71)) | E71: =IF($A71="","",SUMIFS('LANÇAMENTOS'!$G$6:$G$1005,'LANÇAMENTOS'!$I$6:$I$1005,($A$4*12+4),'LANÇAMENTOS'!$B$6:$B$1005,"ENTRADA",'LANÇAMENTOS'!$D$6:$D$1005,$A71)) | F71: =IF($A71="","",SUMIFS('LANÇAMENTOS'!$G$6:$G$1005,'LANÇAMENTOS'!$I$6:$I$1005,($A$4*12+5),'LANÇAMENTOS'!$B$6:$B$1005,"ENTRADA",'LANÇAMENTOS'!$D$6:$D$1005,$A71)) | G71: =IF($A71="","",SUMIFS('LANÇAMENTOS'!$G$6:$G$1005,'LANÇAMENTOS'!$I$6:$I$1005,($A$4*12+6),'LANÇAMENTOS'!$B$6:$B$1005,"ENTRADA",'LANÇAMENTOS'!$D$6:$D$1005,$A71)) | H71: =IF($A71="","",SUMIFS('LANÇAMENTOS'!$G$6:$G$1005,'LANÇAMENTOS'!$I$6:$I$1005,($A$4*12+7),'LANÇAMENTOS'!$B$6:$B$1005,"ENTRADA",'LANÇAMENTOS'!$D$6:$D$1005,$A71)) | I71: =IF($A71="","",SUMIFS('LANÇAMENTOS'!$G$6:$G$1005,'LANÇAMENTOS'!$I$6:$I$1005,($A$4*12+8),'LANÇAMENTOS'!$B$6:$B$1005,"ENTRADA",'LANÇAMENTOS'!$D$6:$D$1005,$A71)) | J71: =IF($A71="","",SUMIFS('LANÇAMENTOS'!$G$6:$G$1005,'LANÇAMENTOS'!$I$6:$I$1005,($A$4*12+9),'LANÇAMENTOS'!$B$6:$B$1005,"ENTRADA",'LANÇAMENTOS'!$D$6:$D$1005,$A71)) | K71: =IF($A71="","",SUMIFS('LANÇAMENTOS'!$G$6:$G$1005,'LANÇAMENTOS'!$I$6:$I$1005,($A$4*12+10),'LANÇAMENTOS'!$B$6:$B$1005,"ENTRADA",'LANÇAMENTOS'!$D$6:$D$1005,$A71)) | L71: =IF($A71="","",SUMIFS('LANÇAMENTOS'!$G$6:$G$1005,'LANÇAMENTOS'!$I$6:$I$1005,($A$4*12+11),'LANÇAMENTOS'!$B$6:$B$1005,"ENTRADA",'LANÇAMENTOS'!$D$6:$D$1005,$A71)) | M71: =IF($A71="","",SUMIFS('LANÇAMENTOS'!$G$6:$G$1005,'LANÇAMENTOS'!$I$6:$I$1005,($A$4*12+12),'LANÇAMENTOS'!$B$6:$B$1005,"ENTRADA",'LANÇAMENTOS'!$D$6:$D$1005,$A71)) | N71: =IF($A71="","",SUM(B71:M71))
A72: =IF(LISTAS!$B10="ENTRADA",LISTAS!$A10,"") | B72: =IF($A72="","",SUMIFS('LANÇAMENTOS'!$G$6:$G$1005,'LANÇAMENTOS'!$I$6:$I$1005,($A$4*12+1),'LANÇAMENTOS'!$B$6:$B$1005,"ENTRADA",'LANÇAMENTOS'!$D$6:$D$1005,$A72)) | C72: =IF($A72="","",SUMIFS('LANÇAMENTOS'!$G$6:$G$1005,'LANÇAMENTOS'!$I$6:$I$1005,($A$4*12+2),'LANÇAMENTOS'!$B$6:$B$1005,"ENTRADA",'LANÇAMENTOS'!$D$6:$D$1005,$A72)) | D72: =IF($A72="","",SUMIFS('LANÇAMENTOS'!$G$6:$G$1005,'LANÇAMENTOS'!$I$6:$I$1005,($A$4*12+3),'LANÇAMENTOS'!$B$6:$B$1005,"ENTRADA",'LANÇAMENTOS'!$D$6:$D$1005,$A72)) | E72: =IF($A72="","",SUMIFS('LANÇAMENTOS'!$G$6:$G$1005,'LANÇAMENTOS'!$I$6:$I$1005,($A$4*12+4),'LANÇAMENTOS'!$B$6:$B$1005,"ENTRADA",'LANÇAMENTOS'!$D$6:$D$1005,$A72)) | F72: =IF($A72="","",SUMIFS('LANÇAMENTOS'!$G$6:$G$1005,'LANÇAMENTOS'!$I$6:$I$1005,($A$4*12+5),'LANÇAMENTOS'!$B$6:$B$1005,"ENTRADA",'LANÇAMENTOS'!$D$6:$D$1005,$A72)) | G72: =IF($A72="","",SUMIFS('LANÇAMENTOS'!$G$6:$G$1005,'LANÇAMENTOS'!$I$6:$I$1005,($A$4*12+6),'LANÇAMENTOS'!$B$6:$B$1005,"ENTRADA",'LANÇAMENTOS'!$D$6:$D$1005,$A72)) | H72: =IF($A72="","",SUMIFS('LANÇAMENTOS'!$G$6:$G$1005,'LANÇAMENTOS'!$I$6:$I$1005,($A$4*12+7),'LANÇAMENTOS'!$B$6:$B$1005,"ENTRADA",'LANÇAMENTOS'!$D$6:$D$1005,$A72)) | I72: =IF($A72="","",SUMIFS('LANÇAMENTOS'!$G$6:$G$1005,'LANÇAMENTOS'!$I$6:$I$1005,($A$4*12+8),'LANÇAMENTOS'!$B$6:$B$1005,"ENTRADA",'LANÇAMENTOS'!$D$6:$D$1005,$A72)) | J72: =IF($A72="","",SUMIFS('LANÇAMENTOS'!$G$6:$G$1005,'LANÇAMENTOS'!$I$6:$I$1005,($A$4*12+9),'LANÇAMENTOS'!$B$6:$B$1005,"ENTRADA",'LANÇAMENTOS'!$D$6:$D$1005,$A72)) | K72: =IF($A72="","",SUMIFS('LANÇAMENTOS'!$G$6:$G$1005,'LANÇAMENTOS'!$I$6:$I$1005,($A$4*12+10),'LANÇAMENTOS'!$B$6:$B$1005,"ENTRADA",'LANÇAMENTOS'!$D$6:$D$1005,$A72)) | L72: =IF($A72="","",SUMIFS('LANÇAMENTOS'!$G$6:$G$1005,'LANÇAMENTOS'!$I$6:$I$1005,($A$4*12+11),'LANÇAMENTOS'!$B$6:$B$1005,"ENTRADA",'LANÇAMENTOS'!$D$6:$D$1005,$A72)) | M72: =IF($A72="","",SUMIFS('LANÇAMENTOS'!$G$6:$G$1005,'LANÇAMENTOS'!$I$6:$I$1005,($A$4*12+12),'LANÇAMENTOS'!$B$6:$B$1005,"ENTRADA",'LANÇAMENTOS'!$D$6:$D$1005,$A72)) | N72: =IF($A72="","",SUM(B72:M72))
A73: =IF(LISTAS!$B11="ENTRADA",LISTAS!$A11,"") | B73: =IF($A73="","",SUMIFS('LANÇAMENTOS'!$G$6:$G$1005,'LANÇAMENTOS'!$I$6:$I$1005,($A$4*12+1),'LANÇAMENTOS'!$B$6:$B$1005,"ENTRADA",'LANÇAMENTOS'!$D$6:$D$1005,$A73)) | C73: =IF($A73="","",SUMIFS('LANÇAMENTOS'!$G$6:$G$1005,'LANÇAMENTOS'!$I$6:$I$1005,($A$4*12+2),'LANÇAMENTOS'!$B$6:$B$1005,"ENTRADA",'LANÇAMENTOS'!$D$6:$D$1005,$A73)) | D73: =IF($A73="","",SUMIFS('LANÇAMENTOS'!$G$6:$G$1005,'LANÇAMENTOS'!$I$6:$I$1005,($A$4*12+3),'LANÇAMENTOS'!$B$6:$B$1005,"ENTRADA",'LANÇAMENTOS'!$D$6:$D$1005,$A73)) | E73: =IF($A73="","",SUMIFS('LANÇAMENTOS'!$G$6:$G$1005,'LANÇAMENTOS'!$I$6:$I$1005,($A$4*12+4),'LANÇAMENTOS'!$B$6:$B$1005,"ENTRADA",'LANÇAMENTOS'!$D$6:$D$1005,$A73)) | F73: =IF($A73="","",SUMIFS('LANÇAMENTOS'!$G$6:$G$1005,'LANÇAMENTOS'!$I$6:$I$1005,($A$4*12+5),'LANÇAMENTOS'!$B$6:$B$1005,"ENTRADA",'LANÇAMENTOS'!$D$6:$D$1005,$A73)) | G73: =IF($A73="","",SUMIFS('LANÇAMENTOS'!$G$6:$G$1005,'LANÇAMENTOS'!$I$6:$I$1005,($A$4*12+6),'LANÇAMENTOS'!$B$6:$B$1005,"ENTRADA",'LANÇAMENTOS'!$D$6:$D$1005,$A73)) | H73: =IF($A73="","",SUMIFS('LANÇAMENTOS'!$G$6:$G$1005,'LANÇAMENTOS'!$I$6:$I$1005,($A$4*12+7),'LANÇAMENTOS'!$B$6:$B$1005,"ENTRADA",'LANÇAMENTOS'!$D$6:$D$1005,$A73)) | I73: =IF($A73="","",SUMIFS('LANÇAMENTOS'!$G$6:$G$1005,'LANÇAMENTOS'!$I$6:$I$1005,($A$4*12+8),'LANÇAMENTOS'!$B$6:$B$1005,"ENTRADA",'LANÇAMENTOS'!$D$6:$D$1005,$A73)) | J73: =IF($A73="","",SUMIFS('LANÇAMENTOS'!$G$6:$G$1005,'LANÇAMENTOS'!$I$6:$I$1005,($A$4*12+9),'LANÇAMENTOS'!$B$6:$B$1005,"ENTRADA",'LANÇAMENTOS'!$D$6:$D$1005,$A73)) | K73: =IF($A73="","",SUMIFS('LANÇAMENTOS'!$G$6:$G$1005,'LANÇAMENTOS'!$I$6:$I$1005,($A$4*12+10),'LANÇAMENTOS'!$B$6:$B$1005,"ENTRADA",'LANÇAMENTOS'!$D$6:$D$1005,$A73)) | L73: =IF($A73="","",SUMIFS('LANÇAMENTOS'!$G$6:$G$1005,'LANÇAMENTOS'!$I$6:$I$1005,($A$4*12+11),'LANÇAMENTOS'!$B$6:$B$1005,"ENTRADA",'LANÇAMENTOS'!$D$6:$D$1005,$A73)) | M73: =IF($A73="","",SUMIFS('LANÇAMENTOS'!$G$6:$G$1005,'LANÇAMENTOS'!$I$6:$I$1005,($A$4*12+12),'LANÇAMENTOS'!$B$6:$B$1005,"ENTRADA",'LANÇAMENTOS'!$D$6:$D$1005,$A73)) | N73: =IF($A73="","",SUM(B73:M73))
A74: =IF(LISTAS!$B12="ENTRADA",LISTAS!$A12,"") | B74: =IF($A74="","",SUMIFS('LANÇAMENTOS'!$G$6:$G$1005,'LANÇAMENTOS'!$I$6:$I$1005,($A$4*12+1),'LANÇAMENTOS'!$B$6:$B$1005,"ENTRADA",'LANÇAMENTOS'!$D$6:$D$1005,$A74)) | C74: =IF($A74="","",SUMIFS('LANÇAMENTOS'!$G$6:$G$1005,'LANÇAMENTOS'!$I$6:$I$1005,($A$4*12+2),'LANÇAMENTOS'!$B$6:$B$1005,"ENTRADA",'LANÇAMENTOS'!$D$6:$D$1005,$A74)) | D74: =IF($A74="","",SUMIFS('LANÇAMENTOS'!$G$6:$G$1005,'LANÇAMENTOS'!$I$6:$I$1005,($A$4*12+3),'LANÇAMENTOS'!$B$6:$B$1005,"ENTRADA",'LANÇAMENTOS'!$D$6:$D$1005,$A74)) | E74: =IF($A74="","",SUMIFS('LANÇAMENTOS'!$G$6:$G$1005,'LANÇAMENTOS'!$I$6:$I$1005,($A$4*12+4),'LANÇAMENTOS'!$B$6:$B$1005,"ENTRADA",'LANÇAMENTOS'!$D$6:$D$1005,$A74)) | F74: =IF($A74="","",SUMIFS('LANÇAMENTOS'!$G$6:$G$1005,'LANÇAMENTOS'!$I$6:$I$1005,($A$4*12+5),'LANÇAMENTOS'!$B$6:$B$1005,"ENTRADA",'LANÇAMENTOS'!$D$6:$D$1005,$A74)) | G74: =IF($A74="","",SUMIFS('LANÇAMENTOS'!$G$6:$G$1005,'LANÇAMENTOS'!$I$6:$I$1005,($A$4*12+6),'LANÇAMENTOS'!$B$6:$B$1005,"ENTRADA",'LANÇAMENTOS'!$D$6:$D$1005,$A74)) | H74: =IF($A74="","",SUMIFS('LANÇAMENTOS'!$G$6:$G$1005,'LANÇAMENTOS'!$I$6:$I$1005,($A$4*12+7),'LANÇAMENTOS'!$B$6:$B$1005,"ENTRADA",'LANÇAMENTOS'!$D$6:$D$1005,$A74)) | I74: =IF($A74="","",SUMIFS('LANÇAMENTOS'!$G$6:$G$1005,'LANÇAMENTOS'!$I$6:$I$1005,($A$4*12+8),'LANÇAMENTOS'!$B$6:$B$1005,"ENTRADA",'LANÇAMENTOS'!$D$6:$D$1005,$A74)) | J74: =IF($A74="","",SUMIFS('LANÇAMENTOS'!$G$6:$G$1005,'LANÇAMENTOS'!$I$6:$I$1005,($A$4*12+9),'LANÇAMENTOS'!$B$6:$B$1005,"ENTRADA",'LANÇAMENTOS'!$D$6:$D$1005,$A74)) | K74: =IF($A74="","",SUMIFS('LANÇAMENTOS'!$G$6:$G$1005,'LANÇAMENTOS'!$I$6:$I$1005,($A$4*12+10),'LANÇAMENTOS'!$B$6:$B$1005,"ENTRADA",'LANÇAMENTOS'!$D$6:$D$1005,$A74)) | L74: =IF($A74="","",SUMIFS('LANÇAMENTOS'!$G$6:$G$1005,'LANÇAMENTOS'!$I$6:$I$1005,($A$4*12+11),'LANÇAMENTOS'!$B$6:$B$1005,"ENTRADA",'LANÇAMENTOS'!$D$6:$D$1005,$A74)) | M74: =IF($A74="","",SUMIFS('LANÇAMENTOS'!$G$6:$G$1005,'LANÇAMENTOS'!$I$6:$I$1005,($A$4*12+12),'LANÇAMENTOS'!$B$6:$B$1005,"ENTRADA",'LANÇAMENTOS'!$D$6:$D$1005,$A74)) | N74: =IF($A74="","",SUM(B74:M74))
A75: =IF(LISTAS!$B13="ENTRADA",LISTAS!$A13,"") | B75: =IF($A75="","",SUMIFS('LANÇAMENTOS'!$G$6:$G$1005,'LANÇAMENTOS'!$I$6:$I$1005,($A$4*12+1),'LANÇAMENTOS'!$B$6:$B$1005,"ENTRADA",'LANÇAMENTOS'!$D$6:$D$1005,$A75)) | C75: =IF($A75="","",SUMIFS('LANÇAMENTOS'!$G$6:$G$1005,'LANÇAMENTOS'!$I$6:$I$1005,($A$4*12+2),'LANÇAMENTOS'!$B$6:$B$1005,"ENTRADA",'LANÇAMENTOS'!$D$6:$D$1005,$A75)) | D75: =IF($A75="","",SUMIFS('LANÇAMENTOS'!$G$6:$G$1005,'LANÇAMENTOS'!$I$6:$I$1005,($A$4*12+3),'LANÇAMENTOS'!$B$6:$B$1005,"ENTRADA",'LANÇAMENTOS'!$D$6:$D$1005,$A75)) | E75: =IF($A75="","",SUMIFS('LANÇAMENTOS'!$G$6:$G$1005,'LANÇAMENTOS'!$I$6:$I$1005,($A$4*12+4),'LANÇAMENTOS'!$B$6:$B$1005,"ENTRADA",'LANÇAMENTOS'!$D$6:$D$1005,$A75)) | F75: =IF($A75="","",SUMIFS('LANÇAMENTOS'!$G$6:$G$1005,'LANÇAMENTOS'!$I$6:$I$1005,($A$4*12+5),'LANÇAMENTOS'!$B$6:$B$1005,"ENTRADA",'LANÇAMENTOS'!$D$6:$D$1005,$A75)) | G75: =IF($A75="","",SUMIFS('LANÇAMENTOS'!$G$6:$G$1005,'LANÇAMENTOS'!$I$6:$I$1005,($A$4*12+6),'LANÇAMENTOS'!$B$6:$B$1005,"ENTRADA",'LANÇAMENTOS'!$D$6:$D$1005,$A75)) | H75: =IF($A75="","",SUMIFS('LANÇAMENTOS'!$G$6:$G$1005,'LANÇAMENTOS'!$I$6:$I$1005,($A$4*12+7),'LANÇAMENTOS'!$B$6:$B$1005,"ENTRADA",'LANÇAMENTOS'!$D$6:$D$1005,$A75)) | I75: =IF($A75="","",SUMIFS('LANÇAMENTOS'!$G$6:$G$1005,'LANÇAMENTOS'!$I$6:$I$1005,($A$4*12+8),'LANÇAMENTOS'!$B$6:$B$1005,"ENTRADA",'LANÇAMENTOS'!$D$6:$D$1005,$A75)) | J75: =IF($A75="","",SUMIFS('LANÇAMENTOS'!$G$6:$G$1005,'LANÇAMENTOS'!$I$6:$I$1005,($A$4*12+9),'LANÇAMENTOS'!$B$6:$B$1005,"ENTRADA",'LANÇAMENTOS'!$D$6:$D$1005,$A75)) | K75: =IF($A75="","",SUMIFS('LANÇAMENTOS'!$G$6:$G$1005,'LANÇAMENTOS'!$I$6:$I$1005,($A$4*12+10),'LANÇAMENTOS'!$B$6:$B$1005,"ENTRADA",'LANÇAMENTOS'!$D$6:$D$1005,$A75)) | L75: =IF($A75="","",SUMIFS('LANÇAMENTOS'!$G$6:$G$1005,'LANÇAMENTOS'!$I$6:$I$1005,($A$4*12+11),'LANÇAMENTOS'!$B$6:$B$1005,"ENTRADA",'LANÇAMENTOS'!$D$6:$D$1005,$A75)) | M75: =IF($A75="","",SUMIFS('LANÇAMENTOS'!$G$6:$G$1005,'LANÇAMENTOS'!$I$6:$I$1005,($A$4*12+12),'LANÇAMENTOS'!$B$6:$B$1005,"ENTRADA",'LANÇAMENTOS'!$D$6:$D$1005,$A75)) | N75: =IF($A75="","",SUM(B75:M75))
A76: =IF(LISTAS!$B14="ENTRADA",LISTAS!$A14,"") | B76: =IF($A76="","",SUMIFS('LANÇAMENTOS'!$G$6:$G$1005,'LANÇAMENTOS'!$I$6:$I$1005,($A$4*12+1),'LANÇAMENTOS'!$B$6:$B$1005,"ENTRADA",'LANÇAMENTOS'!$D$6:$D$1005,$A76)) | C76: =IF($A76="","",SUMIFS('LANÇAMENTOS'!$G$6:$G$1005,'LANÇAMENTOS'!$I$6:$I$1005,($A$4*12+2),'LANÇAMENTOS'!$B$6:$B$1005,"ENTRADA",'LANÇAMENTOS'!$D$6:$D$1005,$A76)) | D76: =IF($A76="","",SUMIFS('LANÇAMENTOS'!$G$6:$G$1005,'LANÇAMENTOS'!$I$6:$I$1005,($A$4*12+3),'LANÇAMENTOS'!$B$6:$B$1005,"ENTRADA",'LANÇAMENTOS'!$D$6:$D$1005,$A76)) | E76: =IF($A76="","",SUMIFS('LANÇAMENTOS'!$G$6:$G$1005,'LANÇAMENTOS'!$I$6:$I$1005,($A$4*12+4),'LANÇAMENTOS'!$B$6:$B$1005,"ENTRADA",'LANÇAMENTOS'!$D$6:$D$1005,$A76)) | F76: =IF($A76="","",SUMIFS('LANÇAMENTOS'!$G$6:$G$1005,'LANÇAMENTOS'!$I$6:$I$1005,($A$4*12+5),'LANÇAMENTOS'!$B$6:$B$1005,"ENTRADA",'LANÇAMENTOS'!$D$6:$D$1005,$A76)) | G76: =IF($A76="","",SUMIFS('LANÇAMENTOS'!$G$6:$G$1005,'LANÇAMENTOS'!$I$6:$I$1005,($A$4*12+6),'LANÇAMENTOS'!$B$6:$B$1005,"ENTRADA",'LANÇAMENTOS'!$D$6:$D$1005,$A76)) | H76: =IF($A76="","",SUMIFS('LANÇAMENTOS'!$G$6:$G$1005,'LANÇAMENTOS'!$I$6:$I$1005,($A$4*12+7),'LANÇAMENTOS'!$B$6:$B$1005,"ENTRADA",'LANÇAMENTOS'!$D$6:$D$1005,$A76)) | I76: =IF($A76="","",SUMIFS('LANÇAMENTOS'!$G$6:$G$1005,'LANÇAMENTOS'!$I$6:$I$1005,($A$4*12+8),'LANÇAMENTOS'!$B$6:$B$1005,"ENTRADA",'LANÇAMENTOS'!$D$6:$D$1005,$A76)) | J76: =IF($A76="","",SUMIFS('LANÇAMENTOS'!$G$6:$G$1005,'LANÇAMENTOS'!$I$6:$I$1005,($A$4*12+9),'LANÇAMENTOS'!$B$6:$B$1005,"ENTRADA",'LANÇAMENTOS'!$D$6:$D$1005,$A76)) | K76: =IF($A76="","",SUMIFS('LANÇAMENTOS'!$G$6:$G$1005,'LANÇAMENTOS'!$I$6:$I$1005,($A$4*12+10),'LANÇAMENTOS'!$B$6:$B$1005,"ENTRADA",'LANÇAMENTOS'!$D$6:$D$1005,$A76)) | L76: =IF($A76="","",SUMIFS('LANÇAMENTOS'!$G$6:$G$1005,'LANÇAMENTOS'!$I$6:$I$1005,($A$4*12+11),'LANÇAMENTOS'!$B$6:$B$1005,"ENTRADA",'LANÇAMENTOS'!$D$6:$D$1005,$A76)) | M76: =IF($A76="","",SUMIFS('LANÇAMENTOS'!$G$6:$G$1005,'LANÇAMENTOS'!$I$6:$I$1005,($A$4*12+12),'LANÇAMENTOS'!$B$6:$B$1005,"ENTRADA",'LANÇAMENTOS'!$D$6:$D$1005,$A76)) | N76: =IF($A76="","",SUM(B76:M76))
A77: =IF(LISTAS!$B15="ENTRADA",LISTAS!$A15,"") | B77: =IF($A77="","",SUMIFS('LANÇAMENTOS'!$G$6:$G$1005,'LANÇAMENTOS'!$I$6:$I$1005,($A$4*12+1),'LANÇAMENTOS'!$B$6:$B$1005,"ENTRADA",'LANÇAMENTOS'!$D$6:$D$1005,$A77)) | C77: =IF($A77="","",SUMIFS('LANÇAMENTOS'!$G$6:$G$1005,'LANÇAMENTOS'!$I$6:$I$1005,($A$4*12+2),'LANÇAMENTOS'!$B$6:$B$1005,"ENTRADA",'LANÇAMENTOS'!$D$6:$D$1005,$A77)) | D77: =IF($A77="","",SUMIFS('LANÇAMENTOS'!$G$6:$G$1005,'LANÇAMENTOS'!$I$6:$I$1005,($A$4*12+3),'LANÇAMENTOS'!$B$6:$B$1005,"ENTRADA",'LANÇAMENTOS'!$D$6:$D$1005,$A77)) | E77: =IF($A77="","",SUMIFS('LANÇAMENTOS'!$G$6:$G$1005,'LANÇAMENTOS'!$I$6:$I$1005,($A$4*12+4),'LANÇAMENTOS'!$B$6:$B$1005,"ENTRADA",'LANÇAMENTOS'!$D$6:$D$1005,$A77)) | F77: =IF($A77="","",SUMIFS('LANÇAMENTOS'!$G$6:$G$1005,'LANÇAMENTOS'!$I$6:$I$1005,($A$4*12+5),'LANÇAMENTOS'!$B$6:$B$1005,"ENTRADA",'LANÇAMENTOS'!$D$6:$D$1005,$A77)) | G77: =IF($A77="","",SUMIFS('LANÇAMENTOS'!$G$6:$G$1005,'LANÇAMENTOS'!$I$6:$I$1005,($A$4*12+6),'LANÇAMENTOS'!$B$6:$B$1005,"ENTRADA",'LANÇAMENTOS'!$D$6:$D$1005,$A77)) | H77: =IF($A77="","",SUMIFS('LANÇAMENTOS'!$G$6:$G$1005,'LANÇAMENTOS'!$I$6:$I$1005,($A$4*12+7),'LANÇAMENTOS'!$B$6:$B$1005,"ENTRADA",'LANÇAMENTOS'!$D$6:$D$1005,$A77)) | I77: =IF($A77="","",SUMIFS('LANÇAMENTOS'!$G$6:$G$1005,'LANÇAMENTOS'!$I$6:$I$1005,($A$4*12+8),'LANÇAMENTOS'!$B$6:$B$1005,"ENTRADA",'LANÇAMENTOS'!$D$6:$D$1005,$A77)) | J77: =IF($A77="","",SUMIFS('LANÇAMENTOS'!$G$6:$G$1005,'LANÇAMENTOS'!$I$6:$I$1005,($A$4*12+9),'LANÇAMENTOS'!$B$6:$B$1005,"ENTRADA",'LANÇAMENTOS'!$D$6:$D$1005,$A77)) | K77: =IF($A77="","",SUMIFS('LANÇAMENTOS'!$G$6:$G$1005,'LANÇAMENTOS'!$I$6:$I$1005,($A$4*12+10),'LANÇAMENTOS'!$B$6:$B$1005,"ENTRADA",'LANÇAMENTOS'!$D$6:$D$1005,$A77)) | L77: =IF($A77="","",SUMIFS('LANÇAMENTOS'!$G$6:$G$1005,'LANÇAMENTOS'!$I$6:$I$1005,($A$4*12+11),'LANÇAMENTOS'!$B$6:$B$1005,"ENTRADA",'LANÇAMENTOS'!$D$6:$D$1005,$A77)) | M77: =IF($A77="","",SUMIFS('LANÇAMENTOS'!$G$6:$G$1005,'LANÇAMENTOS'!$I$6:$I$1005,($A$4*12+12),'LANÇAMENTOS'!$B$6:$B$1005,"ENTRADA",'LANÇAMENTOS'!$D$6:$D$1005,$A77)) | N77: =IF($A77="","",SUM(B77:M77))
A78: =IF(LISTAS!$B16="ENTRADA",LISTAS!$A16,"") | B78: =IF($A78="","",SUMIFS('LANÇAMENTOS'!$G$6:$G$1005,'LANÇAMENTOS'!$I$6:$I$1005,($A$4*12+1),'LANÇAMENTOS'!$B$6:$B$1005,"ENTRADA",'LANÇAMENTOS'!$D$6:$D$1005,$A78)) | C78: =IF($A78="","",SUMIFS('LANÇAMENTOS'!$G$6:$G$1005,'LANÇAMENTOS'!$I$6:$I$1005,($A$4*12+2),'LANÇAMENTOS'!$B$6:$B$1005,"ENTRADA",'LANÇAMENTOS'!$D$6:$D$1005,$A78)) | D78: =IF($A78="","",SUMIFS('LANÇAMENTOS'!$G$6:$G$1005,'LANÇAMENTOS'!$I$6:$I$1005,($A$4*12+3),'LANÇAMENTOS'!$B$6:$B$1005,"ENTRADA",'LANÇAMENTOS'!$D$6:$D$1005,$A78)) | E78: =IF($A78="","",SUMIFS('LANÇAMENTOS'!$G$6:$G$1005,'LANÇAMENTOS'!$I$6:$I$1005,($A$4*12+4),'LANÇAMENTOS'!$B$6:$B$1005,"ENTRADA",'LANÇAMENTOS'!$D$6:$D$1005,$A78)) | F78: =IF($A78="","",SUMIFS('LANÇAMENTOS'!$G$6:$G$1005,'LANÇAMENTOS'!$I$6:$I$1005,($A$4*12+5),'LANÇAMENTOS'!$B$6:$B$1005,"ENTRADA",'LANÇAMENTOS'!$D$6:$D$1005,$A78)) | G78: =IF($A78="","",SUMIFS('LANÇAMENTOS'!$G$6:$G$1005,'LANÇAMENTOS'!$I$6:$I$1005,($A$4*12+6),'LANÇAMENTOS'!$B$6:$B$1005,"ENTRADA",'LANÇAMENTOS'!$D$6:$D$1005,$A78)) | H78: =IF($A78="","",SUMIFS('LANÇAMENTOS'!$G$6:$G$1005,'LANÇAMENTOS'!$I$6:$I$1005,($A$4*12+7),'LANÇAMENTOS'!$B$6:$B$1005,"ENTRADA",'LANÇAMENTOS'!$D$6:$D$1005,$A78)) | I78: =IF($A78="","",SUMIFS('LANÇAMENTOS'!$G$6:$G$1005,'LANÇAMENTOS'!$I$6:$I$1005,($A$4*12+8),'LANÇAMENTOS'!$B$6:$B$1005,"ENTRADA",'LANÇAMENTOS'!$D$6:$D$1005,$A78)) | J78: =IF($A78="","",SUMIFS('LANÇAMENTOS'!$G$6:$G$1005,'LANÇAMENTOS'!$I$6:$I$1005,($A$4*12+9),'LANÇAMENTOS'!$B$6:$B$1005,"ENTRADA",'LANÇAMENTOS'!$D$6:$D$1005,$A78)) | K78: =IF($A78="","",SUMIFS('LANÇAMENTOS'!$G$6:$G$1005,'LANÇAMENTOS'!$I$6:$I$1005,($A$4*12+10),'LANÇAMENTOS'!$B$6:$B$1005,"ENTRADA",'LANÇAMENTOS'!$D$6:$D$1005,$A78)) | L78: =IF($A78="","",SUMIFS('LANÇAMENTOS'!$G$6:$G$1005,'LANÇAMENTOS'!$I$6:$I$1005,($A$4*12+11),'LANÇAMENTOS'!$B$6:$B$1005,"ENTRADA",'LANÇAMENTOS'!$D$6:$D$1005,$A78)) | M78: =IF($A78="","",SUMIFS('LANÇAMENTOS'!$G$6:$G$1005,'LANÇAMENTOS'!$I$6:$I$1005,($A$4*12+12),'LANÇAMENTOS'!$B$6:$B$1005,"ENTRADA",'LANÇAMENTOS'!$D$6:$D$1005,$A78)) | N78: =IF($A78="","",SUM(B78:M78))
A79: =IF(LISTAS!$B17="ENTRADA",LISTAS!$A17,"") | B79: =IF($A79="","",SUMIFS('LANÇAMENTOS'!$G$6:$G$1005,'LANÇAMENTOS'!$I$6:$I$1005,($A$4*12+1),'LANÇAMENTOS'!$B$6:$B$1005,"ENTRADA",'LANÇAMENTOS'!$D$6:$D$1005,$A79)) | C79: =IF($A79="","",SUMIFS('LANÇAMENTOS'!$G$6:$G$1005,'LANÇAMENTOS'!$I$6:$I$1005,($A$4*12+2),'LANÇAMENTOS'!$B$6:$B$1005,"ENTRADA",'LANÇAMENTOS'!$D$6:$D$1005,$A79)) | D79: =IF($A79="","",SUMIFS('LANÇAMENTOS'!$G$6:$G$1005,'LANÇAMENTOS'!$I$6:$I$1005,($A$4*12+3),'LANÇAMENTOS'!$B$6:$B$1005,"ENTRADA",'LANÇAMENTOS'!$D$6:$D$1005,$A79)) | E79: =IF($A79="","",SUMIFS('LANÇAMENTOS'!$G$6:$G$1005,'LANÇAMENTOS'!$I$6:$I$1005,($A$4*12+4),'LANÇAMENTOS'!$B$6:$B$1005,"ENTRADA",'LANÇAMENTOS'!$D$6:$D$1005,$A79)) | F79: =IF($A79="","",SUMIFS('LANÇAMENTOS'!$G$6:$G$1005,'LANÇAMENTOS'!$I$6:$I$1005,($A$4*12+5),'LANÇAMENTOS'!$B$6:$B$1005,"ENTRADA",'LANÇAMENTOS'!$D$6:$D$1005,$A79)) | G79: =IF($A79="","",SUMIFS('LANÇAMENTOS'!$G$6:$G$1005,'LANÇAMENTOS'!$I$6:$I$1005,($A$4*12+6),'LANÇAMENTOS'!$B$6:$B$1005,"ENTRADA",'LANÇAMENTOS'!$D$6:$D$1005,$A79)) | H79: =IF($A79="","",SUMIFS('LANÇAMENTOS'!$G$6:$G$1005,'LANÇAMENTOS'!$I$6:$I$1005,($A$4*12+7),'LANÇAMENTOS'!$B$6:$B$1005,"ENTRADA",'LANÇAMENTOS'!$D$6:$D$1005,$A79)) | I79: =IF($A79="","",SUMIFS('LANÇAMENTOS'!$G$6:$G$1005,'LANÇAMENTOS'!$I$6:$I$1005,($A$4*12+8),'LANÇAMENTOS'!$B$6:$B$1005,"ENTRADA",'LANÇAMENTOS'!$D$6:$D$1005,$A79)) | J79: =IF($A79="","",SUMIFS('LANÇAMENTOS'!$G$6:$G$1005,'LANÇAMENTOS'!$I$6:$I$1005,($A$4*12+9),'LANÇAMENTOS'!$B$6:$B$1005,"ENTRADA",'LANÇAMENTOS'!$D$6:$D$1005,$A79)) | K79: =IF($A79="","",SUMIFS('LANÇAMENTOS'!$G$6:$G$1005,'LANÇAMENTOS'!$I$6:$I$1005,($A$4*12+10),'LANÇAMENTOS'!$B$6:$B$1005,"ENTRADA",'LANÇAMENTOS'!$D$6:$D$1005,$A79)) | L79: =IF($A79="","",SUMIFS('LANÇAMENTOS'!$G$6:$G$1005,'LANÇAMENTOS'!$I$6:$I$1005,($A$4*12+11),'LANÇAMENTOS'!$B$6:$B$1005,"ENTRADA",'LANÇAMENTOS'!$D$6:$D$1005,$A79)) | M79: =IF($A79="","",SUMIFS('LANÇAMENTOS'!$G$6:$G$1005,'LANÇAMENTOS'!$I$6:$I$1005,($A$4*12+12),'LANÇAMENTOS'!$B$6:$B$1005,"ENTRADA",'LANÇAMENTOS'!$D$6:$D$1005,$A79)) | N79: =IF($A79="","",SUM(B79:M79))
... A107: =IF(LISTAS!$B45="ENTRADA",LISTAS!$A45,"") | B107: =IF($A107="","",SUMIFS('LANÇAMENTOS'!$G$6:$G$1005,'LANÇAMENTOS'!$I$6:$I$1005,($A$4*12+1),'LANÇAMENTOS'!$B$6:$B$1005,"ENTRADA",'LANÇAMENTOS'!$D$6:$D$1005,$A107)) | C107: =IF($A107="","",SUMIFS('LANÇAMENTOS'!$G$6:$G$1005,'LANÇAMENTOS'!$I$6:$I$1005,($A$4*12+2),'LANÇAMENTOS'!$B$6:$B$1005,"ENTRADA",'LANÇAMENTOS'!$D$6:$D$1005,$A107)) | D107: =IF($A107="","",SUMIFS('LANÇAMENTOS'!$G$6:$G$1005,'LANÇAMENTOS'!$I$6:$I$1005,($A$4*12+3),'LANÇAMENTOS'!$B$6:$B$1005,"ENTRADA",'LANÇAMENTOS'!$D$6:$D$1005,$A107)) | E107: =IF($A107="","",SUMIFS('LANÇAMENTOS'!$G$6:$G$1005,'LANÇAMENTOS'!$I$6:$I$1005,($A$4*12+4),'LANÇAMENTOS'!$B$6:$B$1005,"ENTRADA",'LANÇAMENTOS'!$D$6:$D$1005,$A107)) | F107: =IF($A107="","",SUMIFS('LANÇAMENTOS'!$G$6:$G$1005,'LANÇAMENTOS'!$I$6:$I$1005,($A$4*12+5),'LANÇAMENTOS'!$B$6:$B$1005,"ENTRADA",'LANÇAMENTOS'!$D$6:$D$1005,$A107)) | G107: =IF($A107="","",SUMIFS('LANÇAMENTOS'!$G$6:$G$1005,'LANÇAMENTOS'!$I$6:$I$1005,($A$4*12+6),'LANÇAMENTOS'!$B$6:$B$1005,"ENTRADA",'LANÇAMENTOS'!$D$6:$D$1005,$A107)) | H107: =IF($A107="","",SUMIFS('LANÇAMENTOS'!$G$6:$G$1005,'LANÇAMENTOS'!$I$6:$I$1005,($A$4*12+7),'LANÇAMENTOS'!$B$6:$B$1005,"ENTRADA",'LANÇAMENTOS'!$D$6:$D$1005,$A107)) | I107: =IF($A107="","",SUMIFS('LANÇAMENTOS'!$G$6:$G$1005,'LANÇAMENTOS'!$I$6:$I$1005,($A$4*12+8),'LANÇAMENTOS'!$B$6:$B$1005,"ENTRADA",'LANÇAMENTOS'!$D$6:$D$1005,$A107)) | J107: =IF($A107="","",SUMIFS('LANÇAMENTOS'!$G$6:$G$1005,'LANÇAMENTOS'!$I$6:$I$1005,($A$4*12+9),'LANÇAMENTOS'!$B$6:$B$1005,"ENTRADA",'LANÇAMENTOS'!$D$6:$D$1005,$A107)) | K107: =IF($A107="","",SUMIFS('LANÇAMENTOS'!$G$6:$G$1005,'LANÇAMENTOS'!$I$6:$I$1005,($A$4*12+10),'LANÇAMENTOS'!$B$6:$B$1005,"ENTRADA",'LANÇAMENTOS'!$D$6:$D$1005,$A107)) | L107: =IF($A107="","",SUMIFS('LANÇAMENTOS'!$G$6:$G$1005,'LANÇAMENTOS'!$I$6:$I$1005,($A$4*12+11),'LANÇAMENTOS'!$B$6:$B$1005,"ENTRADA",'LANÇAMENTOS'!$D$6:$D$1005,$A107)) | M107: =IF($A107="","",SUMIFS('LANÇAMENTOS'!$G$6:$G$1005,'LANÇAMENTOS'!$I$6:$I$1005,($A$4*12+12),'LANÇAMENTOS'!$B$6:$B$1005,"ENTRADA",'LANÇAMENTOS'!$D$6:$D$1005,$A107)) | N107: =IF($A107="","",SUM(B107:M107))
A108: TOTAL ENTRADAS | B108: =SUM(B68:B107) | C108: =SUM(C68:C107) | D108: =SUM(D68:D107) | E108: =SUM(E68:E107) | F108: =SUM(F68:F107) | G108: =SUM(G68:G107) | H108: =SUM(H68:H107) | I108: =SUM(I68:I107) | ... N108: =SUM(N68:N107)
A111: CONFERÊNCIA DO ANO
A112: Entradas: total do ano menos soma das categorias | D112: =D18-N108
A113: Saídas: total do ano menos soma das categorias | D113: =G18-N63
A114: Saldo acumulado bate com a soma dos resultados | D114: =J18-I18

Sheet EXEMPLO
A1: EXEMPLO — COMO PREENCHER CADA CASO
A2: Esta aba é só modelo. Nada aqui entra nas contas. Pode apagar a aba quando não precisar mais.
A4: MODELOS PARA A ABA LANÇAMENTOS
A5: Data | B5: Tipo | C5: Status | D5: Categoria | E5: Descrição | F5: Meio de pagamento | G5: Valor (Gs.) | H5: Por que assim
A6: 46027 | B6: ENTRADA | C6: REALIZADO | D6: Salário | E6: Salário de janeiro | F6: Conta corrente | G6: 8500000 | H6: Dinheiro que já caiu na conta. Status REALIZADO.
A7: 46032 | B7: SAÍDA | C7: REALIZADO | D7: Alimentação | E7: Supermercado da semana | F7: Débito | G7: 780000 | H7: Saída paga no débito. Sai da conta na hora, então é lançamento normal.
A8: 46034 | B8: SAÍDA | C8: REALIZADO | D8: Serviços (luz, água, internet) | E8: Conta de luz | F8: Boleto | G8: 320000 | H8: Boleto pago. Também é lançamento normal.
A9: 46058 | B9: ENTRADA | C9: PROJETADO | D9: Salário | E9: Salário de fevereiro | F9: Conta corrente | G9: 8500000 | H9: Ainda não caiu. Status PROJETADO para já aparecer na projeção.
A10: 46068 | B10: SAÍDA | C10: PROJETADO | D10: Moradia | E10: Aluguel de fevereiro | F10: Transferência | G10: 2500000 | H10: Gasto certo que ainda vai acontecer. PROJETADO.
A11: 46042 | B11: ENTRADA | C11: REALIZADO | D11: Venda | E11: Venda de móvel usado | F11: Dinheiro | G11: 1200000 | H11: Entrada em espécie. Meio = Dinheiro.
A14: MODELOS PARA A ABA CARTÕES
A15: Data da compra | B15: Cartão | C15: Descrição | D15: Categoria | E15: Valor total (Gs.) | F15: Nº parcelas | G15: 1ª parcela | H15: O que a planilha faz
A16: 46040 | B16: Cartão 1 | C16: Geladeira | D16: Manutenção | E16: 6000000 | F16: 12 | H16: Deixe a 1ª parcela em branco: a planilha começa em fev/2026 e cria 12 parcelas de Gs. 500.000.
A17: 46083 | B17: Cartão 1 | C17: Passagem aérea | D17: Lazer | E17: 4500000 | F17: 6 | G17: 46113 | H17: Aqui a 1ª parcela foi digitada. Vão 6 parcelas de Gs. 750.000, de abr a set/2026.
A18: 46061 | B18: Cartão 2 | C18: Farmácia | D18: Saúde | E18: 350000 | F18: 1 | H18: Compra à vista no crédito: 1 parcela. Cai inteira no mês seguinte.
A19: 46146 | B19: Cartão 2 | C19: Notebook | D19: Educação | E19: 10000000 | F19: 7 | H19: Gs. 10.000.000 em 7x não dá número redondo. A planilha ajusta a última parcela para fechar exato.
A22: CASOS QUE CONFUNDEM — O QUE FAZER
A23: Situação | B23: O que fazer
A24: Paguei a fatura do cartão | B24: NÃO lance nada. A parcela já foi contada no mês em que venceu. Lançar de novo contaria o mesmo gasto duas vezes.
A25: Comprei no cartão e paguei à vista (1x) | B25: Lance na aba CARTÕES com Nº de parcelas = 1.
A26: Comprei no débito | B26: Lance na aba LANÇAMENTOS como SAÍDA, Meio = Débito. Débito não é cartão de crédito.
A27: Passei dinheiro da conta para a poupança | B27: Não lance. Transferência entre suas contas não é entrada nem saída.
A28: Recebi um empréstimo | B28: ENTRADA, categoria Empréstimo recebido. As parcelas que você vai pagar são SAÍDA em Empréstimo / Financiamento, uma por mês, com status PROJETADO.
A29: Parcelei uma compra e depois quitei tudo | B29: Mude o Nº de parcelas para o número que você realmente pagou e ajuste o Valor total. A planilha recalcula sozinha.
A30: Errei um lançamento | B30: Selecione a linha inteira e aperte DELETE para limpar. Nunca use Excluir linha, senão as fórmulas automáticas somem.

Sheet PARCELAS
A1: PARCELAS (automático) — NÃO MEXA NESTA ABA
A2: Cada linha é uma compra da aba CARTÕES. As colunas espalham as parcelas pelos meses.
A5: Compra | B5: Valor no mês do RESUMO MENSAL | C5: Mês 1 | D5: Mês 2 | E5: Mês 3 | F5: Mês 4 | G5: Mês 5 | H5: Mês 6 | I5: Mês 7 | J5: Mês 8 | K5: Mês 9 | L5: Mês 10 | M5: Mês 11 | N5: Mês 12 | O5: Mês 13 | P5: Mês 14 | Q5: Mês 15 | R5: Mês 16 | S5: Mês 17 | T5: Mês 18 | U5: Mês 19 | V5: Mês 20 | W5: Mês 21 | X5: Mês 22 | Y5: Mês 23 | Z5: Mês 24 | AA5: Mês 25 | AB5: Mês 26 | AC5: Mês 27 | AD5: Mês 28 | AE5: Mês 29 | AF5: Mês 30 | AG5: Mês 31 | AH5: Mês 32 | AI5: Mês 33 | AJ5: Mês 34 | AK5: Mês 35 | AL5: Mês 36 | AM5: Valor 1 | AN5: Valor 2 | AO5: Valor 3 | AP5: Valor 4 | AQ5: Valor 5 | AR5: Valor 6 | AS5: Valor 7 | AT5: Valor 8 | AU5: Valor 9 | AV5: Valor 10 | AW5: Valor 11 | AX5: Valor 12 | AY5: Valor 13 | AZ5: Valor 14 | BA5: Valor 15 | BB5: Valor 16 | BC5: Valor 17 | BD5: Valor 18 | BE5: Valor 19 | BF5: Valor 20 | BG5: Valor 21 | BH5: Valor 22 | BI5: Valor 23 | BJ5: Valor 24 | BK5: Valor 25 | BL5: Valor 26 | BM5: Valor 27 | BN5: Valor 28 | BO5: Valor 29 | BP5: Valor 30 | BQ5: Valor 31 | BR5: Valor 32 | BS5: Valor 33 | BT5: Valor 34 | BU5: Valor 35 | BV5: Valor 36
A6: =IF(CARTÕES!$C6="","",CARTÕES!$C6) | B6: =SUMPRODUCT((C6:AL6='RESUMO MENSAL'!$C$4)*AM6:BV6) | C6: =IF(OR(CARTÕES!$K6=0,CARTÕES!$F6=""),0,IF(1>CARTÕES!$F6,0,CARTÕES!$K6+1-1)) | D6: =IF(OR(CARTÕES!$K6=0,CARTÕES!$F6=""),0,IF(2>CARTÕES!$F6,0,CARTÕES!$K6+2-1)) | E6: =IF(OR(CARTÕES!$K6=0,CARTÕES!$F6=""),0,IF(3>CARTÕES!$F6,0,CARTÕES!$K6+3-1)) | F6: =IF(OR(CARTÕES!$K6=0,CARTÕES!$F6=""),0,IF(4>CARTÕES!$F6,0,CARTÕES!$K6+4-1)) | G6: =IF(OR(CARTÕES!$K6=0,CARTÕES!$F6=""),0,IF(5>CARTÕES!$F6,0,CARTÕES!$K6+5-1)) | H6: =IF(OR(CARTÕES!$K6=0,CARTÕES!$F6=""),0,IF(6>CARTÕES!$F6,0,CARTÕES!$K6+6-1)) | I6: =IF(OR(CARTÕES!$K6=0,CARTÕES!$F6=""),0,IF(7>CARTÕES!$F6,0,CARTÕES!$K6+7-1)) | J6: =IF(OR(CARTÕES!$K6=0,CARTÕES!$F6=""),0,IF(8>CARTÕES!$F6,0,CARTÕES!$K6+8-1)) | K6: =IF(OR(CARTÕES!$K6=0,CARTÕES!$F6=""),0,IF(9>CARTÕES!$F6,0,CARTÕES!$K6+9-1)) | L6: =IF(OR(CARTÕES!$K6=0,CARTÕES!$F6=""),0,IF(10>CARTÕES!$F6,0,CARTÕES!$K6+10-1)) | M6: =IF(OR(CARTÕES!$K6=0,CARTÕES!$F6=""),0,IF(11>CARTÕES!$F6,0,CARTÕES!$K6+11-1)) | N6: =IF(OR(CARTÕES!$K6=0,CARTÕES!$F6=""),0,IF(12>CARTÕES!$F6,0,CARTÕES!$K6+12-1)) | O6: =IF(OR(CARTÕES!$K6=0,CARTÕES!$F6=""),0,IF(13>CARTÕES!$F6,0,CARTÕES!$K6+13-1)) | P6: =IF(OR(CARTÕES!$K6=0,CARTÕES!$F6=""),0,IF(14>CARTÕES!$F6,0,CARTÕES!$K6+14-1)) | Q6: =IF(OR(CARTÕES!$K6=0,CARTÕES!$F6=""),0,IF(15>CARTÕES!$F6,0,CARTÕES!$K6+15-1)) | R6: =IF(OR(CARTÕES!$K6=0,CARTÕES!$F6=""),0,IF(16>CARTÕES!$F6,0,CARTÕES!$K6+16-1)) | S6: =IF(OR(CARTÕES!$K6=0,CARTÕES!$F6=""),0,IF(17>CARTÕES!$F6,0,CARTÕES!$K6+17-1)) | T6: =IF(OR(CARTÕES!$K6=0,CARTÕES!$F6=""),0,IF(18>CARTÕES!$F6,0,CARTÕES!$K6+18-1)) | U6: =IF(OR(CARTÕES!$K6=0,CARTÕES!$F6=""),0,IF(19>CARTÕES!$F6,0,CARTÕES!$K6+19-1)) | V6: =IF(OR(CARTÕES!$K6=0,CARTÕES!$F6=""),0,IF(20>CARTÕES!$F6,0,CARTÕES!$K6+20-1)) | W6: =IF(OR(CARTÕES!$K6=0,CARTÕES!$F6=""),0,IF(21>CARTÕES!$F6,0,CARTÕES!$K6+21-1)) | X6: =IF(OR(CARTÕES!$K6=0,CARTÕES!$F6=""),0,IF(22>CARTÕES!$F6,0,CARTÕES!$K6+22-1)) | Y6: =IF(OR(CARTÕES!$K6=0,CARTÕES!$F6=""),0,IF(23>CARTÕES!$F6,0,CARTÕES!$K6+23-1)) | Z6: =IF(OR(CARTÕES!$K6=0,CARTÕES!$F6=""),0,IF(24>CARTÕES!$F6,0,CARTÕES!$K6+24-1)) | AA6: =IF(OR(CARTÕES!$K6=0,CARTÕES!$F6=""),0,IF(25>CARTÕES!$F6,0,CARTÕES!$K6+25-1)) | AB6: =IF(OR(CARTÕES!$K6=0,CARTÕES!$F6=""),0,IF(26>CARTÕES!$F6,0,CARTÕES!$K6+26-1)) | AC6: =IF(OR(CARTÕES!$K6=0,CARTÕES!$F6=""),0,IF(27>CARTÕES!$F6,0,CARTÕES!$K6+27-1)) | AD6: =IF(OR(CARTÕES!$K6=0,CARTÕES!$F6=""),0,IF(28>CARTÕES!$F6,0,CARTÕES!$K6+28-1)) | AE6: =IF(OR(CARTÕES!$K6=0,CARTÕES!$F6=""),0,IF(29>CARTÕES!$F6,0,CARTÕES!$K6+29-1)) | AF6: =IF(OR(CARTÕES!$K6=0,CARTÕES!$F6=""),0,IF(30>CARTÕES!$F6,0,CARTÕES!$K6+30-1)) | AG6: =IF(OR(CARTÕES!$K6=0,CARTÕES!$F6=""),0,IF(31>CARTÕES!$F6,0,CARTÕES!$K6+31-1)) | AH6: =IF(OR(CARTÕES!$K6=0,CARTÕES!$F6=""),0,IF(32>CARTÕES!$F6,0,CARTÕES!$K6+32-1)) | AI6: =IF(OR(CARTÕES!$K6=0,CARTÕES!$F6=""),0,IF(33>CARTÕES!$F6,0,CARTÕES!$K6+33-1)) | AJ6: =IF(OR(CARTÕES!$K6=0,CARTÕES!$F6=""),0,IF(34>CARTÕES!$F6,0,CARTÕES!$K6+34-1)) | AK6: =IF(OR(CARTÕES!$K6=0,CARTÕES!$F6=""),0,IF(35>CARTÕES!$F6,0,CARTÕES!$K6+35-1)) | AL6: =IF(OR(CARTÕES!$K6=0,CARTÕES!$F6=""),0,IF(36>CARTÕES!$F6,0,CARTÕES!$K6+36-1)) | AM6: =IF(C6=0,0,IF(1=CARTÕES!$F6,CARTÕES!$E6-(CARTÕES!$F6-1)*ROUND(CARTÕES!$E6/CARTÕES!$F6,0),ROUND(CARTÕES!$E6/CARTÕES!$F6,0))) | AN6: =IF(D6=0,0,IF(2=CARTÕES!$F6,CARTÕES!$E6-(CARTÕES!$F6-1)*ROUND(CARTÕES!$E6/CARTÕES!$F6,0),ROUND(CARTÕES!$E6/CARTÕES!$F6,0))) | AO6: =IF(E6=0,0,IF(3=CARTÕES!$F6,CARTÕES!$E6-(CARTÕES!$F6-1)*ROUND(CARTÕES!$E6/CARTÕES!$F6,0),ROUND(CARTÕES!$E6/CARTÕES!$F6,0))) | AP6: =IF(F6=0,0,IF(4=CARTÕES!$F6,CARTÕES!$E6-(CARTÕES!$F6-1)*ROUND(CARTÕES!$E6/CARTÕES!$F6,0),ROUND(CARTÕES!$E6/CARTÕES!$F6,0))) | AQ6: =IF(G6=0,0,IF(5=CARTÕES!$F6,CARTÕES!$E6-(CARTÕES!$F6-1)*ROUND(CARTÕES!$E6/CARTÕES!$F6,0),ROUND(CARTÕES!$E6/CARTÕES!$F6,0))) | AR6: =IF(H6=0,0,IF(6=CARTÕES!$F6,CARTÕES!$E6-(CARTÕES!$F6-1)*ROUND(CARTÕES!$E6/CARTÕES!$F6,0),ROUND(CARTÕES!$E6/CARTÕES!$F6,0))) | AS6: =IF(I6=0,0,IF(7=CARTÕES!$F6,CARTÕES!$E6-(CARTÕES!$F6-1)*ROUND(CARTÕES!$E6/CARTÕES!$F6,0),ROUND(CARTÕES!$E6/CARTÕES!$F6,0))) | AT6: =IF(J6=0,0,IF(8=CARTÕES!$F6,CARTÕES!$E6-(CARTÕES!$F6-1)*ROUND(CARTÕES!$E6/CARTÕES!$F6,0),ROUND(CARTÕES!$E6/CARTÕES!$F6,0))) | AU6: =IF(K6=0,0,IF(9=CARTÕES!$F6,CARTÕES!$E6-(CARTÕES!$F6-1)*ROUND(CARTÕES!$E6/CARTÕES!$F6,0),ROUND(CARTÕES!$E6/CARTÕES!$F6,0))) | AV6: =IF(L6=0,0,IF(10=CARTÕES!$F6,CARTÕES!$E6-(CARTÕES!$F6-1)*ROUND(CARTÕES!$E6/CARTÕES!$F6,0),ROUND(CARTÕES!$E6/CARTÕES!$F6,0))) | AW6: =IF(M6=0,0,IF(11=CARTÕES!$F6,CARTÕES!$E6-(CARTÕES!$F6-1)*ROUND(CARTÕES!$E6/CARTÕES!$F6,0),ROUND(CARTÕES!$E6/CARTÕES!$F6,0))) | AX6: =IF(N6=0,0,IF(12=CARTÕES!$F6,CARTÕES!$E6-(CARTÕES!$F6-1)*ROUND(CARTÕES!$E6/CARTÕES!$F6,0),ROUND(CARTÕES!$E6/CARTÕES!$F6,0))) | AY6: =IF(O6=0,0,IF(13=CARTÕES!$F6,CARTÕES!$E6-(CARTÕES!$F6-1)*ROUND(CARTÕES!$E6/CARTÕES!$F6,0),ROUND(CARTÕES!$E6/CARTÕES!$F6,0))) | AZ6: =IF(P6=0,0,IF(14=CARTÕES!$F6,CARTÕES!$E6-(CARTÕES!$F6-1)*ROUND(CARTÕES!$E6/CARTÕES!$F6,0),ROUND(CARTÕES!$E6/CARTÕES!$F6,0))) | BA6: =IF(Q6=0,0,IF(15=CARTÕES!$F6,CARTÕES!$E6-(CARTÕES!$F6-1)*ROUND(CARTÕES!$E6/CARTÕES!$F6,0),ROUND(CARTÕES!$E6/CARTÕES!$F6,0))) | BB6: =IF(R6=0,0,IF(16=CARTÕES!$F6,CARTÕES!$E6-(CARTÕES!$F6-1)*ROUND(CARTÕES!$E6/CARTÕES!$F6,0),ROUND(CARTÕES!$E6/CARTÕES!$F6,0))) | BC6: =IF(S6=0,0,IF(17=CARTÕES!$F6,CARTÕES!$E6-(CARTÕES!$F6-1)*ROUND(CARTÕES!$E6/CARTÕES!$F6,0),ROUND(CARTÕES!$E6/CARTÕES!$F6,0))) | BD6: =IF(T6=0,0,IF(18=CARTÕES!$F6,CARTÕES!$E6-(CARTÕES!$F6-1)*ROUND(CARTÕES!$E6/CARTÕES!$F6,0),ROUND(CARTÕES!$E6/CARTÕES!$F6,0))) | BE6: =IF(U6=0,0,IF(19=CARTÕES!$F6,CARTÕES!$E6-(CARTÕES!$F6-1)*ROUND(CARTÕES!$E6/CARTÕES!$F6,0),ROUND(CARTÕES!$E6/CARTÕES!$F6,0))) | BF6: =IF(V6=0,0,IF(20=CARTÕES!$F6,CARTÕES!$E6-(CARTÕES!$F6-1)*ROUND(CARTÕES!$E6/CARTÕES!$F6,0),ROUND(CARTÕES!$E6/CARTÕES!$F6,0))) | BG6: =IF(W6=0,0,IF(21=CARTÕES!$F6,CARTÕES!$E6-(CARTÕES!$F6-1)*ROUND(CARTÕES!$E6/CARTÕES!$F6,0),ROUND(CARTÕES!$E6/CARTÕES!$F6,0))) | BH6: =IF(X6=0,0,IF(22=CARTÕES!$F6,CARTÕES!$E6-(CARTÕES!$F6-1)*ROUND(CARTÕES!$E6/CARTÕES!$F6,0),ROUND(CARTÕES!$E6/CARTÕES!$F6,0))) | BI6: =IF(Y6=0,0,IF(23=CARTÕES!$F6,CARTÕES!$E6-(CARTÕES!$F6-1)*ROUND(CARTÕES!$E6/CARTÕES!$F6,0),ROUND(CARTÕES!$E6/CARTÕES!$F6,0))) | BJ6: =IF(Z6=0,0,IF(24=CARTÕES!$F6,CARTÕES!$E6-(CARTÕES!$F6-1)*ROUND(CARTÕES!$E6/CARTÕES!$F6,0),ROUND(CARTÕES!$E6/CARTÕES!$F6,0))) | BK6: =IF(AA6=0,0,IF(25=CARTÕES!$F6,CARTÕES!$E6-(CARTÕES!$F6-1)*ROUND(CARTÕES!$E6/CARTÕES!$F6,0),ROUND(CARTÕES!$E6/CARTÕES!$F6,0))) | BL6: =IF(AB6=0,0,IF(26=CARTÕES!$F6,CARTÕES!$E6-(CARTÕES!$F6-1)*ROUND(CARTÕES!$E6/CARTÕES!$F6,0),ROUND(CARTÕES!$E6/CARTÕES!$F6,0))) | BM6: =IF(AC6=0,0,IF(27=CARTÕES!$F6,CARTÕES!$E6-(CARTÕES!$F6-1)*ROUND(CARTÕES!$E6/CARTÕES!$F6,0),ROUND(CARTÕES!$E6/CARTÕES!$F6,0))) | BN6: =IF(AD6=0,0,IF(28=CARTÕES!$F6,CARTÕES!$E6-(CARTÕES!$F6-1)*ROUND(CARTÕES!$E6/CARTÕES!$F6,0),ROUND(CARTÕES!$E6/CARTÕES!$F6,0))) | BO6: =IF(AE6=0,0,IF(29=CARTÕES!$F6,CARTÕES!$E6-(CARTÕES!$F6-1)*ROUND(CARTÕES!$E6/CARTÕES!$F6,0),ROUND(CARTÕES!$E6/CARTÕES!$F6,0))) | BP6: =IF(AF6=0,0,IF(30=CARTÕES!$F6,CARTÕES!$E6-(CARTÕES!$F6-1)*ROUND(CARTÕES!$E6/CARTÕES!$F6,0),ROUND(CARTÕES!$E6/CARTÕES!$F6,0))) | BQ6: =IF(AG6=0,0,IF(31=CARTÕES!$F6,CARTÕES!$E6-(CARTÕES!$F6-1)*ROUND(CARTÕES!$E6/CARTÕES!$F6,0),ROUND(CARTÕES!$E6/CARTÕES!$F6,0))) | BR6: =IF(AH6=0,0,IF(32=CARTÕES!$F6,CARTÕES!$E6-(CARTÕES!$F6-1)*ROUND(CARTÕES!$E6/CARTÕES!$F6,0),ROUND(CARTÕES!$E6/CARTÕES!$F6,0))) | BS6: =IF(AI6=0,0,IF(33=CARTÕES!$F6,CARTÕES!$E6-(CARTÕES!$F6-1)*ROUND(CARTÕES!$E6/CARTÕES!$F6,0),ROUND(CARTÕES!$E6/CARTÕES!$F6,0))) | BT6: =IF(AJ6=0,0,IF(34=CARTÕES!$F6,CARTÕES!$E6-(CARTÕES!$F6-1)*ROUND(CARTÕES!$E6/CARTÕES!$F6,0),ROUND(CARTÕES!$E6/CARTÕES!$F6,0))) | BU6: =IF(AK6=0,0,IF(35=CARTÕES!$F6,CARTÕES!$E6-(CARTÕES!$F6-1)*ROUND(CARTÕES!$E6/CARTÕES!$F6,0),ROUND(CARTÕES!$E6/CARTÕES!$F6,0))) | BV6: =IF(AL6=0,0,IF(36=CARTÕES!$F6,CARTÕES!$E6-(CARTÕES!$F6-1)*ROUND(CARTÕES!$E6/CARTÕES!$F6,0),ROUND(CARTÕES!$E6/CARTÕES!$F6,0)))
A7: =IF(CARTÕES!$C7="","",CARTÕES!$C7) | B7: =SUMPRODUCT((C7:AL7='RESUMO MENSAL'!$C$4)*AM7:BV7) | C7: =IF(OR(CARTÕES!$K7=0,CARTÕES!$F7=""),0,IF(1>CARTÕES!$F7,0,CARTÕES!$K7+1-1)) | D7: =IF(OR(CARTÕES!$K7=0,CARTÕES!$F7=""),0,IF(2>CARTÕES!$F7,0,CARTÕES!$K7+2-1)) | E7: =IF(OR(CARTÕES!$K7=0,CARTÕES!$F7=""),0,IF(3>CARTÕES!$F7,0,CARTÕES!$K7+3-1)) | F7: =IF(OR(CARTÕES!$K7=0,CARTÕES!$F7=""),0,IF(4>CARTÕES!$F7,0,CARTÕES!$K7+4-1)) | G7: =IF(OR(CARTÕES!$K7=0,CARTÕES!$F7=""),0,IF(5>CARTÕES!$F7,0,CARTÕES!$K7+5-1)) | H7: =IF(OR(CARTÕES!$K7=0,CARTÕES!$F7=""),0,IF(6>CARTÕES!$F7,0,CARTÕES!$K7+6-1)) | I7: =IF(OR(CARTÕES!$K7=0,CARTÕES!$F7=""),0,IF(7>CARTÕES!$F7,0,CARTÕES!$K7+7-1)) | J7: =IF(OR(CARTÕES!$K7=0,CARTÕES!$F7=""),0,IF(8>CARTÕES!$F7,0,CARTÕES!$K7+8-1)) | K7: =IF(OR(CARTÕES!$K7=0,CARTÕES!$F7=""),0,IF(9>CARTÕES!$F7,0,CARTÕES!$K7+9-1)) | L7: =IF(OR(CARTÕES!$K7=0,CARTÕES!$F7=""),0,IF(10>CARTÕES!$F7,0,CARTÕES!$K7+10-1)) | M7: =IF(OR(CARTÕES!$K7=0,CARTÕES!$F7=""),0,IF(11>CARTÕES!$F7,0,CARTÕES!$K7+11-1)) | N7: =IF(OR(CARTÕES!$K7=0,CARTÕES!$F7=""),0,IF(12>CARTÕES!$F7,0,CARTÕES!$K7+12-1)) | O7: =IF(OR(CARTÕES!$K7=0,CARTÕES!$F7=""),0,IF(13>CARTÕES!$F7,0,CARTÕES!$K7+13-1)) | P7: =IF(OR(CARTÕES!$K7=0,CARTÕES!$F7=""),0,IF(14>CARTÕES!$F7,0,CARTÕES!$K7+14-1)) | Q7: =IF(OR(CARTÕES!$K7=0,CARTÕES!$F7=""),0,IF(15>CARTÕES!$F7,0,CARTÕES!$K7+15-1)) | R7: =IF(OR(CARTÕES!$K7=0,CARTÕES!$F7=""),0,IF(16>CARTÕES!$F7,0,CARTÕES!$K7+16-1)) | S7: =IF(OR(CARTÕES!$K7=0,CARTÕES!$F7=""),0,IF(17>CARTÕES!$F7,0,CARTÕES!$K7+17-1)) | T7: =IF(OR(CARTÕES!$K7=0,CARTÕES!$F7=""),0,IF(18>CARTÕES!$F7,0,CARTÕES!$K7+18-1)) | U7: =IF(OR(CARTÕES!$K7=0,CARTÕES!$F7=""),0,IF(19>CARTÕES!$F7,0,CARTÕES!$K7+19-1)) | V7: =IF(OR(CARTÕES!$K7=0,CARTÕES!$F7=""),0,IF(20>CARTÕES!$F7,0,CARTÕES!$K7+20-1)) | W7: =IF(OR(CARTÕES!$K7=0,CARTÕES!$F7=""),0,IF(21>CARTÕES!$F7,0,CARTÕES!$K7+21-1)) | X7: =IF(OR(CARTÕES!$K7=0,CARTÕES!$F7=""),0,IF(22>CARTÕES!$F7,0,CARTÕES!$K7+22-1)) | Y7: =IF(OR(CARTÕES!$K7=0,CARTÕES!$F7=""),0,IF(23>CARTÕES!$F7,0,CARTÕES!$K7+23-1)) | Z7: =IF(OR(CARTÕES!$K7=0,CARTÕES!$F7=""),0,IF(24>CARTÕES!$F7,0,CARTÕES!$K7+24-1)) | AA7: =IF(OR(CARTÕES!$K7=0,CARTÕES!$F7=""),0,IF(25>CARTÕES!$F7,0,CARTÕES!$K7+25-1)) | AB7: =IF(OR(CARTÕES!$K7=0,CARTÕES!$F7=""),0,IF(26>CARTÕES!$F7,0,CARTÕES!$K7+26-1)) | AC7: =IF(OR(CARTÕES!$K7=0,CARTÕES!$F7=""),0,IF(27>CARTÕES!$F7,0,CARTÕES!$K7+27-1)) | AD7: =IF(OR(CARTÕES!$K7=0,CARTÕES!$F7=""),0,IF(28>CARTÕES!$F7,0,CARTÕES!$K7+28-1)) | AE7: =IF(OR(CARTÕES!$K7=0,CARTÕES!$F7=""),0,IF(29>CARTÕES!$F7,0,CARTÕES!$K7+29-1)) | AF7: =IF(OR(CARTÕES!$K7=0,CARTÕES!$F7=""),0,IF(30>CARTÕES!$F7,0,CARTÕES!$K7+30-1)) | AG7: =IF(OR(CARTÕES!$K7=0,CARTÕES!$F7=""),0,IF(31>CARTÕES!$F7,0,CARTÕES!$K7+31-1)) | AH7: =IF(OR(CARTÕES!$K7=0,CARTÕES!$F7=""),0,IF(32>CARTÕES!$F7,0,CARTÕES!$K7+32-1)) | AI7: =IF(OR(CARTÕES!$K7=0,CARTÕES!$F7=""),0,IF(33>CARTÕES!$F7,0,CARTÕES!$K7+33-1)) | AJ7: =IF(OR(CARTÕES!$K7=0,CARTÕES!$F7=""),0,IF(34>CARTÕES!$F7,0,CARTÕES!$K7+34-1)) | AK7: =IF(OR(CARTÕES!$K7=0,CARTÕES!$F7=""),0,IF(35>CARTÕES!$F7,0,CARTÕES!$K7+35-1)) | AL7: =IF(OR(CARTÕES!$K7=0,CARTÕES!$F7=""),0,IF(36>CARTÕES!$F7,0,CARTÕES!$K7+36-1)) | AM7: =IF(C7=0,0,IF(1=CARTÕES!$F7,CARTÕES!$E7-(CARTÕES!$F7-1)*ROUND(CARTÕES!$E7/CARTÕES!$F7,0),ROUND(CARTÕES!$E7/CARTÕES!$F7,0))) | AN7: =IF(D7=0,0,IF(2=CARTÕES!$F7,CARTÕES!$E7-(CARTÕES!$F7-1)*ROUND(CARTÕES!$E7/CARTÕES!$F7,0),ROUND(CARTÕES!$E7/CARTÕES!$F7,0))) | AO7: =IF(E7=0,0,IF(3=CARTÕES!$F7,CARTÕES!$E7-(CARTÕES!$F7-1)*ROUND(CARTÕES!$E7/CARTÕES!$F7,0),ROUND(CARTÕES!$E7/CARTÕES!$F7,0))) | AP7: =IF(F7=0,0,IF(4=CARTÕES!$F7,CARTÕES!$E7-(CARTÕES!$F7-1)*ROUND(CARTÕES!$E7/CARTÕES!$F7,0),ROUND(CARTÕES!$E7/CARTÕES!$F7,0))) | AQ7: =IF(G7=0,0,IF(5=CARTÕES!$F7,CARTÕES!$E7-(CARTÕES!$F7-1)*ROUND(CARTÕES!$E7/CARTÕES!$F7,0),ROUND(CARTÕES!$E7/CARTÕES!$F7,0))) | AR7: =IF(H7=0,0,IF(6=CARTÕES!$F7,CARTÕES!$E7-(CARTÕES!$F7-1)*ROUND(CARTÕES!$E7/CARTÕES!$F7,0),ROUND(CARTÕES!$E7/CARTÕES!$F7,0))) | AS7: =IF(I7=0,0,IF(7=CARTÕES!$F7,CARTÕES!$E7-(CARTÕES!$F7-1)*ROUND(CARTÕES!$E7/CARTÕES!$F7,0),ROUND(CARTÕES!$E7/CARTÕES!$F7,0))) | AT7: =IF(J7=0,0,IF(8=CARTÕES!$F7,CARTÕES!$E7-(CARTÕES!$F7-1)*ROUND(CARTÕES!$E7/CARTÕES!$F7,0),ROUND(CARTÕES!$E7/CARTÕES!$F7,0))) | AU7: =IF(K7=0,0,IF(9=CARTÕES!$F7,CARTÕES!$E7-(CARTÕES!$F7-1)*ROUND(CARTÕES!$E7/CARTÕES!$F7,0),ROUND(CARTÕES!$E7/CARTÕES!$F7,0))) | AV7: =IF(L7=0,0,IF(10=CARTÕES!$F7,CARTÕES!$E7-(CARTÕES!$F7-1)*ROUND(CARTÕES!$E7/CARTÕES!$F7,0),ROUND(CARTÕES!$E7/CARTÕES!$F7,0))) | AW7: =IF(M7=0,0,IF(11=CARTÕES!$F7,CARTÕES!$E7-(CARTÕES!$F7-1)*ROUND(CARTÕES!$E7/CARTÕES!$F7,0),ROUND(CARTÕES!$E7/CARTÕES!$F7,0))) | AX7: =IF(N7=0,0,IF(12=CARTÕES!$F7,CARTÕES!$E7-(CARTÕES!$F7-1)*ROUND(CARTÕES!$E7/CARTÕES!$F7,0),ROUND(CARTÕES!$E7/CARTÕES!$F7,0))) | AY7: =IF(O7=0,0,IF(13=CARTÕES!$F7,CARTÕES!$E7-(CARTÕES!$F7-1)*ROUND(CARTÕES!$E7/CARTÕES!$F7,0),ROUND(CARTÕES!$E7/CARTÕES!$F7,0))) | AZ7: =IF(P7=0,0,IF(14=CARTÕES!$F7,CARTÕES!$E7-(CARTÕES!$F7-1)*ROUND(CARTÕES!$E7/CARTÕES!$F7,0),ROUND(CARTÕES!$E7/CARTÕES!$F7,0))) | BA7: =IF(Q7=0,0,IF(15=CARTÕES!$F7,CARTÕES!$E7-(CARTÕES!$F7-1)*ROUND(CARTÕES!$E7/CARTÕES!$F7,0),ROUND(CARTÕES!$E7/CARTÕES!$F7,0))) | BB7: =IF(R7=0,0,IF(16=CARTÕES!$F7,CARTÕES!$E7-(CARTÕES!$F7-1)*ROUND(CARTÕES!$E7/CARTÕES!$F7,0),ROUND(CARTÕES!$E7/CARTÕES!$F7,0))) | BC7: =IF(S7=0,0,IF(17=CARTÕES!$F7,CARTÕES!$E7-(CARTÕES!$F7-1)*ROUND(CARTÕES!$E7/CARTÕES!$F7,0),ROUND(CARTÕES!$E7/CARTÕES!$F7,0))) | BD7: =IF(T7=0,0,IF(18=CARTÕES!$F7,CARTÕES!$E7-(CARTÕES!$F7-1)*ROUND(CARTÕES!$E7/CARTÕES!$F7,0),ROUND(CARTÕES!$E7/CARTÕES!$F7,0))) | BE7: =IF(U7=0,0,IF(19=CARTÕES!$F7,CARTÕES!$E7-(CARTÕES!$F7-1)*ROUND(CARTÕES!$E7/CARTÕES!$F7,0),ROUND(CARTÕES!$E7/CARTÕES!$F7,0))) | BF7: =IF(V7=0,0,IF(20=CARTÕES!$F7,CARTÕES!$E7-(CARTÕES!$F7-1)*ROUND(CARTÕES!$E7/CARTÕES!$F7,0),ROUND(CARTÕES!$E7/CARTÕES!$F7,0))) | BG7: =IF(W7=0,0,IF(21=CARTÕES!$F7,CARTÕES!$E7-(CARTÕES!$F7-1)*ROUND(CARTÕES!$E7/CARTÕES!$F7,0),ROUND(CARTÕES!$E7/CARTÕES!$F7,0))) | BH7: =IF(X7=0,0,IF(22=CARTÕES!$F7,CARTÕES!$E7-(CARTÕES!$F7-1)*ROUND(CARTÕES!$E7/CARTÕES!$F7,0),ROUND(CARTÕES!$E7/CARTÕES!$F7,0))) | BI7: =IF(Y7=0,0,IF(23=CARTÕES!$F7,CARTÕES!$E7-(CARTÕES!$F7-1)*ROUND(CARTÕES!$E7/CARTÕES!$F7,0),ROUND(CARTÕES!$E7/CARTÕES!$F7,0))) | BJ7: =IF(Z7=0,0,IF(24=CARTÕES!$F7,CARTÕES!$E7-(CARTÕES!$F7-1)*ROUND(CARTÕES!$E7/CARTÕES!$F7,0),ROUND(CARTÕES!$E7/CARTÕES!$F7,0))) | BK7: =IF(AA7=0,0,IF(25=CARTÕES!$F7,CARTÕES!$E7-(CARTÕES!$F7-1)*ROUND(CARTÕES!$E7/CARTÕES!$F7,0),ROUND(CARTÕES!$E7/CARTÕES!$F7,0))) | BL7: =IF(AB7=0,0,IF(26=CARTÕES!$F7,CARTÕES!$E7-(CARTÕES!$F7-1)*ROUND(CARTÕES!$E7/CARTÕES!$F7,0),ROUND(CARTÕES!$E7/CARTÕES!$F7,0))) | BM7: =IF(AC7=0,0,IF(27=CARTÕES!$F7,CARTÕES!$E7-(CARTÕES!$F7-1)*ROUND(CARTÕES!$E7/CARTÕES!$F7,0),ROUND(CARTÕES!$E7/CARTÕES!$F7,0))) | BN7: =IF(AD7=0,0,IF(28=CARTÕES!$F7,CARTÕES!$E7-(CARTÕES!$F7-1)*ROUND(CARTÕES!$E7/CARTÕES!$F7,0),ROUND(CARTÕES!$E7/CARTÕES!$F7,0))) | BO7: =IF(AE7=0,0,IF(29=CARTÕES!$F7,CARTÕES!$E7-(CARTÕES!$F7-1)*ROUND(CARTÕES!$E7/CARTÕES!$F7,0),ROUND(CARTÕES!$E7/CARTÕES!$F7,0))) | BP7: =IF(AF7=0,0,IF(30=CARTÕES!$F7,CARTÕES!$E7-(CARTÕES!$F7-1)*ROUND(CARTÕES!$E7/CARTÕES!$F7,0),ROUND(CARTÕES!$E7/CARTÕES!$F7,0))) | BQ7: =IF(AG7=0,0,IF(31=CARTÕES!$F7,CARTÕES!$E7-(CARTÕES!$F7-1)*ROUND(CARTÕES!$E7/CARTÕES!$F7,0),ROUND(CARTÕES!$E7/CARTÕES!$F7,0))) | BR7: =IF(AH7=0,0,IF(32=CARTÕES!$F7,CARTÕES!$E7-(CARTÕES!$F7-1)*ROUND(CARTÕES!$E7/CARTÕES!$F7,0),ROUND(CARTÕES!$E7/CARTÕES!$F7,0))) | BS7: =IF(AI7=0,0,IF(33=CARTÕES!$F7,CARTÕES!$E7-(CARTÕES!$F7-1)*ROUND(CARTÕES!$E7/CARTÕES!$F7,0),ROUND(CARTÕES!$E7/CARTÕES!$F7,0))) | BT7: =IF(AJ7=0,0,IF(34=CARTÕES!$F7,CARTÕES!$E7-(CARTÕES!$F7-1)*ROUND(CARTÕES!$E7/CARTÕES!$F7,0),ROUND(CARTÕES!$E7/CARTÕES!$F7,0))) | BU7: =IF(AK7=0,0,IF(35=CARTÕES!$F7,CARTÕES!$E7-(CARTÕES!$F7-1)*ROUND(CARTÕES!$E7/CARTÕES!$F7,0),ROUND(CARTÕES!$E7/CARTÕES!$F7,0))) | BV7: =IF(AL7=0,0,IF(36=CARTÕES!$F7,CARTÕES!$E7-(CARTÕES!$F7-1)*ROUND(CARTÕES!$E7/CARTÕES!$F7,0),ROUND(CARTÕES!$E7/CARTÕES!$F7,0)))
A8: =IF(CARTÕES!$C8="","",CARTÕES!$C8) | B8: =SUMPRODUCT((C8:AL8='RESUMO MENSAL'!$C$4)*AM8:BV8) | C8: =IF(OR(CARTÕES!$K8=0,CARTÕES!$F8=""),0,IF(1>CARTÕES!$F8,0,CARTÕES!$K8+1-1)) | D8: =IF(OR(CARTÕES!$K8=0,CARTÕES!$F8=""),0,IF(2>CARTÕES!$F8,0,CARTÕES!$K8+2-1)) | E8: =IF(OR(CARTÕES!$K8=0,CARTÕES!$F8=""),0,IF(3>CARTÕES!$F8,0,CARTÕES!$K8+3-1)) | F8: =IF(OR(CARTÕES!$K8=0,CARTÕES!$F8=""),0,IF(4>CARTÕES!$F8,0,CARTÕES!$K8+4-1)) | G8: =IF(OR(CARTÕES!$K8=0,CARTÕES!$F8=""),0,IF(5>CARTÕES!$F8,0,CARTÕES!$K8+5-1)) | H8: =IF(OR(CARTÕES!$K8=0,CARTÕES!$F8=""),0,IF(6>CARTÕES!$F8,0,CARTÕES!$K8+6-1)) | I8: =IF(OR(CARTÕES!$K8=0,CARTÕES!$F8=""),0,IF(7>CARTÕES!$F8,0,CARTÕES!$K8+7-1)) | J8: =IF(OR(CARTÕES!$K8=0,CARTÕES!$F8=""),0,IF(8>CARTÕES!$F8,0,CARTÕES!$K8+8-1)) | K8: =IF(OR(CARTÕES!$K8=0,CARTÕES!$F8=""),0,IF(9>CARTÕES!$F8,0,CARTÕES!$K8+9-1)) | L8: =IF(OR(CARTÕES!$K8=0,CARTÕES!$F8=""),0,IF(10>CARTÕES!$F8,0,CARTÕES!$K8+10-1)) | M8: =IF(OR(CARTÕES!$K8=0,CARTÕES!$F8=""),0,IF(11>CARTÕES!$F8,0,CARTÕES!$K8+11-1)) | N8: =IF(OR(CARTÕES!$K8=0,CARTÕES!$F8=""),0,IF(12>CARTÕES!$F8,0,CARTÕES!$K8+12-1)) | O8: =IF(OR(CARTÕES!$K8=0,CARTÕES!$F8=""),0,IF(13>CARTÕES!$F8,0,CARTÕES!$K8+13-1)) | P8: =IF(OR(CARTÕES!$K8=0,CARTÕES!$F8=""),0,IF(14>CARTÕES!$F8,0,CARTÕES!$K8+14-1)) | Q8: =IF(OR(CARTÕES!$K8=0,CARTÕES!$F8=""),0,IF(15>CARTÕES!$F8,0,CARTÕES!$K8+15-1)) | R8: =IF(OR(CARTÕES!$K8=0,CARTÕES!$F8=""),0,IF(16>CARTÕES!$F8,0,CARTÕES!$K8+16-1)) | S8: =IF(OR(CARTÕES!$K8=0,CARTÕES!$F8=""),0,IF(17>CARTÕES!$F8,0,CARTÕES!$K8+17-1)) | T8: =IF(OR(CARTÕES!$K8=0,CARTÕES!$F8=""),0,IF(18>CARTÕES!$F8,0,CARTÕES!$K8+18-1)) | U8: =IF(OR(CARTÕES!$K8=0,CARTÕES!$F8=""),0,IF(19>CARTÕES!$F8,0,CARTÕES!$K8+19-1)) | V8: =IF(OR(CARTÕES!$K8=0,CARTÕES!$F8=""),0,IF(20>CARTÕES!$F8,0,CARTÕES!$K8+20-1)) | W8: =IF(OR(CARTÕES!$K8=0,CARTÕES!$F8=""),0,IF(21>CARTÕES!$F8,0,CARTÕES!$K8+21-1)) | X8: =IF(OR(CARTÕES!$K8=0,CARTÕES!$F8=""),0,IF(22>CARTÕES!$F8,0,CARTÕES!$K8+22-1)) | Y8: =IF(OR(CARTÕES!$K8=0,CARTÕES!$F8=""),0,IF(23>CARTÕES!$F8,0,CARTÕES!$K8+23-1)) | Z8: =IF(OR(CARTÕES!$K8=0,CARTÕES!$F8=""),0,IF(24>CARTÕES!$F8,0,CARTÕES!$K8+24-1)) | AA8: =IF(OR(CARTÕES!$K8=0,CARTÕES!$F8=""),0,IF(25>CARTÕES!$F8,0,CARTÕES!$K8+25-1)) | AB8: =IF(OR(CARTÕES!$K8=0,CARTÕES!$F8=""),0,IF(26>CARTÕES!$F8,0,CARTÕES!$K8+26-1)) | AC8: =IF(OR(CARTÕES!$K8=0,CARTÕES!$F8=""),0,IF(27>CARTÕES!$F8,0,CARTÕES!$K8+27-1)) | AD8: =IF(OR(CARTÕES!$K8=0,CARTÕES!$F8=""),0,IF(28>CARTÕES!$F8,0,CARTÕES!$K8+28-1)) | AE8: =IF(OR(CARTÕES!$K8=0,CARTÕES!$F8=""),0,IF(29>CARTÕES!$F8,0,CARTÕES!$K8+29-1)) | AF8: =IF(OR(CARTÕES!$K8=0,CARTÕES!$F8=""),0,IF(30>CARTÕES!$F8,0,CARTÕES!$K8+30-1)) | AG8: =IF(OR(CARTÕES!$K8=0,CARTÕES!$F8=""),0,IF(31>CARTÕES!$F8,0,CARTÕES!$K8+31-1)) | AH8: =IF(OR(CARTÕES!$K8=0,CARTÕES!$F8=""),0,IF(32>CARTÕES!$F8,0,CARTÕES!$K8+32-1)) | AI8: =IF(OR(CARTÕES!$K8=0,CARTÕES!$F8=""),0,IF(33>CARTÕES!$F8,0,CARTÕES!$K8+33-1)) | AJ8: =IF(OR(CARTÕES!$K8=0,CARTÕES!$F8=""),0,IF(34>CARTÕES!$F8,0,CARTÕES!$K8+34-1)) | AK8: =IF(OR(CARTÕES!$K8=0,CARTÕES!$F8=""),0,IF(35>CARTÕES!$F8,0,CARTÕES!$K8+35-1)) | AL8: =IF(OR(CARTÕES!$K8=0,CARTÕES!$F8=""),0,IF(36>CARTÕES!$F8,0,CARTÕES!$K8+36-1)) | AM8: =IF(C8=0,0,IF(1=CARTÕES!$F8,CARTÕES!$E8-(CARTÕES!$F8-1)*ROUND(CARTÕES!$E8/CARTÕES!$F8,0),ROUND(CARTÕES!$E8/CARTÕES!$F8,0))) | AN8: =IF(D8=0,0,IF(2=CARTÕES!$F8,CARTÕES!$E8-(CARTÕES!$F8-1)*ROUND(CARTÕES!$E8/CARTÕES!$F8,0),ROUND(CARTÕES!$E8/CARTÕES!$F8,0))) | AO8: =IF(E8=0,0,IF(3=CARTÕES!$F8,CARTÕES!$E8-(CARTÕES!$F8-1)*ROUND(CARTÕES!$E8/CARTÕES!$F8,0),ROUND(CARTÕES!$E8/CARTÕES!$F8,0))) | AP8: =IF(F8=0,0,IF(4=CARTÕES!$F8,CARTÕES!$E8-(CARTÕES!$F8-1)*ROUND(CARTÕES!$E8/CARTÕES!$F8,0),ROUND(CARTÕES!$E8/CARTÕES!$F8,0))) | AQ8: =IF(G8=0,0,IF(5=CARTÕES!$F8,CARTÕES!$E8-(CARTÕES!$F8-1)*ROUND(CARTÕES!$E8/CARTÕES!$F8,0),ROUND(CARTÕES!$E8/CARTÕES!$F8,0))) | AR8: =IF(H8=0,0,IF(6=CARTÕES!$F8,CARTÕES!$E8-(CARTÕES!$F8-1)*ROUND(CARTÕES!$E8/CARTÕES!$F8,0),ROUND(CARTÕES!$E8/CARTÕES!$F8,0))) | AS8: =IF(I8=0,0,IF(7=CARTÕES!$F8,CARTÕES!$E8-(CARTÕES!$F8-1)*ROUND(CARTÕES!$E8/CARTÕES!$F8,0),ROUND(CARTÕES!$E8/CARTÕES!$F8,0))) | AT8: =IF(J8=0,0,IF(8=CARTÕES!$F8,CARTÕES!$E8-(CARTÕES!$F8-1)*ROUND(CARTÕES!$E8/CARTÕES!$F8,0),ROUND(CARTÕES!$E8/CARTÕES!$F8,0))) | AU8: =IF(K8=0,0,IF(9=CARTÕES!$F8,CARTÕES!$E8-(CARTÕES!$F8-1)*ROUND(CARTÕES!$E8/CARTÕES!$F8,0),ROUND(CARTÕES!$E8/CARTÕES!$F8,0))) | AV8: =IF(L8=0,0,IF(10=CARTÕES!$F8,CARTÕES!$E8-(CARTÕES!$F8-1)*ROUND(CARTÕES!$E8/CARTÕES!$F8,0),ROUND(CARTÕES!$E8/CARTÕES!$F8,0))) | AW8: =IF(M8=0,0,IF(11=CARTÕES!$F8,CARTÕES!$E8-(CARTÕES!$F8-1)*ROUND(CARTÕES!$E8/CARTÕES!$F8,0),ROUND(CARTÕES!$E8/CARTÕES!$F8,0))) | AX8: =IF(N8=0,0,IF(12=CARTÕES!$F8,CARTÕES!$E8-(CARTÕES!$F8-1)*ROUND(CARTÕES!$E8/CARTÕES!$F8,0),ROUND(CARTÕES!$E8/CARTÕES!$F8,0))) | AY8: =IF(O8=0,0,IF(13=CARTÕES!$F8,CARTÕES!$E8-(CARTÕES!$F8-1)*ROUND(CARTÕES!$E8/CARTÕES!$F8,0),ROUND(CARTÕES!$E8/CARTÕES!$F8,0))) | AZ8: =IF(P8=0,0,IF(14=CARTÕES!$F8,CARTÕES!$E8-(CARTÕES!$F8-1)*ROUND(CARTÕES!$E8/CARTÕES!$F8,0),ROUND(CARTÕES!$E8/CARTÕES!$F8,0))) | BA8: =IF(Q8=0,0,IF(15=CARTÕES!$F8,CARTÕES!$E8-(CARTÕES!$F8-1)*ROUND(CARTÕES!$E8/CARTÕES!$F8,0),ROUND(CARTÕES!$E8/CARTÕES!$F8,0))) | BB8: =IF(R8=0,0,IF(16=CARTÕES!$F8,CARTÕES!$E8-(CARTÕES!$F8-1)*ROUND(CARTÕES!$E8/CARTÕES!$F8,0),ROUND(CARTÕES!$E8/CARTÕES!$F8,0))) | BC8: =IF(S8=0,0,IF(17=CARTÕES!$F8,CARTÕES!$E8-(CARTÕES!$F8-1)*ROUND(CARTÕES!$E8/CARTÕES!$F8,0),ROUND(CARTÕES!$E8/CARTÕES!$F8,0))) | BD8: =IF(T8=0,0,IF(18=CARTÕES!$F8,CARTÕES!$E8-(CARTÕES!$F8-1)*ROUND(CARTÕES!$E8/CARTÕES!$F8,0),ROUND(CARTÕES!$E8/CARTÕES!$F8,0))) | BE8: =IF(U8=0,0,IF(19=CARTÕES!$F8,CARTÕES!$E8-(CARTÕES!$F8-1)*ROUND(CARTÕES!$E8/CARTÕES!$F8,0),ROUND(CARTÕES!$E8/CARTÕES!$F8,0))) | BF8: =IF(V8=0,0,IF(20=CARTÕES!$F8,CARTÕES!$E8-(CARTÕES!$F8-1)*ROUND(CARTÕES!$E8/CARTÕES!$F8,0),ROUND(CARTÕES!$E8/CARTÕES!$F8,0))) | BG8: =IF(W8=0,0,IF(21=CARTÕES!$F8,CARTÕES!$E8-(CARTÕES!$F8-1)*ROUND(CARTÕES!$E8/CARTÕES!$F8,0),ROUND(CARTÕES!$E8/CARTÕES!$F8,0))) | BH8: =IF(X8=0,0,IF(22=CARTÕES!$F8,CARTÕES!$E8-(CARTÕES!$F8-1)*ROUND(CARTÕES!$E8/CARTÕES!$F8,0),ROUND(CARTÕES!$E8/CARTÕES!$F8,0))) | BI8: =IF(Y8=0,0,IF(23=CARTÕES!$F8,CARTÕES!$E8-(CARTÕES!$F8-1)*ROUND(CARTÕES!$E8/CARTÕES!$F8,0),ROUND(CARTÕES!$E8/CARTÕES!$F8,0))) | BJ8: =IF(Z8=0,0,IF(24=CARTÕES!$F8,CARTÕES!$E8-(CARTÕES!$F8-1)*ROUND(CARTÕES!$E8/CARTÕES!$F8,0),ROUND(CARTÕES!$E8/CARTÕES!$F8,0))) | BK8: =IF(AA8=0,0,IF(25=CARTÕES!$F8,CARTÕES!$E8-(CARTÕES!$F8-1)*ROUND(CARTÕES!$E8/CARTÕES!$F8,0),ROUND(CARTÕES!$E8/CARTÕES!$F8,0))) | BL8: =IF(AB8=0,0,IF(26=CARTÕES!$F8,CARTÕES!$E8-(CARTÕES!$F8-1)*ROUND(CARTÕES!$E8/CARTÕES!$F8,0),ROUND(CARTÕES!$E8/CARTÕES!$F8,0))) | BM8: =IF(AC8=0,0,IF(27=CARTÕES!$F8,CARTÕES!$E8-(CARTÕES!$F8-1)*ROUND(CARTÕES!$E8/CARTÕES!$F8,0),ROUND(CARTÕES!$E8/CARTÕES!$F8,0))) | BN8: =IF(AD8=0,0,IF(28=CARTÕES!$F8,CARTÕES!$E8-(CARTÕES!$F8-1)*ROUND(CARTÕES!$E8/CARTÕES!$F8,0),ROUND(CARTÕES!$E8/CARTÕES!$F8,0))) | BO8: =IF(AE8=0,0,IF(29=CARTÕES!$F8,CARTÕES!$E8-(CARTÕES!$F8-1)*ROUND(CARTÕES!$E8/CARTÕES!$F8,0),ROUND(CARTÕES!$E8/CARTÕES!$F8,0))) | BP8: =IF(AF8=0,0,IF(30=CARTÕES!$F8,CARTÕES!$E8-(CARTÕES!$F8-1)*ROUND(CARTÕES!$E8/CARTÕES!$F8,0),ROUND(CARTÕES!$E8/CARTÕES!$F8,0))) | BQ8: =IF(AG8=0,0,IF(31=CARTÕES!$F8,CARTÕES!$E8-(CARTÕES!$F8-1)*ROUND(CARTÕES!$E8/CARTÕES!$F8,0),ROUND(CARTÕES!$E8/CARTÕES!$F8,0))) | BR8: =IF(AH8=0,0,IF(32=CARTÕES!$F8,CARTÕES!$E8-(CARTÕES!$F8-1)*ROUND(CARTÕES!$E8/CARTÕES!$F8,0),ROUND(CARTÕES!$E8/CARTÕES!$F8,0))) | BS8: =IF(AI8=0,0,IF(33=CARTÕES!$F8,CARTÕES!$E8-(CARTÕES!$F8-1)*ROUND(CARTÕES!$E8/CARTÕES!$F8,0),ROUND(CARTÕES!$E8/CARTÕES!$F8,0))) | BT8: =IF(AJ8=0,0,IF(34=CARTÕES!$F8,CARTÕES!$E8-(CARTÕES!$F8-1)*ROUND(CARTÕES!$E8/CARTÕES!$F8,0),ROUND(CARTÕES!$E8/CARTÕES!$F8,0))) | BU8: =IF(AK8=0,0,IF(35=CARTÕES!$F8,CARTÕES!$E8-(CARTÕES!$F8-1)*ROUND(CARTÕES!$E8/CARTÕES!$F8,0),ROUND(CARTÕES!$E8/CARTÕES!$F8,0))) | BV8: =IF(AL8=0,0,IF(36=CARTÕES!$F8,CARTÕES!$E8-(CARTÕES!$F8-1)*ROUND(CARTÕES!$E8/CARTÕES!$F8,0),ROUND(CARTÕES!$E8/CARTÕES!$F8,0)))
A9: =IF(CARTÕES!$C9="","",CARTÕES!$C9) | B9: =SUMPRODUCT((C9:AL9='RESUMO MENSAL'!$C$4)*AM9:BV9) | C9: =IF(OR(CARTÕES!$K9=0,CARTÕES!$F9=""),0,IF(1>CARTÕES!$F9,0,CARTÕES!$K9+1-1)) | D9: =IF(OR(CARTÕES!$K9=0,CARTÕES!$F9=""),0,IF(2>CARTÕES!$F9,0,CARTÕES!$K9+2-1)) | E9: =IF(OR(CARTÕES!$K9=0,CARTÕES!$F9=""),0,IF(3>CARTÕES!$F9,0,CARTÕES!$K9+3-1)) | F9: =IF(OR(CARTÕES!$K9=0,CARTÕES!$F9=""),0,IF(4>CARTÕES!$F9,0,CARTÕES!$K9+4-1)) | G9: =IF(OR(CARTÕES!$K9=0,CARTÕES!$F9=""),0,IF(5>CARTÕES!$F9,0,CARTÕES!$K9+5-1)) | H9: =IF(OR(CARTÕES!$K9=0,CARTÕES!$F9=""),0,IF(6>CARTÕES!$F9,0,CARTÕES!$K9+6-1)) | I9: =IF(OR(CARTÕES!$K9=0,CARTÕES!$F9=""),0,IF(7>CARTÕES!$F9,0,CARTÕES!$K9+7-1)) | J9: =IF(OR(CARTÕES!$K9=0,CARTÕES!$F9=""),0,IF(8>CARTÕES!$F9,0,CARTÕES!$K9+8-1)) | K9: =IF(OR(CARTÕES!$K9=0,CARTÕES!$F9=""),0,IF(9>CARTÕES!$F9,0,CARTÕES!$K9+9-1)) | L9: =IF(OR(CARTÕES!$K9=0,CARTÕES!$F9=""),0,IF(10>CARTÕES!$F9,0,CARTÕES!$K9+10-1)) | M9: =IF(OR(CARTÕES!$K9=0,CARTÕES!$F9=""),0,IF(11>CARTÕES!$F9,0,CARTÕES!$K9+11-1)) | N9: =IF(OR(CARTÕES!$K9=0,CARTÕES!$F9=""),0,IF(12>CARTÕES!$F9,0,CARTÕES!$K9+12-1)) | O9: =IF(OR(CARTÕES!$K9=0,CARTÕES!$F9=""),0,IF(13>CARTÕES!$F9,0,CARTÕES!$K9+13-1)) | P9: =IF(OR(CARTÕES!$K9=0,CARTÕES!$F9=""),0,IF(14>CARTÕES!$F9,0,CARTÕES!$K9+14-1)) | Q9: =IF(OR(CARTÕES!$K9=0,CARTÕES!$F9=""),0,IF(15>CARTÕES!$F9,0,CARTÕES!$K9+15-1)) | R9: =IF(OR(CARTÕES!$K9=0,CARTÕES!$F9=""),0,IF(16>CARTÕES!$F9,0,CARTÕES!$K9+16-1)) | S9: =IF(OR(CARTÕES!$K9=0,CARTÕES!$F9=""),0,IF(17>CARTÕES!$F9,0,CARTÕES!$K9+17-1)) | T9: =IF(OR(CARTÕES!$K9=0,CARTÕES!$F9=""),0,IF(18>CARTÕES!$F9,0,CARTÕES!$K9+18-1)) | U9: =IF(OR(CARTÕES!$K9=0,CARTÕES!$F9=""),0,IF(19>CARTÕES!$F9,0,CARTÕES!$K9+19-1)) | V9: =IF(OR(CARTÕES!$K9=0,CARTÕES!$F9=""),0,IF(20>CARTÕES!$F9,0,CARTÕES!$K9+20-1)) | W9: =IF(OR(CARTÕES!$K9=0,CARTÕES!$F9=""),0,IF(21>CARTÕES!$F9,0,CARTÕES!$K9+21-1)) | X9: =IF(OR(CARTÕES!$K9=0,CARTÕES!$F9=""),0,IF(22>CARTÕES!$F9,0,CARTÕES!$K9+22-1)) | Y9: =IF(OR(CARTÕES!$K9=0,CARTÕES!$F9=""),0,IF(23>CARTÕES!$F9,0,CARTÕES!$K9+23-1)) | Z9: =IF(OR(CARTÕES!$K9=0,CARTÕES!$F9=""),0,IF(24>CARTÕES!$F9,0,CARTÕES!$K9+24-1)) | AA9: =IF(OR(CARTÕES!$K9=0,CARTÕES!$F9=""),0,IF(25>CARTÕES!$F9,0,CARTÕES!$K9+25-1)) | AB9: =IF(OR(CARTÕES!$K9=0,CARTÕES!$F9=""),0,IF(26>CARTÕES!$F9,0,CARTÕES!$K9+26-1)) | AC9: =IF(OR(CARTÕES!$K9=0,CARTÕES!$F9=""),0,IF(27>CARTÕES!$F9,0,CARTÕES!$K9+27-1)) | AD9: =IF(OR(CARTÕES!$K9=0,CARTÕES!$F9=""),0,IF(28>CARTÕES!$F9,0,CARTÕES!$K9+28-1)) | AE9: =IF(OR(CARTÕES!$K9=0,CARTÕES!$F9=""),0,IF(29>CARTÕES!$F9,0,CARTÕES!$K9+29-1)) | AF9: =IF(OR(CARTÕES!$K9=0,CARTÕES!$F9=""),0,IF(30>CARTÕES!$F9,0,CARTÕES!$K9+30-1)) | AG9: =IF(OR(CARTÕES!$K9=0,CARTÕES!$F9=""),0,IF(31>CARTÕES!$F9,0,CARTÕES!$K9+31-1)) | AH9: =IF(OR(CARTÕES!$K9=0,CARTÕES!$F9=""),0,IF(32>CARTÕES!$F9,0,CARTÕES!$K9+32-1)) | AI9: =IF(OR(CARTÕES!$K9=0,CARTÕES!$F9=""),0,IF(33>CARTÕES!$F9,0,CARTÕES!$K9+33-1)) | AJ9: =IF(OR(CARTÕES!$K9=0,CARTÕES!$F9=""),0,IF(34>CARTÕES!$F9,0,CARTÕES!$K9+34-1)) | AK9: =IF(OR(CARTÕES!$K9=0,CARTÕES!$F9=""),0,IF(35>CARTÕES!$F9,0,CARTÕES!$K9+35-1)) | AL9: =IF(OR(CARTÕES!$K9=0,CARTÕES!$F9=""),0,IF(36>CARTÕES!$F9,0,CARTÕES!$K9+36-1)) | AM9: =IF(C9=0,0,IF(1=CARTÕES!$F9,CARTÕES!$E9-(CARTÕES!$F9-1)*ROUND(CARTÕES!$E9/CARTÕES!$F9,0),ROUND(CARTÕES!$E9/CARTÕES!$F9,0))) | AN9: =IF(D9=0,0,IF(2=CARTÕES!$F9,CARTÕES!$E9-(CARTÕES!$F9-1)*ROUND(CARTÕES!$E9/CARTÕES!$F9,0),ROUND(CARTÕES!$E9/CARTÕES!$F9,0))) | AO9: =IF(E9=0,0,IF(3=CARTÕES!$F9,CARTÕES!$E9-(CARTÕES!$F9-1)*ROUND(CARTÕES!$E9/CARTÕES!$F9,0),ROUND(CARTÕES!$E9/CARTÕES!$F9,0))) | AP9: =IF(F9=0,0,IF(4=CARTÕES!$F9,CARTÕES!$E9-(CARTÕES!$F9-1)*ROUND(CARTÕES!$E9/CARTÕES!$F9,0),ROUND(CARTÕES!$E9/CARTÕES!$F9,0))) | AQ9: =IF(G9=0,0,IF(5=CARTÕES!$F9,CARTÕES!$E9-(CARTÕES!$F9-1)*ROUND(CARTÕES!$E9/CARTÕES!$F9,0),ROUND(CARTÕES!$E9/CARTÕES!$F9,0))) | AR9: =IF(H9=0,0,IF(6=CARTÕES!$F9,CARTÕES!$E9-(CARTÕES!$F9-1)*ROUND(CARTÕES!$E9/CARTÕES!$F9,0),ROUND(CARTÕES!$E9/CARTÕES!$F9,0))) | AS9: =IF(I9=0,0,IF(7=CARTÕES!$F9,CARTÕES!$E9-(CARTÕES!$F9-1)*ROUND(CARTÕES!$E9/CARTÕES!$F9,0),ROUND(CARTÕES!$E9/CARTÕES!$F9,0))) | AT9: =IF(J9=0,0,IF(8=CARTÕES!$F9,CARTÕES!$E9-(CARTÕES!$F9-1)*ROUND(CARTÕES!$E9/CARTÕES!$F9,0),ROUND(CARTÕES!$E9/CARTÕES!$F9,0))) | AU9: =IF(K9=0,0,IF(9=CARTÕES!$F9,CARTÕES!$E9-(CARTÕES!$F9-1)*ROUND(CARTÕES!$E9/CARTÕES!$F9,0),ROUND(CARTÕES!$E9/CARTÕES!$F9,0))) | AV9: =IF(L9=0,0,IF(10=CARTÕES!$F9,CARTÕES!$E9-(CARTÕES!$F9-1)*ROUND(CARTÕES!$E9/CARTÕES!$F9,0),ROUND(CARTÕES!$E9/CARTÕES!$F9,0))) | AW9: =IF(M9=0,0,IF(11=CARTÕES!$F9,CARTÕES!$E9-(CARTÕES!$F9-1)*ROUND(CARTÕES!$E9/CARTÕES!$F9,0),ROUND(CARTÕES!$E9/CARTÕES!$F9,0))) | AX9: =IF(N9=0,0,IF(12=CARTÕES!$F9,CARTÕES!$E9-(CARTÕES!$F9-1)*ROUND(CARTÕES!$E9/CARTÕES!$F9,0),ROUND(CARTÕES!$E9/CARTÕES!$F9,0))) | AY9: =IF(O9=0,0,IF(13=CARTÕES!$F9,CARTÕES!$E9-(CARTÕES!$F9-1)*ROUND(CARTÕES!$E9/CARTÕES!$F9,0),ROUND(CARTÕES!$E9/CARTÕES!$F9,0))) | AZ9: =IF(P9=0,0,IF(14=CARTÕES!$F9,CARTÕES!$E9-(CARTÕES!$F9-1)*ROUND(CARTÕES!$E9/CARTÕES!$F9,0),ROUND(CARTÕES!$E9/CARTÕES!$F9,0))) | BA9: =IF(Q9=0,0,IF(15=CARTÕES!$F9,CARTÕES!$E9-(CARTÕES!$F9-1)*ROUND(CARTÕES!$E9/CARTÕES!$F9,0),ROUND(CARTÕES!$E9/CARTÕES!$F9,0))) | BB9: =IF(R9=0,0,IF(16=CARTÕES!$F9,CARTÕES!$E9-(CARTÕES!$F9-1)*ROUND(CARTÕES!$E9/CARTÕES!$F9,0),ROUND(CARTÕES!$E9/CARTÕES!$F9,0))) | BC9: =IF(S9=0,0,IF(17=CARTÕES!$F9,CARTÕES!$E9-(CARTÕES!$F9-1)*ROUND(CARTÕES!$E9/CARTÕES!$F9,0),ROUND(CARTÕES!$E9/CARTÕES!$F9,0))) | BD9: =IF(T9=0,0,IF(18=CARTÕES!$F9,CARTÕES!$E9-(CARTÕES!$F9-1)*ROUND(CARTÕES!$E9/CARTÕES!$F9,0),ROUND(CARTÕES!$E9/CARTÕES!$F9,0))) | BE9: =IF(U9=0,0,IF(19=CARTÕES!$F9,CARTÕES!$E9-(CARTÕES!$F9-1)*ROUND(CARTÕES!$E9/CARTÕES!$F9,0),ROUND(CARTÕES!$E9/CARTÕES!$F9,0))) | BF9: =IF(V9=0,0,IF(20=CARTÕES!$F9,CARTÕES!$E9-(CARTÕES!$F9-1)*ROUND(CARTÕES!$E9/CARTÕES!$F9,0),ROUND(CARTÕES!$E9/CARTÕES!$F9,0))) | BG9: =IF(W9=0,0,IF(21=CARTÕES!$F9,CARTÕES!$E9-(CARTÕES!$F9-1)*ROUND(CARTÕES!$E9/CARTÕES!$F9,0),ROUND(CARTÕES!$E9/CARTÕES!$F9,0))) | BH9: =IF(X9=0,0,IF(22=CARTÕES!$F9,CARTÕES!$E9-(CARTÕES!$F9-1)*ROUND(CARTÕES!$E9/CARTÕES!$F9,0),ROUND(CARTÕES!$E9/CARTÕES!$F9,0))) | BI9: =IF(Y9=0,0,IF(23=CARTÕES!$F9,CARTÕES!$E9-(CARTÕES!$F9-1)*ROUND(CARTÕES!$E9/CARTÕES!$F9,0),ROUND(CARTÕES!$E9/CARTÕES!$F9,0))) | BJ9: =IF(Z9=0,0,IF(24=CARTÕES!$F9,CARTÕES!$E9-(CARTÕES!$F9-1)*ROUND(CARTÕES!$E9/CARTÕES!$F9,0),ROUND(CARTÕES!$E9/CARTÕES!$F9,0))) | BK9: =IF(AA9=0,0,IF(25=CARTÕES!$F9,CARTÕES!$E9-(CARTÕES!$F9-1)*ROUND(CARTÕES!$E9/CARTÕES!$F9,0),ROUND(CARTÕES!$E9/CARTÕES!$F9,0))) | BL9: =IF(AB9=0,0,IF(26=CARTÕES!$F9,CARTÕES!$E9-(CARTÕES!$F9-1)*ROUND(CARTÕES!$E9/CARTÕES!$F9,0),ROUND(CARTÕES!$E9/CARTÕES!$F9,0))) | BM9: =IF(AC9=0,0,IF(27=CARTÕES!$F9,CARTÕES!$E9-(CARTÕES!$F9-1)*ROUND(CARTÕES!$E9/CARTÕES!$F9,0),ROUND(CARTÕES!$E9/CARTÕES!$F9,0))) | BN9: =IF(AD9=0,0,IF(28=CARTÕES!$F9,CARTÕES!$E9-(CARTÕES!$F9-1)*ROUND(CARTÕES!$E9/CARTÕES!$F9,0),ROUND(CARTÕES!$E9/CARTÕES!$F9,0))) | BO9: =IF(AE9=0,0,IF(29=CARTÕES!$F9,CARTÕES!$E9-(CARTÕES!$F9-1)*ROUND(CARTÕES!$E9/CARTÕES!$F9,0),ROUND(CARTÕES!$E9/CARTÕES!$F9,0))) | BP9: =IF(AF9=0,0,IF(30=CARTÕES!$F9,CARTÕES!$E9-(CARTÕES!$F9-1)*ROUND(CARTÕES!$E9/CARTÕES!$F9,0),ROUND(CARTÕES!$E9/CARTÕES!$F9,0))) | BQ9: =IF(AG9=0,0,IF(31=CARTÕES!$F9,CARTÕES!$E9-(CARTÕES!$F9-1)*ROUND(CARTÕES!$E9/CARTÕES!$F9,0),ROUND(CARTÕES!$E9/CARTÕES!$F9,0))) | BR9: =IF(AH9=0,0,IF(32=CARTÕES!$F9,CARTÕES!$E9-(CARTÕES!$F9-1)*ROUND(CARTÕES!$E9/CARTÕES!$F9,0),ROUND(CARTÕES!$E9/CARTÕES!$F9,0))) | BS9: =IF(AI9=0,0,IF(33=CARTÕES!$F9,CARTÕES!$E9-(CARTÕES!$F9-1)*ROUND(CARTÕES!$E9/CARTÕES!$F9,0),ROUND(CARTÕES!$E9/CARTÕES!$F9,0))) | BT9: =IF(AJ9=0,0,IF(34=CARTÕES!$F9,CARTÕES!$E9-(CARTÕES!$F9-1)*ROUND(CARTÕES!$E9/CARTÕES!$F9,0),ROUND(CARTÕES!$E9/CARTÕES!$F9,0))) | BU9: =IF(AK9=0,0,IF(35=CARTÕES!$F9,CARTÕES!$E9-(CARTÕES!$F9-1)*ROUND(CARTÕES!$E9/CARTÕES!$F9,0),ROUND(CARTÕES!$E9/CARTÕES!$F9,0))) | BV9: =IF(AL9=0,0,IF(36=CARTÕES!$F9,CARTÕES!$E9-(CARTÕES!$F9-1)*ROUND(CARTÕES!$E9/CARTÕES!$F9,0),ROUND(CARTÕES!$E9/CARTÕES!$F9,0)))
A10: =IF(CARTÕES!$C10="","",CARTÕES!$C10) | B10: =SUMPRODUCT((C10:AL10='RESUMO MENSAL'!$C$4)*AM10:BV10) | C10: =IF(OR(CARTÕES!$K10=0,CARTÕES!$F10=""),0,IF(1>CARTÕES!$F10,0,CARTÕES!$K10+1-1)) | D10: =IF(OR(CARTÕES!$K10=0,CARTÕES!$F10=""),0,IF(2>CARTÕES!$F10,0,CARTÕES!$K10+2-1)) | E10: =IF(OR(CARTÕES!$K10=0,CARTÕES!$F10=""),0,IF(3>CARTÕES!$F10,0,CARTÕES!$K10+3-1)) | F10: =IF(OR(CARTÕES!$K10=0,CARTÕES!$F10=""),0,IF(4>CARTÕES!$F10,0,CARTÕES!$K10+4-1)) | G10: =IF(OR(CARTÕES!$K10=0,CARTÕES!$F10=""),0,IF(5>CARTÕES!$F10,0,CARTÕES!$K10+5-1)) | H10: =IF(OR(CARTÕES!$K10=0,CARTÕES!$F10=""),0,IF(6>CARTÕES!$F10,0,CARTÕES!$K10+6-1)) | I10: =IF(OR(CARTÕES!$K10=0,CARTÕES!$F10=""),0,IF(7>CARTÕES!$F10,0,CARTÕES!$K10+7-1)) | J10: =IF(OR(CARTÕES!$K10=0,CARTÕES!$F10=""),0,IF(8>CARTÕES!$F10,0,CARTÕES!$K10+8-1)) | K10: =IF(OR(CARTÕES!$K10=0,CARTÕES!$F10=""),0,IF(9>CARTÕES!$F10,0,CARTÕES!$K10+9-1)) | L10: =IF(OR(CARTÕES!$K10=0,CARTÕES!$F10=""),0,IF(10>CARTÕES!$F10,0,CARTÕES!$K10+10-1)) | M10: =IF(OR(CARTÕES!$K10=0,CARTÕES!$F10=""),0,IF(11>CARTÕES!$F10,0,CARTÕES!$K10+11-1)) | N10: =IF(OR(CARTÕES!$K10=0,CARTÕES!$F10=""),0,IF(12>CARTÕES!$F10,0,CARTÕES!$K10+12-1)) | O10: =IF(OR(CARTÕES!$K10=0,CARTÕES!$F10=""),0,IF(13>CARTÕES!$F10,0,CARTÕES!$K10+13-1)) | P10: =IF(OR(CARTÕES!$K10=0,CARTÕES!$F10=""),0,IF(14>CARTÕES!$F10,0,CARTÕES!$K10+14-1)) | Q10: =IF(OR(CARTÕES!$K10=0,CARTÕES!$F10=""),0,IF(15>CARTÕES!$F10,0,CARTÕES!$K10+15-1)) | R10: =IF(OR(CARTÕES!$K10=0,CARTÕES!$F10=""),0,IF(16>CARTÕES!$F10,0,CARTÕES!$K10+16-1)) | S10: =IF(OR(CARTÕES!$K10=0,CARTÕES!$F10=""),0,IF(17>CARTÕES!$F10,0,CARTÕES!$K10+17-1)) | T10: =IF(OR(CARTÕES!$K10=0,CARTÕES!$F10=""),0,IF(18>CARTÕES!$F10,0,CARTÕES!$K10+18-1)) | U10: =IF(OR(CARTÕES!$K10=0,CARTÕES!$F10=""),0,IF(19>CARTÕES!$F10,0,CARTÕES!$K10+19-1)) | V10: =IF(OR(CARTÕES!$K10=0,CARTÕES!$F10=""),0,IF(20>CARTÕES!$F10,0,CARTÕES!$K10+20-1)) | W10: =IF(OR(CARTÕES!$K10=0,CARTÕES!$F10=""),0,IF(21>CARTÕES!$F10,0,CARTÕES!$K10+21-1)) | X10: =IF(OR(CARTÕES!$K10=0,CARTÕES!$F10=""),0,IF(22>CARTÕES!$F10,0,CARTÕES!$K10+22-1)) | Y10: =IF(OR(CARTÕES!$K10=0,CARTÕES!$F10=""),0,IF(23>CARTÕES!$F10,0,CARTÕES!$K10+23-1)) | Z10: =IF(OR(CARTÕES!$K10=0,CARTÕES!$F10=""),0,IF(24>CARTÕES!$F10,0,CARTÕES!$K10+24-1)) | AA10: =IF(OR(CARTÕES!$K10=0,CARTÕES!$F10=""),0,IF(25>CARTÕES!$F10,0,CARTÕES!$K10+25-1)) | AB10: =IF(OR(CARTÕES!$K10=0,CARTÕES!$F10=""),0,IF(26>CARTÕES!$F10,0,CARTÕES!$K10+26-1)) | AC10: =IF(OR(CARTÕES!$K10=0,CARTÕES!$F10=""),0,IF(27>CARTÕES!$F10,0,CARTÕES!$K10+27-1)) | AD10: =IF(OR(CARTÕES!$K10=0,CARTÕES!$F10=""),0,IF(28>CARTÕES!$F10,0,CARTÕES!$K10+28-1)) | AE10: =IF(OR(CARTÕES!$K10=0,CARTÕES!$F10=""),0,IF(29>CARTÕES!$F10,0,CARTÕES!$K10+29-1)) | AF10: =IF(OR(CARTÕES!$K10=0,CARTÕES!$F10=""),0,IF(30>CARTÕES!$F10,0,CARTÕES!$K10+30-1)) | AG10: =IF(OR(CARTÕES!$K10=0,CARTÕES!$F10=""),0,IF(31>CARTÕES!$F10,0,CARTÕES!$K10+31-1)) | AH10: =IF(OR(CARTÕES!$K10=0,CARTÕES!$F10=""),0,IF(32>CARTÕES!$F10,0,CARTÕES!$K10+32-1)) | AI10: =IF(OR(CARTÕES!$K10=0,CARTÕES!$F10=""),0,IF(33>CARTÕES!$F10,0,CARTÕES!$K10+33-1)) | AJ10: =IF(OR(CARTÕES!$K10=0,CARTÕES!$F10=""),0,IF(34>CARTÕES!$F10,0,CARTÕES!$K10+34-1)) | AK10: =IF(OR(CARTÕES!$K10=0,CARTÕES!$F10=""),0,IF(35>CARTÕES!$F10,0,CARTÕES!$K10+35-1)) | AL10: =IF(OR(CARTÕES!$K10=0,CARTÕES!$F10=""),0,IF(36>CARTÕES!$F10,0,CARTÕES!$K10+36-1)) | AM10: =IF(C10=0,0,IF(1=CARTÕES!$F10,CARTÕES!$E10-(CARTÕES!$F10-1)*ROUND(CARTÕES!$E10/CARTÕES!$F10,0),ROUND(CARTÕES!$E10/CARTÕES!$F10,0))) | AN10: =IF(D10=0,0,IF(2=CARTÕES!$F10,CARTÕES!$E10-(CARTÕES!$F10-1)*ROUND(CARTÕES!$E10/CARTÕES!$F10,0),ROUND(CARTÕES!$E10/CARTÕES!$F10,0))) | AO10: =IF(E10=0,0,IF(3=CARTÕES!$F10,CARTÕES!$E10-(CARTÕES!$F10-1)*ROUND(CARTÕES!$E10/CARTÕES!$F10,0),ROUND(CARTÕES!$E10/CARTÕES!$F10,0))) | AP10: =IF(F10=0,0,IF(4=CARTÕES!$F10,CARTÕES!$E10-(CARTÕES!$F10-1)*ROUND(CARTÕES!$E10/CARTÕES!$F10,0),ROUND(CARTÕES!$E10/CARTÕES!$F10,0))) | AQ10: =IF(G10=0,0,IF(5=CARTÕES!$F10,CARTÕES!$E10-(CARTÕES!$F10-1)*ROUND(CARTÕES!$E10/CARTÕES!$F10,0),ROUND(CARTÕES!$E10/CARTÕES!$F10,0))) | AR10: =IF(H10=0,0,IF(6=CARTÕES!$F10,CARTÕES!$E10-(CARTÕES!$F10-1)*ROUND(CARTÕES!$E10/CARTÕES!$F10,0),ROUND(CARTÕES!$E10/CARTÕES!$F10,0))) | AS10: =IF(I10=0,0,IF(7=CARTÕES!$F10,CARTÕES!$E10-(CARTÕES!$F10-1)*ROUND(CARTÕES!$E10/CARTÕES!$F10,0),ROUND(CARTÕES!$E10/CARTÕES!$F10,0))) | AT10: =IF(J10=0,0,IF(8=CARTÕES!$F10,CARTÕES!$E10-(CARTÕES!$F10-1)*ROUND(CARTÕES!$E10/CARTÕES!$F10,0),ROUND(CARTÕES!$E10/CARTÕES!$F10,0))) | AU10: =IF(K10=0,0,IF(9=CARTÕES!$F10,CARTÕES!$E10-(CARTÕES!$F10-1)*ROUND(CARTÕES!$E10/CARTÕES!$F10,0),ROUND(CARTÕES!$E10/CARTÕES!$F10,0))) | AV10: =IF(L10=0,0,IF(10=CARTÕES!$F10,CARTÕES!$E10-(CARTÕES!$F10-1)*ROUND(CARTÕES!$E10/CARTÕES!$F10,0),ROUND(CARTÕES!$E10/CARTÕES!$F10,0))) | AW10: =IF(M10=0,0,IF(11=CARTÕES!$F10,CARTÕES!$E10-(CARTÕES!$F10-1)*ROUND(CARTÕES!$E10/CARTÕES!$F10,0),ROUND(CARTÕES!$E10/CARTÕES!$F10,0))) | AX10: =IF(N10=0,0,IF(12=CARTÕES!$F10,CARTÕES!$E10-(CARTÕES!$F10-1)*ROUND(CARTÕES!$E10/CARTÕES!$F10,0),ROUND(CARTÕES!$E10/CARTÕES!$F10,0))) | AY10: =IF(O10=0,0,IF(13=CARTÕES!$F10,CARTÕES!$E10-(CARTÕES!$F10-1)*ROUND(CARTÕES!$E10/CARTÕES!$F10,0),ROUND(CARTÕES!$E10/CARTÕES!$F10,0))) | AZ10: =IF(P10=0,0,IF(14=CARTÕES!$F10,CARTÕES!$E10-(CARTÕES!$F10-1)*ROUND(CARTÕES!$E10/CARTÕES!$F10,0),ROUND(CARTÕES!$E10/CARTÕES!$F10,0))) | BA10: =IF(Q10=0,0,IF(15=CARTÕES!$F10,CARTÕES!$E10-(CARTÕES!$F10-1)*ROUND(CARTÕES!$E10/CARTÕES!$F10,0),ROUND(CARTÕES!$E10/CARTÕES!$F10,0))) | BB10: =IF(R10=0,0,IF(16=CARTÕES!$F10,CARTÕES!$E10-(CARTÕES!$F10-1)*ROUND(CARTÕES!$E10/CARTÕES!$F10,0),ROUND(CARTÕES!$E10/CARTÕES!$F10,0))) | BC10: =IF(S10=0,0,IF(17=CARTÕES!$F10,CARTÕES!$E10-(CARTÕES!$F10-1)*ROUND(CARTÕES!$E10/CARTÕES!$F10,0),ROUND(CARTÕES!$E10/CARTÕES!$F10,0))) | BD10: =IF(T10=0,0,IF(18=CARTÕES!$F10,CARTÕES!$E10-(CARTÕES!$F10-1)*ROUND(CARTÕES!$E10/CARTÕES!$F10,0),ROUND(CARTÕES!$E10/CARTÕES!$F10,0))) | BE10: =IF(U10=0,0,IF(19=CARTÕES!$F10,CARTÕES!$E10-(CARTÕES!$F10-1)*ROUND(CARTÕES!$E10/CARTÕES!$F10,0),ROUND(CARTÕES!$E10/CARTÕES!$F10,0))) | BF10: =IF(V10=0,0,IF(20=CARTÕES!$F10,CARTÕES!$E10-(CARTÕES!$F10-1)*ROUND(CARTÕES!$E10/CARTÕES!$F10,0),ROUND(CARTÕES!$E10/CARTÕES!$F10,0))) | BG10: =IF(W10=0,0,IF(21=CARTÕES!$F10,CARTÕES!$E10-(CARTÕES!$F10-1)*ROUND(CARTÕES!$E10/CARTÕES!$F10,0),ROUND(CARTÕES!$E10/CARTÕES!$F10,0))) | BH10: =IF(X10=0,0,IF(22=CARTÕES!$F10,CARTÕES!$E10-(CARTÕES!$F10-1)*ROUND(CARTÕES!$E10/CARTÕES!$F10,0),ROUND(CARTÕES!$E10/CARTÕES!$F10,0))) | BI10: =IF(Y10=0,0,IF(23=CARTÕES!$F10,CARTÕES!$E10-(CARTÕES!$F10-1)*ROUND(CARTÕES!$E10/CARTÕES!$F10,0),ROUND(CARTÕES!$E10/CARTÕES!$F10,0))) | BJ10: =IF(Z10=0,0,IF(24=CARTÕES!$F10,CARTÕES!$E10-(CARTÕES!$F10-1)*ROUND(CARTÕES!$E10/CARTÕES!$F10,0),ROUND(CARTÕES!$E10/CARTÕES!$F10,0))) | BK10: =IF(AA10=0,0,IF(25=CARTÕES!$F10,CARTÕES!$E10-(CARTÕES!$F10-1)*ROUND(CARTÕES!$E10/CARTÕES!$F10,0),ROUND(CARTÕES!$E10/CARTÕES!$F10,0))) | BL10: =IF(AB10=0,0,IF(26=CARTÕES!$F10,CARTÕES!$E10-(CARTÕES!$F10-1)*ROUND(CARTÕES!$E10/CARTÕES!$F10,0),ROUND(CARTÕES!$E10/CARTÕES!$F10,0))) | BM10: =IF(AC10=0,0,IF(27=CARTÕES!$F10,CARTÕES!$E10-(CARTÕES!$F10-1)*ROUND(CARTÕES!$E10/CARTÕES!$F10,0),ROUND(CARTÕES!$E10/CARTÕES!$F10,0))) | BN10: =IF(AD10=0,0,IF(28=CARTÕES!$F10,CARTÕES!$E10-(CARTÕES!$F10-1)*ROUND(CARTÕES!$E10/CARTÕES!$F10,0),ROUND(CARTÕES!$E10/CARTÕES!$F10,0))) | BO10: =IF(AE10=0,0,IF(29=CARTÕES!$F10,CARTÕES!$E10-(CARTÕES!$F10-1)*ROUND(CARTÕES!$E10/CARTÕES!$F10,0),ROUND(CARTÕES!$E10/CARTÕES!$F10,0))) | BP10: =IF(AF10=0,0,IF(30=CARTÕES!$F10,CARTÕES!$E10-(CARTÕES!$F10-1)*ROUND(CARTÕES!$E10/CARTÕES!$F10,0),ROUND(CARTÕES!$E10/CARTÕES!$F10,0))) | BQ10: =IF(AG10=0,0,IF(31=CARTÕES!$F10,CARTÕES!$E10-(CARTÕES!$F10-1)*ROUND(CARTÕES!$E10/CARTÕES!$F10,0),ROUND(CARTÕES!$E10/CARTÕES!$F10,0))) | BR10: =IF(AH10=0,0,IF(32=CARTÕES!$F10,CARTÕES!$E10-(CARTÕES!$F10-1)*ROUND(CARTÕES!$E10/CARTÕES!$F10,0),ROUND(CARTÕES!$E10/CARTÕES!$F10,0))) | BS10: =IF(AI10=0,0,IF(33=CARTÕES!$F10,CARTÕES!$E10-(CARTÕES!$F10-1)*ROUND(CARTÕES!$E10/CARTÕES!$F10,0),ROUND(CARTÕES!$E10/CARTÕES!$F10,0))) | BT10: =IF(AJ10=0,0,IF(34=CARTÕES!$F10,CARTÕES!$E10-(CARTÕES!$F10-1)*ROUND(CARTÕES!$E10/CARTÕES!$F10,0),ROUND(CARTÕES!$E10/CARTÕES!$F10,0))) | BU10: =IF(AK10=0,0,IF(35=CARTÕES!$F10,CARTÕES!$E10-(CARTÕES!$F10-1)*ROUND(CARTÕES!$E10/CARTÕES!$F10,0),ROUND(CARTÕES!$E10/CARTÕES!$F10,0))) | BV10: =IF(AL10=0,0,IF(36=CARTÕES!$F10,CARTÕES!$E10-(CARTÕES!$F10-1)*ROUND(CARTÕES!$E10/CARTÕES!$F10,0),ROUND(CARTÕES!$E10/CARTÕES!$F10,0)))
A11: =IF(CARTÕES!$C11="","",CARTÕES!$C11) | B11: =SUMPRODUCT((C11:AL11='RESUMO MENSAL'!$C$4)*AM11:BV11) | C11: =IF(OR(CARTÕES!$K11=0,CARTÕES!$F11=""),0,IF(1>CARTÕES!$F11,0,CARTÕES!$K11+1-1)) | D11: =IF(OR(CARTÕES!$K11=0,CARTÕES!$F11=""),0,IF(2>CARTÕES!$F11,0,CARTÕES!$K11+2-1)) | E11: =IF(OR(CARTÕES!$K11=0,CARTÕES!$F11=""),0,IF(3>CARTÕES!$F11,0,CARTÕES!$K11+3-1)) | F11: =IF(OR(CARTÕES!$K11=0,CARTÕES!$F11=""),0,IF(4>CARTÕES!$F11,0,CARTÕES!$K11+4-1)) | G11: =IF(OR(CARTÕES!$K11=0,CARTÕES!$F11=""),0,IF(5>CARTÕES!$F11,0,CARTÕES!$K11+5-1)) | H11: =IF(OR(CARTÕES!$K11=0,CARTÕES!$F11=""),0,IF(6>CARTÕES!$F11,0,CARTÕES!$K11+6-1)) | I11: =IF(OR(CARTÕES!$K11=0,CARTÕES!$F11=""),0,IF(7>CARTÕES!$F11,0,CARTÕES!$K11+7-1)) | J11: =IF(OR(CARTÕES!$K11=0,CARTÕES!$F11=""),0,IF(8>CARTÕES!$F11,0,CARTÕES!$K11+8-1)) | K11: =IF(OR(CARTÕES!$K11=0,CARTÕES!$F11=""),0,IF(9>CARTÕES!$F11,0,CARTÕES!$K11+9-1)) | L11: =IF(OR(CARTÕES!$K11=0,CARTÕES!$F11=""),0,IF(10>CARTÕES!$F11,0,CARTÕES!$K11+10-1)) | M11: =IF(OR(CARTÕES!$K11=0,CARTÕES!$F11=""),0,IF(11>CARTÕES!$F11,0,CARTÕES!$K11+11-1)) | N11: =IF(OR(CARTÕES!$K11=0,CARTÕES!$F11=""),0,IF(12>CARTÕES!$F11,0,CARTÕES!$K11+12-1)) | O11: =IF(OR(CARTÕES!$K11=0,CARTÕES!$F11=""),0,IF(13>CARTÕES!$F11,0,CARTÕES!$K11+13-1)) | P11: =IF(OR(CARTÕES!$K11=0,CARTÕES!$F11=""),0,IF(14>CARTÕES!$F11,0,CARTÕES!$K11+14-1)) | Q11: =IF(OR(CARTÕES!$K11=0,CARTÕES!$F11=""),0,IF(15>CARTÕES!$F11,0,CARTÕES!$K11+15-1)) | R11: =IF(OR(CARTÕES!$K11=0,CARTÕES!$F11=""),0,IF(16>CARTÕES!$F11,0,CARTÕES!$K11+16-1)) | S11: =IF(OR(CARTÕES!$K11=0,CARTÕES!$F11=""),0,IF(17>CARTÕES!$F11,0,CARTÕES!$K11+17-1)) | T11: =IF(OR(CARTÕES!$K11=0,CARTÕES!$F11=""),0,IF(18>CARTÕES!$F11,0,CARTÕES!$K11+18-1)) | U11: =IF(OR(CARTÕES!$K11=0,CARTÕES!$F11=""),0,IF(19>CARTÕES!$F11,0,CARTÕES!$K11+19-1)) | V11: =IF(OR(CARTÕES!$K11=0,CARTÕES!$F11=""),0,IF(20>CARTÕES!$F11,0,CARTÕES!$K11+20-1)) | W11: =IF(OR(CARTÕES!$K11=0,CARTÕES!$F11=""),0,IF(21>CARTÕES!$F11,0,CARTÕES!$K11+21-1)) | X11: =IF(OR(CARTÕES!$K11=0,CARTÕES!$F11=""),0,IF(22>CARTÕES!$F11,0,CARTÕES!$K11+22-1)) | Y11: =IF(OR(CARTÕES!$K11=0,CARTÕES!$F11=""),0,IF(23>CARTÕES!$F11,0,CARTÕES!$K11+23-1)) | Z11: =IF(OR(CARTÕES!$K11=0,CARTÕES!$F11=""),0,IF(24>CARTÕES!$F11,0,CARTÕES!$K11+24-1)) | AA11: =IF(OR(CARTÕES!$K11=0,CARTÕES!$F11=""),0,IF(25>CARTÕES!$F11,0,CARTÕES!$K11+25-1)) | AB11: =IF(OR(CARTÕES!$K11=0,CARTÕES!$F11=""),0,IF(26>CARTÕES!$F11,0,CARTÕES!$K11+26-1)) | AC11: =IF(OR(CARTÕES!$K11=0,CARTÕES!$F11=""),0,IF(27>CARTÕES!$F11,0,CARTÕES!$K11+27-1)) | AD11: =IF(OR(CARTÕES!$K11=0,CARTÕES!$F11=""),0,IF(28>CARTÕES!$F11,0,CARTÕES!$K11+28-1)) | AE11: =IF(OR(CARTÕES!$K11=0,CARTÕES!$F11=""),0,IF(29>CARTÕES!$F11,0,CARTÕES!$K11+29-1)) | AF11: =IF(OR(CARTÕES!$K11=0,CARTÕES!$F11=""),0,IF(30>CARTÕES!$F11,0,CARTÕES!$K11+30-1)) | AG11: =IF(OR(CARTÕES!$K11=0,CARTÕES!$F11=""),0,IF(31>CARTÕES!$F11,0,CARTÕES!$K11+31-1)) | AH11: =IF(OR(CARTÕES!$K11=0,CARTÕES!$F11=""),0,IF(32>CARTÕES!$F11,0,CARTÕES!$K11+32-1)) | AI11: =IF(OR(CARTÕES!$K11=0,CARTÕES!$F11=""),0,IF(33>CARTÕES!$F11,0,CARTÕES!$K11+33-1)) | AJ11: =IF(OR(CARTÕES!$K11=0,CARTÕES!$F11=""),0,IF(34>CARTÕES!$F11,0,CARTÕES!$K11+34-1)) | AK11: =IF(OR(CARTÕES!$K11=0,CARTÕES!$F11=""),0,IF(35>CARTÕES!$F11,0,CARTÕES!$K11+35-1)) | AL11: =IF(OR(CARTÕES!$K11=0,CARTÕES!$F11=""),0,IF(36>CARTÕES!$F11,0,CARTÕES!$K11+36-1)) | AM11: =IF(C11=0,0,IF(1=CARTÕES!$F11,CARTÕES!$E11-(CARTÕES!$F11-1)*ROUND(CARTÕES!$E11/CARTÕES!$F11,0),ROUND(CARTÕES!$E11/CARTÕES!$F11,0))) | AN11: =IF(D11=0,0,IF(2=CARTÕES!$F11,CARTÕES!$E11-(CARTÕES!$F11-1)*ROUND(CARTÕES!$E11/CARTÕES!$F11,0),ROUND(CARTÕES!$E11/CARTÕES!$F11,0))) | AO11: =IF(E11=0,0,IF(3=CARTÕES!$F11,CARTÕES!$E11-(CARTÕES!$F11-1)*ROUND(CARTÕES!$E11/CARTÕES!$F11,0),ROUND(CARTÕES!$E11/CARTÕES!$F11,0))) | AP11: =IF(F11=0,0,IF(4=CARTÕES!$F11,CARTÕES!$E11-(CARTÕES!$F11-1)*ROUND(CARTÕES!$E11/CARTÕES!$F11,0),ROUND(CARTÕES!$E11/CARTÕES!$F11,0))) | AQ11: =IF(G11=0,0,IF(5=CARTÕES!$F11,CARTÕES!$E11-(CARTÕES!$F11-1)*ROUND(CARTÕES!$E11/CARTÕES!$F11,0),ROUND(CARTÕES!$E11/CARTÕES!$F11,0))) | AR11: =IF(H11=0,0,IF(6=CARTÕES!$F11,CARTÕES!$E11-(CARTÕES!$F11-1)*ROUND(CARTÕES!$E11/CARTÕES!$F11,0),ROUND(CARTÕES!$E11/CARTÕES!$F11,0))) | AS11: =IF(I11=0,0,IF(7=CARTÕES!$F11,CARTÕES!$E11-(CARTÕES!$F11-1)*ROUND(CARTÕES!$E11/CARTÕES!$F11,0),ROUND(CARTÕES!$E11/CARTÕES!$F11,0))) | AT11: =IF(J11=0,0,IF(8=CARTÕES!$F11,CARTÕES!$E11-(CARTÕES!$F11-1)*ROUND(CARTÕES!$E11/CARTÕES!$F11,0),ROUND(CARTÕES!$E11/CARTÕES!$F11,0))) | AU11: =IF(K11=0,0,IF(9=CARTÕES!$F11,CARTÕES!$E11-(CARTÕES!$F11-1)*ROUND(CARTÕES!$E11/CARTÕES!$F11,0),ROUND(CARTÕES!$E11/CARTÕES!$F11,0))) | AV11: =IF(L11=0,0,IF(10=CARTÕES!$F11,CARTÕES!$E11-(CARTÕES!$F11-1)*ROUND(CARTÕES!$E11/CARTÕES!$F11,0),ROUND(CARTÕES!$E11/CARTÕES!$F11,0))) | AW11: =IF(M11=0,0,IF(11=CARTÕES!$F11,CARTÕES!$E11-(CARTÕES!$F11-1)*ROUND(CARTÕES!$E11/CARTÕES!$F11,0),ROUND(CARTÕES!$E11/CARTÕES!$F11,0))) | AX11: =IF(N11=0,0,IF(12=CARTÕES!$F11,CARTÕES!$E11-(CARTÕES!$F11-1)*ROUND(CARTÕES!$E11/CARTÕES!$F11,0),ROUND(CARTÕES!$E11/CARTÕES!$F11,0))) | AY11: =IF(O11=0,0,IF(13=CARTÕES!$F11,CARTÕES!$E11-(CARTÕES!$F11-1)*ROUND(CARTÕES!$E11/CARTÕES!$F11,0),ROUND(CARTÕES!$E11/CARTÕES!$F11,0))) | AZ11: =IF(P11=0,0,IF(14=CARTÕES!$F11,CARTÕES!$E11-(CARTÕES!$F11-1)*ROUND(CARTÕES!$E11/CARTÕES!$F11,0),ROUND(CARTÕES!$E11/CARTÕES!$F11,0))) | BA11: =IF(Q11=0,0,IF(15=CARTÕES!$F11,CARTÕES!$E11-(CARTÕES!$F11-1)*ROUND(CARTÕES!$E11/CARTÕES!$F11,0),ROUND(CARTÕES!$E11/CARTÕES!$F11,0))) | BB11: =IF(R11=0,0,IF(16=CARTÕES!$F11,CARTÕES!$E11-(CARTÕES!$F11-1)*ROUND(CARTÕES!$E11/CARTÕES!$F11,0),ROUND(CARTÕES!$E11/CARTÕES!$F11,0))) | BC11: =IF(S11=0,0,IF(17=CARTÕES!$F11,CARTÕES!$E11-(CARTÕES!$F11-1)*ROUND(CARTÕES!$E11/CARTÕES!$F11,0),ROUND(CARTÕES!$E11/CARTÕES!$F11,0))) | BD11: =IF(T11=0,0,IF(18=CARTÕES!$F11,CARTÕES!$E11-(CARTÕES!$F11-1)*ROUND(CARTÕES!$E11/CARTÕES!$F11,0),ROUND(CARTÕES!$E11/CARTÕES!$F11,0))) | BE11: =IF(U11=0,0,IF(19=CARTÕES!$F11,CARTÕES!$E11-(CARTÕES!$F11-1)*ROUND(CARTÕES!$E11/CARTÕES!$F11,0),ROUND(CARTÕES!$E11/CARTÕES!$F11,0))) | BF11: =IF(V11=0,0,IF(20=CARTÕES!$F11,CARTÕES!$E11-(CARTÕES!$F11-1)*ROUND(CARTÕES!$E11/CARTÕES!$F11,0),ROUND(CARTÕES!$E11/CARTÕES!$F11,0))) | BG11: =IF(W11=0,0,IF(21=CARTÕES!$F11,CARTÕES!$E11-(CARTÕES!$F11-1)*ROUND(CARTÕES!$E11/CARTÕES!$F11,0),ROUND(CARTÕES!$E11/CARTÕES!$F11,0))) | BH11: =IF(X11=0,0,IF(22=CARTÕES!$F11,CARTÕES!$E11-(CARTÕES!$F11-1)*ROUND(CARTÕES!$E11/CARTÕES!$F11,0),ROUND(CARTÕES!$E11/CARTÕES!$F11,0))) | BI11: =IF(Y11=0,0,IF(23=CARTÕES!$F11,CARTÕES!$E11-(CARTÕES!$F11-1)*ROUND(CARTÕES!$E11/CARTÕES!$F11,0),ROUND(CARTÕES!$E11/CARTÕES!$F11,0))) | BJ11: =IF(Z11=0,0,IF(24=CARTÕES!$F11,CARTÕES!$E11-(CARTÕES!$F11-1)*ROUND(CARTÕES!$E11/CARTÕES!$F11,0),ROUND(CARTÕES!$E11/CARTÕES!$F11,0))) | BK11: =IF(AA11=0,0,IF(25=CARTÕES!$F11,CARTÕES!$E11-(CARTÕES!$F11-1)*ROUND(CARTÕES!$E11/CARTÕES!$F11,0),ROUND(CARTÕES!$E11/CARTÕES!$F11,0))) | BL11: =IF(AB11=0,0,IF(26=CARTÕES!$F11,CARTÕES!$E11-(CARTÕES!$F11-1)*ROUND(CARTÕES!$E11/CARTÕES!$F11,0),ROUND(CARTÕES!$E11/CARTÕES!$F11,0))) | BM11: =IF(AC11=0,0,IF(27=CARTÕES!$F11,CARTÕES!$E11-(CARTÕES!$F11-1)*ROUND(CARTÕES!$E11/CARTÕES!$F11,0),ROUND(CARTÕES!$E11/CARTÕES!$F11,0))) | BN11: =IF(AD11=0,0,IF(28=CARTÕES!$F11,CARTÕES!$E11-(CARTÕES!$F11-1)*ROUND(CARTÕES!$E11/CARTÕES!$F11,0),ROUND(CARTÕES!$E11/CARTÕES!$F11,0))) | BO11: =IF(AE11=0,0,IF(29=CARTÕES!$F11,CARTÕES!$E11-(CARTÕES!$F11-1)*ROUND(CARTÕES!$E11/CARTÕES!$F11,0),ROUND(CARTÕES!$E11/CARTÕES!$F11,0))) | BP11: =IF(AF11=0,0,IF(30=CARTÕES!$F11,CARTÕES!$E11-(CARTÕES!$F11-1)*ROUND(CARTÕES!$E11/CARTÕES!$F11,0),ROUND(CARTÕES!$E11/CARTÕES!$F11,0))) | BQ11: =IF(AG11=0,0,IF(31=CARTÕES!$F11,CARTÕES!$E11-(CARTÕES!$F11-1)*ROUND(CARTÕES!$E11/CARTÕES!$F11,0),ROUND(CARTÕES!$E11/CARTÕES!$F11,0))) | BR11: =IF(AH11=0,0,IF(32=CARTÕES!$F11,CARTÕES!$E11-(CARTÕES!$F11-1)*ROUND(CARTÕES!$E11/CARTÕES!$F11,0),ROUND(CARTÕES!$E11/CARTÕES!$F11,0))) | BS11: =IF(AI11=0,0,IF(33=CARTÕES!$F11,CARTÕES!$E11-(CARTÕES!$F11-1)*ROUND(CARTÕES!$E11/CARTÕES!$F11,0),ROUND(CARTÕES!$E11/CARTÕES!$F11,0))) | BT11: =IF(AJ11=0,0,IF(34=CARTÕES!$F11,CARTÕES!$E11-(CARTÕES!$F11-1)*ROUND(CARTÕES!$E11/CARTÕES!$F11,0),ROUND(CARTÕES!$E11/CARTÕES!$F11,0))) | BU11: =IF(AK11=0,0,IF(35=CARTÕES!$F11,CARTÕES!$E11-(CARTÕES!$F11-1)*ROUND(CARTÕES!$E11/CARTÕES!$F11,0),ROUND(CARTÕES!$E11/CARTÕES!$F11,0))) | BV11: =IF(AL11=0,0,IF(36=CARTÕES!$F11,CARTÕES!$E11-(CARTÕES!$F11-1)*ROUND(CARTÕES!$E11/CARTÕES!$F11,0),ROUND(CARTÕES!$E11/CARTÕES!$F11,0)))
A12: =IF(CARTÕES!$C12="","",CARTÕES!$C12) | B12: =SUMPRODUCT((C12:AL12='RESUMO MENSAL'!$C$4)*AM12:BV12) | C12: =IF(OR(CARTÕES!$K12=0,CARTÕES!$F12=""),0,IF(1>CARTÕES!$F12,0,CARTÕES!$K12+1-1)) | D12: =IF(OR(CARTÕES!$K12=0,CARTÕES!$F12=""),0,IF(2>CARTÕES!$F12,0,CARTÕES!$K12+2-1)) | E12: =IF(OR(CARTÕES!$K12=0,CARTÕES!$F12=""),0,IF(3>CARTÕES!$F12,0,CARTÕES!$K12+3-1)) | F12: =IF(OR(CARTÕES!$K12=0,CARTÕES!$F12=""),0,IF(4>CARTÕES!$F12,0,CARTÕES!$K12+4-1)) | G12: =IF(OR(CARTÕES!$K12=0,CARTÕES!$F12=""),0,IF(5>CARTÕES!$F12,0,CARTÕES!$K12+5-1)) | H12: =IF(OR(CARTÕES!$K12=0,CARTÕES!$F12=""),0,IF(6>CARTÕES!$F12,0,CARTÕES!$K12+6-1)) | I12: =IF(OR(CARTÕES!$K12=0,CARTÕES!$F12=""),0,IF(7>CARTÕES!$F12,0,CARTÕES!$K12+7-1)) | J12: =IF(OR(CARTÕES!$K12=0,CARTÕES!$F12=""),0,IF(8>CARTÕES!$F12,0,CARTÕES!$K12+8-1)) | K12: =IF(OR(CARTÕES!$K12=0,CARTÕES!$F12=""),0,IF(9>CARTÕES!$F12,0,CARTÕES!$K12+9-1)) | L12: =IF(OR(CARTÕES!$K12=0,CARTÕES!$F12=""),0,IF(10>CARTÕES!$F12,0,CARTÕES!$K12+10-1)) | M12: =IF(OR(CARTÕES!$K12=0,CARTÕES!$F12=""),0,IF(11>CARTÕES!$F12,0,CARTÕES!$K12+11-1)) | N12: =IF(OR(CARTÕES!$K12=0,CARTÕES!$F12=""),0,IF(12>CARTÕES!$F12,0,CARTÕES!$K12+12-1)) | O12: =IF(OR(CARTÕES!$K12=0,CARTÕES!$F12=""),0,IF(13>CARTÕES!$F12,0,CARTÕES!$K12+13-1)) | P12: =IF(OR(CARTÕES!$K12=0,CARTÕES!$F12=""),0,IF(14>CARTÕES!$F12,0,CARTÕES!$K12+14-1)) | Q12: =IF(OR(CARTÕES!$K12=0,CARTÕES!$F12=""),0,IF(15>CARTÕES!$F12,0,CARTÕES!$K12+15-1)) | R12: =IF(OR(CARTÕES!$K12=0,CARTÕES!$F12=""),0,IF(16>CARTÕES!$F12,0,CARTÕES!$K12+16-1)) | S12: =IF(OR(CARTÕES!$K12=0,CARTÕES!$F12=""),0,IF(17>CARTÕES!$F12,0,CARTÕES!$K12+17-1)) | T12: =IF(OR(CARTÕES!$K12=0,CARTÕES!$F12=""),0,IF(18>CARTÕES!$F12,0,CARTÕES!$K12+18-1)) | U12: =IF(OR(CARTÕES!$K12=0,CARTÕES!$F12=""),0,IF(19>CARTÕES!$F12,0,CARTÕES!$K12+19-1)) | V12: =IF(OR(CARTÕES!$K12=0,CARTÕES!$F12=""),0,IF(20>CARTÕES!$F12,0,CARTÕES!$K12+20-1)) | W12: =IF(OR(CARTÕES!$K12=0,CARTÕES!$F12=""),0,IF(21>CARTÕES!$F12,0,CARTÕES!$K12+21-1)) | X12: =IF(OR(CARTÕES!$K12=0,CARTÕES!$F12=""),0,IF(22>CARTÕES!$F12,0,CARTÕES!$K12+22-1)) | Y12: =IF(OR(CARTÕES!$K12=0,CARTÕES!$F12=""),0,IF(23>CARTÕES!$F12,0,CARTÕES!$K12+23-1)) | Z12: =IF(OR(CARTÕES!$K12=0,CARTÕES!$F12=""),0,IF(24>CARTÕES!$F12,0,CARTÕES!$K12+24-1)) | AA12: =IF(OR(CARTÕES!$K12=0,CARTÕES!$F12=""),0,IF(25>CARTÕES!$F12,0,CARTÕES!$K12+25-1)) | AB12: =IF(OR(CARTÕES!$K12=0,CARTÕES!$F12=""),0,IF(26>CARTÕES!$F12,0,CARTÕES!$K12+26-1)) | AC12: =IF(OR(CARTÕES!$K12=0,CARTÕES!$F12=""),0,IF(27>CARTÕES!$F12,0,CARTÕES!$K12+27-1)) | AD12: =IF(OR(CARTÕES!$K12=0,CARTÕES!$F12=""),0,IF(28>CARTÕES!$F12,0,CARTÕES!$K12+28-1)) | AE12: =IF(OR(CARTÕES!$K12=0,CARTÕES!$F12=""),0,IF(29>CARTÕES!$F12,0,CARTÕES!$K12+29-1)) | AF12: =IF(OR(CARTÕES!$K12=0,CARTÕES!$F12=""),0,IF(30>CARTÕES!$F12,0,CARTÕES!$K12+30-1)) | AG12: =IF(OR(CARTÕES!$K12=0,CARTÕES!$F12=""),0,IF(31>CARTÕES!$F12,0,CARTÕES!$K12+31-1)) | AH12: =IF(OR(CARTÕES!$K12=0,CARTÕES!$F12=""),0,IF(32>CARTÕES!$F12,0,CARTÕES!$K12+32-1)) | AI12: =IF(OR(CARTÕES!$K12=0,CARTÕES!$F12=""),0,IF(33>CARTÕES!$F12,0,CARTÕES!$K12+33-1)) | AJ12: =IF(OR(CARTÕES!$K12=0,CARTÕES!$F12=""),0,IF(34>CARTÕES!$F12,0,CARTÕES!$K12+34-1)) | AK12: =IF(OR(CARTÕES!$K12=0,CARTÕES!$F12=""),0,IF(35>CARTÕES!$F12,0,CARTÕES!$K12+35-1)) | AL12: =IF(OR(CARTÕES!$K12=0,CARTÕES!$F12=""),0,IF(36>CARTÕES!$F12,0,CARTÕES!$K12+36-1)) | AM12: =IF(C12=0,0,IF(1=CARTÕES!$F12,CARTÕES!$E12-(CARTÕES!$F12-1)*ROUND(CARTÕES!$E12/CARTÕES!$F12,0),ROUND(CARTÕES!$E12/CARTÕES!$F12,0))) | AN12: =IF(D12=0,0,IF(2=CARTÕES!$F12,CARTÕES!$E12-(CARTÕES!$F12-1)*ROUND(CARTÕES!$E12/CARTÕES!$F12,0),ROUND(CARTÕES!$E12/CARTÕES!$F12,0))) | AO12: =IF(E12=0,0,IF(3=CARTÕES!$F12,CARTÕES!$E12-(CARTÕES!$F12-1)*ROUND(CARTÕES!$E12/CARTÕES!$F12,0),ROUND(CARTÕES!$E12/CARTÕES!$F12,0))) | AP12: =IF(F12=0,0,IF(4=CARTÕES!$F12,CARTÕES!$E12-(CARTÕES!$F12-1)*ROUND(CARTÕES!$E12/CARTÕES!$F12,0),ROUND(CARTÕES!$E12/CARTÕES!$F12,0))) | AQ12: =IF(G12=0,0,IF(5=CARTÕES!$F12,CARTÕES!$E12-(CARTÕES!$F12-1)*ROUND(CARTÕES!$E12/CARTÕES!$F12,0),ROUND(CARTÕES!$E12/CARTÕES!$F12,0))) | AR12: =IF(H12=0,0,IF(6=CARTÕES!$F12,CARTÕES!$E12-(CARTÕES!$F12-1)*ROUND(CARTÕES!$E12/CARTÕES!$F12,0),ROUND(CARTÕES!$E12/CARTÕES!$F12,0))) | AS12: =IF(I12=0,0,IF(7=CARTÕES!$F12,CARTÕES!$E12-(CARTÕES!$F12-1)*ROUND(CARTÕES!$E12/CARTÕES!$F12,0),ROUND(CARTÕES!$E12/CARTÕES!$F12,0))) | AT12: =IF(J12=0,0,IF(8=CARTÕES!$F12,CARTÕES!$E12-(CARTÕES!$F12-1)*ROUND(CARTÕES!$E12/CARTÕES!$F12,0),ROUND(CARTÕES!$E12/CARTÕES!$F12,0))) | AU12: =IF(K12=0,0,IF(9=CARTÕES!$F12,CARTÕES!$E12-(CARTÕES!$F12-1)*ROUND(CARTÕES!$E12/CARTÕES!$F12,0),ROUND(CARTÕES!$E12/CARTÕES!$F12,0))) | AV12: =IF(L12=0,0,IF(10=CARTÕES!$F12,CARTÕES!$E12-(CARTÕES!$F12-1)*ROUND(CARTÕES!$E12/CARTÕES!$F12,0),ROUND(CARTÕES!$E12/CARTÕES!$F12,0))) | AW12: =IF(M12=0,0,IF(11=CARTÕES!$F12,CARTÕES!$E12-(CARTÕES!$F12-1)*ROUND(CARTÕES!$E12/CARTÕES!$F12,0),ROUND(CARTÕES!$E12/CARTÕES!$F12,0))) | AX12: =IF(N12=0,0,IF(12=CARTÕES!$F12,CARTÕES!$E12-(CARTÕES!$F12-1)*ROUND(CARTÕES!$E12/CARTÕES!$F12,0),ROUND(CARTÕES!$E12/CARTÕES!$F12,0))) | AY12: =IF(O12=0,0,IF(13=CARTÕES!$F12,CARTÕES!$E12-(CARTÕES!$F12-1)*ROUND(CARTÕES!$E12/CARTÕES!$F12,0),ROUND(CARTÕES!$E12/CARTÕES!$F12,0))) | AZ12: =IF(P12=0,0,IF(14=CARTÕES!$F12,CARTÕES!$E12-(CARTÕES!$F12-1)*ROUND(CARTÕES!$E12/CARTÕES!$F12,0),ROUND(CARTÕES!$E12/CARTÕES!$F12,0))) | BA12: =IF(Q12=0,0,IF(15=CARTÕES!$F12,CARTÕES!$E12-(CARTÕES!$F12-1)*ROUND(CARTÕES!$E12/CARTÕES!$F12,0),ROUND(CARTÕES!$E12/CARTÕES!$F12,0))) | BB12: =IF(R12=0,0,IF(16=CARTÕES!$F12,CARTÕES!$E12-(CARTÕES!$F12-1)*ROUND(CARTÕES!$E12/CARTÕES!$F12,0),ROUND(CARTÕES!$E12/CARTÕES!$F12,0))) | BC12: =IF(S12=0,0,IF(17=CARTÕES!$F12,CARTÕES!$E12-(CARTÕES!$F12-1)*ROUND(CARTÕES!$E12/CARTÕES!$F12,0),ROUND(CARTÕES!$E12/CARTÕES!$F12,0))) | BD12: =IF(T12=0,0,IF(18=CARTÕES!$F12,CARTÕES!$E12-(CARTÕES!$F12-1)*ROUND(CARTÕES!$E12/CARTÕES!$F12,0),ROUND(CARTÕES!$E12/CARTÕES!$F12,0))) | BE12: =IF(U12=0,0,IF(19=CARTÕES!$F12,CARTÕES!$E12-(CARTÕES!$F12-1)*ROUND(CARTÕES!$E12/CARTÕES!$F12,0),ROUND(CARTÕES!$E12/CARTÕES!$F12,0))) | BF12: =IF(V12=0,0,IF(20=CARTÕES!$F12,CARTÕES!$E12-(CARTÕES!$F12-1)*ROUND(CARTÕES!$E12/CARTÕES!$F12,0),ROUND(CARTÕES!$E12/CARTÕES!$F12,0))) | BG12: =IF(W12=0,0,IF(21=CARTÕES!$F12,CARTÕES!$E12-(CARTÕES!$F12-1)*ROUND(CARTÕES!$E12/CARTÕES!$F12,0),ROUND(CARTÕES!$E12/CARTÕES!$F12,0))) | BH12: =IF(X12=0,0,IF(22=CARTÕES!$F12,CARTÕES!$E12-(CARTÕES!$F12-1)*ROUND(CARTÕES!$E12/CARTÕES!$F12,0),ROUND(CARTÕES!$E12/CARTÕES!$F12,0))) | BI12: =IF(Y12=0,0,IF(23=CARTÕES!$F12,CARTÕES!$E12-(CARTÕES!$F12-1)*ROUND(CARTÕES!$E12/CARTÕES!$F12,0),ROUND(CARTÕES!$E12/CARTÕES!$F12,0))) | BJ12: =IF(Z12=0,0,IF(24=CARTÕES!$F12,CARTÕES!$E12-(CARTÕES!$F12-1)*ROUND(CARTÕES!$E12/CARTÕES!$F12,0),ROUND(CARTÕES!$E12/CARTÕES!$F12,0))) | BK12: =IF(AA12=0,0,IF(25=CARTÕES!$F12,CARTÕES!$E12-(CARTÕES!$F12-1)*ROUND(CARTÕES!$E12/CARTÕES!$F12,0),ROUND(CARTÕES!$E12/CARTÕES!$F12,0))) | BL12: =IF(AB12=0,0,IF(26=CARTÕES!$F12,CARTÕES!$E12-(CARTÕES!$F12-1)*ROUND(CARTÕES!$E12/CARTÕES!$F12,0),ROUND(CARTÕES!$E12/CARTÕES!$F12,0))) | BM12: =IF(AC12=0,0,IF(27=CARTÕES!$F12,CARTÕES!$E12-(CARTÕES!$F12-1)*ROUND(CARTÕES!$E12/CARTÕES!$F12,0),ROUND(CARTÕES!$E12/CARTÕES!$F12,0))) | BN12: =IF(AD12=0,0,IF(28=CARTÕES!$F12,CARTÕES!$E12-(CARTÕES!$F12-1)*ROUND(CARTÕES!$E12/CARTÕES!$F12,0),ROUND(CARTÕES!$E12/CARTÕES!$F12,0))) | BO12: =IF(AE12=0,0,IF(29=CARTÕES!$F12,CARTÕES!$E12-(CARTÕES!$F12-1)*ROUND(CARTÕES!$E12/CARTÕES!$F12,0),ROUND(CARTÕES!$E12/CARTÕES!$F12,0))) | BP12: =IF(AF12=0,0,IF(30=CARTÕES!$F12,CARTÕES!$E12-(CARTÕES!$F12-1)*ROUND(CARTÕES!$E12/CARTÕES!$F12,0),ROUND(CARTÕES!$E12/CARTÕES!$F12,0))) | BQ12: =IF(AG12=0,0,IF(31=CARTÕES!$F12,CARTÕES!$E12-(CARTÕES!$F12-1)*ROUND(CARTÕES!$E12/CARTÕES!$F12,0),ROUND(CARTÕES!$E12/CARTÕES!$F12,0))) | BR12: =IF(AH12=0,0,IF(32=CARTÕES!$F12,CARTÕES!$E12-(CARTÕES!$F12-1)*ROUND(CARTÕES!$E12/CARTÕES!$F12,0),ROUND(CARTÕES!$E12/CARTÕES!$F12,0))) | BS12: =IF(AI12=0,0,IF(33=CARTÕES!$F12,CARTÕES!$E12-(CARTÕES!$F12-1)*ROUND(CARTÕES!$E12/CARTÕES!$F12,0),ROUND(CARTÕES!$E12/CARTÕES!$F12,0))) | BT12: =IF(AJ12=0,0,IF(34=CARTÕES!$F12,CARTÕES!$E12-(CARTÕES!$F12-1)*ROUND(CARTÕES!$E12/CARTÕES!$F12,0),ROUND(CARTÕES!$E12/CARTÕES!$F12,0))) | BU12: =IF(AK12=0,0,IF(35=CARTÕES!$F12,CARTÕES!$E12-(CARTÕES!$F12-1)*ROUND(CARTÕES!$E12/CARTÕES!$F12,0),ROUND(CARTÕES!$E12/CARTÕES!$F12,0))) | BV12: =IF(AL12=0,0,IF(36=CARTÕES!$F12,CARTÕES!$E12-(CARTÕES!$F12-1)*ROUND(CARTÕES!$E12/CARTÕES!$F12,0),ROUND(CARTÕES!$E12/CARTÕES!$F12,0)))
A13: =IF(CARTÕES!$C13="","",CARTÕES!$C13) | B13: =SUMPRODUCT((C13:AL13='RESUMO MENSAL'!$C$4)*AM13:BV13) | C13: =IF(OR(CARTÕES!$K13=0,CARTÕES!$F13=""),0,IF(1>CARTÕES!$F13,0,CARTÕES!$K13+1-1)) | D13: =IF(OR(CARTÕES!$K13=0,CARTÕES!$F13=""),0,IF(2>CARTÕES!$F13,0,CARTÕES!$K13+2-1)) | E13: =IF(OR(CARTÕES!$K13=0,CARTÕES!$F13=""),0,IF(3>CARTÕES!$F13,0,CARTÕES!$K13+3-1)) | F13: =IF(OR(CARTÕES!$K13=0,CARTÕES!$F13=""),0,IF(4>CARTÕES!$F13,0,CARTÕES!$K13+4-1)) | G13: =IF(OR(CARTÕES!$K13=0,CARTÕES!$F13=""),0,IF(5>CARTÕES!$F13,0,CARTÕES!$K13+5-1)) | H13: =IF(OR(CARTÕES!$K13=0,CARTÕES!$F13=""),0,IF(6>CARTÕES!$F13,0,CARTÕES!$K13+6-1)) | I13: =IF(OR(CARTÕES!$K13=0,CARTÕES!$F13=""),0,IF(7>CARTÕES!$F13,0,CARTÕES!$K13+7-1)) | J13: =IF(OR(CARTÕES!$K13=0,CARTÕES!$F13=""),0,IF(8>CARTÕES!$F13,0,CARTÕES!$K13+8-1)) | K13: =IF(OR(CARTÕES!$K13=0,CARTÕES!$F13=""),0,IF(9>CARTÕES!$F13,0,CARTÕES!$K13+9-1)) | L13: =IF(OR(CARTÕES!$K13=0,CARTÕES!$F13=""),0,IF(10>CARTÕES!$F13,0,CARTÕES!$K13+10-1)) | M13: =IF(OR(CARTÕES!$K13=0,CARTÕES!$F13=""),0,IF(11>CARTÕES!$F13,0,CARTÕES!$K13+11-1)) | N13: =IF(OR(CARTÕES!$K13=0,CARTÕES!$F13=""),0,IF(12>CARTÕES!$F13,0,CARTÕES!$K13+12-1)) | O13: =IF(OR(CARTÕES!$K13=0,CARTÕES!$F13=""),0,IF(13>CARTÕES!$F13,0,CARTÕES!$K13+13-1)) | P13: =IF(OR(CARTÕES!$K13=0,CARTÕES!$F13=""),0,IF(14>CARTÕES!$F13,0,CARTÕES!$K13+14-1)) | Q13: =IF(OR(CARTÕES!$K13=0,CARTÕES!$F13=""),0,IF(15>CARTÕES!$F13,0,CARTÕES!$K13+15-1)) | R13: =IF(OR(CARTÕES!$K13=0,CARTÕES!$F13=""),0,IF(16>CARTÕES!$F13,0,CARTÕES!$K13+16-1)) | S13: =IF(OR(CARTÕES!$K13=0,CARTÕES!$F13=""),0,IF(17>CARTÕES!$F13,0,CARTÕES!$K13+17-1)) | T13: =IF(OR(CARTÕES!$K13=0,CARTÕES!$F13=""),0,IF(18>CARTÕES!$F13,0,CARTÕES!$K13+18-1)) | U13: =IF(OR(CARTÕES!$K13=0,CARTÕES!$F13=""),0,IF(19>CARTÕES!$F13,0,CARTÕES!$K13+19-1)) | V13: =IF(OR(CARTÕES!$K13=0,CARTÕES!$F13=""),0,IF(20>CARTÕES!$F13,0,CARTÕES!$K13+20-1)) | W13: =IF(OR(CARTÕES!$K13=0,CARTÕES!$F13=""),0,IF(21>CARTÕES!$F13,0,CARTÕES!$K13+21-1)) | X13: =IF(OR(CARTÕES!$K13=0,CARTÕES!$F13=""),0,IF(22>CARTÕES!$F13,0,CARTÕES!$K13+22-1)) | Y13: =IF(OR(CARTÕES!$K13=0,CARTÕES!$F13=""),0,IF(23>CARTÕES!$F13,0,CARTÕES!$K13+23-1)) | Z13: =IF(OR(CARTÕES!$K13=0,CARTÕES!$F13=""),0,IF(24>CARTÕES!$F13,0,CARTÕES!$K13+24-1)) | AA13: =IF(OR(CARTÕES!$K13=0,CARTÕES!$F13=""),0,IF(25>CARTÕES!$F13,0,CARTÕES!$K13+25-1)) | AB13: =IF(OR(CARTÕES!$K13=0,CARTÕES!$F13=""),0,IF(26>CARTÕES!$F13,0,CARTÕES!$K13+26-1)) | AC13: =IF(OR(CARTÕES!$K13=0,CARTÕES!$F13=""),0,IF(27>CARTÕES!$F13,0,CARTÕES!$K13+27-1)) | AD13: =IF(OR(CARTÕES!$K13=0,CARTÕES!$F13=""),0,IF(28>CARTÕES!$F13,0,CARTÕES!$K13+28-1)) | AE13: =IF(OR(CARTÕES!$K13=0,CARTÕES!$F13=""),0,IF(29>CARTÕES!$F13,0,CARTÕES!$K13+29-1)) | AF13: =IF(OR(CARTÕES!$K13=0,CARTÕES!$F13=""),0,IF(30>CARTÕES!$F13,0,CARTÕES!$K13+30-1)) | AG13: =IF(OR(CARTÕES!$K13=0,CARTÕES!$F13=""),0,IF(31>CARTÕES!$F13,0,CARTÕES!$K13+31-1)) | AH13: =IF(OR(CARTÕES!$K13=0,CARTÕES!$F13=""),0,IF(32>CARTÕES!$F13,0,CARTÕES!$K13+32-1)) | AI13: =IF(OR(CARTÕES!$K13=0,CARTÕES!$F13=""),0,IF(33>CARTÕES!$F13,0,CARTÕES!$K13+33-1)) | AJ13: =IF(OR(CARTÕES!$K13=0,CARTÕES!$F13=""),0,IF(34>CARTÕES!$F13,0,CARTÕES!$K13+34-1)) | AK13: =IF(OR(CARTÕES!$K13=0,CARTÕES!$F13=""),0,IF(35>CARTÕES!$F13,0,CARTÕES!$K13+35-1)) | AL13: =IF(OR(CARTÕES!$K13=0,CARTÕES!$F13=""),0,IF(36>CARTÕES!$F13,0,CARTÕES!$K13+36-1)) | AM13: =IF(C13=0,0,IF(1=CARTÕES!$F13,CARTÕES!$E13-(CARTÕES!$F13-1)*ROUND(CARTÕES!$E13/CARTÕES!$F13,0),ROUND(CARTÕES!$E13/CARTÕES!$F13,0))) | AN13: =IF(D13=0,0,IF(2=CARTÕES!$F13,CARTÕES!$E13-(CARTÕES!$F13-1)*ROUND(CARTÕES!$E13/CARTÕES!$F13,0),ROUND(CARTÕES!$E13/CARTÕES!$F13,0))) | AO13: =IF(E13=0,0,IF(3=CARTÕES!$F13,CARTÕES!$E13-(CARTÕES!$F13-1)*ROUND(CARTÕES!$E13/CARTÕES!$F13,0),ROUND(CARTÕES!$E13/CARTÕES!$F13,0))) | AP13: =IF(F13=0,0,IF(4=CARTÕES!$F13,CARTÕES!$E13-(CARTÕES!$F13-1)*ROUND(CARTÕES!$E13/CARTÕES!$F13,0),ROUND(CARTÕES!$E13/CARTÕES!$F13,0))) | AQ13: =IF(G13=0,0,IF(5=CARTÕES!$F13,CARTÕES!$E13-(CARTÕES!$F13-1)*ROUND(CARTÕES!$E13/CARTÕES!$F13,0),ROUND(CARTÕES!$E13/CARTÕES!$F13,0))) | AR13: =IF(H13=0,0,IF(6=CARTÕES!$F13,CARTÕES!$E13-(CARTÕES!$F13-1)*ROUND(CARTÕES!$E13/CARTÕES!$F13,0),ROUND(CARTÕES!$E13/CARTÕES!$F13,0))) | AS13: =IF(I13=0,0,IF(7=CARTÕES!$F13,CARTÕES!$E13-(CARTÕES!$F13-1)*ROUND(CARTÕES!$E13/CARTÕES!$F13,0),ROUND(CARTÕES!$E13/CARTÕES!$F13,0))) | AT13: =IF(J13=0,0,IF(8=CARTÕES!$F13,CARTÕES!$E13-(CARTÕES!$F13-1)*ROUND(CARTÕES!$E13/CARTÕES!$F13,0),ROUND(CARTÕES!$E13/CARTÕES!$F13,0))) | AU13: =IF(K13=0,0,IF(9=CARTÕES!$F13,CARTÕES!$E13-(CARTÕES!$F13-1)*ROUND(CARTÕES!$E13/CARTÕES!$F13,0),ROUND(CARTÕES!$E13/CARTÕES!$F13,0))) | AV13: =IF(L13=0,0,IF(10=CARTÕES!$F13,CARTÕES!$E13-(CARTÕES!$F13-1)*ROUND(CARTÕES!$E13/CARTÕES!$F13,0),ROUND(CARTÕES!$E13/CARTÕES!$F13,0))) | AW13: =IF(M13=0,0,IF(11=CARTÕES!$F13,CARTÕES!$E13-(CARTÕES!$F13-1)*ROUND(CARTÕES!$E13/CARTÕES!$F13,0),ROUND(CARTÕES!$E13/CARTÕES!$F13,0))) | AX13: =IF(N13=0,0,IF(12=CARTÕES!$F13,CARTÕES!$E13-(CARTÕES!$F13-1)*ROUND(CARTÕES!$E13/CARTÕES!$F13,0),ROUND(CARTÕES!$E13/CARTÕES!$F13,0))) | AY13: =IF(O13=0,0,IF(13=CARTÕES!$F13,CARTÕES!$E13-(CARTÕES!$F13-1)*ROUND(CARTÕES!$E13/CARTÕES!$F13,0),ROUND(CARTÕES!$E13/CARTÕES!$F13,0))) | AZ13: =IF(P13=0,0,IF(14=CARTÕES!$F13,CARTÕES!$E13-(CARTÕES!$F13-1)*ROUND(CARTÕES!$E13/CARTÕES!$F13,0),ROUND(CARTÕES!$E13/CARTÕES!$F13,0))) | BA13: =IF(Q13=0,0,IF(15=CARTÕES!$F13,CARTÕES!$E13-(CARTÕES!$F13-1)*ROUND(CARTÕES!$E13/CARTÕES!$F13,0),ROUND(CARTÕES!$E13/CARTÕES!$F13,0))) | BB13: =IF(R13=0,0,IF(16=CARTÕES!$F13,CARTÕES!$E13-(CARTÕES!$F13-1)*ROUND(CARTÕES!$E13/CARTÕES!$F13,0),ROUND(CARTÕES!$E13/CARTÕES!$F13,0))) | BC13: =IF(S13=0,0,IF(17=CARTÕES!$F13,CARTÕES!$E13-(CARTÕES!$F13-1)*ROUND(CARTÕES!$E13/CARTÕES!$F13,0),ROUND(CARTÕES!$E13/CARTÕES!$F13,0))) | BD13: =IF(T13=0,0,IF(18=CARTÕES!$F13,CARTÕES!$E13-(CARTÕES!$F13-1)*ROUND(CARTÕES!$E13/CARTÕES!$F13,0),ROUND(CARTÕES!$E13/CARTÕES!$F13,0))) | BE13: =IF(U13=0,0,IF(19=CARTÕES!$F13,CARTÕES!$E13-(CARTÕES!$F13-1)*ROUND(CARTÕES!$E13/CARTÕES!$F13,0),ROUND(CARTÕES!$E13/CARTÕES!$F13,0))) | BF13: =IF(V13=0,0,IF(20=CARTÕES!$F13,CARTÕES!$E13-(CARTÕES!$F13-1)*ROUND(CARTÕES!$E13/CARTÕES!$F13,0),ROUND(CARTÕES!$E13/CARTÕES!$F13,0))) | BG13: =IF(W13=0,0,IF(21=CARTÕES!$F13,CARTÕES!$E13-(CARTÕES!$F13-1)*ROUND(CARTÕES!$E13/CARTÕES!$F13,0),ROUND(CARTÕES!$E13/CARTÕES!$F13,0))) | BH13: =IF(X13=0,0,IF(22=CARTÕES!$F13,CARTÕES!$E13-(CARTÕES!$F13-1)*ROUND(CARTÕES!$E13/CARTÕES!$F13,0),ROUND(CARTÕES!$E13/CARTÕES!$F13,0))) | BI13: =IF(Y13=0,0,IF(23=CARTÕES!$F13,CARTÕES!$E13-(CARTÕES!$F13-1)*ROUND(CARTÕES!$E13/CARTÕES!$F13,0),ROUND(CARTÕES!$E13/CARTÕES!$F13,0))) | BJ13: =IF(Z13=0,0,IF(24=CARTÕES!$F13,CARTÕES!$E13-(CARTÕES!$F13-1)*ROUND(CARTÕES!$E13/CARTÕES!$F13,0),ROUND(CARTÕES!$E13/CARTÕES!$F13,0))) | BK13: =IF(AA13=0,0,IF(25=CARTÕES!$F13,CARTÕES!$E13-(CARTÕES!$F13-1)*ROUND(CARTÕES!$E13/CARTÕES!$F13,0),ROUND(CARTÕES!$E13/CARTÕES!$F13,0))) | BL13: =IF(AB13=0,0,IF(26=CARTÕES!$F13,CARTÕES!$E13-(CARTÕES!$F13-1)*ROUND(CARTÕES!$E13/CARTÕES!$F13,0),ROUND(CARTÕES!$E13/CARTÕES!$F13,0))) | BM13: =IF(AC13=0,0,IF(27=CARTÕES!$F13,CARTÕES!$E13-(CARTÕES!$F13-1)*ROUND(CARTÕES!$E13/CARTÕES!$F13,0),ROUND(CARTÕES!$E13/CARTÕES!$F13,0))) | BN13: =IF(AD13=0,0,IF(28=CARTÕES!$F13,CARTÕES!$E13-(CARTÕES!$F13-1)*ROUND(CARTÕES!$E13/CARTÕES!$F13,0),ROUND(CARTÕES!$E13/CARTÕES!$F13,0))) | BO13: =IF(AE13=0,0,IF(29=CARTÕES!$F13,CARTÕES!$E13-(CARTÕES!$F13-1)*ROUND(CARTÕES!$E13/CARTÕES!$F13,0),ROUND(CARTÕES!$E13/CARTÕES!$F13,0))) | BP13: =IF(AF13=0,0,IF(30=CARTÕES!$F13,CARTÕES!$E13-(CARTÕES!$F13-1)*ROUND(CARTÕES!$E13/CARTÕES!$F13,0),ROUND(CARTÕES!$E13/CARTÕES!$F13,0))) | BQ13: =IF(AG13=0,0,IF(31=CARTÕES!$F13,CARTÕES!$E13-(CARTÕES!$F13-1)*ROUND(CARTÕES!$E13/CARTÕES!$F13,0),ROUND(CARTÕES!$E13/CARTÕES!$F13,0))) | BR13: =IF(AH13=0,0,IF(32=CARTÕES!$F13,CARTÕES!$E13-(CARTÕES!$F13-1)*ROUND(CARTÕES!$E13/CARTÕES!$F13,0),ROUND(CARTÕES!$E13/CARTÕES!$F13,0))) | BS13: =IF(AI13=0,0,IF(33=CARTÕES!$F13,CARTÕES!$E13-(CARTÕES!$F13-1)*ROUND(CARTÕES!$E13/CARTÕES!$F13,0),ROUND(CARTÕES!$E13/CARTÕES!$F13,0))) | BT13: =IF(AJ13=0,0,IF(34=CARTÕES!$F13,CARTÕES!$E13-(CARTÕES!$F13-1)*ROUND(CARTÕES!$E13/CARTÕES!$F13,0),ROUND(CARTÕES!$E13/CARTÕES!$F13,0))) | BU13: =IF(AK13=0,0,IF(35=CARTÕES!$F13,CARTÕES!$E13-(CARTÕES!$F13-1)*ROUND(CARTÕES!$E13/CARTÕES!$F13,0),ROUND(CARTÕES!$E13/CARTÕES!$F13,0))) | BV13: =IF(AL13=0,0,IF(36=CARTÕES!$F13,CARTÕES!$E13-(CARTÕES!$F13-1)*ROUND(CARTÕES!$E13/CARTÕES!$F13,0),ROUND(CARTÕES!$E13/CARTÕES!$F13,0)))
A14: =IF(CARTÕES!$C14="","",CARTÕES!$C14) | B14: =SUMPRODUCT((C14:AL14='RESUMO MENSAL'!$C$4)*AM14:BV14) | C14: =IF(OR(CARTÕES!$K14=0,CARTÕES!$F14=""),0,IF(1>CARTÕES!$F14,0,CARTÕES!$K14+1-1)) | D14: =IF(OR(CARTÕES!$K14=0,CARTÕES!$F14=""),0,IF(2>CARTÕES!$F14,0,CARTÕES!$K14+2-1)) | E14: =IF(OR(CARTÕES!$K14=0,CARTÕES!$F14=""),0,IF(3>CARTÕES!$F14,0,CARTÕES!$K14+3-1)) | F14: =IF(OR(CARTÕES!$K14=0,CARTÕES!$F14=""),0,IF(4>CARTÕES!$F14,0,CARTÕES!$K14+4-1)) | G14: =IF(OR(CARTÕES!$K14=0,CARTÕES!$F14=""),0,IF(5>CARTÕES!$F14,0,CARTÕES!$K14+5-1)) | H14: =IF(OR(CARTÕES!$K14=0,CARTÕES!$F14=""),0,IF(6>CARTÕES!$F14,0,CARTÕES!$K14+6-1)) | I14: =IF(OR(CARTÕES!$K14=0,CARTÕES!$F14=""),0,IF(7>CARTÕES!$F14,0,CARTÕES!$K14+7-1)) | J14: =IF(OR(CARTÕES!$K14=0,CARTÕES!$F14=""),0,IF(8>CARTÕES!$F14,0,CARTÕES!$K14+8-1)) | K14: =IF(OR(CARTÕES!$K14=0,CARTÕES!$F14=""),0,IF(9>CARTÕES!$F14,0,CARTÕES!$K14+9-1)) | L14: =IF(OR(CARTÕES!$K14=0,CARTÕES!$F14=""),0,IF(10>CARTÕES!$F14,0,CARTÕES!$K14+10-1)) | M14: =IF(OR(CARTÕES!$K14=0,CARTÕES!$F14=""),0,IF(11>CARTÕES!$F14,0,CARTÕES!$K14+11-1)) | N14: =IF(OR(CARTÕES!$K14=0,CARTÕES!$F14=""),0,IF(12>CARTÕES!$F14,0,CARTÕES!$K14+12-1)) | O14: =IF(OR(CARTÕES!$K14=0,CARTÕES!$F14=""),0,IF(13>CARTÕES!$F14,0,CARTÕES!$K14+13-1)) | P14: =IF(OR(CARTÕES!$K14=0,CARTÕES!$F14=""),0,IF(14>CARTÕES!$F14,0,CARTÕES!$K14+14-1)) | Q14: =IF(OR(CARTÕES!$K14=0,CARTÕES!$F14=""),0,IF(15>CARTÕES!$F14,0,CARTÕES!$K14+15-1)) | R14: =IF(OR(CARTÕES!$K14=0,CARTÕES!$F14=""),0,IF(16>CARTÕES!$F14,0,CARTÕES!$K14+16-1)) | S14: =IF(OR(CARTÕES!$K14=0,CARTÕES!$F14=""),0,IF(17>CARTÕES!$F14,0,CARTÕES!$K14+17-1)) | T14: =IF(OR(CARTÕES!$K14=0,CARTÕES!$F14=""),0,IF(18>CARTÕES!$F14,0,CARTÕES!$K14+18-1)) | U14: =IF(OR(CARTÕES!$K14=0,CARTÕES!$F14=""),0,IF(19>CARTÕES!$F14,0,CARTÕES!$K14+19-1)) | V14: =IF(OR(CARTÕES!$K14=0,CARTÕES!$F14=""),0,IF(20>CARTÕES!$F14,0,CARTÕES!$K14+20-1)) | W14: =IF(OR(CARTÕES!$K14=0,CARTÕES!$F14=""),0,IF(21>CARTÕES!$F14,0,CARTÕES!$K14+21-1)) | X14: =IF(OR(CARTÕES!$K14=0,CARTÕES!$F14=""),0,IF(22>CARTÕES!$F14,0,CARTÕES!$K14+22-1)) | Y14: =IF(OR(CARTÕES!$K14=0,CARTÕES!$F14=""),0,IF(23>CARTÕES!$F14,0,CARTÕES!$K14+23-1)) | Z14: =IF(OR(CARTÕES!$K14=0,CARTÕES!$F14=""),0,IF(24>CARTÕES!$F14,0,CARTÕES!$K14+24-1)) | AA14: =IF(OR(CARTÕES!$K14=0,CARTÕES!$F14=""),0,IF(25>CARTÕES!$F14,0,CARTÕES!$K14+25-1)) | AB14: =IF(OR(CARTÕES!$K14=0,CARTÕES!$F14=""),0,IF(26>CARTÕES!$F14,0,CARTÕES!$K14+26-1)) | AC14: =IF(OR(CARTÕES!$K14=0,CARTÕES!$F14=""),0,IF(27>CARTÕES!$F14,0,CARTÕES!$K14+27-1)) | AD14: =IF(OR(CARTÕES!$K14=0,CARTÕES!$F14=""),0,IF(28>CARTÕES!$F14,0,CARTÕES!$K14+28-1)) | AE14: =IF(OR(CARTÕES!$K14=0,CARTÕES!$F14=""),0,IF(29>CARTÕES!$F14,0,CARTÕES!$K14+29-1)) | AF14: =IF(OR(CARTÕES!$K14=0,CARTÕES!$F14=""),0,IF(30>CARTÕES!$F14,0,CARTÕES!$K14+30-1)) | AG14: =IF(OR(CARTÕES!$K14=0,CARTÕES!$F14=""),0,IF(31>CARTÕES!$F14,0,CARTÕES!$K14+31-1)) | AH14: =IF(OR(CARTÕES!$K14=0,CARTÕES!$F14=""),0,IF(32>CARTÕES!$F14,0,CARTÕES!$K14+32-1)) | AI14: =IF(OR(CARTÕES!$K14=0,CARTÕES!$F14=""),0,IF(33>CARTÕES!$F14,0,CARTÕES!$K14+33-1)) | AJ14: =IF(OR(CARTÕES!$K14=0,CARTÕES!$F14=""),0,IF(34>CARTÕES!$F14,0,CARTÕES!$K14+34-1)) | AK14: =IF(OR(CARTÕES!$K14=0,CARTÕES!$F14=""),0,IF(35>CARTÕES!$F14,0,CARTÕES!$K14+35-1)) | AL14: =IF(OR(CARTÕES!$K14=0,CARTÕES!$F14=""),0,IF(36>CARTÕES!$F14,0,CARTÕES!$K14+36-1)) | AM14: =IF(C14=0,0,IF(1=CARTÕES!$F14,CARTÕES!$E14-(CARTÕES!$F14-1)*ROUND(CARTÕES!$E14/CARTÕES!$F14,0),ROUND(CARTÕES!$E14/CARTÕES!$F14,0))) | AN14: =IF(D14=0,0,IF(2=CARTÕES!$F14,CARTÕES!$E14-(CARTÕES!$F14-1)*ROUND(CARTÕES!$E14/CARTÕES!$F14,0),ROUND(CARTÕES!$E14/CARTÕES!$F14,0))) | AO14: =IF(E14=0,0,IF(3=CARTÕES!$F14,CARTÕES!$E14-(CARTÕES!$F14-1)*ROUND(CARTÕES!$E14/CARTÕES!$F14,0),ROUND(CARTÕES!$E14/CARTÕES!$F14,0))) | AP14: =IF(F14=0,0,IF(4=CARTÕES!$F14,CARTÕES!$E14-(CARTÕES!$F14-1)*ROUND(CARTÕES!$E14/CARTÕES!$F14,0),ROUND(CARTÕES!$E14/CARTÕES!$F14,0))) | AQ14: =IF(G14=0,0,IF(5=CARTÕES!$F14,CARTÕES!$E14-(CARTÕES!$F14-1)*ROUND(CARTÕES!$E14/CARTÕES!$F14,0),ROUND(CARTÕES!$E14/CARTÕES!$F14,0))) | AR14: =IF(H14=0,0,IF(6=CARTÕES!$F14,CARTÕES!$E14-(CARTÕES!$F14-1)*ROUND(CARTÕES!$E14/CARTÕES!$F14,0),ROUND(CARTÕES!$E14/CARTÕES!$F14,0))) | AS14: =IF(I14=0,0,IF(7=CARTÕES!$F14,CARTÕES!$E14-(CARTÕES!$F14-1)*ROUND(CARTÕES!$E14/CARTÕES!$F14,0),ROUND(CARTÕES!$E14/CARTÕES!$F14,0))) | AT14: =IF(J14=0,0,IF(8=CARTÕES!$F14,CARTÕES!$E14-(CARTÕES!$F14-1)*ROUND(CARTÕES!$E14/CARTÕES!$F14,0),ROUND(CARTÕES!$E14/CARTÕES!$F14,0))) | AU14: =IF(K14=0,0,IF(9=CARTÕES!$F14,CARTÕES!$E14-(CARTÕES!$F14-1)*ROUND(CARTÕES!$E14/CARTÕES!$F14,0),ROUND(CARTÕES!$E14/CARTÕES!$F14,0))) | AV14: =IF(L14=0,0,IF(10=CARTÕES!$F14,CARTÕES!$E14-(CARTÕES!$F14-1)*ROUND(CARTÕES!$E14/CARTÕES!$F14,0),ROUND(CARTÕES!$E14/CARTÕES!$F14,0))) | AW14: =IF(M14=0,0,IF(11=CARTÕES!$F14,CARTÕES!$E14-(CARTÕES!$F14-1)*ROUND(CARTÕES!$E14/CARTÕES!$F14,0),ROUND(CARTÕES!$E14/CARTÕES!$F14,0))) | AX14: =IF(N14=0,0,IF(12=CARTÕES!$F14,CARTÕES!$E14-(CARTÕES!$F14-1)*ROUND(CARTÕES!$E14/CARTÕES!$F14,0),ROUND(CARTÕES!$E14/CARTÕES!$F14,0))) | AY14: =IF(O14=0,0,IF(13=CARTÕES!$F14,CARTÕES!$E14-(CARTÕES!$F14-1)*ROUND(CARTÕES!$E14/CARTÕES!$F14,0),ROUND(CARTÕES!$E14/CARTÕES!$F14,0))) | AZ14: =IF(P14=0,0,IF(14=CARTÕES!$F14,CARTÕES!$E14-(CARTÕES!$F14-1)*ROUND(CARTÕES!$E14/CARTÕES!$F14,0),ROUND(CARTÕES!$E14/CARTÕES!$F14,0))) | BA14: =IF(Q14=0,0,IF(15=CARTÕES!$F14,CARTÕES!$E14-(CARTÕES!$F14-1)*ROUND(CARTÕES!$E14/CARTÕES!$F14,0),ROUND(CARTÕES!$E14/CARTÕES!$F14,0))) | BB14: =IF(R14=0,0,IF(16=CARTÕES!$F14,CARTÕES!$E14-(CARTÕES!$F14-1)*ROUND(CARTÕES!$E14/CARTÕES!$F14,0),ROUND(CARTÕES!$E14/CARTÕES!$F14,0))) | BC14: =IF(S14=0,0,IF(17=CARTÕES!$F14,CARTÕES!$E14-(CARTÕES!$F14-1)*ROUND(CARTÕES!$E14/CARTÕES!$F14,0),ROUND(CARTÕES!$E14/CARTÕES!$F14,0))) | BD14: =IF(T14=0,0,IF(18=CARTÕES!$F14,CARTÕES!$E14-(CARTÕES!$F14-1)*ROUND(CARTÕES!$E14/CARTÕES!$F14,0),ROUND(CARTÕES!$E14/CARTÕES!$F14,0))) | BE14: =IF(U14=0,0,IF(19=CARTÕES!$F14,CARTÕES!$E14-(CARTÕES!$F14-1)*ROUND(CARTÕES!$E14/CARTÕES!$F14,0),ROUND(CARTÕES!$E14/CARTÕES!$F14,0))) | BF14: =IF(V14=0,0,IF(20=CARTÕES!$F14,CARTÕES!$E14-(CARTÕES!$F14-1)*ROUND(CARTÕES!$E14/CARTÕES!$F14,0),ROUND(CARTÕES!$E14/CARTÕES!$F14,0))) | BG14: =IF(W14=0,0,IF(21=CARTÕES!$F14,CARTÕES!$E14-(CARTÕES!$F14-1)*ROUND(CARTÕES!$E14/CARTÕES!$F14,0),ROUND(CARTÕES!$E14/CARTÕES!$F14,0))) | BH14: =IF(X14=0,0,IF(22=CARTÕES!$F14,CARTÕES!$E14-(CARTÕES!$F14-1)*ROUND(CARTÕES!$E14/CARTÕES!$F14,0),ROUND(CARTÕES!$E14/CARTÕES!$F14,0))) | BI14: =IF(Y14=0,0,IF(23=CARTÕES!$F14,CARTÕES!$E14-(CARTÕES!$F14-1)*ROUND(CARTÕES!$E14/CARTÕES!$F14,0),ROUND(CARTÕES!$E14/CARTÕES!$F14,0))) | BJ14: =IF(Z14=0,0,IF(24=CARTÕES!$F14,CARTÕES!$E14-(CARTÕES!$F14-1)*ROUND(CARTÕES!$E14/CARTÕES!$F14,0),ROUND(CARTÕES!$E14/CARTÕES!$F14,0))) | BK14: =IF(AA14=0,0,IF(25=CARTÕES!$F14,CARTÕES!$E14-(CARTÕES!$F14-1)*ROUND(CARTÕES!$E14/CARTÕES!$F14,0),ROUND(CARTÕES!$E14/CARTÕES!$F14,0))) | BL14: =IF(AB14=0,0,IF(26=CARTÕES!$F14,CARTÕES!$E14-(CARTÕES!$F14-1)*ROUND(CARTÕES!$E14/CARTÕES!$F14,0),ROUND(CARTÕES!$E14/CARTÕES!$F14,0))) | BM14: =IF(AC14=0,0,IF(27=CARTÕES!$F14,CARTÕES!$E14-(CARTÕES!$F14-1)*ROUND(CARTÕES!$E14/CARTÕES!$F14,0),ROUND(CARTÕES!$E14/CARTÕES!$F14,0))) | BN14: =IF(AD14=0,0,IF(28=CARTÕES!$F14,CARTÕES!$E14-(CARTÕES!$F14-1)*ROUND(CARTÕES!$E14/CARTÕES!$F14,0),ROUND(CARTÕES!$E14/CARTÕES!$F14,0))) | BO14: =IF(AE14=0,0,IF(29=CARTÕES!$F14,CARTÕES!$E14-(CARTÕES!$F14-1)*ROUND(CARTÕES!$E14/CARTÕES!$F14,0),ROUND(CARTÕES!$E14/CARTÕES!$F14,0))) | BP14: =IF(AF14=0,0,IF(30=CARTÕES!$F14,CARTÕES!$E14-(CARTÕES!$F14-1)*ROUND(CARTÕES!$E14/CARTÕES!$F14,0),ROUND(CARTÕES!$E14/CARTÕES!$F14,0))) | BQ14: =IF(AG14=0,0,IF(31=CARTÕES!$F14,CARTÕES!$E14-(CARTÕES!$F14-1)*ROUND(CARTÕES!$E14/CARTÕES!$F14,0),ROUND(CARTÕES!$E14/CARTÕES!$F14,0))) | BR14: =IF(AH14=0,0,IF(32=CARTÕES!$F14,CARTÕES!$E14-(CARTÕES!$F14-1)*ROUND(CARTÕES!$E14/CARTÕES!$F14,0),ROUND(CARTÕES!$E14/CARTÕES!$F14,0))) | BS14: =IF(AI14=0,0,IF(33=CARTÕES!$F14,CARTÕES!$E14-(CARTÕES!$F14-1)*ROUND(CARTÕES!$E14/CARTÕES!$F14,0),ROUND(CARTÕES!$E14/CARTÕES!$F14,0))) | BT14: =IF(AJ14=0,0,IF(34=CARTÕES!$F14,CARTÕES!$E14-(CARTÕES!$F14-1)*ROUND(CARTÕES!$E14/CARTÕES!$F14,0),ROUND(CARTÕES!$E14/CARTÕES!$F14,0))) | BU14: =IF(AK14=0,0,IF(35=CARTÕES!$F14,CARTÕES!$E14-(CARTÕES!$F14-1)*ROUND(CARTÕES!$E14/CARTÕES!$F14,0),ROUND(CARTÕES!$E14/CARTÕES!$F14,0))) | BV14: =IF(AL14=0,0,IF(36=CARTÕES!$F14,CARTÕES!$E14-(CARTÕES!$F14-1)*ROUND(CARTÕES!$E14/CARTÕES!$F14,0),ROUND(CARTÕES!$E14/CARTÕES!$F14,0)))
A15: =IF(CARTÕES!$C15="","",CARTÕES!$C15) | B15: =SUMPRODUCT((C15:AL15='RESUMO MENSAL'!$C$4)*AM15:BV15) | C15: =IF(OR(CARTÕES!$K15=0,CARTÕES!$F15=""),0,IF(1>CARTÕES!$F15,0,CARTÕES!$K15+1-1)) | D15: =IF(OR(CARTÕES!$K15=0,CARTÕES!$F15=""),0,IF(2>CARTÕES!$F15,0,CARTÕES!$K15+2-1)) | E15: =IF(OR(CARTÕES!$K15=0,CARTÕES!$F15=""),0,IF(3>CARTÕES!$F15,0,CARTÕES!$K15+3-1)) | F15: =IF(OR(CARTÕES!$K15=0,CARTÕES!$F15=""),0,IF(4>CARTÕES!$F15,0,CARTÕES!$K15+4-1)) | G15: =IF(OR(CARTÕES!$K15=0,CARTÕES!$F15=""),0,IF(5>CARTÕES!$F15,0,CARTÕES!$K15+5-1)) | H15: =IF(OR(CARTÕES!$K15=0,CARTÕES!$F15=""),0,IF(6>CARTÕES!$F15,0,CARTÕES!$K15+6-1)) | I15: =IF(OR(CARTÕES!$K15=0,CARTÕES!$F15=""),0,IF(7>CARTÕES!$F15,0,CARTÕES!$K15+7-1)) | J15: =IF(OR(CARTÕES!$K15=0,CARTÕES!$F15=""),0,IF(8>CARTÕES!$F15,0,CARTÕES!$K15+8-1)) | K15: =IF(OR(CARTÕES!$K15=0,CARTÕES!$F15=""),0,IF(9>CARTÕES!$F15,0,CARTÕES!$K15+9-1)) | L15: =IF(OR(CARTÕES!$K15=0,CARTÕES!$F15=""),0,IF(10>CARTÕES!$F15,0,CARTÕES!$K15+10-1)) | M15: =IF(OR(CARTÕES!$K15=0,CARTÕES!$F15=""),0,IF(11>CARTÕES!$F15,0,CARTÕES!$K15+11-1)) | N15: =IF(OR(CARTÕES!$K15=0,CARTÕES!$F15=""),0,IF(12>CARTÕES!$F15,0,CARTÕES!$K15+12-1)) | O15: =IF(OR(CARTÕES!$K15=0,CARTÕES!$F15=""),0,IF(13>CARTÕES!$F15,0,CARTÕES!$K15+13-1)) | P15: =IF(OR(CARTÕES!$K15=0,CARTÕES!$F15=""),0,IF(14>CARTÕES!$F15,0,CARTÕES!$K15+14-1)) | Q15: =IF(OR(CARTÕES!$K15=0,CARTÕES!$F15=""),0,IF(15>CARTÕES!$F15,0,CARTÕES!$K15+15-1)) | R15: =IF(OR(CARTÕES!$K15=0,CARTÕES!$F15=""),0,IF(16>CARTÕES!$F15,0,CARTÕES!$K15+16-1)) | S15: =IF(OR(CARTÕES!$K15=0,CARTÕES!$F15=""),0,IF(17>CARTÕES!$F15,0,CARTÕES!$K15+17-1)) | T15: =IF(OR(CARTÕES!$K15=0,CARTÕES!$F15=""),0,IF(18>CARTÕES!$F15,0,CARTÕES!$K15+18-1)) | U15: =IF(OR(CARTÕES!$K15=0,CARTÕES!$F15=""),0,IF(19>CARTÕES!$F15,0,CARTÕES!$K15+19-1)) | V15: =IF(OR(CARTÕES!$K15=0,CARTÕES!$F15=""),0,IF(20>CARTÕES!$F15,0,CARTÕES!$K15+20-1)) | W15: =IF(OR(CARTÕES!$K15=0,CARTÕES!$F15=""),0,IF(21>CARTÕES!$F15,0,CARTÕES!$K15+21-1)) | X15: =IF(OR(CARTÕES!$K15=0,CARTÕES!$F15=""),0,IF(22>CARTÕES!$F15,0,CARTÕES!$K15+22-1)) | Y15: =IF(OR(CARTÕES!$K15=0,CARTÕES!$F15=""),0,IF(23>CARTÕES!$F15,0,CARTÕES!$K15+23-1)) | Z15: =IF(OR(CARTÕES!$K15=0,CARTÕES!$F15=""),0,IF(24>CARTÕES!$F15,0,CARTÕES!$K15+24-1)) | AA15: =IF(OR(CARTÕES!$K15=0,CARTÕES!$F15=""),0,IF(25>CARTÕES!$F15,0,CARTÕES!$K15+25-1)) | AB15: =IF(OR(CARTÕES!$K15=0,CARTÕES!$F15=""),0,IF(26>CARTÕES!$F15,0,CARTÕES!$K15+26-1)) | AC15: =IF(OR(CARTÕES!$K15=0,CARTÕES!$F15=""),0,IF(27>CARTÕES!$F15,0,CARTÕES!$K15+27-1)) | AD15: =IF(OR(CARTÕES!$K15=0,CARTÕES!$F15=""),0,IF(28>CARTÕES!$F15,0,CARTÕES!$K15+28-1)) | AE15: =IF(OR(CARTÕES!$K15=0,CARTÕES!$F15=""),0,IF(29>CARTÕES!$F15,0,CARTÕES!$K15+29-1)) | AF15: =IF(OR(CARTÕES!$K15=0,CARTÕES!$F15=""),0,IF(30>CARTÕES!$F15,0,CARTÕES!$K15+30-1)) | AG15: =IF(OR(CARTÕES!$K15=0,CARTÕES!$F15=""),0,IF(31>CARTÕES!$F15,0,CARTÕES!$K15+31-1)) | AH15: =IF(OR(CARTÕES!$K15=0,CARTÕES!$F15=""),0,IF(32>CARTÕES!$F15,0,CARTÕES!$K15+32-1)) | AI15: =IF(OR(CARTÕES!$K15=0,CARTÕES!$F15=""),0,IF(33>CARTÕES!$F15,0,CARTÕES!$K15+33-1)) | AJ15: =IF(OR(CARTÕES!$K15=0,CARTÕES!$F15=""),0,IF(34>CARTÕES!$F15,0,CARTÕES!$K15+34-1)) | AK15: =IF(OR(CARTÕES!$K15=0,CARTÕES!$F15=""),0,IF(35>CARTÕES!$F15,0,CARTÕES!$K15+35-1)) | AL15: =IF(OR(CARTÕES!$K15=0,CARTÕES!$F15=""),0,IF(36>CARTÕES!$F15,0,CARTÕES!$K15+36-1)) | AM15: =IF(C15=0,0,IF(1=CARTÕES!$F15,CARTÕES!$E15-(CARTÕES!$F15-1)*ROUND(CARTÕES!$E15/CARTÕES!$F15,0),ROUND(CARTÕES!$E15/CARTÕES!$F15,0))) | AN15: =IF(D15=0,0,IF(2=CARTÕES!$F15,CARTÕES!$E15-(CARTÕES!$F15-1)*ROUND(CARTÕES!$E15/CARTÕES!$F15,0),ROUND(CARTÕES!$E15/CARTÕES!$F15,0))) | AO15: =IF(E15=0,0,IF(3=CARTÕES!$F15,CARTÕES!$E15-(CARTÕES!$F15-1)*ROUND(CARTÕES!$E15/CARTÕES!$F15,0),ROUND(CARTÕES!$E15/CARTÕES!$F15,0))) | AP15: =IF(F15=0,0,IF(4=CARTÕES!$F15,CARTÕES!$E15-(CARTÕES!$F15-1)*ROUND(CARTÕES!$E15/CARTÕES!$F15,0),ROUND(CARTÕES!$E15/CARTÕES!$F15,0))) | AQ15: =IF(G15=0,0,IF(5=CARTÕES!$F15,CARTÕES!$E15-(CARTÕES!$F15-1)*ROUND(CARTÕES!$E15/CARTÕES!$F15,0),ROUND(CARTÕES!$E15/CARTÕES!$F15,0))) | AR15: =IF(H15=0,0,IF(6=CARTÕES!$F15,CARTÕES!$E15-(CARTÕES!$F15-1)*ROUND(CARTÕES!$E15/CARTÕES!$F15,0),ROUND(CARTÕES!$E15/CARTÕES!$F15,0))) | AS15: =IF(I15=0,0,IF(7=CARTÕES!$F15,CARTÕES!$E15-(CARTÕES!$F15-1)*ROUND(CARTÕES!$E15/CARTÕES!$F15,0),ROUND(CARTÕES!$E15/CARTÕES!$F15,0))) | AT15: =IF(J15=0,0,IF(8=CARTÕES!$F15,CARTÕES!$E15-(CARTÕES!$F15-1)*ROUND(CARTÕES!$E15/CARTÕES!$F15,0),ROUND(CARTÕES!$E15/CARTÕES!$F15,0))) | AU15: =IF(K15=0,0,IF(9=CARTÕES!$F15,CARTÕES!$E15-(CARTÕES!$F15-1)*ROUND(CARTÕES!$E15/CARTÕES!$F15,0),ROUND(CARTÕES!$E15/CARTÕES!$F15,0))) | AV15: =IF(L15=0,0,IF(10=CARTÕES!$F15,CARTÕES!$E15-(CARTÕES!$F15-1)*ROUND(CARTÕES!$E15/CARTÕES!$F15,0),ROUND(CARTÕES!$E15/CARTÕES!$F15,0))) | AW15: =IF(M15=0,0,IF(11=CARTÕES!$F15,CARTÕES!$E15-(CARTÕES!$F15-1)*ROUND(CARTÕES!$E15/CARTÕES!$F15,0),ROUND(CARTÕES!$E15/CARTÕES!$F15,0))) | AX15: =IF(N15=0,0,IF(12=CARTÕES!$F15,CARTÕES!$E15-(CARTÕES!$F15-1)*ROUND(CARTÕES!$E15/CARTÕES!$F15,0),ROUND(CARTÕES!$E15/CARTÕES!$F15,0))) | AY15: =IF(O15=0,0,IF(13=CARTÕES!$F15,CARTÕES!$E15-(CARTÕES!$F15-1)*ROUND(CARTÕES!$E15/CARTÕES!$F15,0),ROUND(CARTÕES!$E15/CARTÕES!$F15,0))) | AZ15: =IF(P15=0,0,IF(14=CARTÕES!$F15,CARTÕES!$E15-(CARTÕES!$F15-1)*ROUND(CARTÕES!$E15/CARTÕES!$F15,0),ROUND(CARTÕES!$E15/CARTÕES!$F15,0))) | BA15: =IF(Q15=0,0,IF(15=CARTÕES!$F15,CARTÕES!$E15-(CARTÕES!$F15-1)*ROUND(CARTÕES!$E15/CARTÕES!$F15,0),ROUND(CARTÕES!$E15/CARTÕES!$F15,0))) | BB15: =IF(R15=0,0,IF(16=CARTÕES!$F15,CARTÕES!$E15-(CARTÕES!$F15-1)*ROUND(CARTÕES!$E15/CARTÕES!$F15,0),ROUND(CARTÕES!$E15/CARTÕES!$F15,0))) | BC15: =IF(S15=0,0,IF(17=CARTÕES!$F15,CARTÕES!$E15-(CARTÕES!$F15-1)*ROUND(CARTÕES!$E15/CARTÕES!$F15,0),ROUND(CARTÕES!$E15/CARTÕES!$F15,0))) | BD15: =IF(T15=0,0,IF(18=CARTÕES!$F15,CARTÕES!$E15-(CARTÕES!$F15-1)*ROUND(CARTÕES!$E15/CARTÕES!$F15,0),ROUND(CARTÕES!$E15/CARTÕES!$F15,0))) | BE15: =IF(U15=0,0,IF(19=CARTÕES!$F15,CARTÕES!$E15-(CARTÕES!$F15-1)*ROUND(CARTÕES!$E15/CARTÕES!$F15,0),ROUND(CARTÕES!$E15/CARTÕES!$F15,0))) | BF15: =IF(V15=0,0,IF(20=CARTÕES!$F15,CARTÕES!$E15-(CARTÕES!$F15-1)*ROUND(CARTÕES!$E15/CARTÕES!$F15,0),ROUND(CARTÕES!$E15/CARTÕES!$F15,0))) | BG15: =IF(W15=0,0,IF(21=CARTÕES!$F15,CARTÕES!$E15-(CARTÕES!$F15-1)*ROUND(CARTÕES!$E15/CARTÕES!$F15,0),ROUND(CARTÕES!$E15/CARTÕES!$F15,0))) | BH15: =IF(X15=0,0,IF(22=CARTÕES!$F15,CARTÕES!$E15-(CARTÕES!$F15-1)*ROUND(CARTÕES!$E15/CARTÕES!$F15,0),ROUND(CARTÕES!$E15/CARTÕES!$F15,0))) | BI15: =IF(Y15=0,0,IF(23=CARTÕES!$F15,CARTÕES!$E15-(CARTÕES!$F15-1)*ROUND(CARTÕES!$E15/CARTÕES!$F15,0),ROUND(CARTÕES!$E15/CARTÕES!$F15,0))) | BJ15: =IF(Z15=0,0,IF(24=CARTÕES!$F15,CARTÕES!$E15-(CARTÕES!$F15-1)*ROUND(CARTÕES!$E15/CARTÕES!$F15,0),ROUND(CARTÕES!$E15/CARTÕES!$F15,0))) | BK15: =IF(AA15=0,0,IF(25=CARTÕES!$F15,CARTÕES!$E15-(CARTÕES!$F15-1)*ROUND(CARTÕES!$E15/CARTÕES!$F15,0),ROUND(CARTÕES!$E15/CARTÕES!$F15,0))) | BL15: =IF(AB15=0,0,IF(26=CARTÕES!$F15,CARTÕES!$E15-(CARTÕES!$F15-1)*ROUND(CARTÕES!$E15/CARTÕES!$F15,0),ROUND(CARTÕES!$E15/CARTÕES!$F15,0))) | BM15: =IF(AC15=0,0,IF(27=CARTÕES!$F15,CARTÕES!$E15-(CARTÕES!$F15-1)*ROUND(CARTÕES!$E15/CARTÕES!$F15,0),ROUND(CARTÕES!$E15/CARTÕES!$F15,0))) | BN15: =IF(AD15=0,0,IF(28=CARTÕES!$F15,CARTÕES!$E15-(CARTÕES!$F15-1)*ROUND(CARTÕES!$E15/CARTÕES!$F15,0),ROUND(CARTÕES!$E15/CARTÕES!$F15,0))) | BO15: =IF(AE15=0,0,IF(29=CARTÕES!$F15,CARTÕES!$E15-(CARTÕES!$F15-1)*ROUND(CARTÕES!$E15/CARTÕES!$F15,0),ROUND(CARTÕES!$E15/CARTÕES!$F15,0))) | BP15: =IF(AF15=0,0,IF(30=CARTÕES!$F15,CARTÕES!$E15-(CARTÕES!$F15-1)*ROUND(CARTÕES!$E15/CARTÕES!$F15,0),ROUND(CARTÕES!$E15/CARTÕES!$F15,0))) | BQ15: =IF(AG15=0,0,IF(31=CARTÕES!$F15,CARTÕES!$E15-(CARTÕES!$F15-1)*ROUND(CARTÕES!$E15/CARTÕES!$F15,0),ROUND(CARTÕES!$E15/CARTÕES!$F15,0))) | BR15: =IF(AH15=0,0,IF(32=CARTÕES!$F15,CARTÕES!$E15-(CARTÕES!$F15-1)*ROUND(CARTÕES!$E15/CARTÕES!$F15,0),ROUND(CARTÕES!$E15/CARTÕES!$F15,0))) | BS15: =IF(AI15=0,0,IF(33=CARTÕES!$F15,CARTÕES!$E15-(CARTÕES!$F15-1)*ROUND(CARTÕES!$E15/CARTÕES!$F15,0),ROUND(CARTÕES!$E15/CARTÕES!$F15,0))) | BT15: =IF(AJ15=0,0,IF(34=CARTÕES!$F15,CARTÕES!$E15-(CARTÕES!$F15-1)*ROUND(CARTÕES!$E15/CARTÕES!$F15,0),ROUND(CARTÕES!$E15/CARTÕES!$F15,0))) | BU15: =IF(AK15=0,0,IF(35=CARTÕES!$F15,CARTÕES!$E15-(CARTÕES!$F15-1)*ROUND(CARTÕES!$E15/CARTÕES!$F15,0),ROUND(CARTÕES!$E15/CARTÕES!$F15,0))) | BV15: =IF(AL15=0,0,IF(36=CARTÕES!$F15,CARTÕES!$E15-(CARTÕES!$F15-1)*ROUND(CARTÕES!$E15/CARTÕES!$F15,0),ROUND(CARTÕES!$E15/CARTÕES!$F15,0)))
A16: =IF(CARTÕES!$C16="","",CARTÕES!$C16) | B16: =SUMPRODUCT((C16:AL16='RESUMO MENSAL'!$C$4)*AM16:BV16) | C16: =IF(OR(CARTÕES!$K16=0,CARTÕES!$F16=""),0,IF(1>CARTÕES!$F16,0,CARTÕES!$K16+1-1)) | D16: =IF(OR(CARTÕES!$K16=0,CARTÕES!$F16=""),0,IF(2>CARTÕES!$F16,0,CARTÕES!$K16+2-1)) | E16: =IF(OR(CARTÕES!$K16=0,CARTÕES!$F16=""),0,IF(3>CARTÕES!$F16,0,CARTÕES!$K16+3-1)) | F16: =IF(OR(CARTÕES!$K16=0,CARTÕES!$F16=""),0,IF(4>CARTÕES!$F16,0,CARTÕES!$K16+4-1)) | G16: =IF(OR(CARTÕES!$K16=0,CARTÕES!$F16=""),0,IF(5>CARTÕES!$F16,0,CARTÕES!$K16+5-1)) | H16: =IF(OR(CARTÕES!$K16=0,CARTÕES!$F16=""),0,IF(6>CARTÕES!$F16,0,CARTÕES!$K16+6-1)) | I16: =IF(OR(CARTÕES!$K16=0,CARTÕES!$F16=""),0,IF(7>CARTÕES!$F16,0,CARTÕES!$K16+7-1)) | J16: =IF(OR(CARTÕES!$K16=0,CARTÕES!$F16=""),0,IF(8>CARTÕES!$F16,0,CARTÕES!$K16+8-1)) | K16: =IF(OR(CARTÕES!$K16=0,CARTÕES!$F16=""),0,IF(9>CARTÕES!$F16,0,CARTÕES!$K16+9-1)) | L16: =IF(OR(CARTÕES!$K16=0,CARTÕES!$F16=""),0,IF(10>CARTÕES!$F16,0,CARTÕES!$K16+10-1)) | M16: =IF(OR(CARTÕES!$K16=0,CARTÕES!$F16=""),0,IF(11>CARTÕES!$F16,0,CARTÕES!$K16+11-1)) | N16: =IF(OR(CARTÕES!$K16=0,CARTÕES!$F16=""),0,IF(12>CARTÕES!$F16,0,CARTÕES!$K16+12-1)) | O16: =IF(OR(CARTÕES!$K16=0,CARTÕES!$F16=""),0,IF(13>CARTÕES!$F16,0,CARTÕES!$K16+13-1)) | P16: =IF(OR(CARTÕES!$K16=0,CARTÕES!$F16=""),0,IF(14>CARTÕES!$F16,0,CARTÕES!$K16+14-1)) | Q16: =IF(OR(CARTÕES!$K16=0,CARTÕES!$F16=""),0,IF(15>CARTÕES!$F16,0,CARTÕES!$K16+15-1)) | R16: =IF(OR(CARTÕES!$K16=0,CARTÕES!$F16=""),0,IF(16>CARTÕES!$F16,0,CARTÕES!$K16+16-1)) | S16: =IF(OR(CARTÕES!$K16=0,CARTÕES!$F16=""),0,IF(17>CARTÕES!$F16,0,CARTÕES!$K16+17-1)) | T16: =IF(OR(CARTÕES!$K16=0,CARTÕES!$F16=""),0,IF(18>CARTÕES!$F16,0,CARTÕES!$K16+18-1)) | U16: =IF(OR(CARTÕES!$K16=0,CARTÕES!$F16=""),0,IF(19>CARTÕES!$F16,0,CARTÕES!$K16+19-1)) | V16: =IF(OR(CARTÕES!$K16=0,CARTÕES!$F16=""),0,IF(20>CARTÕES!$F16,0,CARTÕES!$K16+20-1)) | W16: =IF(OR(CARTÕES!$K16=0,CARTÕES!$F16=""),0,IF(21>CARTÕES!$F16,0,CARTÕES!$K16+21-1)) | X16: =IF(OR(CARTÕES!$K16=0,CARTÕES!$F16=""),0,IF(22>CARTÕES!$F16,0,CARTÕES!$K16+22-1)) | Y16: =IF(OR(CARTÕES!$K16=0,CARTÕES!$F16=""),0,IF(23>CARTÕES!$F16,0,CARTÕES!$K16+23-1)) | Z16: =IF(OR(CARTÕES!$K16=0,CARTÕES!$F16=""),0,IF(24>CARTÕES!$F16,0,CARTÕES!$K16+24-1)) | AA16: =IF(OR(CARTÕES!$K16=0,CARTÕES!$F16=""),0,IF(25>CARTÕES!$F16,0,CARTÕES!$K16+25-1)) | AB16: =IF(OR(CARTÕES!$K16=0,CARTÕES!$F16=""),0,IF(26>CARTÕES!$F16,0,CARTÕES!$K16+26-1)) | AC16: =IF(OR(CARTÕES!$K16=0,CARTÕES!$F16=""),0,IF(27>CARTÕES!$F16,0,CARTÕES!$K16+27-1)) | AD16: =IF(OR(CARTÕES!$K16=0,CARTÕES!$F16=""),0,IF(28>CARTÕES!$F16,0,CARTÕES!$K16+28-1)) | AE16: =IF(OR(CARTÕES!$K16=0,CARTÕES!$F16=""),0,IF(29>CARTÕES!$F16,0,CARTÕES!$K16+29-1)) | AF16: =IF(OR(CARTÕES!$K16=0,CARTÕES!$F16=""),0,IF(30>CARTÕES!$F16,0,CARTÕES!$K16+30-1)) | AG16: =IF(OR(CARTÕES!$K16=0,CARTÕES!$F16=""),0,IF(31>CARTÕES!$F16,0,CARTÕES!$K16+31-1)) | AH16: =IF(OR(CARTÕES!$K16=0,CARTÕES!$F16=""),0,IF(32>CARTÕES!$F16,0,CARTÕES!$K16+32-1)) | AI16: =IF(OR(CARTÕES!$K16=0,CARTÕES!$F16=""),0,IF(33>CARTÕES!$F16,0,CARTÕES!$K16+33-1)) | AJ16: =IF(OR(CARTÕES!$K16=0,CARTÕES!$F16=""),0,IF(34>CARTÕES!$F16,0,CARTÕES!$K16+34-1)) | AK16: =IF(OR(CARTÕES!$K16=0,CARTÕES!$F16=""),0,IF(35>CARTÕES!$F16,0,CARTÕES!$K16+35-1)) | AL16: =IF(OR(CARTÕES!$K16=0,CARTÕES!$F16=""),0,IF(36>CARTÕES!$F16,0,CARTÕES!$K16+36-1)) | AM16: =IF(C16=0,0,IF(1=CARTÕES!$F16,CARTÕES!$E16-(CARTÕES!$F16-1)*ROUND(CARTÕES!$E16/CARTÕES!$F16,0),ROUND(CARTÕES!$E16/CARTÕES!$F16,0))) | AN16: =IF(D16=0,0,IF(2=CARTÕES!$F16,CARTÕES!$E16-(CARTÕES!$F16-1)*ROUND(CARTÕES!$E16/CARTÕES!$F16,0),ROUND(CARTÕES!$E16/CARTÕES!$F16,0))) | AO16: =IF(E16=0,0,IF(3=CARTÕES!$F16,CARTÕES!$E16-(CARTÕES!$F16-1)*ROUND(CARTÕES!$E16/CARTÕES!$F16,0),ROUND(CARTÕES!$E16/CARTÕES!$F16,0))) | AP16: =IF(F16=0,0,IF(4=CARTÕES!$F16,CARTÕES!$E16-(CARTÕES!$F16-1)*ROUND(CARTÕES!$E16/CARTÕES!$F16,0),ROUND(CARTÕES!$E16/CARTÕES!$F16,0))) | AQ16: =IF(G16=0,0,IF(5=CARTÕES!$F16,CARTÕES!$E16-(CARTÕES!$F16-1)*ROUND(CARTÕES!$E16/CARTÕES!$F16,0),ROUND(CARTÕES!$E16/CARTÕES!$F16,0))) | AR16: =IF(H16=0,0,IF(6=CARTÕES!$F16,CARTÕES!$E16-(CARTÕES!$F16-1)*ROUND(CARTÕES!$E16/CARTÕES!$F16,0),ROUND(CARTÕES!$E16/CARTÕES!$F16,0))) | AS16: =IF(I16=0,0,IF(7=CARTÕES!$F16,CARTÕES!$E16-(CARTÕES!$F16-1)*ROUND(CARTÕES!$E16/CARTÕES!$F16,0),ROUND(CARTÕES!$E16/CARTÕES!$F16,0))) | AT16: =IF(J16=0,0,IF(8=CARTÕES!$F16,CARTÕES!$E16-(CARTÕES!$F16-1)*ROUND(CARTÕES!$E16/CARTÕES!$F16,0),ROUND(CARTÕES!$E16/CARTÕES!$F16,0))) | AU16: =IF(K16=0,0,IF(9=CARTÕES!$F16,CARTÕES!$E16-(CARTÕES!$F16-1)*ROUND(CARTÕES!$E16/CARTÕES!$F16,0),ROUND(CARTÕES!$E16/CARTÕES!$F16,0))) | AV16: =IF(L16=0,0,IF(10=CARTÕES!$F16,CARTÕES!$E16-(CARTÕES!$F16-1)*ROUND(CARTÕES!$E16/CARTÕES!$F16,0),ROUND(CARTÕES!$E16/CARTÕES!$F16,0))) | AW16: =IF(M16=0,0,IF(11=CARTÕES!$F16,CARTÕES!$E16-(CARTÕES!$F16-1)*ROUND(CARTÕES!$E16/CARTÕES!$F16,0),ROUND(CARTÕES!$E16/CARTÕES!$F16,0))) | AX16: =IF(N16=0,0,IF(12=CARTÕES!$F16,CARTÕES!$E16-(CARTÕES!$F16-1)*ROUND(CARTÕES!$E16/CARTÕES!$F16,0),ROUND(CARTÕES!$E16/CARTÕES!$F16,0))) | AY16: =IF(O16=0,0,IF(13=CARTÕES!$F16,CARTÕES!$E16-(CARTÕES!$F16-1)*ROUND(CARTÕES!$E16/CARTÕES!$F16,0),ROUND(CARTÕES!$E16/CARTÕES!$F16,0))) | AZ16: =IF(P16=0,0,IF(14=CARTÕES!$F16,CARTÕES!$E16-(CARTÕES!$F16-1)*ROUND(CARTÕES!$E16/CARTÕES!$F16,0),ROUND(CARTÕES!$E16/CARTÕES!$F16,0))) | BA16: =IF(Q16=0,0,IF(15=CARTÕES!$F16,CARTÕES!$E16-(CARTÕES!$F16-1)*ROUND(CARTÕES!$E16/CARTÕES!$F16,0),ROUND(CARTÕES!$E16/CARTÕES!$F16,0))) | BB16: =IF(R16=0,0,IF(16=CARTÕES!$F16,CARTÕES!$E16-(CARTÕES!$F16-1)*ROUND(CARTÕES!$E16/CARTÕES!$F16,0),ROUND(CARTÕES!$E16/CARTÕES!$F16,0))) | BC16: =IF(S16=0,0,IF(17=CARTÕES!$F16,CARTÕES!$E16-(CARTÕES!$F16-1)*ROUND(CARTÕES!$E16/CARTÕES!$F16,0),ROUND(CARTÕES!$E16/CARTÕES!$F16,0))) | BD16: =IF(T16=0,0,IF(18=CARTÕES!$F16,CARTÕES!$E16-(CARTÕES!$F16-1)*ROUND(CARTÕES!$E16/CARTÕES!$F16,0),ROUND(CARTÕES!$E16/CARTÕES!$F16,0))) | BE16: =IF(U16=0,0,IF(19=CARTÕES!$F16,CARTÕES!$E16-(CARTÕES!$F16-1)*ROUND(CARTÕES!$E16/CARTÕES!$F16,0),ROUND(CARTÕES!$E16/CARTÕES!$F16,0))) | BF16: =IF(V16=0,0,IF(20=CARTÕES!$F16,CARTÕES!$E16-(CARTÕES!$F16-1)*ROUND(CARTÕES!$E16/CARTÕES!$F16,0),ROUND(CARTÕES!$E16/CARTÕES!$F16,0))) | BG16: =IF(W16=0,0,IF(21=CARTÕES!$F16,CARTÕES!$E16-(CARTÕES!$F16-1)*ROUND(CARTÕES!$E16/CARTÕES!$F16,0),ROUND(CARTÕES!$E16/CARTÕES!$F16,0))) | BH16: =IF(X16=0,0,IF(22=CARTÕES!$F16,CARTÕES!$E16-(CARTÕES!$F16-1)*ROUND(CARTÕES!$E16/CARTÕES!$F16,0),ROUND(CARTÕES!$E16/CARTÕES!$F16,0))) | BI16: =IF(Y16=0,0,IF(23=CARTÕES!$F16,CARTÕES!$E16-(CARTÕES!$F16-1)*ROUND(CARTÕES!$E16/CARTÕES!$F16,0),ROUND(CARTÕES!$E16/CARTÕES!$F16,0))) | BJ16: =IF(Z16=0,0,IF(24=CARTÕES!$F16,CARTÕES!$E16-(CARTÕES!$F16-1)*ROUND(CARTÕES!$E16/CARTÕES!$F16,0),ROUND(CARTÕES!$E16/CARTÕES!$F16,0))) | BK16: =IF(AA16=0,0,IF(25=CARTÕES!$F16,CARTÕES!$E16-(CARTÕES!$F16-1)*ROUND(CARTÕES!$E16/CARTÕES!$F16,0),ROUND(CARTÕES!$E16/CARTÕES!$F16,0))) | BL16: =IF(AB16=0,0,IF(26=CARTÕES!$F16,CARTÕES!$E16-(CARTÕES!$F16-1)*ROUND(CARTÕES!$E16/CARTÕES!$F16,0),ROUND(CARTÕES!$E16/CARTÕES!$F16,0))) | BM16: =IF(AC16=0,0,IF(27=CARTÕES!$F16,CARTÕES!$E16-(CARTÕES!$F16-1)*ROUND(CARTÕES!$E16/CARTÕES!$F16,0),ROUND(CARTÕES!$E16/CARTÕES!$F16,0))) | BN16: =IF(AD16=0,0,IF(28=CARTÕES!$F16,CARTÕES!$E16-(CARTÕES!$F16-1)*ROUND(CARTÕES!$E16/CARTÕES!$F16,0),ROUND(CARTÕES!$E16/CARTÕES!$F16,0))) | BO16: =IF(AE16=0,0,IF(29=CARTÕES!$F16,CARTÕES!$E16-(CARTÕES!$F16-1)*ROUND(CARTÕES!$E16/CARTÕES!$F16,0),ROUND(CARTÕES!$E16/CARTÕES!$F16,0))) | BP16: =IF(AF16=0,0,IF(30=CARTÕES!$F16,CARTÕES!$E16-(CARTÕES!$F16-1)*ROUND(CARTÕES!$E16/CARTÕES!$F16,0),ROUND(CARTÕES!$E16/CARTÕES!$F16,0))) | BQ16: =IF(AG16=0,0,IF(31=CARTÕES!$F16,CARTÕES!$E16-(CARTÕES!$F16-1)*ROUND(CARTÕES!$E16/CARTÕES!$F16,0),ROUND(CARTÕES!$E16/CARTÕES!$F16,0))) | BR16: =IF(AH16=0,0,IF(32=CARTÕES!$F16,CARTÕES!$E16-(CARTÕES!$F16-1)*ROUND(CARTÕES!$E16/CARTÕES!$F16,0),ROUND(CARTÕES!$E16/CARTÕES!$F16,0))) | BS16: =IF(AI16=0,0,IF(33=CARTÕES!$F16,CARTÕES!$E16-(CARTÕES!$F16-1)*ROUND(CARTÕES!$E16/CARTÕES!$F16,0),ROUND(CARTÕES!$E16/CARTÕES!$F16,0))) | BT16: =IF(AJ16=0,0,IF(34=CARTÕES!$F16,CARTÕES!$E16-(CARTÕES!$F16-1)*ROUND(CARTÕES!$E16/CARTÕES!$F16,0),ROUND(CARTÕES!$E16/CARTÕES!$F16,0))) | BU16: =IF(AK16=0,0,IF(35=CARTÕES!$F16,CARTÕES!$E16-(CARTÕES!$F16-1)*ROUND(CARTÕES!$E16/CARTÕES!$F16,0),ROUND(CARTÕES!$E16/CARTÕES!$F16,0))) | BV16: =IF(AL16=0,0,IF(36=CARTÕES!$F16,CARTÕES!$E16-(CARTÕES!$F16-1)*ROUND(CARTÕES!$E16/CARTÕES!$F16,0),ROUND(CARTÕES!$E16/CARTÕES!$F16,0)))
A17: =IF(CARTÕES!$C17="","",CARTÕES!$C17) | B17: =SUMPRODUCT((C17:AL17='RESUMO MENSAL'!$C$4)*AM17:BV17) | C17: =IF(OR(CARTÕES!$K17=0,CARTÕES!$F17=""),0,IF(1>CARTÕES!$F17,0,CARTÕES!$K17+1-1)) | D17: =IF(OR(CARTÕES!$K17=0,CARTÕES!$F17=""),0,IF(2>CARTÕES!$F17,0,CARTÕES!$K17+2-1)) | E17: =IF(OR(CARTÕES!$K17=0,CARTÕES!$F17=""),0,IF(3>CARTÕES!$F17,0,CARTÕES!$K17+3-1)) | F17: =IF(OR(CARTÕES!$K17=0,CARTÕES!$F17=""),0,IF(4>CARTÕES!$F17,0,CARTÕES!$K17+4-1)) | G17: =IF(OR(CARTÕES!$K17=0,CARTÕES!$F17=""),0,IF(5>CARTÕES!$F17,0,CARTÕES!$K17+5-1)) | H17: =IF(OR(CARTÕES!$K17=0,CARTÕES!$F17=""),0,IF(6>CARTÕES!$F17,0,CARTÕES!$K17+6-1)) | I17: =IF(OR(CARTÕES!$K17=0,CARTÕES!$F17=""),0,IF(7>CARTÕES!$F17,0,CARTÕES!$K17+7-1)) | J17: =IF(OR(CARTÕES!$K17=0,CARTÕES!$F17=""),0,IF(8>CARTÕES!$F17,0,CARTÕES!$K17+8-1)) | K17: =IF(OR(CARTÕES!$K17=0,CARTÕES!$F17=""),0,IF(9>CARTÕES!$F17,0,CARTÕES!$K17+9-1)) | L17: =IF(OR(CARTÕES!$K17=0,CARTÕES!$F17=""),0,IF(10>CARTÕES!$F17,0,CARTÕES!$K17+10-1)) | M17: =IF(OR(CARTÕES!$K17=0,CARTÕES!$F17=""),0,IF(11>CARTÕES!$F17,0,CARTÕES!$K17+11-1)) | N17: =IF(OR(CARTÕES!$K17=0,CARTÕES!$F17=""),0,IF(12>CARTÕES!$F17,0,CARTÕES!$K17+12-1)) | O17: =IF(OR(CARTÕES!$K17=0,CARTÕES!$F17=""),0,IF(13>CARTÕES!$F17,0,CARTÕES!$K17+13-1)) | P17: =IF(OR(CARTÕES!$K17=0,CARTÕES!$F17=""),0,IF(14>CARTÕES!$F17,0,CARTÕES!$K17+14-1)) | Q17: =IF(OR(CARTÕES!$K17=0,CARTÕES!$F17=""),0,IF(15>CARTÕES!$F17,0,CARTÕES!$K17+15-1)) | R17: =IF(OR(CARTÕES!$K17=0,CARTÕES!$F17=""),0,IF(16>CARTÕES!$F17,0,CARTÕES!$K17+16-1)) | S17: =IF(OR(CARTÕES!$K17=0,CARTÕES!$F17=""),0,IF(17>CARTÕES!$F17,0,CARTÕES!$K17+17-1)) | T17: =IF(OR(CARTÕES!$K17=0,CARTÕES!$F17=""),0,IF(18>CARTÕES!$F17,0,CARTÕES!$K17+18-1)) | U17: =IF(OR(CARTÕES!$K17=0,CARTÕES!$F17=""),0,IF(19>CARTÕES!$F17,0,CARTÕES!$K17+19-1)) | V17: =IF(OR(CARTÕES!$K17=0,CARTÕES!$F17=""),0,IF(20>CARTÕES!$F17,0,CARTÕES!$K17+20-1)) | W17: =IF(OR(CARTÕES!$K17=0,CARTÕES!$F17=""),0,IF(21>CARTÕES!$F17,0,CARTÕES!$K17+21-1)) | X17: =IF(OR(CARTÕES!$K17=0,CARTÕES!$F17=""),0,IF(22>CARTÕES!$F17,0,CARTÕES!$K17+22-1)) | Y17: =IF(OR(CARTÕES!$K17=0,CARTÕES!$F17=""),0,IF(23>CARTÕES!$F17,0,CARTÕES!$K17+23-1)) | Z17: =IF(OR(CARTÕES!$K17=0,CARTÕES!$F17=""),0,IF(24>CARTÕES!$F17,0,CARTÕES!$K17+24-1)) | AA17: =IF(OR(CARTÕES!$K17=0,CARTÕES!$F17=""),0,IF(25>CARTÕES!$F17,0,CARTÕES!$K17+25-1)) | AB17: =IF(OR(CARTÕES!$K17=0,CARTÕES!$F17=""),0,IF(26>CARTÕES!$F17,0,CARTÕES!$K17+26-1)) | AC17: =IF(OR(CARTÕES!$K17=0,CARTÕES!$F17=""),0,IF(27>CARTÕES!$F17,0,CARTÕES!$K17+27-1)) | AD17: =IF(OR(CARTÕES!$K17=0,CARTÕES!$F17=""),0,IF(28>CARTÕES!$F17,0,CARTÕES!$K17+28-1)) | AE17: =IF(OR(CARTÕES!$K17=0,CARTÕES!$F17=""),0,IF(29>CARTÕES!$F17,0,CARTÕES!$K17+29-1)) | AF17: =IF(OR(CARTÕES!$K17=0,CARTÕES!$F17=""),0,IF(30>CARTÕES!$F17,0,CARTÕES!$K17+30-1)) | AG17: =IF(OR(CARTÕES!$K17=0,CARTÕES!$F17=""),0,IF(31>CARTÕES!$F17,0,CARTÕES!$K17+31-1)) | AH17: =IF(OR(CARTÕES!$K17=0,CARTÕES!$F17=""),0,IF(32>CARTÕES!$F17,0,CARTÕES!$K17+32-1)) | AI17: =IF(OR(CARTÕES!$K17=0,CARTÕES!$F17=""),0,IF(33>CARTÕES!$F17,0,CARTÕES!$K17+33-1)) | AJ17: =IF(OR(CARTÕES!$K17=0,CARTÕES!$F17=""),0,IF(34>CARTÕES!$F17,0,CARTÕES!$K17+34-1)) | AK17: =IF(OR(CARTÕES!$K17=0,CARTÕES!$F17=""),0,IF(35>CARTÕES!$F17,0,CARTÕES!$K17+35-1)) | AL17: =IF(OR(CARTÕES!$K17=0,CARTÕES!$F17=""),0,IF(36>CARTÕES!$F17,0,CARTÕES!$K17+36-1)) | AM17: =IF(C17=0,0,IF(1=CARTÕES!$F17,CARTÕES!$E17-(CARTÕES!$F17-1)*ROUND(CARTÕES!$E17/CARTÕES!$F17,0),ROUND(CARTÕES!$E17/CARTÕES!$F17,0))) | AN17: =IF(D17=0,0,IF(2=CARTÕES!$F17,CARTÕES!$E17-(CARTÕES!$F17-1)*ROUND(CARTÕES!$E17/CARTÕES!$F17,0),ROUND(CARTÕES!$E17/CARTÕES!$F17,0))) | AO17: =IF(E17=0,0,IF(3=CARTÕES!$F17,CARTÕES!$E17-(CARTÕES!$F17-1)*ROUND(CARTÕES!$E17/CARTÕES!$F17,0),ROUND(CARTÕES!$E17/CARTÕES!$F17,0))) | AP17: =IF(F17=0,0,IF(4=CARTÕES!$F17,CARTÕES!$E17-(CARTÕES!$F17-1)*ROUND(CARTÕES!$E17/CARTÕES!$F17,0),ROUND(CARTÕES!$E17/CARTÕES!$F17,0))) | AQ17: =IF(G17=0,0,IF(5=CARTÕES!$F17,CARTÕES!$E17-(CARTÕES!$F17-1)*ROUND(CARTÕES!$E17/CARTÕES!$F17,0),ROUND(CARTÕES!$E17/CARTÕES!$F17,0))) | AR17: =IF(H17=0,0,IF(6=CARTÕES!$F17,CARTÕES!$E17-(CARTÕES!$F17-1)*ROUND(CARTÕES!$E17/CARTÕES!$F17,0),ROUND(CARTÕES!$E17/CARTÕES!$F17,0))) | AS17: =IF(I17=0,0,IF(7=CARTÕES!$F17,CARTÕES!$E17-(CARTÕES!$F17-1)*ROUND(CARTÕES!$E17/CARTÕES!$F17,0),ROUND(CARTÕES!$E17/CARTÕES!$F17,0))) | AT17: =IF(J17=0,0,IF(8=CARTÕES!$F17,CARTÕES!$E17-(CARTÕES!$F17-1)*ROUND(CARTÕES!$E17/CARTÕES!$F17,0),ROUND(CARTÕES!$E17/CARTÕES!$F17,0))) | AU17: =IF(K17=0,0,IF(9=CARTÕES!$F17,CARTÕES!$E17-(CARTÕES!$F17-1)*ROUND(CARTÕES!$E17/CARTÕES!$F17,0),ROUND(CARTÕES!$E17/CARTÕES!$F17,0))) | AV17: =IF(L17=0,0,IF(10=CARTÕES!$F17,CARTÕES!$E17-(CARTÕES!$F17-1)*ROUND(CARTÕES!$E17/CARTÕES!$F17,0),ROUND(CARTÕES!$E17/CARTÕES!$F17,0))) | AW17: =IF(M17=0,0,IF(11=CARTÕES!$F17,CARTÕES!$E17-(CARTÕES!$F17-1)*ROUND(CARTÕES!$E17/CARTÕES!$F17,0),ROUND(CARTÕES!$E17/CARTÕES!$F17,0))) | AX17: =IF(N17=0,0,IF(12=CARTÕES!$F17,CARTÕES!$E17-(CARTÕES!$F17-1)*ROUND(CARTÕES!$E17/CARTÕES!$F17,0),ROUND(CARTÕES!$E17/CARTÕES!$F17,0))) | AY17: =IF(O17=0,0,IF(13=CARTÕES!$F17,CARTÕES!$E17-(CARTÕES!$F17-1)*ROUND(CARTÕES!$E17/CARTÕES!$F17,0),ROUND(CARTÕES!$E17/CARTÕES!$F17,0))) | AZ17: =IF(P17=0,0,IF(14=CARTÕES!$F17,CARTÕES!$E17-(CARTÕES!$F17-1)*ROUND(CARTÕES!$E17/CARTÕES!$F17,0),ROUND(CARTÕES!$E17/CARTÕES!$F17,0))) | BA17: =IF(Q17=0,0,IF(15=CARTÕES!$F17,CARTÕES!$E17-(CARTÕES!$F17-1)*ROUND(CARTÕES!$E17/CARTÕES!$F17,0),ROUND(CARTÕES!$E17/CARTÕES!$F17,0))) | BB17: =IF(R17=0,0,IF(16=CARTÕES!$F17,CARTÕES!$E17-(CARTÕES!$F17-1)*ROUND(CARTÕES!$E17/CARTÕES!$F17,0),ROUND(CARTÕES!$E17/CARTÕES!$F17,0))) | BC17: =IF(S17=0,0,IF(17=CARTÕES!$F17,CARTÕES!$E17-(CARTÕES!$F17-1)*ROUND(CARTÕES!$E17/CARTÕES!$F17,0),ROUND(CARTÕES!$E17/CARTÕES!$F17,0))) | BD17: =IF(T17=0,0,IF(18=CARTÕES!$F17,CARTÕES!$E17-(CARTÕES!$F17-1)*ROUND(CARTÕES!$E17/CARTÕES!$F17,0),ROUND(CARTÕES!$E17/CARTÕES!$F17,0))) | BE17: =IF(U17=0,0,IF(19=CARTÕES!$F17,CARTÕES!$E17-(CARTÕES!$F17-1)*ROUND(CARTÕES!$E17/CARTÕES!$F17,0),ROUND(CARTÕES!$E17/CARTÕES!$F17,0))) | BF17: =IF(V17=0,0,IF(20=CARTÕES!$F17,CARTÕES!$E17-(CARTÕES!$F17-1)*ROUND(CARTÕES!$E17/CARTÕES!$F17,0),ROUND(CARTÕES!$E17/CARTÕES!$F17,0))) | BG17: =IF(W17=0,0,IF(21=CARTÕES!$F17,CARTÕES!$E17-(CARTÕES!$F17-1)*ROUND(CARTÕES!$E17/CARTÕES!$F17,0),ROUND(CARTÕES!$E17/CARTÕES!$F17,0))) | BH17: =IF(X17=0,0,IF(22=CARTÕES!$F17,CARTÕES!$E17-(CARTÕES!$F17-1)*ROUND(CARTÕES!$E17/CARTÕES!$F17,0),ROUND(CARTÕES!$E17/CARTÕES!$F17,0))) | BI17: =IF(Y17=0,0,IF(23=CARTÕES!$F17,CARTÕES!$E17-(CARTÕES!$F17-1)*ROUND(CARTÕES!$E17/CARTÕES!$F17,0),ROUND(CARTÕES!$E17/CARTÕES!$F17,0))) | BJ17: =IF(Z17=0,0,IF(24=CARTÕES!$F17,CARTÕES!$E17-(CARTÕES!$F17-1)*ROUND(CARTÕES!$E17/CARTÕES!$F17,0),ROUND(CARTÕES!$E17/CARTÕES!$F17,0))) | BK17: =IF(AA17=0,0,IF(25=CARTÕES!$F17,CARTÕES!$E17-(CARTÕES!$F17-1)*ROUND(CARTÕES!$E17/CARTÕES!$F17,0),ROUND(CARTÕES!$E17/CARTÕES!$F17,0))) | BL17: =IF(AB17=0,0,IF(26=CARTÕES!$F17,CARTÕES!$E17-(CARTÕES!$F17-1)*ROUND(CARTÕES!$E17/CARTÕES!$F17,0),ROUND(CARTÕES!$E17/CARTÕES!$F17,0))) | BM17: =IF(AC17=0,0,IF(27=CARTÕES!$F17,CARTÕES!$E17-(CARTÕES!$F17-1)*ROUND(CARTÕES!$E17/CARTÕES!$F17,0),ROUND(CARTÕES!$E17/CARTÕES!$F17,0))) | BN17: =IF(AD17=0,0,IF(28=CARTÕES!$F17,CARTÕES!$E17-(CARTÕES!$F17-1)*ROUND(CARTÕES!$E17/CARTÕES!$F17,0),ROUND(CARTÕES!$E17/CARTÕES!$F17,0))) | BO17: =IF(AE17=0,0,IF(29=CARTÕES!$F17,CARTÕES!$E17-(CARTÕES!$F17-1)*ROUND(CARTÕES!$E17/CARTÕES!$F17,0),ROUND(CARTÕES!$E17/CARTÕES!$F17,0))) | BP17: =IF(AF17=0,0,IF(30=CARTÕES!$F17,CARTÕES!$E17-(CARTÕES!$F17-1)*ROUND(CARTÕES!$E17/CARTÕES!$F17,0),ROUND(CARTÕES!$E17/CARTÕES!$F17,0))) | BQ17: =IF(AG17=0,0,IF(31=CARTÕES!$F17,CARTÕES!$E17-(CARTÕES!$F17-1)*ROUND(CARTÕES!$E17/CARTÕES!$F17,0),ROUND(CARTÕES!$E17/CARTÕES!$F17,0))) | BR17: =IF(AH17=0,0,IF(32=CARTÕES!$F17,CARTÕES!$E17-(CARTÕES!$F17-1)*ROUND(CARTÕES!$E17/CARTÕES!$F17,0),ROUND(CARTÕES!$E17/CARTÕES!$F17,0))) | BS17: =IF(AI17=0,0,IF(33=CARTÕES!$F17,CARTÕES!$E17-(CARTÕES!$F17-1)*ROUND(CARTÕES!$E17/CARTÕES!$F17,0),ROUND(CARTÕES!$E17/CARTÕES!$F17,0))) | BT17: =IF(AJ17=0,0,IF(34=CARTÕES!$F17,CARTÕES!$E17-(CARTÕES!$F17-1)*ROUND(CARTÕES!$E17/CARTÕES!$F17,0),ROUND(CARTÕES!$E17/CARTÕES!$F17,0))) | BU17: =IF(AK17=0,0,IF(35=CARTÕES!$F17,CARTÕES!$E17-(CARTÕES!$F17-1)*ROUND(CARTÕES!$E17/CARTÕES!$F17,0),ROUND(CARTÕES!$E17/CARTÕES!$F17,0))) | BV17: =IF(AL17=0,0,IF(36=CARTÕES!$F17,CARTÕES!$E17-(CARTÕES!$F17-1)*ROUND(CARTÕES!$E17/CARTÕES!$F17,0),ROUND(CARTÕES!$E17/CARTÕES!$F17,0)))
