Workbook

Sheet DASHBOARD
A1: PAINEL FINANCEIRO PESSOAL - GUARANI (Gs.)
A2: Data de referencia e parametros na aba CFG_Sistema. Valores REALIZADOS salvo quando o titulo do indicador disser projetado.
A4: DINHEIRO
A5: SALDO TOTAL DAS CONTAS | C5: RESERVADO PARA METAS | E5: SALDO DISPONIVEL (LIVRE) | G5: SALDO PROJETADO (FIM DO HORIZONTE)
A6: =SUM(C_SALDO) -> 0 | C6: =SUM(C_RESERV) -> 0 | E6: =SUM(C_DISP) -> 0 | G6: =INDEX(PJ_SALDO,COUNT(PJ_SALDO)) -> 0
A8: INVESTIMENTOS E PATRIMONIO
A9: TOTAL INVESTIDO | C9: RENDIMENTO REALIZADO | E9: RENDIMENTO PROJETADO | G9: PATRIMONIO LIQUIDO TOTAL
A10: =SUM(I_SALDO) -> 0 | C10: =SUM(I_REND) -> 0 | E10: =SUM(I_RENDPROJ) -> 0 | G10: =PAT_PL_TOTAL -> 0
A12: DIVIDAS
A13: DIVIDA DE CARTOES | C13: LIMITE DISPONIVEL EM CARTOES | E13: SALDO DEVEDOR DE COMPROMISSOS | G13: PARCELAS + FATURAS PROXIMOS 12 MESES
A14: =SUM(K_DIVIDA) -> 0 | C14: =SUM(K_DISP) -> 0 | E14: =SUM(CM_DEVEDOR) -> 0 | G14: =SUMIFS(L_Valor,L_Data,">"&CFG_HOJE,L_Data,"<="&EDATE(CFG_HOJE,12),L_Status,"PROJETADO",L_ParcID,"<>")+SUMIFS(L_Valor,L_Data,">"&CFG_HOJE,L_Data,"<="&EDATE(CFG_HOJE,12),L_Status,"PROJETADO",L_Tipo,"PAGAMENTO_CARTAO") -> 0
A16: FLUXO DO MES CORRENTE
A17: RECEITAS REALIZADAS NO MES | C17: DESPESAS REALIZADAS NO MES | E17: RESULTADO DO MES | G17: MENOR SALDO PROJETADO NO HORIZONTE
A18: =SUMIFS(L_VRec,L_Data,">="&DATE(YEAR(CFG_HOJE),MONTH(CFG_HOJE),1),L_Data,"<="&EOMONTH(CFG_HOJE,0),L_Status,"REALIZADO") -> 0 | C18: =SUMIFS(L_VDesp,L_Data,">="&DATE(YEAR(CFG_HOJE),MONTH(CFG_HOJE),1),L_Data,"<="&EOMONTH(CFG_HOJE,0),L_Status,"REALIZADO") -> 0 | E18: =SUMIFS(L_VRec,L_Data,">="&DATE(YEAR(CFG_HOJE),MONTH(CFG_HOJE),1),L_Data,"<="&EOMONTH(CFG_HOJE,0),L_Status,"REALIZADO")+SUMIFS(L_VRend,L_Data,">="&DATE(YEAR(CFG_HOJE),MONTH(CFG_HOJE),1),L_Data,"<="&EOMONTH(CFG_HOJE,0),L_Status,"REALIZADO")-(SUMIFS(L_VDesp,L_Data,">="&DATE(YEAR(CFG_HOJE),MONTH(CFG_HOJE),1),L_Data,"<="&EOMONTH(CFG_HOJE,0),L_Status,"REALIZADO")) -> 0 | G18: =MIN(PJ_SALDO) -> 0
A20: METAS
A21: METAS ATIVAS | C21: VALOR ACUMULADO NAS METAS | E21: VALOR RESTANTE NAS METAS | G21: CONCLUSAO MEDIA DAS METAS ATIVAS
A22: =COUNTIF(M_STATUS,"Ativa") -> 0 | C22: =SUMIFS(M_RESERV,M_STATUS,"Ativa") -> 0 | E22: =SUMIFS(M_FALTA,M_STATUS,"Ativa") -> 0 | G22: =IF(COUNTIF(M_STATUS,"Ativa")=0,0,SUMIFS(M_RESERV,M_STATUS,"Ativa")/SUMIFS(M_OBJ,M_STATUS,"Ativa")) -> 0
A24: CONTROLE
A25: ALERTAS ATIVOS | C25: LANCAMENTOS REGISTRADOS | E25: LANCAMENTOS COM ERRO | G25: TESTES COM FALHA
A26: =AL_TOTAL -> 0 | C26: =COUNTIF(L_Status,"REALIZADO")+COUNTIF(L_Status,"PROJETADO") -> 0 | E26: =SUMPRODUCT((LEFT(L_Valid,4)="ERRO")*1) -> 0 | G26: =TS_FALHAS -> 0
A28: SALDO DAS CONTAS
A29: Conta | B29: Saldo_Calculado | C29: Reservado | D29: Disponivel | E29: Saldo_Projetado
A30: =IF(CAD_Contas!$A5="","",CAD_Contas!$B5) | B30: =IF(CAD_Contas!$A5="","",CAD_Contas!$J5) | C30: =IF(CAD_Contas!$A5="","",CAD_Contas!$K5) | D30: =IF(CAD_Contas!$A5="","",CAD_Contas!$L5) | E30: =IF(CAD_Contas!$A5="","",CAD_Contas!$O5)
A31: =IF(CAD_Contas!$A6="","",CAD_Contas!$B6) | B31: =IF(CAD_Contas!$A6="","",CAD_Contas!$J6) | C31: =IF(CAD_Contas!$A6="","",CAD_Contas!$K6) | D31: =IF(CAD_Contas!$A6="","",CAD_Contas!$L6) | E31: =IF(CAD_Contas!$A6="","",CAD_Contas!$O6)
A32: =IF(CAD_Contas!$A7="","",CAD_Contas!$B7) | B32: =IF(CAD_Contas!$A7="","",CAD_Contas!$J7) | C32: =IF(CAD_Contas!$A7="","",CAD_Contas!$K7) | D32: =IF(CAD_Contas!$A7="","",CAD_Contas!$L7) | E32: =IF(CAD_Contas!$A7="","",CAD_Contas!$O7)
A33: =IF(CAD_Contas!$A8="","",CAD_Contas!$B8) | B33: =IF(CAD_Contas!$A8="","",CAD_Contas!$J8) | C33: =IF(CAD_Contas!$A8="","",CAD_Contas!$K8) | D33: =IF(CAD_Contas!$A8="","",CAD_Contas!$L8) | E33: =IF(CAD_Contas!$A8="","",CAD_Contas!$O8)
A34: =IF(CAD_Contas!$A9="","",CAD_Contas!$B9) | B34: =IF(CAD_Contas!$A9="","",CAD_Contas!$J9) | C34: =IF(CAD_Contas!$A9="","",CAD_Contas!$K9) | D34: =IF(CAD_Contas!$A9="","",CAD_Contas!$L9) | E34: =IF(CAD_Contas!$A9="","",CAD_Contas!$O9)
A35: =IF(CAD_Contas!$A10="","",CAD_Contas!$B10) | B35: =IF(CAD_Contas!$A10="","",CAD_Contas!$J10) | C35: =IF(CAD_Contas!$A10="","",CAD_Contas!$K10) | D35: =IF(CAD_Contas!$A10="","",CAD_Contas!$L10) | E35: =IF(CAD_Contas!$A10="","",CAD_Contas!$O10)
A36: =IF(CAD_Contas!$A11="","",CAD_Contas!$B11) | B36: =IF(CAD_Contas!$A11="","",CAD_Contas!$J11) | C36: =IF(CAD_Contas!$A11="","",CAD_Contas!$K11) | D36: =IF(CAD_Contas!$A11="","",CAD_Contas!$L11) | E36: =IF(CAD_Contas!$A11="","",CAD_Contas!$O11)
A37: =IF(CAD_Contas!$A12="","",CAD_Contas!$B12) | B37: =IF(CAD_Contas!$A12="","",CAD_Contas!$J12) | C37: =IF(CAD_Contas!$A12="","",CAD_Contas!$K12) | D37: =IF(CAD_Contas!$A12="","",CAD_Contas!$L12) | E37: =IF(CAD_Contas!$A12="","",CAD_Contas!$O12)
A38: =IF(CAD_Contas!$A13="","",CAD_Contas!$B13) | B38: =IF(CAD_Contas!$A13="","",CAD_Contas!$J13) | C38: =IF(CAD_Contas!$A13="","",CAD_Contas!$K13) | D38: =IF(CAD_Contas!$A13="","",CAD_Contas!$L13) | E38: =IF(CAD_Contas!$A13="","",CAD_Contas!$O13)
A39: =IF(CAD_Contas!$A14="","",CAD_Contas!$B14) | B39: =IF(CAD_Contas!$A14="","",CAD_Contas!$J14) | C39: =IF(CAD_Contas!$A14="","",CAD_Contas!$K14) | D39: =IF(CAD_Contas!$A14="","",CAD_Contas!$L14) | E39: =IF(CAD_Contas!$A14="","",CAD_Contas!$O14)
A40: =IF(CAD_Contas!$A15="","",CAD_Contas!$B15) | B40: =IF(CAD_Contas!$A15="","",CAD_Contas!$J15) | C40: =IF(CAD_Contas!$A15="","",CAD_Contas!$K15) | D40: =IF(CAD_Contas!$A15="","",CAD_Contas!$L15) | E40: =IF(CAD_Contas!$A15="","",CAD_Contas!$O15)
A41: =IF(CAD_Contas!$A16="","",CAD_Contas!$B16) | B41: =IF(CAD_Contas!$A16="","",CAD_Contas!$J16) | C41: =IF(CAD_Contas!$A16="","",CAD_Contas!$K16) | D41: =IF(CAD_Contas!$A16="","",CAD_Contas!$L16) | E41: =IF(CAD_Contas!$A16="","",CAD_Contas!$O16)
... A69: =IF(CAD_Contas!$A44="","",CAD_Contas!$B44) | B69: =IF(CAD_Contas!$A44="","",CAD_Contas!$J44) | C69: =IF(CAD_Contas!$A44="","",CAD_Contas!$K44) | D69: =IF(CAD_Contas!$A44="","",CAD_Contas!$L44) | E69: =IF(CAD_Contas!$A44="","",CAD_Contas!$O44)
A71: METAS FINANCEIRAS
A72: Meta | B72: Objetivo | C72: Acumulado | D72: Faltante | E72: Concluido | F72: Situacao
A73: =IF(CAD_Metas!$A5="","",CAD_Metas!$B5) | B73: =IF(CAD_Metas!$A5="","",CAD_Metas!$C5) | C73: =IF(CAD_Metas!$A5="","",CAD_Metas!$H5) | D73: =IF(CAD_Metas!$A5="","",CAD_Metas!$J5) | E73: =IF(CAD_Metas!$A5="","",CAD_Metas!$I5) | F73: =IF(CAD_Metas!$A5="","",CAD_Metas!$O5)
A74: =IF(CAD_Metas!$A6="","",CAD_Metas!$B6) | B74: =IF(CAD_Metas!$A6="","",CAD_Metas!$C6) | C74: =IF(CAD_Metas!$A6="","",CAD_Metas!$H6) | D74: =IF(CAD_Metas!$A6="","",CAD_Metas!$J6) | E74: =IF(CAD_Metas!$A6="","",CAD_Metas!$I6) | F74: =IF(CAD_Metas!$A6="","",CAD_Metas!$O6)
A75: =IF(CAD_Metas!$A7="","",CAD_Metas!$B7) | B75: =IF(CAD_Metas!$A7="","",CAD_Metas!$C7) | C75: =IF(CAD_Metas!$A7="","",CAD_Metas!$H7) | D75: =IF(CAD_Metas!$A7="","",CAD_Metas!$J7) | E75: =IF(CAD_Metas!$A7="","",CAD_Metas!$I7) | F75: =IF(CAD_Metas!$A7="","",CAD_Metas!$O7)
A76: =IF(CAD_Metas!$A8="","",CAD_Metas!$B8) | B76: =IF(CAD_Metas!$A8="","",CAD_Metas!$C8) | C76: =IF(CAD_Metas!$A8="","",CAD_Metas!$H8) | D76: =IF(CAD_Metas!$A8="","",CAD_Metas!$J8) | E76: =IF(CAD_Metas!$A8="","",CAD_Metas!$I8) | F76: =IF(CAD_Metas!$A8="","",CAD_Metas!$O8)
A77: =IF(CAD_Metas!$A9="","",CAD_Metas!$B9) | B77: =IF(CAD_Metas!$A9="","",CAD_Metas!$C9) | C77: =IF(CAD_Metas!$A9="","",CAD_Metas!$H9) | D77: =IF(CAD_Metas!$A9="","",CAD_Metas!$J9) | E77: =IF(CAD_Metas!$A9="","",CAD_Metas!$I9) | F77: =IF(CAD_Metas!$A9="","",CAD_Metas!$O9)
A78: =IF(CAD_Metas!$A10="","",CAD_Metas!$B10) | B78: =IF(CAD_Metas!$A10="","",CAD_Metas!$C10) | C78: =IF(CAD_Metas!$A10="","",CAD_Metas!$H10) | D78: =IF(CAD_Metas!$A10="","",CAD_Metas!$J10) | E78: =IF(CAD_Metas!$A10="","",CAD_Metas!$I10) | F78: =IF(CAD_Metas!$A10="","",CAD_Metas!$O10)
A79: =IF(CAD_Metas!$A11="","",CAD_Metas!$B11) | B79: =IF(CAD_Metas!$A11="","",CAD_Metas!$C11) | C79: =IF(CAD_Metas!$A11="","",CAD_Metas!$H11) | D79: =IF(CAD_Metas!$A11="","",CAD_Metas!$J11) | E79: =IF(CAD_Metas!$A11="","",CAD_Metas!$I11) | F79: =IF(CAD_Metas!$A11="","",CAD_Metas!$O11)
A80: =IF(CAD_Metas!$A12="","",CAD_Metas!$B12) | B80: =IF(CAD_Metas!$A12="","",CAD_Metas!$C12) | C80: =IF(CAD_Metas!$A12="","",CAD_Metas!$H12) | D80: =IF(CAD_Metas!$A12="","",CAD_Metas!$J12) | E80: =IF(CAD_Metas!$A12="","",CAD_Metas!$I12) | F80: =IF(CAD_Metas!$A12="","",CAD_Metas!$O12)
A81: =IF(CAD_Metas!$A13="","",CAD_Metas!$B13) | B81: =IF(CAD_Metas!$A13="","",CAD_Metas!$C13) | C81: =IF(CAD_Metas!$A13="","",CAD_Metas!$H13) | D81: =IF(CAD_Metas!$A13="","",CAD_Metas!$J13) | E81: =IF(CAD_Metas!$A13="","",CAD_Metas!$I13) | F81: =IF(CAD_Metas!$A13="","",CAD_Metas!$O13)
A82: =IF(CAD_Metas!$A14="","",CAD_Metas!$B14) | B82: =IF(CAD_Metas!$A14="","",CAD_Metas!$C14) | C82: =IF(CAD_Metas!$A14="","",CAD_Metas!$H14) | D82: =IF(CAD_Metas!$A14="","",CAD_Metas!$J14) | E82: =IF(CAD_Metas!$A14="","",CAD_Metas!$I14) | F82: =IF(CAD_Metas!$A14="","",CAD_Metas!$O14)
A83: =IF(CAD_Metas!$A15="","",CAD_Metas!$B15) | B83: =IF(CAD_Metas!$A15="","",CAD_Metas!$C15) | C83: =IF(CAD_Metas!$A15="","",CAD_Metas!$H15) | D83: =IF(CAD_Metas!$A15="","",CAD_Metas!$J15) | E83: =IF(CAD_Metas!$A15="","",CAD_Metas!$I15) | F83: =IF(CAD_Metas!$A15="","",CAD_Metas!$O15)
A84: =IF(CAD_Metas!$A16="","",CAD_Metas!$B16) | B84: =IF(CAD_Metas!$A16="","",CAD_Metas!$C16) | C84: =IF(CAD_Metas!$A16="","",CAD_Metas!$H16) | D84: =IF(CAD_Metas!$A16="","",CAD_Metas!$J16) | E84: =IF(CAD_Metas!$A16="","",CAD_Metas!$I16) | F84: =IF(CAD_Metas!$A16="","",CAD_Metas!$O16)
... A112: =IF(CAD_Metas!$A44="","",CAD_Metas!$B44) | B112: =IF(CAD_Metas!$A44="","",CAD_Metas!$C44) | C112: =IF(CAD_Metas!$A44="","",CAD_Metas!$H44) | D112: =IF(CAD_Metas!$A44="","",CAD_Metas!$J44) | E112: =IF(CAD_Metas!$A44="","",CAD_Metas!$I44) | F112: =IF(CAD_Metas!$A44="","",CAD_Metas!$O44)

Sheet LANCAR
A1: LANCAR - TELA DE LANCAMENTO RAPIDO
A2: Preencha as celulas amarelas. O sistema resolve os IDs e monta a linha pronta. Copie a LINHA PRONTA e cole na primeira linha vazia de LANCAMENTOS (colunas B ate S). O ID do lancamento e gerado automaticamente pela planilha.
A4: Data | B4: 46270
A5: Descricao | B5: Exemplo: Supermercado da semana
A6: Tipo de operacao | B6: DESPESA
A7: Status | B7: REALIZADO
A8: Valor (Gs.) | B8: 250000
A9: Origem - tipo | B9: CONTA | C9: ID resolvido | D9: =IF($B$9="EXTERNO","",IFERROR(INDEX(ENT_ID,MATCH(1,INDEX((ENT_NOME=$B$10)*(ENT_TIPO=$B$9),0),0)),"NAO ENCONTRADO")) -> NAO ENCONTRADO
A10: Origem - nome
A11: Destino - tipo | B11: EXTERNO | C11: ID resolvido | D11: =IF($B$11="EXTERNO","",IFERROR(INDEX(ENT_ID,MATCH(1,INDEX((ENT_NOME=$B$12)*(ENT_TIPO=$B$11),0),0)),"NAO ENCONTRADO"))
A12: Destino - nome | B12: (Externo)
A13: Categoria | B13: Alimentacao | C13: ID resolvido | D13: =IF($B$13="","",IFERROR(INDEX(CAT_ID,MATCH($B$13,CAT_NOME,0)),"NAO ENCONTRADO")) -> CAT-000001
A14: Subcategoria | B14: Supermercado | C14: ID resolvido | D14: =IF($B$14="","",IFERROR(INDEX(SUB_ID,MATCH(1,INDEX((SUB_NOME=$B$14)*(SUB_CATID=$D$13),0),0)),"NAO ENCONTRADO")) -> SUB-000001
A15: Forma de pagamento | B15: Debito
A16: Compromisso (opcional) | C16: ID resolvido | D16: =IF($B$16="","",IFERROR(INDEX(CM_ID,MATCH($B$16,CM_NOME,0)),"NAO ENCONTRADO"))
A17: Numero da parcela (vazio = proxima em aberto) | C17: Parcela resolvida | D17: =IF($D$16="","",IF($B$17="",IFERROR(INDEX(P_ID,MATCH(1,INDEX((P_CMP=$D$16)*(P_STATUS<>"PAGA")*(P_STATUS<>"CANCELADA"),0),0)),""),IFERROR(INDEX(P_ID,MATCH(1,INDEX((P_CMP=$D$16)*(P_NUM=$B$17),0),0)),"NAO ENCONTRADA")))
A18: Meta (opcional) | C18: Rotulo / vencimento / valor da parcela | D18: =IF($D$17="","",IFERROR(INDEX(P_ROT,MATCH($D$17,P_ID,0))&" venc "&DAY(INDEX(P_VENC,MATCH($D$17,P_ID,0)))&"/"&MONTH(INDEX(P_VENC,MATCH($D$17,P_ID,0)))&"/"&YEAR(INDEX(P_VENC,MATCH($D$17,P_ID,0)))&" Gs. "&TEXT(INDEX(P_VALOR,MATCH($D$17,P_ID,0)),"#,##0"),"?"))
A19: Recorrencia (opcional)
A20: Lancamento relacionado (estorno, opcional)
A21: Observacao
A23: VERIFICACAO ANTES DE COLAR
A24: Classificacao economica do lancamento | B24: =IFERROR(INDEX(MAP_CLASS,MATCH($B$6,MAP_TIPO,0)),"TIPO INVALIDO") -> DESPESA
A25: Efeito no caixa | B25: =IF(AND($B$11="CONTA",$B$9<>"CONTA"),"ENTRADA de caixa",IF(AND($B$9="CONTA",$B$11<>"CONTA"),"SAIDA de caixa","NAO afeta o caixa")) -> SAIDA de caixa
A26: Situacao do preenchimento | B26: =IF($B$8<=0,"ERRO: valor deve ser maior que zero",IF(AND($B$9="EXTERNO",$B$11="EXTERNO"),"ERRO: origem e destino externos",IF(AND($B$9<>"EXTERNO",$D$9=""),"ERRO: origem nao resolvida",IF(AND($B$11<>"EXTERNO",$D$11=""),"ERRO: destino nao resolvido",IF($D$13="","ERRO: categoria nao resolvida",IF(AND($B$14<>"",$D$14="NAO ENCONTRADO"),"ERRO: subcategoria nao pertence a categoria",IF(AND($D$16<>"",$D$17=""),"ATENCAO: compromisso sem parcela em aberto","PRONTO PARA COLAR"))))))) -> PRONTO PARA COLAR
A27: Aviso de vinculo | B27: =IF(AND($D$16="",$D$18="",$B$19="",$B$20=""),"Sem vinculos","ATENCAO: este lancamento fica vinculado a "&TRIM(IF($D$16<>"","compromisso/parcela ","")&IF($D$18<>"","meta ","")&IF($B$19<>"","recorrencia ","")&IF($B$20<>"","estorno",""))) -> Sem vinculos
A29: LINHA PRONTA PARA COPIAR (COLE EM LANCAMENTOS, COLUNAS B ATE S)
A30: Data | B30: Descricao | C30: Tipo_Operacao | D30: Status | E30: Valor | F30: Origem_Tipo | G30: Origem_ID | H30: Destino_Tipo | I30: Destino_ID | J30: Categoria_ID | K30: Subcategoria_ID | L30: Forma_Pagamento | M30: ID_Compromisso | N30: ID_Parcela | O30: ID_Meta | P30: ID_Recorrencia | Q30: ID_Relacionado | R30: Observacao
A31: =$B$4 -> 46270 | B31: =$B$5 -> Exemplo: Supermercado da semana | C31: =$B$6 -> DESPESA | D31: =$B$7 -> REALIZADO | E31: =$B$8 -> 250000 | F31: =$B$9 -> CONTA | G31: =$D$9 -> NAO ENCONTRADO | H31: =$B$11 -> EXTERNO | I31: =$D$11 | J31: =$D$13 -> CAT-000001 | K31: =$D$14 -> SUB-000001 | L31: =$B$15 -> Debito | M31: =$D$16 | N31: =$D$17 | O31: =$D$18 | P31: =$B$19 -> 0 | Q31: =$B$20 -> 0 | R31: =$B$21 -> 0
A33: ASSISTENTE DE RESGATE DE INVESTIMENTO (GERA DOIS LANCAMENTOS)
A34: Regra: o rendimento e reconhecido como RECEITA FINANCEIRA (lancamento 1) e o resgate transfere o dinheiro do investimento para a conta sem virar receita (lancamento 2). Se o rendimento ja foi lancado mes a mes, informe 0 no campo Rendimento apurado e use apenas o lancamento 2.
A35: Investimento (nome) | C35: ID | D35: =IFERROR(INDEX(I_ID,MATCH($B$35,I_NOME,0)),"NAO ENCONTRADO") -> NAO ENCONTRADO
A36: Conta de destino (nome) | C36: ID | D36: =IFERROR(INDEX(C_ID,MATCH($B$36,C_NOME,0)),"NAO ENCONTRADO") -> NAO ENCONTRADO
A37: Data do resgate | B37: 46270
A38: Valor total resgatado | B38: 3000000
A39: Rendimento apurado ainda nao lancado | B39: 0 | C39: Principal do resgate | D39: =MAX(0,$B$38-$B$39) -> 3000000
A41: Data | B41: Descricao | C41: Tipo_Operacao | D41: Status | E41: Valor | F41: Origem_Tipo | G41: Origem_ID | H41: Destino_Tipo | I41: Destino_ID | J41: Categoria_ID | K41: Subcategoria_ID | L41: Forma_Pagamento | M41: ID_Compromisso | N41: ID_Parcela | O41: ID_Meta | P41: ID_Recorrencia | Q41: ID_Relacionado | R41: Observacao
A42: =$B$37 -> 46270 | B42: ="Rendimento de "&$B$35 -> Rendimento de | C42: ="RENDIMENTO" -> RENDIMENTO | D42: ="REALIZADO" -> REALIZADO | E42: =$B$39 -> 0 | F42: ="EXTERNO" -> EXTERNO | G42: ="" | H42: ="INVESTIMENTO" -> INVESTIMENTO | I42: =$D$35 -> NAO ENCONTRADO | J42: =IFERROR(INDEX(CAT_ID,MATCH("Receitas",CAT_NOME,0)),"") -> CAT-000010 | K42: =IFERROR(INDEX(SUB_ID,MATCH(1,INDEX((SUB_NOME="Rendimento financeiro"),0),0)),"") -> SUB-000044 | L42: ="Transferencia" -> Transferencia | M42: ="" | N42: ="" | O42: ="" | P42: ="" | Q42: ="" | R42: ="Rendimento reconhecido no momento do resgate" -> Rendimento reconhecido no momento do resgate
A43: =$B$37 -> 46270 | B43: ="Resgate de "&$B$35 -> Resgate de | C43: ="RESGATE" -> RESGATE | D43: ="REALIZADO" -> REALIZADO | E43: =$B$38 -> 3000000 | F43: ="INVESTIMENTO" -> INVESTIMENTO | G43: =$D$35 -> NAO ENCONTRADO | H43: ="CONTA" -> CONTA | I43: =$D$36 -> NAO ENCONTRADO | J43: =IFERROR(INDEX(CAT_ID,MATCH("Investimentos",CAT_NOME,0)),"") -> CAT-000009 | K43: =IFERROR(INDEX(SUB_ID,MATCH(1,INDEX((SUB_NOME="Resgate"),0),0)),"") -> SUB-000039 | L43: ="Transferencia" -> Transferencia | M43: ="" | N43: ="" | O43: ="" | P43: ="" | Q43: ="" | R43: ="Operacao neutra: principal nao e receita" -> Operacao neutra: principal nao e receita
A46: ASSISTENTE DE MOVIMENTO DE META (COLE EM MOV_METAS, COLUNAS B ATE H)
A47: Meta (nome)
A48: Tipo de movimento | B48: RESERVA
A49: Data | B49: 46270
A50: Valor | B50: 1500000
A51: Destino da retirada (se for saida)
A52: Meta de destino (se for transferencia)
A53: Observacao | B53: Reserva mensal
A55: Data | B55: ID_Meta | C55: Tipo_Movimento | D55: Valor | E55: Destino_Retirada | F55: ID_Meta_Destino | G55: Observacao
A56: =$B$49 -> 46270 | B56: =IFERROR(INDEX(M_ID,MATCH($B$47,M_NOME,0)),"NAO ENCONTRADO") -> NAO ENCONTRADO | C56: =$B$48 -> RESERVA | D56: =$B$50 -> 1500000 | E56: =$B$51 -> 0 | F56: =IF($B$52="","",IFERROR(INDEX(M_ID,MATCH($B$52,M_NOME,0)),"NAO ENCONTRADO")) | G56: =$B$53 -> Reserva mensal

Sheet LANCAMENTOS
A1: LANCAMENTOS - LIVRO UNICO DE OPERACOES
A2: PARA APAGAR UM REGISTRO: selecione as celulas AMARELAS da linha e pressione DELETE (limpar conteudo). NUNCA use 'Excluir linha' nem classifique (sort) esta aba: os IDs sao gerados pela posicao da linha e os vinculos seriam quebrados em silencio. Para anular um lancamento sem perder o historico use o campo Status (CANCELADO / Inativo). Para pesquisar use os filtros do cabecalho. As colunas cinzas sao calculadas - nao digite nelas. Para anular um lancamento troque o Status para CANCELADO (o historico permanece e o efeito financeiro desaparece).
A4: ID_Lancamento | B4: Data | C4: Descricao | D4: Tipo_Operacao | E4: Status | F4: Valor | G4: Origem_Tipo | H4: Origem_ID | I4: Destino_Tipo | J4: Destino_ID | K4: Categoria_ID | L4: Subcategoria_ID | M4: Forma_Pagamento | N4: ID_Compromisso | O4: ID_Parcela | P4: ID_Meta | Q4: ID_Recorrencia | R4: ID_Relacionado | S4: Observacao | T4: Ano | U4: Mes | V4: AnoMes | W4: Classificacao | X4: Categoria | Y4: Subcategoria | Z4: Origem_Nome | AA4: Destino_Nome | AB4: Entrada_Caixa | AC4: Saida_Caixa | AD4: Vlr_Receita | AE4: Vlr_Despesa | AF4: Vlr_Rend_Fin | AG4: Efeito_Conta | AH4: Efeito_Cartao | AI4: Efeito_Investim | AJ4: Validacao | AK4: Vinculos
A5: =IF($B5="","","LAN-"&TEXT(ROW()-4,"000000")) | T5: =IF($B5="","",YEAR($B5)) | U5: =IF($B5="","",MONTH($B5)) | V5: =IF($B5="","",YEAR($B5)*100+MONTH($B5)) | W5: =IF($D5="","",IFERROR(INDEX(MAP_CLASS,MATCH($D5,MAP_TIPO,0)),"TIPO INVALIDO")) | X5: =IF($K5="","",IFERROR(INDEX(CAT_NOME,MATCH($K5,CAT_ID,0)),"?")) | Y5: =IF($L5="","",IFERROR(INDEX(SUB_NOME,MATCH($L5,SUB_ID,0)),"?")) | Z5: =IF($G5="","",IF($G5="EXTERNO","(Externo)",IFERROR(INDEX(ENT_NOME,MATCH($H5,ENT_ID,0)),"?"))) | AA5: =IF($I5="","",IF($I5="EXTERNO","(Externo)",IFERROR(INDEX(ENT_NOME,MATCH($J5,ENT_ID,0)),"?"))) | AB5: =IF($B5="",0,IF(AND($I5="CONTA",$G5<>"CONTA"),$F5,0)) -> 0 | AC5: =IF($B5="",0,IF(AND($G5="CONTA",$I5<>"CONTA"),$F5,0)) -> 0 | AD5: =IF($W5="RECEITA",$F5,0) -> 0 | AE5: =IF($W5="DESPESA",$F5,0) -> 0 | AF5: =IF($W5="RECEITA_FINANCEIRA",$F5,0) -> 0 | AG5: =IF($B5="",0,IF($I5="CONTA",$F5,0)-IF($G5="CONTA",$F5,0)) -> 0 | AH5: =IF($B5="",0,IF($G5="CARTAO",$F5,0)-IF($I5="CARTAO",$F5,0)) -> 0 | AI5: =IF($B5="",0,IF($I5="INVESTIMENTO",$F5,0)-IF($G5="INVESTIMENTO",$F5,0)) -> 0 | AJ5: =IF($B5="","",IF(NOT(ISNUMBER($F5)),"ERRO: valor nao numerico",IF($F5<=0,"ERRO: valor deve ser maior que zero",IF(COUNTIF(MAP_TIPO,$D5)=0,"ERRO: tipo de operacao nao cadastrado",IF(COUNTIF(LST_STATUS,$E5)=0,"ERRO: status invalido",IF(AND($G5="EXTERNO",$I5="EXTERNO"),"ERRO: origem e destino externos",IF(AND($G5<>"EXTERNO",COUNTIFS(ENT_ID,$H5,ENT_TIPO,$G5)=0),"ERRO: origem inexistente",IF(AND($I5<>"EXTERNO",COUNTIFS(ENT_ID,$J5,ENT_TIPO,$I5)=0),"ERRO: destino inexistente",IF(AND($K5<>"",COUNTIF(CAT_ID,$K5)=0),"ERRO: categoria inexistente",IF(AND($L5<>"",COUNTIF(SUB_ID,$L5)=0),"ERRO: subcategoria inexistente",IF(AND($L5<>"",$K5<>"",IFERROR(INDEX(SUB_CATID,MATCH($L5,SUB_ID,0)),"")<>$K5),"ERRO: subcategoria nao pertence a categoria",IF(AND($O5<>"",COUNTIF(P_ID,$O5)=0),"ERRO: parcela inexistente",IF(AND($N5<>"",COUNTIF(CM_ID,$N5)=0),"ERRO: compromisso inexistente","OK"))))))))))))) | AK5: =IF($B5="","",IF(AND($N5="",$O5="",$P5="",$Q5="",$R5=""),"","VINCULADO: "&TRIM(IF($N5<>"",$N5&" ","")&IF($O5<>"",$O5&" ","")&IF($P5<>"",$P5&" ","")&IF($Q5<>"",$Q5&" ","")&IF($R5<>"",$R5,""))))
A6: =IF($B6="","","LAN-"&TEXT(ROW()-4,"000000")) | T6: =IF($B6="","",YEAR($B6)) | U6: =IF($B6="","",MONTH($B6)) | V6: =IF($B6="","",YEAR($B6)*100+MONTH($B6)) | W6: =IF($D6="","",IFERROR(INDEX(MAP_CLASS,MATCH($D6,MAP_TIPO,0)),"TIPO INVALIDO")) | X6: =IF($K6="","",IFERROR(INDEX(CAT_NOME,MATCH($K6,CAT_ID,0)),"?")) | Y6: =IF($L6="","",IFERROR(INDEX(SUB_NOME,MATCH($L6,SUB_ID,0)),"?")) | Z6: =IF($G6="","",IF($G6="EXTERNO","(Externo)",IFERROR(INDEX(ENT_NOME,MATCH($H6,ENT_ID,0)),"?"))) | AA6: =IF($I6="","",IF($I6="EXTERNO","(Externo)",IFERROR(INDEX(ENT_NOME,MATCH($J6,ENT_ID,0)),"?"))) | AB6: =IF($B6="",0,IF(AND($I6="CONTA",$G6<>"CONTA"),$F6,0)) -> 0 | AC6: =IF($B6="",0,IF(AND($G6="CONTA",$I6<>"CONTA"),$F6,0)) -> 0 | AD6: =IF($W6="RECEITA",$F6,0) -> 0 | AE6: =IF($W6="DESPESA",$F6,0) -> 0 | AF6: =IF($W6="RECEITA_FINANCEIRA",$F6,0) -> 0 | AG6: =IF($B6="",0,IF($I6="CONTA",$F6,0)-IF($G6="CONTA",$F6,0)) -> 0 | AH6: =IF($B6="",0,IF($G6="CARTAO",$F6,0)-IF($I6="CARTAO",$F6,0)) -> 0 | AI6: =IF($B6="",0,IF($I6="INVESTIMENTO",$F6,0)-IF($G6="INVESTIMENTO",$F6,0)) -> 0 | AJ6: =IF($B6="","",IF(NOT(ISNUMBER($F6)),"ERRO: valor nao numerico",IF($F6<=0,"ERRO: valor deve ser maior que zero",IF(COUNTIF(MAP_TIPO,$D6)=0,"ERRO: tipo de operacao nao cadastrado",IF(COUNTIF(LST_STATUS,$E6)=0,"ERRO: status invalido",IF(AND($G6="EXTERNO",$I6="EXTERNO"),"ERRO: origem e destino externos",IF(AND($G6<>"EXTERNO",COUNTIFS(ENT_ID,$H6,ENT_TIPO,$G6)=0),"ERRO: origem inexistente",IF(AND($I6<>"EXTERNO",COUNTIFS(ENT_ID,$J6,ENT_TIPO,$I6)=0),"ERRO: destino inexistente",IF(AND($K6<>"",COUNTIF(CAT_ID,$K6)=0),"ERRO: categoria inexistente",IF(AND($L6<>"",COUNTIF(SUB_ID,$L6)=0),"ERRO: subcategoria inexistente",IF(AND($L6<>"",$K6<>"",IFERROR(INDEX(SUB_CATID,MATCH($L6,SUB_ID,0)),"")<>$K6),"ERRO: subcategoria nao pertence a categoria",IF(AND($O6<>"",COUNTIF(P_ID,$O6)=0),"ERRO: parcela inexistente",IF(AND($N6<>"",COUNTIF(CM_ID,$N6)=0),"ERRO: compromisso inexistente","OK"))))))))))))) | AK6: =IF($B6="","",IF(AND($N6="",$O6="",$P6="",$Q6="",$R6=""),"","VINCULADO: "&TRIM(IF($N6<>"",$N6&" ","")&IF($O6<>"",$O6&" ","")&IF($P6<>"",$P6&" ","")&IF($Q6<>"",$Q6&" ","")&IF($R6<>"",$R6,""))))
A7: =IF($B7="","","LAN-"&TEXT(ROW()-4,"000000")) | T7: =IF($B7="","",YEAR($B7)) | U7: =IF($B7="","",MONTH($B7)) | V7: =IF($B7="","",YEAR($B7)*100+MONTH($B7)) | W7: =IF($D7="","",IFERROR(INDEX(MAP_CLASS,MATCH($D7,MAP_TIPO,0)),"TIPO INVALIDO")) | X7: =IF($K7="","",IFERROR(INDEX(CAT_NOME,MATCH($K7,CAT_ID,0)),"?")) | Y7: =IF($L7="","",IFERROR(INDEX(SUB_NOME,MATCH($L7,SUB_ID,0)),"?")) | Z7: =IF($G7="","",IF($G7="EXTERNO","(Externo)",IFERROR(INDEX(ENT_NOME,MATCH($H7,ENT_ID,0)),"?"))) | AA7: =IF($I7="","",IF($I7="EXTERNO","(Externo)",IFERROR(INDEX(ENT_NOME,MATCH($J7,ENT_ID,0)),"?"))) | AB7: =IF($B7="",0,IF(AND($I7="CONTA",$G7<>"CONTA"),$F7,0)) -> 0 | AC7: =IF($B7="",0,IF(AND($G7="CONTA",$I7<>"CONTA"),$F7,0)) -> 0 | AD7: =IF($W7="RECEITA",$F7,0) -> 0 | AE7: =IF($W7="DESPESA",$F7,0) -> 0 | AF7: =IF($W7="RECEITA_FINANCEIRA",$F7,0) -> 0 | AG7: =IF($B7="",0,IF($I7="CONTA",$F7,0)-IF($G7="CONTA",$F7,0)) -> 0 | AH7: =IF($B7="",0,IF($G7="CARTAO",$F7,0)-IF($I7="CARTAO",$F7,0)) -> 0 | AI7: =IF($B7="",0,IF($I7="INVESTIMENTO",$F7,0)-IF($G7="INVESTIMENTO",$F7,0)) -> 0 | AJ7: =IF($B7="","",IF(NOT(ISNUMBER($F7)),"ERRO: valor nao numerico",IF($F7<=0,"ERRO: valor deve ser maior que zero",IF(COUNTIF(MAP_TIPO,$D7)=0,"ERRO: tipo de operacao nao cadastrado",IF(COUNTIF(LST_STATUS,$E7)=0,"ERRO: status invalido",IF(AND($G7="EXTERNO",$I7="EXTERNO"),"ERRO: origem e destino externos",IF(AND($G7<>"EXTERNO",COUNTIFS(ENT_ID,$H7,ENT_TIPO,$G7)=0),"ERRO: origem inexistente",IF(AND($I7<>"EXTERNO",COUNTIFS(ENT_ID,$J7,ENT_TIPO,$I7)=0),"ERRO: destino inexistente",IF(AND($K7<>"",COUNTIF(CAT_ID,$K7)=0),"ERRO: categoria inexistente",IF(AND($L7<>"",COUNTIF(SUB_ID,$L7)=0),"ERRO: subcategoria inexistente",IF(AND($L7<>"",$K7<>"",IFERROR(INDEX(SUB_CATID,MATCH($L7,SUB_ID,0)),"")<>$K7),"ERRO: subcategoria nao pertence a categoria",IF(AND($O7<>"",COUNTIF(P_ID,$O7)=0),"ERRO: parcela inexistente",IF(AND($N7<>"",COUNTIF(CM_ID,$N7)=0),"ERRO: compromisso inexistente","OK"))))))))))))) | AK7: =IF($B7="","",IF(AND($N7="",$O7="",$P7="",$Q7="",$R7=""),"","VINCULADO: "&TRIM(IF($N7<>"",$N7&" ","")&IF($O7<>"",$O7&" ","")&IF($P7<>"",$P7&" ","")&IF($Q7<>"",$Q7&" ","")&IF($R7<>"",$R7,""))))
A8: =IF($B8="","","LAN-"&TEXT(ROW()-4,"000000")) | T8: =IF($B8="","",YEAR($B8)) | U8: =IF($B8="","",MONTH($B8)) | V8: =IF($B8="","",YEAR($B8)*100+MONTH($B8)) | W8: =IF($D8="","",IFERROR(INDEX(MAP_CLASS,MATCH($D8,MAP_TIPO,0)),"TIPO INVALIDO")) | X8: =IF($K8="","",IFERROR(INDEX(CAT_NOME,MATCH($K8,CAT_ID,0)),"?")) | Y8: =IF($L8="","",IFERROR(INDEX(SUB_NOME,MATCH($L8,SUB_ID,0)),"?")) | Z8: =IF($G8="","",IF($G8="EXTERNO","(Externo)",IFERROR(INDEX(ENT_NOME,MATCH($H8,ENT_ID,0)),"?"))) | AA8: =IF($I8="","",IF($I8="EXTERNO","(Externo)",IFERROR(INDEX(ENT_NOME,MATCH($J8,ENT_ID,0)),"?"))) | AB8: =IF($B8="",0,IF(AND($I8="CONTA",$G8<>"CONTA"),$F8,0)) -> 0 | AC8: =IF($B8="",0,IF(AND($G8="CONTA",$I8<>"CONTA"),$F8,0)) -> 0 | AD8: =IF($W8="RECEITA",$F8,0) -> 0 | AE8: =IF($W8="DESPESA",$F8,0) -> 0 | AF8: =IF($W8="RECEITA_FINANCEIRA",$F8,0) -> 0 | AG8: =IF($B8="",0,IF($I8="CONTA",$F8,0)-IF($G8="CONTA",$F8,0)) -> 0 | AH8: =IF($B8="",0,IF($G8="CARTAO",$F8,0)-IF($I8="CARTAO",$F8,0)) -> 0 | AI8: =IF($B8="",0,IF($I8="INVESTIMENTO",$F8,0)-IF($G8="INVESTIMENTO",$F8,0)) -> 0 | AJ8: =IF($B8="","",IF(NOT(ISNUMBER($F8)),"ERRO: valor nao numerico",IF($F8<=0,"ERRO: valor deve ser maior que zero",IF(COUNTIF(MAP_TIPO,$D8)=0,"ERRO: tipo de operacao nao cadastrado",IF(COUNTIF(LST_STATUS,$E8)=0,"ERRO: status invalido",IF(AND($G8="EXTERNO",$I8="EXTERNO"),"ERRO: origem e destino externos",IF(AND($G8<>"EXTERNO",COUNTIFS(ENT_ID,$H8,ENT_TIPO,$G8)=0),"ERRO: origem inexistente",IF(AND($I8<>"EXTERNO",COUNTIFS(ENT_ID,$J8,ENT_TIPO,$I8)=0),"ERRO: destino inexistente",IF(AND($K8<>"",COUNTIF(CAT_ID,$K8)=0),"ERRO: categoria inexistente",IF(AND($L8<>"",COUNTIF(SUB_ID,$L8)=0),"ERRO: subcategoria inexistente",IF(AND($L8<>"",$K8<>"",IFERROR(INDEX(SUB_CATID,MATCH($L8,SUB_ID,0)),"")<>$K8),"ERRO: subcategoria nao pertence a categoria",IF(AND($O8<>"",COUNTIF(P_ID,$O8)=0),"ERRO: parcela inexistente",IF(AND($N8<>"",COUNTIF(CM_ID,$N8)=0),"ERRO: compromisso inexistente","OK"))))))))))))) | AK8: =IF($B8="","",IF(AND($N8="",$O8="",$P8="",$Q8="",$R8=""),"","VINCULADO: "&TRIM(IF($N8<>"",$N8&" ","")&IF($O8<>"",$O8&" ","")&IF($P8<>"",$P8&" ","")&IF($Q8<>"",$Q8&" ","")&IF($R8<>"",$R8,""))))
A9: =IF($B9="","","LAN-"&TEXT(ROW()-4,"000000")) | T9: =IF($B9="","",YEAR($B9)) | U9: =IF($B9="","",MONTH($B9)) | V9: =IF($B9="","",YEAR($B9)*100+MONTH($B9)) | W9: =IF($D9="","",IFERROR(INDEX(MAP_CLASS,MATCH($D9,MAP_TIPO,0)),"TIPO INVALIDO")) | X9: =IF($K9="","",IFERROR(INDEX(CAT_NOME,MATCH($K9,CAT_ID,0)),"?")) | Y9: =IF($L9="","",IFERROR(INDEX(SUB_NOME,MATCH($L9,SUB_ID,0)),"?")) | Z9: =IF($G9="","",IF($G9="EXTERNO","(Externo)",IFERROR(INDEX(ENT_NOME,MATCH($H9,ENT_ID,0)),"?"))) | AA9: =IF($I9="","",IF($I9="EXTERNO","(Externo)",IFERROR(INDEX(ENT_NOME,MATCH($J9,ENT_ID,0)),"?"))) | AB9: =IF($B9="",0,IF(AND($I9="CONTA",$G9<>"CONTA"),$F9,0)) -> 0 | AC9: =IF($B9="",0,IF(AND($G9="CONTA",$I9<>"CONTA"),$F9,0)) -> 0 | AD9: =IF($W9="RECEITA",$F9,0) -> 0 | AE9: =IF($W9="DESPESA",$F9,0) -> 0 | AF9: =IF($W9="RECEITA_FINANCEIRA",$F9,0) -> 0 | AG9: =IF($B9="",0,IF($I9="CONTA",$F9,0)-IF($G9="CONTA",$F9,0)) -> 0 | AH9: =IF($B9="",0,IF($G9="CARTAO",$F9,0)-IF($I9="CARTAO",$F9,0)) -> 0 | AI9: =IF($B9="",0,IF($I9="INVESTIMENTO",$F9,0)-IF($G9="INVESTIMENTO",$F9,0)) -> 0 | AJ9: =IF($B9="","",IF(NOT(ISNUMBER($F9)),"ERRO: valor nao numerico",IF($F9<=0,"ERRO: valor deve ser maior que zero",IF(COUNTIF(MAP_TIPO,$D9)=0,"ERRO: tipo de operacao nao cadastrado",IF(COUNTIF(LST_STATUS,$E9)=0,"ERRO: status invalido",IF(AND($G9="EXTERNO",$I9="EXTERNO"),"ERRO: origem e destino externos",IF(AND($G9<>"EXTERNO",COUNTIFS(ENT_ID,$H9,ENT_TIPO,$G9)=0),"ERRO: origem inexistente",IF(AND($I9<>"EXTERNO",COUNTIFS(ENT_ID,$J9,ENT_TIPO,$I9)=0),"ERRO: destino inexistente",IF(AND($K9<>"",COUNTIF(CAT_ID,$K9)=0),"ERRO: categoria inexistente",IF(AND($L9<>"",COUNTIF(SUB_ID,$L9)=0),"ERRO: subcategoria inexistente",IF(AND($L9<>"",$K9<>"",IFERROR(INDEX(SUB_CATID,MATCH($L9,SUB_ID,0)),"")<>$K9),"ERRO: subcategoria nao pertence a categoria",IF(AND($O9<>"",COUNTIF(P_ID,$O9)=0),"ERRO: parcela inexistente",IF(AND($N9<>"",COUNTIF(CM_ID,$N9)=0),"ERRO: compromisso inexistente","OK"))))))))))))) | AK9: =IF($B9="","",IF(AND($N9="",$O9="",$P9="",$Q9="",$R9=""),"","VINCULADO: "&TRIM(IF($N9<>"",$N9&" ","")&IF($O9<>"",$O9&" ","")&IF($P9<>"",$P9&" ","")&IF($Q9<>"",$Q9&" ","")&IF($R9<>"",$R9,""))))
A10: =IF($B10="","","LAN-"&TEXT(ROW()-4,"000000")) | T10: =IF($B10="","",YEAR($B10)) | U10: =IF($B10="","",MONTH($B10)) | V10: =IF($B10="","",YEAR($B10)*100+MONTH($B10)) | W10: =IF($D10="","",IFERROR(INDEX(MAP_CLASS,MATCH($D10,MAP_TIPO,0)),"TIPO INVALIDO")) | X10: =IF($K10="","",IFERROR(INDEX(CAT_NOME,MATCH($K10,CAT_ID,0)),"?")) | Y10: =IF($L10="","",IFERROR(INDEX(SUB_NOME,MATCH($L10,SUB_ID,0)),"?")) | Z10: =IF($G10="","",IF($G10="EXTERNO","(Externo)",IFERROR(INDEX(ENT_NOME,MATCH($H10,ENT_ID,0)),"?"))) | AA10: =IF($I10="","",IF($I10="EXTERNO","(Externo)",IFERROR(INDEX(ENT_NOME,MATCH($J10,ENT_ID,0)),"?"))) | AB10: =IF($B10="",0,IF(AND($I10="CONTA",$G10<>"CONTA"),$F10,0)) -> 0 | AC10: =IF($B10="",0,IF(AND($G10="CONTA",$I10<>"CONTA"),$F10,0)) -> 0 | AD10: =IF($W10="RECEITA",$F10,0) -> 0 | AE10: =IF($W10="DESPESA",$F10,0) -> 0 | AF10: =IF($W10="RECEITA_FINANCEIRA",$F10,0) -> 0 | AG10: =IF($B10="",0,IF($I10="CONTA",$F10,0)-IF($G10="CONTA",$F10,0)) -> 0 | AH10: =IF($B10="",0,IF($G10="CARTAO",$F10,0)-IF($I10="CARTAO",$F10,0)) -> 0 | AI10: =IF($B10="",0,IF($I10="INVESTIMENTO",$F10,0)-IF($G10="INVESTIMENTO",$F10,0)) -> 0 | AJ10: =IF($B10="","",IF(NOT(ISNUMBER($F10)),"ERRO: valor nao numerico",IF($F10<=0,"ERRO: valor deve ser maior que zero",IF(COUNTIF(MAP_TIPO,$D10)=0,"ERRO: tipo de operacao nao cadastrado",IF(COUNTIF(LST_STATUS,$E10)=0,"ERRO: status invalido",IF(AND($G10="EXTERNO",$I10="EXTERNO"),"ERRO: origem e destino externos",IF(AND($G10<>"EXTERNO",COUNTIFS(ENT_ID,$H10,ENT_TIPO,$G10)=0),"ERRO: origem inexistente",IF(AND($I10<>"EXTERNO",COUNTIFS(ENT_ID,$J10,ENT_TIPO,$I10)=0),"ERRO: destino inexistente",IF(AND($K10<>"",COUNTIF(CAT_ID,$K10)=0),"ERRO: categoria inexistente",IF(AND($L10<>"",COUNTIF(SUB_ID,$L10)=0),"ERRO: subcategoria inexistente",IF(AND($L10<>"",$K10<>"",IFERROR(INDEX(SUB_CATID,MATCH($L10,SUB_ID,0)),"")<>$K10),"ERRO: subcategoria nao pertence a categoria",IF(AND($O10<>"",COUNTIF(P_ID,$O10)=0),"ERRO: parcela inexistente",IF(AND($N10<>"",COUNTIF(CM_ID,$N10)=0),"ERRO: compromisso inexistente","OK"))))))))))))) | AK10: =IF($B10="","",IF(AND($N10="",$O10="",$P10="",$Q10="",$R10=""),"","VINCULADO: "&TRIM(IF($N10<>"",$N10&" ","")&IF($O10<>"",$O10&" ","")&IF($P10<>"",$P10&" ","")&IF($Q10<>"",$Q10&" ","")&IF($R10<>"",$R10,""))))
A11: =IF($B11="","","LAN-"&TEXT(ROW()-4,"000000")) | T11: =IF($B11="","",YEAR($B11)) | U11: =IF($B11="","",MONTH($B11)) | V11: =IF($B11="","",YEAR($B11)*100+MONTH($B11)) | W11: =IF($D11="","",IFERROR(INDEX(MAP_CLASS,MATCH($D11,MAP_TIPO,0)),"TIPO INVALIDO")) | X11: =IF($K11="","",IFERROR(INDEX(CAT_NOME,MATCH($K11,CAT_ID,0)),"?")) | Y11: =IF($L11="","",IFERROR(INDEX(SUB_NOME,MATCH($L11,SUB_ID,0)),"?")) | Z11: =IF($G11="","",IF($G11="EXTERNO","(Externo)",IFERROR(INDEX(ENT_NOME,MATCH($H11,ENT_ID,0)),"?"))) | AA11: =IF($I11="","",IF($I11="EXTERNO","(Externo)",IFERROR(INDEX(ENT_NOME,MATCH($J11,ENT_ID,0)),"?"))) | AB11: =IF($B11="",0,IF(AND($I11="CONTA",$G11<>"CONTA"),$F11,0)) -> 0 | AC11: =IF($B11="",0,IF(AND($G11="CONTA",$I11<>"CONTA"),$F11,0)) -> 0 | AD11: =IF($W11="RECEITA",$F11,0) -> 0 | AE11: =IF($W11="DESPESA",$F11,0) -> 0 | AF11: =IF($W11="RECEITA_FINANCEIRA",$F11,0) -> 0 | AG11: =IF($B11="",0,IF($I11="CONTA",$F11,0)-IF($G11="CONTA",$F11,0)) -> 0 | AH11: =IF($B11="",0,IF($G11="CARTAO",$F11,0)-IF($I11="CARTAO",$F11,0)) -> 0 | AI11: =IF($B11="",0,IF($I11="INVESTIMENTO",$F11,0)-IF($G11="INVESTIMENTO",$F11,0)) -> 0 | AJ11: =IF($B11="","",IF(NOT(ISNUMBER($F11)),"ERRO: valor nao numerico",IF($F11<=0,"ERRO: valor deve ser maior que zero",IF(COUNTIF(MAP_TIPO,$D11)=0,"ERRO: tipo de operacao nao cadastrado",IF(COUNTIF(LST_STATUS,$E11)=0,"ERRO: status invalido",IF(AND($G11="EXTERNO",$I11="EXTERNO"),"ERRO: origem e destino externos",IF(AND($G11<>"EXTERNO",COUNTIFS(ENT_ID,$H11,ENT_TIPO,$G11)=0),"ERRO: origem inexistente",IF(AND($I11<>"EXTERNO",COUNTIFS(ENT_ID,$J11,ENT_TIPO,$I11)=0),"ERRO: destino inexistente",IF(AND($K11<>"",COUNTIF(CAT_ID,$K11)=0),"ERRO: categoria inexistente",IF(AND($L11<>"",COUNTIF(SUB_ID,$L11)=0),"ERRO: subcategoria inexistente",IF(AND($L11<>"",$K11<>"",IFERROR(INDEX(SUB_CATID,MATCH($L11,SUB_ID,0)),"")<>$K11),"ERRO: subcategoria nao pertence a categoria",IF(AND($O11<>"",COUNTIF(P_ID,$O11)=0),"ERRO: parcela inexistente",IF(AND($N11<>"",COUNTIF(CM_ID,$N11)=0),"ERRO: compromisso inexistente","OK"))))))))))))) | AK11: =IF($B11="","",IF(AND($N11="",$O11="",$P11="",$Q11="",$R11=""),"","VINCULADO: "&TRIM(IF($N11<>"",$N11&" ","")&IF($O11<>"",$O11&" ","")&IF($P11<>"",$P11&" ","")&IF($Q11<>"",$Q11&" ","")&IF($R11<>"",$R11,""))))
A12: =IF($B12="","","LAN-"&TEXT(ROW()-4,"000000")) | T12: =IF($B12="","",YEAR($B12)) | U12: =IF($B12="","",MONTH($B12)) | V12: =IF($B12="","",YEAR($B12)*100+MONTH($B12)) | W12: =IF($D12="","",IFERROR(INDEX(MAP_CLASS,MATCH($D12,MAP_TIPO,0)),"TIPO INVALIDO")) | X12: =IF($K12="","",IFERROR(INDEX(CAT_NOME,MATCH($K12,CAT_ID,0)),"?")) | Y12: =IF($L12="","",IFERROR(INDEX(SUB_NOME,MATCH($L12,SUB_ID,0)),"?")) | Z12: =IF($G12="","",IF($G12="EXTERNO","(Externo)",IFERROR(INDEX(ENT_NOME,MATCH($H12,ENT_ID,0)),"?"))) | AA12: =IF($I12="","",IF($I12="EXTERNO","(Externo)",IFERROR(INDEX(ENT_NOME,MATCH($J12,ENT_ID,0)),"?"))) | AB12: =IF($B12="",0,IF(AND($I12="CONTA",$G12<>"CONTA"),$F12,0)) -> 0 | AC12: =IF($B12="",0,IF(AND($G12="CONTA",$I12<>"CONTA"),$F12,0)) -> 0 | AD12: =IF($W12="RECEITA",$F12,0) -> 0 | AE12: =IF($W12="DESPESA",$F12,0) -> 0 | AF12: =IF($W12="RECEITA_FINANCEIRA",$F12,0) -> 0 | AG12: =IF($B12="",0,IF($I12="CONTA",$F12,0)-IF($G12="CONTA",$F12,0)) -> 0 | AH12: =IF($B12="",0,IF($G12="CARTAO",$F12,0)-IF($I12="CARTAO",$F12,0)) -> 0 | AI12: =IF($B12="",0,IF($I12="INVESTIMENTO",$F12,0)-IF($G12="INVESTIMENTO",$F12,0)) -> 0 | AJ12: =IF($B12="","",IF(NOT(ISNUMBER($F12)),"ERRO: valor nao numerico",IF($F12<=0,"ERRO: valor deve ser maior que zero",IF(COUNTIF(MAP_TIPO,$D12)=0,"ERRO: tipo de operacao nao cadastrado",IF(COUNTIF(LST_STATUS,$E12)=0,"ERRO: status invalido",IF(AND($G12="EXTERNO",$I12="EXTERNO"),"ERRO: origem e destino externos",IF(AND($G12<>"EXTERNO",COUNTIFS(ENT_ID,$H12,ENT_TIPO,$G12)=0),"ERRO: origem inexistente",IF(AND($I12<>"EXTERNO",COUNTIFS(ENT_ID,$J12,ENT_TIPO,$I12)=0),"ERRO: destino inexistente",IF(AND($K12<>"",COUNTIF(CAT_ID,$K12)=0),"ERRO: categoria inexistente",IF(AND($L12<>"",COUNTIF(SUB_ID,$L12)=0),"ERRO: subcategoria inexistente",IF(AND($L12<>"",$K12<>"",IFERROR(INDEX(SUB_CATID,MATCH($L12,SUB_ID,0)),"")<>$K12),"ERRO: subcategoria nao pertence a categoria",IF(AND($O12<>"",COUNTIF(P_ID,$O12)=0),"ERRO: parcela inexistente",IF(AND($N12<>"",COUNTIF(CM_ID,$N12)=0),"ERRO: compromisso inexistente","OK"))))))))))))) | AK12: =IF($B12="","",IF(AND($N12="",$O12="",$P12="",$Q12="",$R12=""),"","VINCULADO: "&TRIM(IF($N12<>"",$N12&" ","")&IF($O12<>"",$O12&" ","")&IF($P12<>"",$P12&" ","")&IF($Q12<>"",$Q12&" ","")&IF($R12<>"",$R12,""))))
A13: =IF($B13="","","LAN-"&TEXT(ROW()-4,"000000")) | T13: =IF($B13="","",YEAR($B13)) | U13: =IF($B13="","",MONTH($B13)) | V13: =IF($B13="","",YEAR($B13)*100+MONTH($B13)) | W13: =IF($D13="","",IFERROR(INDEX(MAP_CLASS,MATCH($D13,MAP_TIPO,0)),"TIPO INVALIDO")) | X13: =IF($K13="","",IFERROR(INDEX(CAT_NOME,MATCH($K13,CAT_ID,0)),"?")) | Y13: =IF($L13="","",IFERROR(INDEX(SUB_NOME,MATCH($L13,SUB_ID,0)),"?")) | Z13: =IF($G13="","",IF($G13="EXTERNO","(Externo)",IFERROR(INDEX(ENT_NOME,MATCH($H13,ENT_ID,0)),"?"))) | AA13: =IF($I13="","",IF($I13="EXTERNO","(Externo)",IFERROR(INDEX(ENT_NOME,MATCH($J13,ENT_ID,0)),"?"))) | AB13: =IF($B13="",0,IF(AND($I13="CONTA",$G13<>"CONTA"),$F13,0)) -> 0 | AC13: =IF($B13="",0,IF(AND($G13="CONTA",$I13<>"CONTA"),$F13,0)) -> 0 | AD13: =IF($W13="RECEITA",$F13,0) -> 0 | AE13: =IF($W13="DESPESA",$F13,0) -> 0 | AF13: =IF($W13="RECEITA_FINANCEIRA",$F13,0) -> 0 | AG13: =IF($B13="",0,IF($I13="CONTA",$F13,0)-IF($G13="CONTA",$F13,0)) -> 0 | AH13: =IF($B13="",0,IF($G13="CARTAO",$F13,0)-IF($I13="CARTAO",$F13,0)) -> 0 | AI13: =IF($B13="",0,IF($I13="INVESTIMENTO",$F13,0)-IF($G13="INVESTIMENTO",$F13,0)) -> 0 | AJ13: =IF($B13="","",IF(NOT(ISNUMBER($F13)),"ERRO: valor nao numerico",IF($F13<=0,"ERRO: valor deve ser maior que zero",IF(COUNTIF(MAP_TIPO,$D13)=0,"ERRO: tipo de operacao nao cadastrado",IF(COUNTIF(LST_STATUS,$E13)=0,"ERRO: status invalido",IF(AND($G13="EXTERNO",$I13="EXTERNO"),"ERRO: origem e destino externos",IF(AND($G13<>"EXTERNO",COUNTIFS(ENT_ID,$H13,ENT_TIPO,$G13)=0),"ERRO: origem inexistente",IF(AND($I13<>"EXTERNO",COUNTIFS(ENT_ID,$J13,ENT_TIPO,$I13)=0),"ERRO: destino inexistente",IF(AND($K13<>"",COUNTIF(CAT_ID,$K13)=0),"ERRO: categoria inexistente",IF(AND($L13<>"",COUNTIF(SUB_ID,$L13)=0),"ERRO: subcategoria inexistente",IF(AND($L13<>"",$K13<>"",IFERROR(INDEX(SUB_CATID,MATCH($L13,SUB_ID,0)),"")<>$K13),"ERRO: subcategoria nao pertence a categoria",IF(AND($O13<>"",COUNTIF(P_ID,$O13)=0),"ERRO: parcela inexistente",IF(AND($N13<>"",COUNTIF(CM_ID,$N13)=0),"ERRO: compromisso inexistente","OK"))))))))))))) | AK13: =IF($B13="","",IF(AND($N13="",$O13="",$P13="",$Q13="",$R13=""),"","VINCULADO: "&TRIM(IF($N13<>"",$N13&" ","")&IF($O13<>"",$O13&" ","")&IF($P13<>"",$P13&" ","")&IF($Q13<>"",$Q13&" ","")&IF($R13<>"",$R13,""))))
A14: =IF($B14="","","LAN-"&TEXT(ROW()-4,"000000")) | T14: =IF($B14="","",YEAR($B14)) | U14: =IF($B14="","",MONTH($B14)) | V14: =IF($B14="","",YEAR($B14)*100+MONTH($B14)) | W14: =IF($D14="","",IFERROR(INDEX(MAP_CLASS,MATCH($D14,MAP_TIPO,0)),"TIPO INVALIDO")) | X14: =IF($K14="","",IFERROR(INDEX(CAT_NOME,MATCH($K14,CAT_ID,0)),"?")) | Y14: =IF($L14="","",IFERROR(INDEX(SUB_NOME,MATCH($L14,SUB_ID,0)),"?")) | Z14: =IF($G14="","",IF($G14="EXTERNO","(Externo)",IFERROR(INDEX(ENT_NOME,MATCH($H14,ENT_ID,0)),"?"))) | AA14: =IF($I14="","",IF($I14="EXTERNO","(Externo)",IFERROR(INDEX(ENT_NOME,MATCH($J14,ENT_ID,0)),"?"))) | AB14: =IF($B14="",0,IF(AND($I14="CONTA",$G14<>"CONTA"),$F14,0)) -> 0 | AC14: =IF($B14="",0,IF(AND($G14="CONTA",$I14<>"CONTA"),$F14,0)) -> 0 | AD14: =IF($W14="RECEITA",$F14,0) -> 0 | AE14: =IF($W14="DESPESA",$F14,0) -> 0 | AF14: =IF($W14="RECEITA_FINANCEIRA",$F14,0) -> 0 | AG14: =IF($B14="",0,IF($I14="CONTA",$F14,0)-IF($G14="CONTA",$F14,0)) -> 0 | AH14: =IF($B14="",0,IF($G14="CARTAO",$F14,0)-IF($I14="CARTAO",$F14,0)) -> 0 | AI14: =IF($B14="",0,IF($I14="INVESTIMENTO",$F14,0)-IF($G14="INVESTIMENTO",$F14,0)) -> 0 | AJ14: =IF($B14="","",IF(NOT(ISNUMBER($F14)),"ERRO: valor nao numerico",IF($F14<=0,"ERRO: valor deve ser maior que zero",IF(COUNTIF(MAP_TIPO,$D14)=0,"ERRO: tipo de operacao nao cadastrado",IF(COUNTIF(LST_STATUS,$E14)=0,"ERRO: status invalido",IF(AND($G14="EXTERNO",$I14="EXTERNO"),"ERRO: origem e destino externos",IF(AND($G14<>"EXTERNO",COUNTIFS(ENT_ID,$H14,ENT_TIPO,$G14)=0),"ERRO: origem inexistente",IF(AND($I14<>"EXTERNO",COUNTIFS(ENT_ID,$J14,ENT_TIPO,$I14)=0),"ERRO: destino inexistente",IF(AND($K14<>"",COUNTIF(CAT_ID,$K14)=0),"ERRO: categoria inexistente",IF(AND($L14<>"",COUNTIF(SUB_ID,$L14)=0),"ERRO: subcategoria inexistente",IF(AND($L14<>"",$K14<>"",IFERROR(INDEX(SUB_CATID,MATCH($L14,SUB_ID,0)),"")<>$K14),"ERRO: subcategoria nao pertence a categoria",IF(AND($O14<>"",COUNTIF(P_ID,$O14)=0),"ERRO: parcela inexistente",IF(AND($N14<>"",COUNTIF(CM_ID,$N14)=0),"ERRO: compromisso inexistente","OK"))))))))))))) | AK14: =IF($B14="","",IF(AND($N14="",$O14="",$P14="",$Q14="",$R14=""),"","VINCULADO: "&TRIM(IF($N14<>"",$N14&" ","")&IF($O14<>"",$O14&" ","")&IF($P14<>"",$P14&" ","")&IF($Q14<>"",$Q14&" ","")&IF($R14<>"",$R14,""))))
A15: =IF($B15="","","LAN-"&TEXT(ROW()-4,"000000")) | T15: =IF($B15="","",YEAR($B15)) | U15: =IF($B15="","",MONTH($B15)) | V15: =IF($B15="","",YEAR($B15)*100+MONTH($B15)) | W15: =IF($D15="","",IFERROR(INDEX(MAP_CLASS,MATCH($D15,MAP_TIPO,0)),"TIPO INVALIDO")) | X15: =IF($K15="","",IFERROR(INDEX(CAT_NOME,MATCH($K15,CAT_ID,0)),"?")) | Y15: =IF($L15="","",IFERROR(INDEX(SUB_NOME,MATCH($L15,SUB_ID,0)),"?")) | Z15: =IF($G15="","",IF($G15="EXTERNO","(Externo)",IFERROR(INDEX(ENT_NOME,MATCH($H15,ENT_ID,0)),"?"))) | AA15: =IF($I15="","",IF($I15="EXTERNO","(Externo)",IFERROR(INDEX(ENT_NOME,MATCH($J15,ENT_ID,0)),"?"))) | AB15: =IF($B15="",0,IF(AND($I15="CONTA",$G15<>"CONTA"),$F15,0)) -> 0 | AC15: =IF($B15="",0,IF(AND($G15="CONTA",$I15<>"CONTA"),$F15,0)) -> 0 | AD15: =IF($W15="RECEITA",$F15,0) -> 0 | AE15: =IF($W15="DESPESA",$F15,0) -> 0 | AF15: =IF($W15="RECEITA_FINANCEIRA",$F15,0) -> 0 | AG15: =IF($B15="",0,IF($I15="CONTA",$F15,0)-IF($G15="CONTA",$F15,0)) -> 0 | AH15: =IF($B15="",0,IF($G15="CARTAO",$F15,0)-IF($I15="CARTAO",$F15,0)) -> 0 | AI15: =IF($B15="",0,IF($I15="INVESTIMENTO",$F15,0)-IF($G15="INVESTIMENTO",$F15,0)) -> 0 | AJ15: =IF($B15="","",IF(NOT(ISNUMBER($F15)),"ERRO: valor nao numerico",IF($F15<=0,"ERRO: valor deve ser maior que zero",IF(COUNTIF(MAP_TIPO,$D15)=0,"ERRO: tipo de operacao nao cadastrado",IF(COUNTIF(LST_STATUS,$E15)=0,"ERRO: status invalido",IF(AND($G15="EXTERNO",$I15="EXTERNO"),"ERRO: origem e destino externos",IF(AND($G15<>"EXTERNO",COUNTIFS(ENT_ID,$H15,ENT_TIPO,$G15)=0),"ERRO: origem inexistente",IF(AND($I15<>"EXTERNO",COUNTIFS(ENT_ID,$J15,ENT_TIPO,$I15)=0),"ERRO: destino inexistente",IF(AND($K15<>"",COUNTIF(CAT_ID,$K15)=0),"ERRO: categoria inexistente",IF(AND($L15<>"",COUNTIF(SUB_ID,$L15)=0),"ERRO: subcategoria inexistente",IF(AND($L15<>"",$K15<>"",IFERROR(INDEX(SUB_CATID,MATCH($L15,SUB_ID,0)),"")<>$K15),"ERRO: subcategoria nao pertence a categoria",IF(AND($O15<>"",COUNTIF(P_ID,$O15)=0),"ERRO: parcela inexistente",IF(AND($N15<>"",COUNTIF(CM_ID,$N15)=0),"ERRO: compromisso inexistente","OK"))))))))))))) | AK15: =IF($B15="","",IF(AND($N15="",$O15="",$P15="",$Q15="",$R15=""),"","VINCULADO: "&TRIM(IF($N15<>"",$N15&" ","")&IF($O15<>"",$O15&" ","")&IF($P15<>"",$P15&" ","")&IF($Q15<>"",$Q15&" ","")&IF($R15<>"",$R15,""))))
A16: =IF($B16="","","LAN-"&TEXT(ROW()-4,"000000")) | T16: =IF($B16="","",YEAR($B16)) | U16: =IF($B16="","",MONTH($B16)) | V16: =IF($B16="","",YEAR($B16)*100+MONTH($B16)) | W16: =IF($D16="","",IFERROR(INDEX(MAP_CLASS,MATCH($D16,MAP_TIPO,0)),"TIPO INVALIDO")) | X16: =IF($K16="","",IFERROR(INDEX(CAT_NOME,MATCH($K16,CAT_ID,0)),"?")) | Y16: =IF($L16="","",IFERROR(INDEX(SUB_NOME,MATCH($L16,SUB_ID,0)),"?")) | Z16: =IF($G16="","",IF($G16="EXTERNO","(Externo)",IFERROR(INDEX(ENT_NOME,MATCH($H16,ENT_ID,0)),"?"))) | AA16: =IF($I16="","",IF($I16="EXTERNO","(Externo)",IFERROR(INDEX(ENT_NOME,MATCH($J16,ENT_ID,0)),"?"))) | AB16: =IF($B16="",0,IF(AND($I16="CONTA",$G16<>"CONTA"),$F16,0)) -> 0 | AC16: =IF($B16="",0,IF(AND($G16="CONTA",$I16<>"CONTA"),$F16,0)) -> 0 | AD16: =IF($W16="RECEITA",$F16,0) -> 0 | AE16: =IF($W16="DESPESA",$F16,0) -> 0 | AF16: =IF($W16="RECEITA_FINANCEIRA",$F16,0) -> 0 | AG16: =IF($B16="",0,IF($I16="CONTA",$F16,0)-IF($G16="CONTA",$F16,0)) -> 0 | AH16: =IF($B16="",0,IF($G16="CARTAO",$F16,0)-IF($I16="CARTAO",$F16,0)) -> 0 | AI16: =IF($B16="",0,IF($I16="INVESTIMENTO",$F16,0)-IF($G16="INVESTIMENTO",$F16,0)) -> 0 | AJ16: =IF($B16="","",IF(NOT(ISNUMBER($F16)),"ERRO: valor nao numerico",IF($F16<=0,"ERRO: valor deve ser maior que zero",IF(COUNTIF(MAP_TIPO,$D16)=0,"ERRO: tipo de operacao nao cadastrado",IF(COUNTIF(LST_STATUS,$E16)=0,"ERRO: status invalido",IF(AND($G16="EXTERNO",$I16="EXTERNO"),"ERRO: origem e destino externos",IF(AND($G16<>"EXTERNO",COUNTIFS(ENT_ID,$H16,ENT_TIPO,$G16)=0),"ERRO: origem inexistente",IF(AND($I16<>"EXTERNO",COUNTIFS(ENT_ID,$J16,ENT_TIPO,$I16)=0),"ERRO: destino inexistente",IF(AND($K16<>"",COUNTIF(CAT_ID,$K16)=0),"ERRO: categoria inexistente",IF(AND($L16<>"",COUNTIF(SUB_ID,$L16)=0),"ERRO: subcategoria inexistente",IF(AND($L16<>"",$K16<>"",IFERROR(INDEX(SUB_CATID,MATCH($L16,SUB_ID,0)),"")<>$K16),"ERRO: subcategoria nao pertence a categoria",IF(AND($O16<>"",COUNTIF(P_ID,$O16)=0),"ERRO: parcela inexistente",IF(AND($N16<>"",COUNTIF(CM_ID,$N16)=0),"ERRO: compromisso inexistente","OK"))))))))))))) | AK16: =IF($B16="","",IF(AND($N16="",$O16="",$P16="",$Q16="",$R16=""),"","VINCULADO: "&TRIM(IF($N16<>"",$N16&" ","")&IF($O16<>"",$O16&" ","")&IF($P16<>"",$P16&" ","")&IF($Q16<>"",$Q16&" ","")&IF($R16<>"",$R16,""))))
... A904: =IF($B904="","","LAN-"&TEXT(ROW()-4,"000000")) | T904: =IF($B904="","",YEAR($B904)) | U904: =IF($B904="","",MONTH($B904)) | V904: =IF($B904="","",YEAR($B904)*100+MONTH($B904)) | W904: =IF($D904="","",IFERROR(INDEX(MAP_CLASS,MATCH($D904,MAP_TIPO,0)),"TIPO INVALIDO")) | X904: =IF($K904="","",IFERROR(INDEX(CAT_NOME,MATCH($K904,CAT_ID,0)),"?")) | Y904: =IF($L904="","",IFERROR(INDEX(SUB_NOME,MATCH($L904,SUB_ID,0)),"?")) | Z904: =IF($G904="","",IF($G904="EXTERNO","(Externo)",IFERROR(INDEX(ENT_NOME,MATCH($H904,ENT_ID,0)),"?"))) | AA904: =IF($I904="","",IF($I904="EXTERNO","(Externo)",IFERROR(INDEX(ENT_NOME,MATCH($J904,ENT_ID,0)),"?"))) | AB904: =IF($B904="",0,IF(AND($I904="CONTA",$G904<>"CONTA"),$F904,0)) -> 0 | AC904: =IF($B904="",0,IF(AND($G904="CONTA",$I904<>"CONTA"),$F904,0)) -> 0 | AD904: =IF($W904="RECEITA",$F904,0) -> 0 | AE904: =IF($W904="DESPESA",$F904,0) -> 0 | AF904: =IF($W904="RECEITA_FINANCEIRA",$F904,0) -> 0 | AG904: =IF($B904="",0,IF($I904="CONTA",$F904,0)-IF($G904="CONTA",$F904,0)) -> 0 | AH904: =IF($B904="",0,IF($G904="CARTAO",$F904,0)-IF($I904="CARTAO",$F904,0)) -> 0 | AI904: =IF($B904="",0,IF($I904="INVESTIMENTO",$F904,0)-IF($G904="INVESTIMENTO",$F904,0)) -> 0 | AJ904: =IF($B904="","",IF(NOT(ISNUMBER($F904)),"ERRO: valor nao numerico",IF($F904<=0,"ERRO: valor deve ser maior que zero",IF(COUNTIF(MAP_TIPO,$D904)=0,"ERRO: tipo de operacao nao cadastrado",IF(COUNTIF(LST_STATUS,$E904)=0,"ERRO: status invalido",IF(AND($G904="EXTERNO",$I904="EXTERNO"),"ERRO: origem e destino externos",IF(AND($G904<>"EXTERNO",COUNTIFS(ENT_ID,$H904,ENT_TIPO,$G904)=0),"ERRO: origem inexistente",IF(AND($I904<>"EXTERNO",COUNTIFS(ENT_ID,$J904,ENT_TIPO,$I904)=0),"ERRO: destino inexistente",IF(AND($K904<>"",COUNTIF(CAT_ID,$K904)=0),"ERRO: categoria inexistente",IF(AND($L904<>"",COUNTIF(SUB_ID,$L904)=0),"ERRO: subcategoria inexistente",IF(AND($L904<>"",$K904<>"",IFERROR(INDEX(SUB_CATID,MATCH($L904,SUB_ID,0)),"")<>$K904),"ERRO: subcategoria nao pertence a categoria",IF(AND($O904<>"",COUNTIF(P_ID,$O904)=0),"ERRO: parcela inexistente",IF(AND($N904<>"",COUNTIF(CM_ID,$N904)=0),"ERRO: compromisso inexistente","OK"))))))))))))) | AK904: =IF($B904="","",IF(AND($N904="",$O904="",$P904="",$Q904="",$R904=""),"","VINCULADO: "&TRIM(IF($N904<>"",$N904&" ","")&IF($O904<>"",$O904&" ","")&IF($P904<>"",$P904&" ","")&IF($Q904<>"",$Q904&" ","")&IF($R904<>"",$R904,""))))

Sheet PARCELAS
A1: PARCELAS - CRONOGRAMA DE TODOS OS COMPROMISSOS
A2: PARA APAGAR UM REGISTRO: selecione as celulas AMARELAS da linha e pressione DELETE (limpar conteudo). NUNCA use 'Excluir linha' nem classifique (sort) esta aba: os IDs sao gerados pela posicao da linha e os vinculos seriam quebrados em silencio. Para anular um lancamento sem perder o historico use o campo Status (CANCELADO / Inativo). Para pesquisar use os filtros do cabecalho. O cronograma e gerado uma unica vez por compromisso. Use a aba GERADOR para produzir o cronograma de um novo compromisso e cole o resultado (colunas B ate E) no fim desta lista.
A4: ID_Parcela | B4: ID_Compromisso | C4: Num_Parcela | D4: Data_Vencimento | E4: Valor_Parcela | F4: Observacao | G4: Compromisso | H4: Total_Parcelas | I4: Rotulo | J4: Pago_Antes_Sistema | K4: Pagto_Realizado | L4: Data_Pagamento | M4: Qtd_Lanc_Realizados | N4: Qtd_Lanc_Projetados | O4: Status_Parcela | P4: Dias_Atraso | Q4: Diferenca_Valor
A5: =IF($B5="","","PAR-"&TEXT(ROW()-4,"000000")) | G5: =IF($B5="","",IFERROR(INDEX(CM_NOME,MATCH($B5,CM_ID,0)),"?")) | H5: =IF($B5="","",IFERROR(INDEX(CM_QTD,MATCH($B5,CM_ID,0)),"")) | I5: =IF($A5="","",$C5&"/"&$H5) | J5: =IF($A5="","",IF($C5<=IFERROR(INDEX(CM_PAGASANTES,MATCH($B5,CM_ID,0)),0),"SIM","NAO")) | K5: =IF($A5="",0,SUMIFS(L_Valor,L_ParcID,$A5,L_Status,"REALIZADO")) -> 0 | L5: =IF($A5="","",IFERROR(INDEX(L_Data,MATCH(1,INDEX((L_ParcID=$A5)*(L_Status="REALIZADO"),0),0)),"")) | M5: =IF($A5="",0,COUNTIFS(L_ParcID,$A5,L_Status,"REALIZADO")) -> 0 | N5: =IF($A5="",0,COUNTIFS(L_ParcID,$A5,L_Status,"PROJETADO")) -> 0 | O5: =IF($A5="","",IF($J5="SIM","PAGA",IF($M5>0,"PAGA",IF($D5<CFG_HOJE,"ATRASADA",IF($D5<=EOMONTH(CFG_HOJE,0),"ABERTA","PROJETADA"))))) | P5: =IF($O5="ATRASADA",CFG_HOJE-$D5,0) -> 0 | Q5: =IF($A5="",0,IF(AND($O5="PAGA",$J5="NAO"),$K5-$E5,0)) -> 0
A6: =IF($B6="","","PAR-"&TEXT(ROW()-4,"000000")) | G6: =IF($B6="","",IFERROR(INDEX(CM_NOME,MATCH($B6,CM_ID,0)),"?")) | H6: =IF($B6="","",IFERROR(INDEX(CM_QTD,MATCH($B6,CM_ID,0)),"")) | I6: =IF($A6="","",$C6&"/"&$H6) | J6: =IF($A6="","",IF($C6<=IFERROR(INDEX(CM_PAGASANTES,MATCH($B6,CM_ID,0)),0),"SIM","NAO")) | K6: =IF($A6="",0,SUMIFS(L_Valor,L_ParcID,$A6,L_Status,"REALIZADO")) -> 0 | L6: =IF($A6="","",IFERROR(INDEX(L_Data,MATCH(1,INDEX((L_ParcID=$A6)*(L_Status="REALIZADO"),0),0)),"")) | M6: =IF($A6="",0,COUNTIFS(L_ParcID,$A6,L_Status,"REALIZADO")) -> 0 | N6: =IF($A6="",0,COUNTIFS(L_ParcID,$A6,L_Status,"PROJETADO")) -> 0 | O6: =IF($A6="","",IF($J6="SIM","PAGA",IF($M6>0,"PAGA",IF($D6<CFG_HOJE,"ATRASADA",IF($D6<=EOMONTH(CFG_HOJE,0),"ABERTA","PROJETADA"))))) | P6: =IF($O6="ATRASADA",CFG_HOJE-$D6,0) -> 0 | Q6: =IF($A6="",0,IF(AND($O6="PAGA",$J6="NAO"),$K6-$E6,0)) -> 0
A7: =IF($B7="","","PAR-"&TEXT(ROW()-4,"000000")) | G7: =IF($B7="","",IFERROR(INDEX(CM_NOME,MATCH($B7,CM_ID,0)),"?")) | H7: =IF($B7="","",IFERROR(INDEX(CM_QTD,MATCH($B7,CM_ID,0)),"")) | I7: =IF($A7="","",$C7&"/"&$H7) | J7: =IF($A7="","",IF($C7<=IFERROR(INDEX(CM_PAGASANTES,MATCH($B7,CM_ID,0)),0),"SIM","NAO")) | K7: =IF($A7="",0,SUMIFS(L_Valor,L_ParcID,$A7,L_Status,"REALIZADO")) -> 0 | L7: =IF($A7="","",IFERROR(INDEX(L_Data,MATCH(1,INDEX((L_ParcID=$A7)*(L_Status="REALIZADO"),0),0)),"")) | M7: =IF($A7="",0,COUNTIFS(L_ParcID,$A7,L_Status,"REALIZADO")) -> 0 | N7: =IF($A7="",0,COUNTIFS(L_ParcID,$A7,L_Status,"PROJETADO")) -> 0 | O7: =IF($A7="","",IF($J7="SIM","PAGA",IF($M7>0,"PAGA",IF($D7<CFG_HOJE,"ATRASADA",IF($D7<=EOMONTH(CFG_HOJE,0),"ABERTA","PROJETADA"))))) | P7: =IF($O7="ATRASADA",CFG_HOJE-$D7,0) -> 0 | Q7: =IF($A7="",0,IF(AND($O7="PAGA",$J7="NAO"),$K7-$E7,0)) -> 0
A8: =IF($B8="","","PAR-"&TEXT(ROW()-4,"000000")) | G8: =IF($B8="","",IFERROR(INDEX(CM_NOME,MATCH($B8,CM_ID,0)),"?")) | H8: =IF($B8="","",IFERROR(INDEX(CM_QTD,MATCH($B8,CM_ID,0)),"")) | I8: =IF($A8="","",$C8&"/"&$H8) | J8: =IF($A8="","",IF($C8<=IFERROR(INDEX(CM_PAGASANTES,MATCH($B8,CM_ID,0)),0),"SIM","NAO")) | K8: =IF($A8="",0,SUMIFS(L_Valor,L_ParcID,$A8,L_Status,"REALIZADO")) -> 0 | L8: =IF($A8="","",IFERROR(INDEX(L_Data,MATCH(1,INDEX((L_ParcID=$A8)*(L_Status="REALIZADO"),0),0)),"")) | M8: =IF($A8="",0,COUNTIFS(L_ParcID,$A8,L_Status,"REALIZADO")) -> 0 | N8: =IF($A8="",0,COUNTIFS(L_ParcID,$A8,L_Status,"PROJETADO")) -> 0 | O8: =IF($A8="","",IF($J8="SIM","PAGA",IF($M8>0,"PAGA",IF($D8<CFG_HOJE,"ATRASADA",IF($D8<=EOMONTH(CFG_HOJE,0),"ABERTA","PROJETADA"))))) | P8: =IF($O8="ATRASADA",CFG_HOJE-$D8,0) -> 0 | Q8: =IF($A8="",0,IF(AND($O8="PAGA",$J8="NAO"),$K8-$E8,0)) -> 0
A9: =IF($B9="","","PAR-"&TEXT(ROW()-4,"000000")) | G9: =IF($B9="","",IFERROR(INDEX(CM_NOME,MATCH($B9,CM_ID,0)),"?")) | H9: =IF($B9="","",IFERROR(INDEX(CM_QTD,MATCH($B9,CM_ID,0)),"")) | I9: =IF($A9="","",$C9&"/"&$H9) | J9: =IF($A9="","",IF($C9<=IFERROR(INDEX(CM_PAGASANTES,MATCH($B9,CM_ID,0)),0),"SIM","NAO")) | K9: =IF($A9="",0,SUMIFS(L_Valor,L_ParcID,$A9,L_Status,"REALIZADO")) -> 0 | L9: =IF($A9="","",IFERROR(INDEX(L_Data,MATCH(1,INDEX((L_ParcID=$A9)*(L_Status="REALIZADO"),0),0)),"")) | M9: =IF($A9="",0,COUNTIFS(L_ParcID,$A9,L_Status,"REALIZADO")) -> 0 | N9: =IF($A9="",0,COUNTIFS(L_ParcID,$A9,L_Status,"PROJETADO")) -> 0 | O9: =IF($A9="","",IF($J9="SIM","PAGA",IF($M9>0,"PAGA",IF($D9<CFG_HOJE,"ATRASADA",IF($D9<=EOMONTH(CFG_HOJE,0),"ABERTA","PROJETADA"))))) | P9: =IF($O9="ATRASADA",CFG_HOJE-$D9,0) -> 0 | Q9: =IF($A9="",0,IF(AND($O9="PAGA",$J9="NAO"),$K9-$E9,0)) -> 0
A10: =IF($B10="","","PAR-"&TEXT(ROW()-4,"000000")) | G10: =IF($B10="","",IFERROR(INDEX(CM_NOME,MATCH($B10,CM_ID,0)),"?")) | H10: =IF($B10="","",IFERROR(INDEX(CM_QTD,MATCH($B10,CM_ID,0)),"")) | I10: =IF($A10="","",$C10&"/"&$H10) | J10: =IF($A10="","",IF($C10<=IFERROR(INDEX(CM_PAGASANTES,MATCH($B10,CM_ID,0)),0),"SIM","NAO")) | K10: =IF($A10="",0,SUMIFS(L_Valor,L_ParcID,$A10,L_Status,"REALIZADO")) -> 0 | L10: =IF($A10="","",IFERROR(INDEX(L_Data,MATCH(1,INDEX((L_ParcID=$A10)*(L_Status="REALIZADO"),0),0)),"")) | M10: =IF($A10="",0,COUNTIFS(L_ParcID,$A10,L_Status,"REALIZADO")) -> 0 | N10: =IF($A10="",0,COUNTIFS(L_ParcID,$A10,L_Status,"PROJETADO")) -> 0 | O10: =IF($A10="","",IF($J10="SIM","PAGA",IF($M10>0,"PAGA",IF($D10<CFG_HOJE,"ATRASADA",IF($D10<=EOMONTH(CFG_HOJE,0),"ABERTA","PROJETADA"))))) | P10: =IF($O10="ATRASADA",CFG_HOJE-$D10,0) -> 0 | Q10: =IF($A10="",0,IF(AND($O10="PAGA",$J10="NAO"),$K10-$E10,0)) -> 0
A11: =IF($B11="","","PAR-"&TEXT(ROW()-4,"000000")) | G11: =IF($B11="","",IFERROR(INDEX(CM_NOME,MATCH($B11,CM_ID,0)),"?")) | H11: =IF($B11="","",IFERROR(INDEX(CM_QTD,MATCH($B11,CM_ID,0)),"")) | I11: =IF($A11="","",$C11&"/"&$H11) | J11: =IF($A11="","",IF($C11<=IFERROR(INDEX(CM_PAGASANTES,MATCH($B11,CM_ID,0)),0),"SIM","NAO")) | K11: =IF($A11="",0,SUMIFS(L_Valor,L_ParcID,$A11,L_Status,"REALIZADO")) -> 0 | L11: =IF($A11="","",IFERROR(INDEX(L_Data,MATCH(1,INDEX((L_ParcID=$A11)*(L_Status="REALIZADO"),0),0)),"")) | M11: =IF($A11="",0,COUNTIFS(L_ParcID,$A11,L_Status,"REALIZADO")) -> 0 | N11: =IF($A11="",0,COUNTIFS(L_ParcID,$A11,L_Status,"PROJETADO")) -> 0 | O11: =IF($A11="","",IF($J11="SIM","PAGA",IF($M11>0,"PAGA",IF($D11<CFG_HOJE,"ATRASADA",IF($D11<=EOMONTH(CFG_HOJE,0),"ABERTA","PROJETADA"))))) | P11: =IF($O11="ATRASADA",CFG_HOJE-$D11,0) -> 0 | Q11: =IF($A11="",0,IF(AND($O11="PAGA",$J11="NAO"),$K11-$E11,0)) -> 0
A12: =IF($B12="","","PAR-"&TEXT(ROW()-4,"000000")) | G12: =IF($B12="","",IFERROR(INDEX(CM_NOME,MATCH($B12,CM_ID,0)),"?")) | H12: =IF($B12="","",IFERROR(INDEX(CM_QTD,MATCH($B12,CM_ID,0)),"")) | I12: =IF($A12="","",$C12&"/"&$H12) | J12: =IF($A12="","",IF($C12<=IFERROR(INDEX(CM_PAGASANTES,MATCH($B12,CM_ID,0)),0),"SIM","NAO")) | K12: =IF($A12="",0,SUMIFS(L_Valor,L_ParcID,$A12,L_Status,"REALIZADO")) -> 0 | L12: =IF($A12="","",IFERROR(INDEX(L_Data,MATCH(1,INDEX((L_ParcID=$A12)*(L_Status="REALIZADO"),0),0)),"")) | M12: =IF($A12="",0,COUNTIFS(L_ParcID,$A12,L_Status,"REALIZADO")) -> 0 | N12: =IF($A12="",0,COUNTIFS(L_ParcID,$A12,L_Status,"PROJETADO")) -> 0 | O12: =IF($A12="","",IF($J12="SIM","PAGA",IF($M12>0,"PAGA",IF($D12<CFG_HOJE,"ATRASADA",IF($D12<=EOMONTH(CFG_HOJE,0),"ABERTA","PROJETADA"))))) | P12: =IF($O12="ATRASADA",CFG_HOJE-$D12,0) -> 0 | Q12: =IF($A12="",0,IF(AND($O12="PAGA",$J12="NAO"),$K12-$E12,0)) -> 0
A13: =IF($B13="","","PAR-"&TEXT(ROW()-4,"000000")) | G13: =IF($B13="","",IFERROR(INDEX(CM_NOME,MATCH($B13,CM_ID,0)),"?")) | H13: =IF($B13="","",IFERROR(INDEX(CM_QTD,MATCH($B13,CM_ID,0)),"")) | I13: =IF($A13="","",$C13&"/"&$H13) | J13: =IF($A13="","",IF($C13<=IFERROR(INDEX(CM_PAGASANTES,MATCH($B13,CM_ID,0)),0),"SIM","NAO")) | K13: =IF($A13="",0,SUMIFS(L_Valor,L_ParcID,$A13,L_Status,"REALIZADO")) -> 0 | L13: =IF($A13="","",IFERROR(INDEX(L_Data,MATCH(1,INDEX((L_ParcID=$A13)*(L_Status="REALIZADO"),0),0)),"")) | M13: =IF($A13="",0,COUNTIFS(L_ParcID,$A13,L_Status,"REALIZADO")) -> 0 | N13: =IF($A13="",0,COUNTIFS(L_ParcID,$A13,L_Status,"PROJETADO")) -> 0 | O13: =IF($A13="","",IF($J13="SIM","PAGA",IF($M13>0,"PAGA",IF($D13<CFG_HOJE,"ATRASADA",IF($D13<=EOMONTH(CFG_HOJE,0),"ABERTA","PROJETADA"))))) | P13: =IF($O13="ATRASADA",CFG_HOJE-$D13,0) -> 0 | Q13: =IF($A13="",0,IF(AND($O13="PAGA",$J13="NAO"),$K13-$E13,0)) -> 0
A14: =IF($B14="","","PAR-"&TEXT(ROW()-4,"000000")) | G14: =IF($B14="","",IFERROR(INDEX(CM_NOME,MATCH($B14,CM_ID,0)),"?")) | H14: =IF($B14="","",IFERROR(INDEX(CM_QTD,MATCH($B14,CM_ID,0)),"")) | I14: =IF($A14="","",$C14&"/"&$H14) | J14: =IF($A14="","",IF($C14<=IFERROR(INDEX(CM_PAGASANTES,MATCH($B14,CM_ID,0)),0),"SIM","NAO")) | K14: =IF($A14="",0,SUMIFS(L_Valor,L_ParcID,$A14,L_Status,"REALIZADO")) -> 0 | L14: =IF($A14="","",IFERROR(INDEX(L_Data,MATCH(1,INDEX((L_ParcID=$A14)*(L_Status="REALIZADO"),0),0)),"")) | M14: =IF($A14="",0,COUNTIFS(L_ParcID,$A14,L_Status,"REALIZADO")) -> 0 | N14: =IF($A14="",0,COUNTIFS(L_ParcID,$A14,L_Status,"PROJETADO")) -> 0 | O14: =IF($A14="","",IF($J14="SIM","PAGA",IF($M14>0,"PAGA",IF($D14<CFG_HOJE,"ATRASADA",IF($D14<=EOMONTH(CFG_HOJE,0),"ABERTA","PROJETADA"))))) | P14: =IF($O14="ATRASADA",CFG_HOJE-$D14,0) -> 0 | Q14: =IF($A14="",0,IF(AND($O14="PAGA",$J14="NAO"),$K14-$E14,0)) -> 0
A15: =IF($B15="","","PAR-"&TEXT(ROW()-4,"000000")) | G15: =IF($B15="","",IFERROR(INDEX(CM_NOME,MATCH($B15,CM_ID,0)),"?")) | H15: =IF($B15="","",IFERROR(INDEX(CM_QTD,MATCH($B15,CM_ID,0)),"")) | I15: =IF($A15="","",$C15&"/"&$H15) | J15: =IF($A15="","",IF($C15<=IFERROR(INDEX(CM_PAGASANTES,MATCH($B15,CM_ID,0)),0),"SIM","NAO")) | K15: =IF($A15="",0,SUMIFS(L_Valor,L_ParcID,$A15,L_Status,"REALIZADO")) -> 0 | L15: =IF($A15="","",IFERROR(INDEX(L_Data,MATCH(1,INDEX((L_ParcID=$A15)*(L_Status="REALIZADO"),0),0)),"")) | M15: =IF($A15="",0,COUNTIFS(L_ParcID,$A15,L_Status,"REALIZADO")) -> 0 | N15: =IF($A15="",0,COUNTIFS(L_ParcID,$A15,L_Status,"PROJETADO")) -> 0 | O15: =IF($A15="","",IF($J15="SIM","PAGA",IF($M15>0,"PAGA",IF($D15<CFG_HOJE,"ATRASADA",IF($D15<=EOMONTH(CFG_HOJE,0),"ABERTA","PROJETADA"))))) | P15: =IF($O15="ATRASADA",CFG_HOJE-$D15,0) -> 0 | Q15: =IF($A15="",0,IF(AND($O15="PAGA",$J15="NAO"),$K15-$E15,0)) -> 0
A16: =IF($B16="","","PAR-"&TEXT(ROW()-4,"000000")) | G16: =IF($B16="","",IFERROR(INDEX(CM_NOME,MATCH($B16,CM_ID,0)),"?")) | H16: =IF($B16="","",IFERROR(INDEX(CM_QTD,MATCH($B16,CM_ID,0)),"")) | I16: =IF($A16="","",$C16&"/"&$H16) | J16: =IF($A16="","",IF($C16<=IFERROR(INDEX(CM_PAGASANTES,MATCH($B16,CM_ID,0)),0),"SIM","NAO")) | K16: =IF($A16="",0,SUMIFS(L_Valor,L_ParcID,$A16,L_Status,"REALIZADO")) -> 0 | L16: =IF($A16="","",IFERROR(INDEX(L_Data,MATCH(1,INDEX((L_ParcID=$A16)*(L_Status="REALIZADO"),0),0)),"")) | M16: =IF($A16="",0,COUNTIFS(L_ParcID,$A16,L_Status,"REALIZADO")) -> 0 | N16: =IF($A16="",0,COUNTIFS(L_ParcID,$A16,L_Status,"PROJETADO")) -> 0 | O16: =IF($A16="","",IF($J16="SIM","PAGA",IF($M16>0,"PAGA",IF($D16<CFG_HOJE,"ATRASADA",IF($D16<=EOMONTH(CFG_HOJE,0),"ABERTA","PROJETADA"))))) | P16: =IF($O16="ATRASADA",CFG_HOJE-$D16,0) -> 0 | Q16: =IF($A16="",0,IF(AND($O16="PAGA",$J16="NAO"),$K16-$E16,0)) -> 0
... A704: =IF($B704="","","PAR-"&TEXT(ROW()-4,"000000")) | G704: =IF($B704="","",IFERROR(INDEX(CM_NOME,MATCH($B704,CM_ID,0)),"?")) | H704: =IF($B704="","",IFERROR(INDEX(CM_QTD,MATCH($B704,CM_ID,0)),"")) | I704: =IF($A704="","",$C704&"/"&$H704) | J704: =IF($A704="","",IF($C704<=IFERROR(INDEX(CM_PAGASANTES,MATCH($B704,CM_ID,0)),0),"SIM","NAO")) | K704: =IF($A704="",0,SUMIFS(L_Valor,L_ParcID,$A704,L_Status,"REALIZADO")) -> 0 | L704: =IF($A704="","",IFERROR(INDEX(L_Data,MATCH(1,INDEX((L_ParcID=$A704)*(L_Status="REALIZADO"),0),0)),"")) | M704: =IF($A704="",0,COUNTIFS(L_ParcID,$A704,L_Status,"REALIZADO")) -> 0 | N704: =IF($A704="",0,COUNTIFS(L_ParcID,$A704,L_Status,"PROJETADO")) -> 0 | O704: =IF($A704="","",IF($J704="SIM","PAGA",IF($M704>0,"PAGA",IF($D704<CFG_HOJE,"ATRASADA",IF($D704<=EOMONTH(CFG_HOJE,0),"ABERTA","PROJETADA"))))) | P704: =IF($O704="ATRASADA",CFG_HOJE-$D704,0) -> 0 | Q704: =IF($A704="",0,IF(AND($O704="PAGA",$J704="NAO"),$K704-$E704,0)) -> 0

Sheet MOV_METAS
A1: MOV_METAS - MOVIMENTACAO DAS RESERVAS DE METAS
A2: PARA APAGAR UM REGISTRO: selecione as celulas AMARELAS da linha e pressione DELETE (limpar conteudo). NUNCA use 'Excluir linha' nem classifique (sort) esta aba: os IDs sao gerados pela posicao da linha e os vinculos seriam quebrados em silencio. Para anular um lancamento sem perder o historico use o campo Status (CANCELADO / Inativo). Para pesquisar use os filtros do cabecalho. Esta aba registra apenas RESERVAS LOGICAS. O dinheiro continua na conta; nenhuma linha daqui altera o saldo bancario.
A4: ID_Movimento | B4: Data | C4: ID_Meta | D4: Tipo_Movimento | E4: Valor | F4: Destino_Retirada | G4: ID_Meta_Destino | H4: Observacao | I4: Meta_Nome | J4: Sinal | K4: Valor_Com_Sinal | L4: Conta_Vinculada | M4: Validacao
A5: =IF($B5="","","MOV-"&TEXT(ROW()-4,"000000")) | I5: =IF($C5="","",IFERROR(INDEX(M_NOME,MATCH($C5,M_ID,0)),"?")) | J5: =IF($D5="",0,IFERROR(INDEX(MAP_SINALMOV,MATCH($D5,LST_TIPOMOV,0)),0)) -> 0 | K5: =IF($A5="",0,$E5*$J5) -> 0 | L5: =IF($C5="","",IFERROR(INDEX(M_CONTA,MATCH($C5,M_ID,0)),"")) | M5: =IF($B5="","",IF($E5<=0,"ERRO: valor deve ser maior que zero",IF(COUNTIF(M_ID,$C5)=0,"ERRO: meta inexistente",IF(COUNTIF(LST_TIPOMOV,$D5)=0,"ERRO: tipo de movimento invalido",IF(AND($D5="TRANSF_SAIDA",COUNTIF(M_ID,$G5)=0),"ERRO: informe a meta de destino",IF(AND($J5=-1,$F5=""),"ATENCAO: informe o destino da retirada","OK"))))))
A6: =IF($B6="","","MOV-"&TEXT(ROW()-4,"000000")) | I6: =IF($C6="","",IFERROR(INDEX(M_NOME,MATCH($C6,M_ID,0)),"?")) | J6: =IF($D6="",0,IFERROR(INDEX(MAP_SINALMOV,MATCH($D6,LST_TIPOMOV,0)),0)) -> 0 | K6: =IF($A6="",0,$E6*$J6) -> 0 | L6: =IF($C6="","",IFERROR(INDEX(M_CONTA,MATCH($C6,M_ID,0)),"")) | M6: =IF($B6="","",IF($E6<=0,"ERRO: valor deve ser maior que zero",IF(COUNTIF(M_ID,$C6)=0,"ERRO: meta inexistente",IF(COUNTIF(LST_TIPOMOV,$D6)=0,"ERRO: tipo de movimento invalido",IF(AND($D6="TRANSF_SAIDA",COUNTIF(M_ID,$G6)=0),"ERRO: informe a meta de destino",IF(AND($J6=-1,$F6=""),"ATENCAO: informe o destino da retirada","OK"))))))
A7: =IF($B7="","","MOV-"&TEXT(ROW()-4,"000000")) | I7: =IF($C7="","",IFERROR(INDEX(M_NOME,MATCH($C7,M_ID,0)),"?")) | J7: =IF($D7="",0,IFERROR(INDEX(MAP_SINALMOV,MATCH($D7,LST_TIPOMOV,0)),0)) -> 0 | K7: =IF($A7="",0,$E7*$J7) -> 0 | L7: =IF($C7="","",IFERROR(INDEX(M_CONTA,MATCH($C7,M_ID,0)),"")) | M7: =IF($B7="","",IF($E7<=0,"ERRO: valor deve ser maior que zero",IF(COUNTIF(M_ID,$C7)=0,"ERRO: meta inexistente",IF(COUNTIF(LST_TIPOMOV,$D7)=0,"ERRO: tipo de movimento invalido",IF(AND($D7="TRANSF_SAIDA",COUNTIF(M_ID,$G7)=0),"ERRO: informe a meta de destino",IF(AND($J7=-1,$F7=""),"ATENCAO: informe o destino da retirada","OK"))))))
A8: =IF($B8="","","MOV-"&TEXT(ROW()-4,"000000")) | I8: =IF($C8="","",IFERROR(INDEX(M_NOME,MATCH($C8,M_ID,0)),"?")) | J8: =IF($D8="",0,IFERROR(INDEX(MAP_SINALMOV,MATCH($D8,LST_TIPOMOV,0)),0)) -> 0 | K8: =IF($A8="",0,$E8*$J8) -> 0 | L8: =IF($C8="","",IFERROR(INDEX(M_CONTA,MATCH($C8,M_ID,0)),"")) | M8: =IF($B8="","",IF($E8<=0,"ERRO: valor deve ser maior que zero",IF(COUNTIF(M_ID,$C8)=0,"ERRO: meta inexistente",IF(COUNTIF(LST_TIPOMOV,$D8)=0,"ERRO: tipo de movimento invalido",IF(AND($D8="TRANSF_SAIDA",COUNTIF(M_ID,$G8)=0),"ERRO: informe a meta de destino",IF(AND($J8=-1,$F8=""),"ATENCAO: informe o destino da retirada","OK"))))))
A9: =IF($B9="","","MOV-"&TEXT(ROW()-4,"000000")) | I9: =IF($C9="","",IFERROR(INDEX(M_NOME,MATCH($C9,M_ID,0)),"?")) | J9: =IF($D9="",0,IFERROR(INDEX(MAP_SINALMOV,MATCH($D9,LST_TIPOMOV,0)),0)) -> 0 | K9: =IF($A9="",0,$E9*$J9) -> 0 | L9: =IF($C9="","",IFERROR(INDEX(M_CONTA,MATCH($C9,M_ID,0)),"")) | M9: =IF($B9="","",IF($E9<=0,"ERRO: valor deve ser maior que zero",IF(COUNTIF(M_ID,$C9)=0,"ERRO: meta inexistente",IF(COUNTIF(LST_TIPOMOV,$D9)=0,"ERRO: tipo de movimento invalido",IF(AND($D9="TRANSF_SAIDA",COUNTIF(M_ID,$G9)=0),"ERRO: informe a meta de destino",IF(AND($J9=-1,$F9=""),"ATENCAO: informe o destino da retirada","OK"))))))
A10: =IF($B10="","","MOV-"&TEXT(ROW()-4,"000000")) | I10: =IF($C10="","",IFERROR(INDEX(M_NOME,MATCH($C10,M_ID,0)),"?")) | J10: =IF($D10="",0,IFERROR(INDEX(MAP_SINALMOV,MATCH($D10,LST_TIPOMOV,0)),0)) -> 0 | K10: =IF($A10="",0,$E10*$J10) -> 0 | L10: =IF($C10="","",IFERROR(INDEX(M_CONTA,MATCH($C10,M_ID,0)),"")) | M10: =IF($B10="","",IF($E10<=0,"ERRO: valor deve ser maior que zero",IF(COUNTIF(M_ID,$C10)=0,"ERRO: meta inexistente",IF(COUNTIF(LST_TIPOMOV,$D10)=0,"ERRO: tipo de movimento invalido",IF(AND($D10="TRANSF_SAIDA",COUNTIF(M_ID,$G10)=0),"ERRO: informe a meta de destino",IF(AND($J10=-1,$F10=""),"ATENCAO: informe o destino da retirada","OK"))))))
A11: =IF($B11="","","MOV-"&TEXT(ROW()-4,"000000")) | I11: =IF($C11="","",IFERROR(INDEX(M_NOME,MATCH($C11,M_ID,0)),"?")) | J11: =IF($D11="",0,IFERROR(INDEX(MAP_SINALMOV,MATCH($D11,LST_TIPOMOV,0)),0)) -> 0 | K11: =IF($A11="",0,$E11*$J11) -> 0 | L11: =IF($C11="","",IFERROR(INDEX(M_CONTA,MATCH($C11,M_ID,0)),"")) | M11: =IF($B11="","",IF($E11<=0,"ERRO: valor deve ser maior que zero",IF(COUNTIF(M_ID,$C11)=0,"ERRO: meta inexistente",IF(COUNTIF(LST_TIPOMOV,$D11)=0,"ERRO: tipo de movimento invalido",IF(AND($D11="TRANSF_SAIDA",COUNTIF(M_ID,$G11)=0),"ERRO: informe a meta de destino",IF(AND($J11=-1,$F11=""),"ATENCAO: informe o destino da retirada","OK"))))))
A12: =IF($B12="","","MOV-"&TEXT(ROW()-4,"000000")) | I12: =IF($C12="","",IFERROR(INDEX(M_NOME,MATCH($C12,M_ID,0)),"?")) | J12: =IF($D12="",0,IFERROR(INDEX(MAP_SINALMOV,MATCH($D12,LST_TIPOMOV,0)),0)) -> 0 | K12: =IF($A12="",0,$E12*$J12) -> 0 | L12: =IF($C12="","",IFERROR(INDEX(M_CONTA,MATCH($C12,M_ID,0)),"")) | M12: =IF($B12="","",IF($E12<=0,"ERRO: valor deve ser maior que zero",IF(COUNTIF(M_ID,$C12)=0,"ERRO: meta inexistente",IF(COUNTIF(LST_TIPOMOV,$D12)=0,"ERRO: tipo de movimento invalido",IF(AND($D12="TRANSF_SAIDA",COUNTIF(M_ID,$G12)=0),"ERRO: informe a meta de destino",IF(AND($J12=-1,$F12=""),"ATENCAO: informe o destino da retirada","OK"))))))
A13: =IF($B13="","","MOV-"&TEXT(ROW()-4,"000000")) | I13: =IF($C13="","",IFERROR(INDEX(M_NOME,MATCH($C13,M_ID,0)),"?")) | J13: =IF($D13="",0,IFERROR(INDEX(MAP_SINALMOV,MATCH($D13,LST_TIPOMOV,0)),0)) -> 0 | K13: =IF($A13="",0,$E13*$J13) -> 0 | L13: =IF($C13="","",IFERROR(INDEX(M_CONTA,MATCH($C13,M_ID,0)),"")) | M13: =IF($B13="","",IF($E13<=0,"ERRO: valor deve ser maior que zero",IF(COUNTIF(M_ID,$C13)=0,"ERRO: meta inexistente",IF(COUNTIF(LST_TIPOMOV,$D13)=0,"ERRO: tipo de movimento invalido",IF(AND($D13="TRANSF_SAIDA",COUNTIF(M_ID,$G13)=0),"ERRO: informe a meta de destino",IF(AND($J13=-1,$F13=""),"ATENCAO: informe o destino da retirada","OK"))))))
A14: =IF($B14="","","MOV-"&TEXT(ROW()-4,"000000")) | I14: =IF($C14="","",IFERROR(INDEX(M_NOME,MATCH($C14,M_ID,0)),"?")) | J14: =IF($D14="",0,IFERROR(INDEX(MAP_SINALMOV,MATCH($D14,LST_TIPOMOV,0)),0)) -> 0 | K14: =IF($A14="",0,$E14*$J14) -> 0 | L14: =IF($C14="","",IFERROR(INDEX(M_CONTA,MATCH($C14,M_ID,0)),"")) | M14: =IF($B14="","",IF($E14<=0,"ERRO: valor deve ser maior que zero",IF(COUNTIF(M_ID,$C14)=0,"ERRO: meta inexistente",IF(COUNTIF(LST_TIPOMOV,$D14)=0,"ERRO: tipo de movimento invalido",IF(AND($D14="TRANSF_SAIDA",COUNTIF(M_ID,$G14)=0),"ERRO: informe a meta de destino",IF(AND($J14=-1,$F14=""),"ATENCAO: informe o destino da retirada","OK"))))))
A15: =IF($B15="","","MOV-"&TEXT(ROW()-4,"000000")) | I15: =IF($C15="","",IFERROR(INDEX(M_NOME,MATCH($C15,M_ID,0)),"?")) | J15: =IF($D15="",0,IFERROR(INDEX(MAP_SINALMOV,MATCH($D15,LST_TIPOMOV,0)),0)) -> 0 | K15: =IF($A15="",0,$E15*$J15) -> 0 | L15: =IF($C15="","",IFERROR(INDEX(M_CONTA,MATCH($C15,M_ID,0)),"")) | M15: =IF($B15="","",IF($E15<=0,"ERRO: valor deve ser maior que zero",IF(COUNTIF(M_ID,$C15)=0,"ERRO: meta inexistente",IF(COUNTIF(LST_TIPOMOV,$D15)=0,"ERRO: tipo de movimento invalido",IF(AND($D15="TRANSF_SAIDA",COUNTIF(M_ID,$G15)=0),"ERRO: informe a meta de destino",IF(AND($J15=-1,$F15=""),"ATENCAO: informe o destino da retirada","OK"))))))
A16: =IF($B16="","","MOV-"&TEXT(ROW()-4,"000000")) | I16: =IF($C16="","",IFERROR(INDEX(M_NOME,MATCH($C16,M_ID,0)),"?")) | J16: =IF($D16="",0,IFERROR(INDEX(MAP_SINALMOV,MATCH($D16,LST_TIPOMOV,0)),0)) -> 0 | K16: =IF($A16="",0,$E16*$J16) -> 0 | L16: =IF($C16="","",IFERROR(INDEX(M_CONTA,MATCH($C16,M_ID,0)),"")) | M16: =IF($B16="","",IF($E16<=0,"ERRO: valor deve ser maior que zero",IF(COUNTIF(M_ID,$C16)=0,"ERRO: meta inexistente",IF(COUNTIF(LST_TIPOMOV,$D16)=0,"ERRO: tipo de movimento invalido",IF(AND($D16="TRANSF_SAIDA",COUNTIF(M_ID,$G16)=0),"ERRO: informe a meta de destino",IF(AND($J16=-1,$F16=""),"ATENCAO: informe o destino da retirada","OK"))))))
... A304: =IF($B304="","","MOV-"&TEXT(ROW()-4,"000000")) | I304: =IF($C304="","",IFERROR(INDEX(M_NOME,MATCH($C304,M_ID,0)),"?")) | J304: =IF($D304="",0,IFERROR(INDEX(MAP_SINALMOV,MATCH($D304,LST_TIPOMOV,0)),0)) -> 0 | K304: =IF($A304="",0,$E304*$J304) -> 0 | L304: =IF($C304="","",IFERROR(INDEX(M_CONTA,MATCH($C304,M_ID,0)),"")) | M304: =IF($B304="","",IF($E304<=0,"ERRO: valor deve ser maior que zero",IF(COUNTIF(M_ID,$C304)=0,"ERRO: meta inexistente",IF(COUNTIF(LST_TIPOMOV,$D304)=0,"ERRO: tipo de movimento invalido",IF(AND($D304="TRANSF_SAIDA",COUNTIF(M_ID,$G304)=0),"ERRO: informe a meta de destino",IF(AND($J304=-1,$F304=""),"ATENCAO: informe o destino da retirada","OK"))))))

Sheet CAD_Instituicoes
A1: CAD_INSTITUICOES - BANCOS E EMISSORES
A2: PARA APAGAR UM REGISTRO: selecione as celulas AMARELAS da linha e pressione DELETE (limpar conteudo). NUNCA use 'Excluir linha' nem classifique (sort) esta aba: os IDs sao gerados pela posicao da linha e os vinculos seriam quebrados em silencio. Para anular um lancamento sem perder o historico use o campo Status (CANCELADO / Inativo). Para pesquisar use os filtros do cabecalho.
A4: ID_Instituicao | B4: Nome | C4: Tipo | D4: Qtd_Contas | E4: Qtd_Cartoes | F4: Qtd_Investimentos | G4: Observacao
A5: =IF($B5="","","INS-"&TEXT(ROW()-4,"000000")) | D5: =IF($A5="","",COUNTIF(CAD_Contas!$D$5:$D$44,$A5)) | E5: =IF($A5="","",COUNTIF(CAD_Cartoes!$D$5:$D$44,$A5)) | F5: =IF($A5="","",COUNTIF(CAD_Investimentos!$D$5:$D$44,$A5))
A6: =IF($B6="","","INS-"&TEXT(ROW()-4,"000000")) | D6: =IF($A6="","",COUNTIF(CAD_Contas!$D$5:$D$44,$A6)) | E6: =IF($A6="","",COUNTIF(CAD_Cartoes!$D$5:$D$44,$A6)) | F6: =IF($A6="","",COUNTIF(CAD_Investimentos!$D$5:$D$44,$A6))
A7: =IF($B7="","","INS-"&TEXT(ROW()-4,"000000")) | D7: =IF($A7="","",COUNTIF(CAD_Contas!$D$5:$D$44,$A7)) | E7: =IF($A7="","",COUNTIF(CAD_Cartoes!$D$5:$D$44,$A7)) | F7: =IF($A7="","",COUNTIF(CAD_Investimentos!$D$5:$D$44,$A7))
A8: =IF($B8="","","INS-"&TEXT(ROW()-4,"000000")) | D8: =IF($A8="","",COUNTIF(CAD_Contas!$D$5:$D$44,$A8)) | E8: =IF($A8="","",COUNTIF(CAD_Cartoes!$D$5:$D$44,$A8)) | F8: =IF($A8="","",COUNTIF(CAD_Investimentos!$D$5:$D$44,$A8))
A9: =IF($B9="","","INS-"&TEXT(ROW()-4,"000000")) | D9: =IF($A9="","",COUNTIF(CAD_Contas!$D$5:$D$44,$A9)) | E9: =IF($A9="","",COUNTIF(CAD_Cartoes!$D$5:$D$44,$A9)) | F9: =IF($A9="","",COUNTIF(CAD_Investimentos!$D$5:$D$44,$A9))
A10: =IF($B10="","","INS-"&TEXT(ROW()-4,"000000")) | D10: =IF($A10="","",COUNTIF(CAD_Contas!$D$5:$D$44,$A10)) | E10: =IF($A10="","",COUNTIF(CAD_Cartoes!$D$5:$D$44,$A10)) | F10: =IF($A10="","",COUNTIF(CAD_Investimentos!$D$5:$D$44,$A10))
A11: =IF($B11="","","INS-"&TEXT(ROW()-4,"000000")) | D11: =IF($A11="","",COUNTIF(CAD_Contas!$D$5:$D$44,$A11)) | E11: =IF($A11="","",COUNTIF(CAD_Cartoes!$D$5:$D$44,$A11)) | F11: =IF($A11="","",COUNTIF(CAD_Investimentos!$D$5:$D$44,$A11))
A12: =IF($B12="","","INS-"&TEXT(ROW()-4,"000000")) | D12: =IF($A12="","",COUNTIF(CAD_Contas!$D$5:$D$44,$A12)) | E12: =IF($A12="","",COUNTIF(CAD_Cartoes!$D$5:$D$44,$A12)) | F12: =IF($A12="","",COUNTIF(CAD_Investimentos!$D$5:$D$44,$A12))
A13: =IF($B13="","","INS-"&TEXT(ROW()-4,"000000")) | D13: =IF($A13="","",COUNTIF(CAD_Contas!$D$5:$D$44,$A13)) | E13: =IF($A13="","",COUNTIF(CAD_Cartoes!$D$5:$D$44,$A13)) | F13: =IF($A13="","",COUNTIF(CAD_Investimentos!$D$5:$D$44,$A13))
A14: =IF($B14="","","INS-"&TEXT(ROW()-4,"000000")) | D14: =IF($A14="","",COUNTIF(CAD_Contas!$D$5:$D$44,$A14)) | E14: =IF($A14="","",COUNTIF(CAD_Cartoes!$D$5:$D$44,$A14)) | F14: =IF($A14="","",COUNTIF(CAD_Investimentos!$D$5:$D$44,$A14))
A15: =IF($B15="","","INS-"&TEXT(ROW()-4,"000000")) | D15: =IF($A15="","",COUNTIF(CAD_Contas!$D$5:$D$44,$A15)) | E15: =IF($A15="","",COUNTIF(CAD_Cartoes!$D$5:$D$44,$A15)) | F15: =IF($A15="","",COUNTIF(CAD_Investimentos!$D$5:$D$44,$A15))
A16: =IF($B16="","","INS-"&TEXT(ROW()-4,"000000")) | D16: =IF($A16="","",COUNTIF(CAD_Contas!$D$5:$D$44,$A16)) | E16: =IF($A16="","",COUNTIF(CAD_Cartoes!$D$5:$D$44,$A16)) | F16: =IF($A16="","",COUNTIF(CAD_Investimentos!$D$5:$D$44,$A16))
... A44: =IF($B44="","","INS-"&TEXT(ROW()-4,"000000")) | D44: =IF($A44="","",COUNTIF(CAD_Contas!$D$5:$D$44,$A44)) | E44: =IF($A44="","",COUNTIF(CAD_Cartoes!$D$5:$D$44,$A44)) | F44: =IF($A44="","",COUNTIF(CAD_Investimentos!$D$5:$D$44,$A44))

Sheet CAD_Contas
A1: CAD_CONTAS - CONTAS BANCARIAS E DINHEIRO FISICO
A2: PARA APAGAR UM REGISTRO: selecione as celulas AMARELAS da linha e pressione DELETE (limpar conteudo). NUNCA use 'Excluir linha' nem classifique (sort) esta aba: os IDs sao gerados pela posicao da linha e os vinculos seriam quebrados em silencio. Para anular um lancamento sem perder o historico use o campo Status (CANCELADO / Inativo). Para pesquisar use os filtros do cabecalho.
A4: ID_Conta | B4: Nome | C4: Instituicao | D4: ID_Instituicao | E4: Tipo | F4: Saldo_Inicial | G4: Data_Saldo_Inicial | H4: Entradas_Realizadas | I4: Saidas_Realizadas | J4: Saldo_Calculado | K4: Reservado_Metas | L4: Saldo_Disponivel | M4: Entradas_Projetadas | N4: Saidas_Projetadas | O4: Saldo_Projetado | P4: Status | Q4: Observacao
A5: =IF($B5="","","CON-"&TEXT(ROW()-4,"000000")) | D5: =IF($C5="","",IFERROR(INDEX(INS_ID,MATCH($C5,INS_NOME,0)),"?")) | H5: =IF($A5="",0,SUMIFS(L_Valor,L_DestTipo,"CONTA",L_DestID,$A5,L_Status,"REALIZADO")) -> 0 | I5: =IF($A5="",0,SUMIFS(L_Valor,L_OrigTipo,"CONTA",L_OrigID,$A5,L_Status,"REALIZADO")) -> 0 | J5: =IF($A5="","",$F5+$H5-$I5) | K5: =IF($A5="",0,SUMIFS(MM_VALSINAL,MM_CONTA,$A5)) -> 0 | L5: =IF($A5="","",$J5-$K5) | M5: =IF($A5="",0,SUMIFS(L_Valor,L_DestTipo,"CONTA",L_DestID,$A5,L_Status,"PROJETADO")) -> 0 | N5: =IF($A5="",0,SUMIFS(L_Valor,L_OrigTipo,"CONTA",L_OrigID,$A5,L_Status,"PROJETADO")) -> 0 | O5: =IF($A5="","",$J5+$M5-$N5)
A6: =IF($B6="","","CON-"&TEXT(ROW()-4,"000000")) | D6: =IF($C6="","",IFERROR(INDEX(INS_ID,MATCH($C6,INS_NOME,0)),"?")) | H6: =IF($A6="",0,SUMIFS(L_Valor,L_DestTipo,"CONTA",L_DestID,$A6,L_Status,"REALIZADO")) -> 0 | I6: =IF($A6="",0,SUMIFS(L_Valor,L_OrigTipo,"CONTA",L_OrigID,$A6,L_Status,"REALIZADO")) -> 0 | J6: =IF($A6="","",$F6+$H6-$I6) | K6: =IF($A6="",0,SUMIFS(MM_VALSINAL,MM_CONTA,$A6)) -> 0 | L6: =IF($A6="","",$J6-$K6) | M6: =IF($A6="",0,SUMIFS(L_Valor,L_DestTipo,"CONTA",L_DestID,$A6,L_Status,"PROJETADO")) -> 0 | N6: =IF($A6="",0,SUMIFS(L_Valor,L_OrigTipo,"CONTA",L_OrigID,$A6,L_Status,"PROJETADO")) -> 0 | O6: =IF($A6="","",$J6+$M6-$N6)
A7: =IF($B7="","","CON-"&TEXT(ROW()-4,"000000")) | D7: =IF($C7="","",IFERROR(INDEX(INS_ID,MATCH($C7,INS_NOME,0)),"?")) | H7: =IF($A7="",0,SUMIFS(L_Valor,L_DestTipo,"CONTA",L_DestID,$A7,L_Status,"REALIZADO")) -> 0 | I7: =IF($A7="",0,SUMIFS(L_Valor,L_OrigTipo,"CONTA",L_OrigID,$A7,L_Status,"REALIZADO")) -> 0 | J7: =IF($A7="","",$F7+$H7-$I7) | K7: =IF($A7="",0,SUMIFS(MM_VALSINAL,MM_CONTA,$A7)) -> 0 | L7: =IF($A7="","",$J7-$K7) | M7: =IF($A7="",0,SUMIFS(L_Valor,L_DestTipo,"CONTA",L_DestID,$A7,L_Status,"PROJETADO")) -> 0 | N7: =IF($A7="",0,SUMIFS(L_Valor,L_OrigTipo,"CONTA",L_OrigID,$A7,L_Status,"PROJETADO")) -> 0 | O7: =IF($A7="","",$J7+$M7-$N7)
A8: =IF($B8="","","CON-"&TEXT(ROW()-4,"000000")) | D8: =IF($C8="","",IFERROR(INDEX(INS_ID,MATCH($C8,INS_NOME,0)),"?")) | H8: =IF($A8="",0,SUMIFS(L_Valor,L_DestTipo,"CONTA",L_DestID,$A8,L_Status,"REALIZADO")) -> 0 | I8: =IF($A8="",0,SUMIFS(L_Valor,L_OrigTipo,"CONTA",L_OrigID,$A8,L_Status,"REALIZADO")) -> 0 | J8: =IF($A8="","",$F8+$H8-$I8) | K8: =IF($A8="",0,SUMIFS(MM_VALSINAL,MM_CONTA,$A8)) -> 0 | L8: =IF($A8="","",$J8-$K8) | M8: =IF($A8="",0,SUMIFS(L_Valor,L_DestTipo,"CONTA",L_DestID,$A8,L_Status,"PROJETADO")) -> 0 | N8: =IF($A8="",0,SUMIFS(L_Valor,L_OrigTipo,"CONTA",L_OrigID,$A8,L_Status,"PROJETADO")) -> 0 | O8: =IF($A8="","",$J8+$M8-$N8)
A9: =IF($B9="","","CON-"&TEXT(ROW()-4,"000000")) | D9: =IF($C9="","",IFERROR(INDEX(INS_ID,MATCH($C9,INS_NOME,0)),"?")) | H9: =IF($A9="",0,SUMIFS(L_Valor,L_DestTipo,"CONTA",L_DestID,$A9,L_Status,"REALIZADO")) -> 0 | I9: =IF($A9="",0,SUMIFS(L_Valor,L_OrigTipo,"CONTA",L_OrigID,$A9,L_Status,"REALIZADO")) -> 0 | J9: =IF($A9="","",$F9+$H9-$I9) | K9: =IF($A9="",0,SUMIFS(MM_VALSINAL,MM_CONTA,$A9)) -> 0 | L9: =IF($A9="","",$J9-$K9) | M9: =IF($A9="",0,SUMIFS(L_Valor,L_DestTipo,"CONTA",L_DestID,$A9,L_Status,"PROJETADO")) -> 0 | N9: =IF($A9="",0,SUMIFS(L_Valor,L_OrigTipo,"CONTA",L_OrigID,$A9,L_Status,"PROJETADO")) -> 0 | O9: =IF($A9="","",$J9+$M9-$N9)
A10: =IF($B10="","","CON-"&TEXT(ROW()-4,"000000")) | D10: =IF($C10="","",IFERROR(INDEX(INS_ID,MATCH($C10,INS_NOME,0)),"?")) | H10: =IF($A10="",0,SUMIFS(L_Valor,L_DestTipo,"CONTA",L_DestID,$A10,L_Status,"REALIZADO")) -> 0 | I10: =IF($A10="",0,SUMIFS(L_Valor,L_OrigTipo,"CONTA",L_OrigID,$A10,L_Status,"REALIZADO")) -> 0 | J10: =IF($A10="","",$F10+$H10-$I10) | K10: =IF($A10="",0,SUMIFS(MM_VALSINAL,MM_CONTA,$A10)) -> 0 | L10: =IF($A10="","",$J10-$K10) | M10: =IF($A10="",0,SUMIFS(L_Valor,L_DestTipo,"CONTA",L_DestID,$A10,L_Status,"PROJETADO")) -> 0 | N10: =IF($A10="",0,SUMIFS(L_Valor,L_OrigTipo,"CONTA",L_OrigID,$A10,L_Status,"PROJETADO")) -> 0 | O10: =IF($A10="","",$J10+$M10-$N10)
A11: =IF($B11="","","CON-"&TEXT(ROW()-4,"000000")) | D11: =IF($C11="","",IFERROR(INDEX(INS_ID,MATCH($C11,INS_NOME,0)),"?")) | H11: =IF($A11="",0,SUMIFS(L_Valor,L_DestTipo,"CONTA",L_DestID,$A11,L_Status,"REALIZADO")) -> 0 | I11: =IF($A11="",0,SUMIFS(L_Valor,L_OrigTipo,"CONTA",L_OrigID,$A11,L_Status,"REALIZADO")) -> 0 | J11: =IF($A11="","",$F11+$H11-$I11) | K11: =IF($A11="",0,SUMIFS(MM_VALSINAL,MM_CONTA,$A11)) -> 0 | L11: =IF($A11="","",$J11-$K11) | M11: =IF($A11="",0,SUMIFS(L_Valor,L_DestTipo,"CONTA",L_DestID,$A11,L_Status,"PROJETADO")) -> 0 | N11: =IF($A11="",0,SUMIFS(L_Valor,L_OrigTipo,"CONTA",L_OrigID,$A11,L_Status,"PROJETADO")) -> 0 | O11: =IF($A11="","",$J11+$M11-$N11)
A12: =IF($B12="","","CON-"&TEXT(ROW()-4,"000000")) | D12: =IF($C12="","",IFERROR(INDEX(INS_ID,MATCH($C12,INS_NOME,0)),"?")) | H12: =IF($A12="",0,SUMIFS(L_Valor,L_DestTipo,"CONTA",L_DestID,$A12,L_Status,"REALIZADO")) -> 0 | I12: =IF($A12="",0,SUMIFS(L_Valor,L_OrigTipo,"CONTA",L_OrigID,$A12,L_Status,"REALIZADO")) -> 0 | J12: =IF($A12="","",$F12+$H12-$I12) | K12: =IF($A12="",0,SUMIFS(MM_VALSINAL,MM_CONTA,$A12)) -> 0 | L12: =IF($A12="","",$J12-$K12) | M12: =IF($A12="",0,SUMIFS(L_Valor,L_DestTipo,"CONTA",L_DestID,$A12,L_Status,"PROJETADO")) -> 0 | N12: =IF($A12="",0,SUMIFS(L_Valor,L_OrigTipo,"CONTA",L_OrigID,$A12,L_Status,"PROJETADO")) -> 0 | O12: =IF($A12="","",$J12+$M12-$N12)
A13: =IF($B13="","","CON-"&TEXT(ROW()-4,"000000")) | D13: =IF($C13="","",IFERROR(INDEX(INS_ID,MATCH($C13,INS_NOME,0)),"?")) | H13: =IF($A13="",0,SUMIFS(L_Valor,L_DestTipo,"CONTA",L_DestID,$A13,L_Status,"REALIZADO")) -> 0 | I13: =IF($A13="",0,SUMIFS(L_Valor,L_OrigTipo,"CONTA",L_OrigID,$A13,L_Status,"REALIZADO")) -> 0 | J13: =IF($A13="","",$F13+$H13-$I13) | K13: =IF($A13="",0,SUMIFS(MM_VALSINAL,MM_CONTA,$A13)) -> 0 | L13: =IF($A13="","",$J13-$K13) | M13: =IF($A13="",0,SUMIFS(L_Valor,L_DestTipo,"CONTA",L_DestID,$A13,L_Status,"PROJETADO")) -> 0 | N13: =IF($A13="",0,SUMIFS(L_Valor,L_OrigTipo,"CONTA",L_OrigID,$A13,L_Status,"PROJETADO")) -> 0 | O13: =IF($A13="","",$J13+$M13-$N13)
A14: =IF($B14="","","CON-"&TEXT(ROW()-4,"000000")) | D14: =IF($C14="","",IFERROR(INDEX(INS_ID,MATCH($C14,INS_NOME,0)),"?")) | H14: =IF($A14="",0,SUMIFS(L_Valor,L_DestTipo,"CONTA",L_DestID,$A14,L_Status,"REALIZADO")) -> 0 | I14: =IF($A14="",0,SUMIFS(L_Valor,L_OrigTipo,"CONTA",L_OrigID,$A14,L_Status,"REALIZADO")) -> 0 | J14: =IF($A14="","",$F14+$H14-$I14) | K14: =IF($A14="",0,SUMIFS(MM_VALSINAL,MM_CONTA,$A14)) -> 0 | L14: =IF($A14="","",$J14-$K14) | M14: =IF($A14="",0,SUMIFS(L_Valor,L_DestTipo,"CONTA",L_DestID,$A14,L_Status,"PROJETADO")) -> 0 | N14: =IF($A14="",0,SUMIFS(L_Valor,L_OrigTipo,"CONTA",L_OrigID,$A14,L_Status,"PROJETADO")) -> 0 | O14: =IF($A14="","",$J14+$M14-$N14)
A15: =IF($B15="","","CON-"&TEXT(ROW()-4,"000000")) | D15: =IF($C15="","",IFERROR(INDEX(INS_ID,MATCH($C15,INS_NOME,0)),"?")) | H15: =IF($A15="",0,SUMIFS(L_Valor,L_DestTipo,"CONTA",L_DestID,$A15,L_Status,"REALIZADO")) -> 0 | I15: =IF($A15="",0,SUMIFS(L_Valor,L_OrigTipo,"CONTA",L_OrigID,$A15,L_Status,"REALIZADO")) -> 0 | J15: =IF($A15="","",$F15+$H15-$I15) | K15: =IF($A15="",0,SUMIFS(MM_VALSINAL,MM_CONTA,$A15)) -> 0 | L15: =IF($A15="","",$J15-$K15) | M15: =IF($A15="",0,SUMIFS(L_Valor,L_DestTipo,"CONTA",L_DestID,$A15,L_Status,"PROJETADO")) -> 0 | N15: =IF($A15="",0,SUMIFS(L_Valor,L_OrigTipo,"CONTA",L_OrigID,$A15,L_Status,"PROJETADO")) -> 0 | O15: =IF($A15="","",$J15+$M15-$N15)
A16: =IF($B16="","","CON-"&TEXT(ROW()-4,"000000")) | D16: =IF($C16="","",IFERROR(INDEX(INS_ID,MATCH($C16,INS_NOME,0)),"?")) | H16: =IF($A16="",0,SUMIFS(L_Valor,L_DestTipo,"CONTA",L_DestID,$A16,L_Status,"REALIZADO")) -> 0 | I16: =IF($A16="",0,SUMIFS(L_Valor,L_OrigTipo,"CONTA",L_OrigID,$A16,L_Status,"REALIZADO")) -> 0 | J16: =IF($A16="","",$F16+$H16-$I16) | K16: =IF($A16="",0,SUMIFS(MM_VALSINAL,MM_CONTA,$A16)) -> 0 | L16: =IF($A16="","",$J16-$K16) | M16: =IF($A16="",0,SUMIFS(L_Valor,L_DestTipo,"CONTA",L_DestID,$A16,L_Status,"PROJETADO")) -> 0 | N16: =IF($A16="",0,SUMIFS(L_Valor,L_OrigTipo,"CONTA",L_OrigID,$A16,L_Status,"PROJETADO")) -> 0 | O16: =IF($A16="","",$J16+$M16-$N16)
... A44: =IF($B44="","","CON-"&TEXT(ROW()-4,"000000")) | D44: =IF($C44="","",IFERROR(INDEX(INS_ID,MATCH($C44,INS_NOME,0)),"?")) | H44: =IF($A44="",0,SUMIFS(L_Valor,L_DestTipo,"CONTA",L_DestID,$A44,L_Status,"REALIZADO")) -> 0 | I44: =IF($A44="",0,SUMIFS(L_Valor,L_OrigTipo,"CONTA",L_OrigID,$A44,L_Status,"REALIZADO")) -> 0 | J44: =IF($A44="","",$F44+$H44-$I44) | K44: =IF($A44="",0,SUMIFS(MM_VALSINAL,MM_CONTA,$A44)) -> 0 | L44: =IF($A44="","",$J44-$K44) | M44: =IF($A44="",0,SUMIFS(L_Valor,L_DestTipo,"CONTA",L_DestID,$A44,L_Status,"PROJETADO")) -> 0 | N44: =IF($A44="",0,SUMIFS(L_Valor,L_OrigTipo,"CONTA",L_OrigID,$A44,L_Status,"PROJETADO")) -> 0 | O44: =IF($A44="","",$J44+$M44-$N44)

Sheet CAD_Cartoes
A1: CAD_CARTOES - CARTOES DE CREDITO
A2: PARA APAGAR UM REGISTRO: selecione as celulas AMARELAS da linha e pressione DELETE (limpar conteudo). NUNCA use 'Excluir linha' nem classifique (sort) esta aba: os IDs sao gerados pela posicao da linha e os vinculos seriam quebrados em silencio. Para anular um lancamento sem perder o historico use o campo Status (CANCELADO / Inativo). Para pesquisar use os filtros do cabecalho.
A4: ID_Cartao | B4: Nome | C4: Instituicao | D4: ID_Instituicao | E4: Limite | F4: Divida_Inicial | G4: Data_Divida_Inicial | H4: Dia_Fechamento | I4: Dia_Vencimento | J4: Compras_Realizadas | K4: Pagamentos_Realizados | L4: Divida_Atual | M4: Pct_Limite_Utilizado | N4: Limite_Disponivel | O4: Fechamento_Ciclo_Atual | P4: Inicio_Ciclo_Atual | Q4: Vencimento_Fatura_Atual | R4: Fatura_Atual | S4: Faturas_Futuras | T4: Parcelas_Futuras | U4: Comprometimento_Futuro | V4: Status | W4: Observacao
A5: =IF($B5="","","CAR-"&TEXT(ROW()-4,"000000")) | D5: =IF($C5="","",IFERROR(INDEX(INS_ID,MATCH($C5,INS_NOME,0)),"?")) | J5: =IF($A5="",0,SUMIFS(L_Valor,L_OrigTipo,"CARTAO",L_OrigID,$A5,L_Status,"REALIZADO")) -> 0 | K5: =IF($A5="",0,SUMIFS(L_Valor,L_DestTipo,"CARTAO",L_DestID,$A5,L_Status,"REALIZADO")) -> 0 | L5: =IF($A5="","",$F5+$J5-$K5) | M5: =IF(OR($A5="",$E5=0),0,$L5/$E5) -> 0 | N5: =IF($A5="","",$E5-$L5) | O5: =IF($A5="","",MIN(EOMONTH(DATE(YEAR(CFG_HOJE),MONTH(CFG_HOJE)+IF(DAY(CFG_HOJE)>$H5,1,0),1),0),DATE(YEAR(CFG_HOJE),MONTH(CFG_HOJE)+IF(DAY(CFG_HOJE)>$H5,1,0),1)+$H5-1)) | P5: =IF($A5="","",EDATE($O5,-1)+1) | Q5: =IF($A5="","",MIN(EOMONTH(DATE(YEAR($O5),MONTH($O5)+IF($I5>$H5,0,1),1),0),DATE(YEAR($O5),MONTH($O5)+IF($I5>$H5,0,1),1)+$I5-1)) | R5: =IF($A5="",0,SUMIFS(L_Valor,L_OrigTipo,"CARTAO",L_OrigID,$A5,L_Data,">="&$P5,L_Data,"<="&$O5,L_Status,"REALIZADO")+SUMIFS(L_Valor,L_OrigTipo,"CARTAO",L_OrigID,$A5,L_Data,">="&$P5,L_Data,"<="&$O5,L_Status,"PROJETADO")) -> 0 | S5: =IF($A5="",0,SUMIFS(L_Valor,L_OrigTipo,"CARTAO",L_OrigID,$A5,L_Data,">"&$O5,L_Status,"PROJETADO")) -> 0 | T5: =IF($A5="",0,SUMIFS(L_Valor,L_OrigTipo,"CARTAO",L_OrigID,$A5,L_Status,"PROJETADO",L_ParcID,"<>")) -> 0 | U5: =IF($A5="","",$L5+$S5)
A6: =IF($B6="","","CAR-"&TEXT(ROW()-4,"000000")) | D6: =IF($C6="","",IFERROR(INDEX(INS_ID,MATCH($C6,INS_NOME,0)),"?")) | J6: =IF($A6="",0,SUMIFS(L_Valor,L_OrigTipo,"CARTAO",L_OrigID,$A6,L_Status,"REALIZADO")) -> 0 | K6: =IF($A6="",0,SUMIFS(L_Valor,L_DestTipo,"CARTAO",L_DestID,$A6,L_Status,"REALIZADO")) -> 0 | L6: =IF($A6="","",$F6+$J6-$K6) | M6: =IF(OR($A6="",$E6=0),0,$L6/$E6) -> 0 | N6: =IF($A6="","",$E6-$L6) | O6: =IF($A6="","",MIN(EOMONTH(DATE(YEAR(CFG_HOJE),MONTH(CFG_HOJE)+IF(DAY(CFG_HOJE)>$H6,1,0),1),0),DATE(YEAR(CFG_HOJE),MONTH(CFG_HOJE)+IF(DAY(CFG_HOJE)>$H6,1,0),1)+$H6-1)) | P6: =IF($A6="","",EDATE($O6,-1)+1) | Q6: =IF($A6="","",MIN(EOMONTH(DATE(YEAR($O6),MONTH($O6)+IF($I6>$H6,0,1),1),0),DATE(YEAR($O6),MONTH($O6)+IF($I6>$H6,0,1),1)+$I6-1)) | R6: =IF($A6="",0,SUMIFS(L_Valor,L_OrigTipo,"CARTAO",L_OrigID,$A6,L_Data,">="&$P6,L_Data,"<="&$O6,L_Status,"REALIZADO")+SUMIFS(L_Valor,L_OrigTipo,"CARTAO",L_OrigID,$A6,L_Data,">="&$P6,L_Data,"<="&$O6,L_Status,"PROJETADO")) -> 0 | S6: =IF($A6="",0,SUMIFS(L_Valor,L_OrigTipo,"CARTAO",L_OrigID,$A6,L_Data,">"&$O6,L_Status,"PROJETADO")) -> 0 | T6: =IF($A6="",0,SUMIFS(L_Valor,L_OrigTipo,"CARTAO",L_OrigID,$A6,L_Status,"PROJETADO",L_ParcID,"<>")) -> 0 | U6: =IF($A6="","",$L6+$S6)
A7: =IF($B7="","","CAR-"&TEXT(ROW()-4,"000000")) | D7: =IF($C7="","",IFERROR(INDEX(INS_ID,MATCH($C7,INS_NOME,0)),"?")) | J7: =IF($A7="",0,SUMIFS(L_Valor,L_OrigTipo,"CARTAO",L_OrigID,$A7,L_Status,"REALIZADO")) -> 0 | K7: =IF($A7="",0,SUMIFS(L_Valor,L_DestTipo,"CARTAO",L_DestID,$A7,L_Status,"REALIZADO")) -> 0 | L7: =IF($A7="","",$F7+$J7-$K7) | M7: =IF(OR($A7="",$E7=0),0,$L7/$E7) -> 0 | N7: =IF($A7="","",$E7-$L7) | O7: =IF($A7="","",MIN(EOMONTH(DATE(YEAR(CFG_HOJE),MONTH(CFG_HOJE)+IF(DAY(CFG_HOJE)>$H7,1,0),1),0),DATE(YEAR(CFG_HOJE),MONTH(CFG_HOJE)+IF(DAY(CFG_HOJE)>$H7,1,0),1)+$H7-1)) | P7: =IF($A7="","",EDATE($O7,-1)+1) | Q7: =IF($A7="","",MIN(EOMONTH(DATE(YEAR($O7),MONTH($O7)+IF($I7>$H7,0,1),1),0),DATE(YEAR($O7),MONTH($O7)+IF($I7>$H7,0,1),1)+$I7-1)) | R7: =IF($A7="",0,SUMIFS(L_Valor,L_OrigTipo,"CARTAO",L_OrigID,$A7,L_Data,">="&$P7,L_Data,"<="&$O7,L_Status,"REALIZADO")+SUMIFS(L_Valor,L_OrigTipo,"CARTAO",L_OrigID,$A7,L_Data,">="&$P7,L_Data,"<="&$O7,L_Status,"PROJETADO")) -> 0 | S7: =IF($A7="",0,SUMIFS(L_Valor,L_OrigTipo,"CARTAO",L_OrigID,$A7,L_Data,">"&$O7,L_Status,"PROJETADO")) -> 0 | T7: =IF($A7="",0,SUMIFS(L_Valor,L_OrigTipo,"CARTAO",L_OrigID,$A7,L_Status,"PROJETADO",L_ParcID,"<>")) -> 0 | U7: =IF($A7="","",$L7+$S7)
A8: =IF($B8="","","CAR-"&TEXT(ROW()-4,"000000")) | D8: =IF($C8="","",IFERROR(INDEX(INS_ID,MATCH($C8,INS_NOME,0)),"?")) | J8: =IF($A8="",0,SUMIFS(L_Valor,L_OrigTipo,"CARTAO",L_OrigID,$A8,L_Status,"REALIZADO")) -> 0 | K8: =IF($A8="",0,SUMIFS(L_Valor,L_DestTipo,"CARTAO",L_DestID,$A8,L_Status,"REALIZADO")) -> 0 | L8: =IF($A8="","",$F8+$J8-$K8) | M8: =IF(OR($A8="",$E8=0),0,$L8/$E8) -> 0 | N8: =IF($A8="","",$E8-$L8) | O8: =IF($A8="","",MIN(EOMONTH(DATE(YEAR(CFG_HOJE),MONTH(CFG_HOJE)+IF(DAY(CFG_HOJE)>$H8,1,0),1),0),DATE(YEAR(CFG_HOJE),MONTH(CFG_HOJE)+IF(DAY(CFG_HOJE)>$H8,1,0),1)+$H8-1)) | P8: =IF($A8="","",EDATE($O8,-1)+1) | Q8: =IF($A8="","",MIN(EOMONTH(DATE(YEAR($O8),MONTH($O8)+IF($I8>$H8,0,1),1),0),DATE(YEAR($O8),MONTH($O8)+IF($I8>$H8,0,1),1)+$I8-1)) | R8: =IF($A8="",0,SUMIFS(L_Valor,L_OrigTipo,"CARTAO",L_OrigID,$A8,L_Data,">="&$P8,L_Data,"<="&$O8,L_Status,"REALIZADO")+SUMIFS(L_Valor,L_OrigTipo,"CARTAO",L_OrigID,$A8,L_Data,">="&$P8,L_Data,"<="&$O8,L_Status,"PROJETADO")) -> 0 | S8: =IF($A8="",0,SUMIFS(L_Valor,L_OrigTipo,"CARTAO",L_OrigID,$A8,L_Data,">"&$O8,L_Status,"PROJETADO")) -> 0 | T8: =IF($A8="",0,SUMIFS(L_Valor,L_OrigTipo,"CARTAO",L_OrigID,$A8,L_Status,"PROJETADO",L_ParcID,"<>")) -> 0 | U8: =IF($A8="","",$L8+$S8)
A9: =IF($B9="","","CAR-"&TEXT(ROW()-4,"000000")) | D9: =IF($C9="","",IFERROR(INDEX(INS_ID,MATCH($C9,INS_NOME,0)),"?")) | J9: =IF($A9="",0,SUMIFS(L_Valor,L_OrigTipo,"CARTAO",L_OrigID,$A9,L_Status,"REALIZADO")) -> 0 | K9: =IF($A9="",0,SUMIFS(L_Valor,L_DestTipo,"CARTAO",L_DestID,$A9,L_Status,"REALIZADO")) -> 0 | L9: =IF($A9="","",$F9+$J9-$K9) | M9: =IF(OR($A9="",$E9=0),0,$L9/$E9) -> 0 | N9: =IF($A9="","",$E9-$L9) | O9: =IF($A9="","",MIN(EOMONTH(DATE(YEAR(CFG_HOJE),MONTH(CFG_HOJE)+IF(DAY(CFG_HOJE)>$H9,1,0),1),0),DATE(YEAR(CFG_HOJE),MONTH(CFG_HOJE)+IF(DAY(CFG_HOJE)>$H9,1,0),1)+$H9-1)) | P9: =IF($A9="","",EDATE($O9,-1)+1) | Q9: =IF($A9="","",MIN(EOMONTH(DATE(YEAR($O9),MONTH($O9)+IF($I9>$H9,0,1),1),0),DATE(YEAR($O9),MONTH($O9)+IF($I9>$H9,0,1),1)+$I9-1)) | R9: =IF($A9="",0,SUMIFS(L_Valor,L_OrigTipo,"CARTAO",L_OrigID,$A9,L_Data,">="&$P9,L_Data,"<="&$O9,L_Status,"REALIZADO")+SUMIFS(L_Valor,L_OrigTipo,"CARTAO",L_OrigID,$A9,L_Data,">="&$P9,L_Data,"<="&$O9,L_Status,"PROJETADO")) -> 0 | S9: =IF($A9="",0,SUMIFS(L_Valor,L_OrigTipo,"CARTAO",L_OrigID,$A9,L_Data,">"&$O9,L_Status,"PROJETADO")) -> 0 | T9: =IF($A9="",0,SUMIFS(L_Valor,L_OrigTipo,"CARTAO",L_OrigID,$A9,L_Status,"PROJETADO",L_ParcID,"<>")) -> 0 | U9: =IF($A9="","",$L9+$S9)
A10: =IF($B10="","","CAR-"&TEXT(ROW()-4,"000000")) | D10: =IF($C10="","",IFERROR(INDEX(INS_ID,MATCH($C10,INS_NOME,0)),"?")) | J10: =IF($A10="",0,SUMIFS(L_Valor,L_OrigTipo,"CARTAO",L_OrigID,$A10,L_Status,"REALIZADO")) -> 0 | K10: =IF($A10="",0,SUMIFS(L_Valor,L_DestTipo,"CARTAO",L_DestID,$A10,L_Status,"REALIZADO")) -> 0 | L10: =IF($A10="","",$F10+$J10-$K10) | M10: =IF(OR($A10="",$E10=0),0,$L10/$E10) -> 0 | N10: =IF($A10="","",$E10-$L10) | O10: =IF($A10="","",MIN(EOMONTH(DATE(YEAR(CFG_HOJE),MONTH(CFG_HOJE)+IF(DAY(CFG_HOJE)>$H10,1,0),1),0),DATE(YEAR(CFG_HOJE),MONTH(CFG_HOJE)+IF(DAY(CFG_HOJE)>$H10,1,0),1)+$H10-1)) | P10: =IF($A10="","",EDATE($O10,-1)+1) | Q10: =IF($A10="","",MIN(EOMONTH(DATE(YEAR($O10),MONTH($O10)+IF($I10>$H10,0,1),1),0),DATE(YEAR($O10),MONTH($O10)+IF($I10>$H10,0,1),1)+$I10-1)) | R10: =IF($A10="",0,SUMIFS(L_Valor,L_OrigTipo,"CARTAO",L_OrigID,$A10,L_Data,">="&$P10,L_Data,"<="&$O10,L_Status,"REALIZADO")+SUMIFS(L_Valor,L_OrigTipo,"CARTAO",L_OrigID,$A10,L_Data,">="&$P10,L_Data,"<="&$O10,L_Status,"PROJETADO")) -> 0 | S10: =IF($A10="",0,SUMIFS(L_Valor,L_OrigTipo,"CARTAO",L_OrigID,$A10,L_Data,">"&$O10,L_Status,"PROJETADO")) -> 0 | T10: =IF($A10="",0,SUMIFS(L_Valor,L_OrigTipo,"CARTAO",L_OrigID,$A10,L_Status,"PROJETADO",L_ParcID,"<>")) -> 0 | U10: =IF($A10="","",$L10+$S10)
A11: =IF($B11="","","CAR-"&TEXT(ROW()-4,"000000")) | D11: =IF($C11="","",IFERROR(INDEX(INS_ID,MATCH($C11,INS_NOME,0)),"?")) | J11: =IF($A11="",0,SUMIFS(L_Valor,L_OrigTipo,"CARTAO",L_OrigID,$A11,L_Status,"REALIZADO")) -> 0 | K11: =IF($A11="",0,SUMIFS(L_Valor,L_DestTipo,"CARTAO",L_DestID,$A11,L_Status,"REALIZADO")) -> 0 | L11: =IF($A11="","",$F11+$J11-$K11) | M11: =IF(OR($A11="",$E11=0),0,$L11/$E11) -> 0 | N11: =IF($A11="","",$E11-$L11) | O11: =IF($A11="","",MIN(EOMONTH(DATE(YEAR(CFG_HOJE),MONTH(CFG_HOJE)+IF(DAY(CFG_HOJE)>$H11,1,0),1),0),DATE(YEAR(CFG_HOJE),MONTH(CFG_HOJE)+IF(DAY(CFG_HOJE)>$H11,1,0),1)+$H11-1)) | P11: =IF($A11="","",EDATE($O11,-1)+1) | Q11: =IF($A11="","",MIN(EOMONTH(DATE(YEAR($O11),MONTH($O11)+IF($I11>$H11,0,1),1),0),DATE(YEAR($O11),MONTH($O11)+IF($I11>$H11,0,1),1)+$I11-1)) | R11: =IF($A11="",0,SUMIFS(L_Valor,L_OrigTipo,"CARTAO",L_OrigID,$A11,L_Data,">="&$P11,L_Data,"<="&$O11,L_Status,"REALIZADO")+SUMIFS(L_Valor,L_OrigTipo,"CARTAO",L_OrigID,$A11,L_Data,">="&$P11,L_Data,"<="&$O11,L_Status,"PROJETADO")) -> 0 | S11: =IF($A11="",0,SUMIFS(L_Valor,L_OrigTipo,"CARTAO",L_OrigID,$A11,L_Data,">"&$O11,L_Status,"PROJETADO")) -> 0 | T11: =IF($A11="",0,SUMIFS(L_Valor,L_OrigTipo,"CARTAO",L_OrigID,$A11,L_Status,"PROJETADO",L_ParcID,"<>")) -> 0 | U11: =IF($A11="","",$L11+$S11)
A12: =IF($B12="","","CAR-"&TEXT(ROW()-4,"000000")) | D12: =IF($C12="","",IFERROR(INDEX(INS_ID,MATCH($C12,INS_NOME,0)),"?")) | J12: =IF($A12="",0,SUMIFS(L_Valor,L_OrigTipo,"CARTAO",L_OrigID,$A12,L_Status,"REALIZADO")) -> 0 | K12: =IF($A12="",0,SUMIFS(L_Valor,L_DestTipo,"CARTAO",L_DestID,$A12,L_Status,"REALIZADO")) -> 0 | L12: =IF($A12="","",$F12+$J12-$K12) | M12: =IF(OR($A12="",$E12=0),0,$L12/$E12) -> 0 | N12: =IF($A12="","",$E12-$L12) | O12: =IF($A12="","",MIN(EOMONTH(DATE(YEAR(CFG_HOJE),MONTH(CFG_HOJE)+IF(DAY(CFG_HOJE)>$H12,1,0),1),0),DATE(YEAR(CFG_HOJE),MONTH(CFG_HOJE)+IF(DAY(CFG_HOJE)>$H12,1,0),1)+$H12-1)) | P12: =IF($A12="","",EDATE($O12,-1)+1) | Q12: =IF($A12="","",MIN(EOMONTH(DATE(YEAR($O12),MONTH($O12)+IF($I12>$H12,0,1),1),0),DATE(YEAR($O12),MONTH($O12)+IF($I12>$H12,0,1),1)+$I12-1)) | R12: =IF($A12="",0,SUMIFS(L_Valor,L_OrigTipo,"CARTAO",L_OrigID,$A12,L_Data,">="&$P12,L_Data,"<="&$O12,L_Status,"REALIZADO")+SUMIFS(L_Valor,L_OrigTipo,"CARTAO",L_OrigID,$A12,L_Data,">="&$P12,L_Data,"<="&$O12,L_Status,"PROJETADO")) -> 0 | S12: =IF($A12="",0,SUMIFS(L_Valor,L_OrigTipo,"CARTAO",L_OrigID,$A12,L_Data,">"&$O12,L_Status,"PROJETADO")) -> 0 | T12: =IF($A12="",0,SUMIFS(L_Valor,L_OrigTipo,"CARTAO",L_OrigID,$A12,L_Status,"PROJETADO",L_ParcID,"<>")) -> 0 | U12: =IF($A12="","",$L12+$S12)
A13: =IF($B13="","","CAR-"&TEXT(ROW()-4,"000000")) | D13: =IF($C13="","",IFERROR(INDEX(INS_ID,MATCH($C13,INS_NOME,0)),"?")) | J13: =IF($A13="",0,SUMIFS(L_Valor,L_OrigTipo,"CARTAO",L_OrigID,$A13,L_Status,"REALIZADO")) -> 0 | K13: =IF($A13="",0,SUMIFS(L_Valor,L_DestTipo,"CARTAO",L_DestID,$A13,L_Status,"REALIZADO")) -> 0 | L13: =IF($A13="","",$F13+$J13-$K13) | M13: =IF(OR($A13="",$E13=0),0,$L13/$E13) -> 0 | N13: =IF($A13="","",$E13-$L13) | O13: =IF($A13="","",MIN(EOMONTH(DATE(YEAR(CFG_HOJE),MONTH(CFG_HOJE)+IF(DAY(CFG_HOJE)>$H13,1,0),1),0),DATE(YEAR(CFG_HOJE),MONTH(CFG_HOJE)+IF(DAY(CFG_HOJE)>$H13,1,0),1)+$H13-1)) | P13: =IF($A13="","",EDATE($O13,-1)+1) | Q13: =IF($A13="","",MIN(EOMONTH(DATE(YEAR($O13),MONTH($O13)+IF($I13>$H13,0,1),1),0),DATE(YEAR($O13),MONTH($O13)+IF($I13>$H13,0,1),1)+$I13-1)) | R13: =IF($A13="",0,SUMIFS(L_Valor,L_OrigTipo,"CARTAO",L_OrigID,$A13,L_Data,">="&$P13,L_Data,"<="&$O13,L_Status,"REALIZADO")+SUMIFS(L_Valor,L_OrigTipo,"CARTAO",L_OrigID,$A13,L_Data,">="&$P13,L_Data,"<="&$O13,L_Status,"PROJETADO")) -> 0 | S13: =IF($A13="",0,SUMIFS(L_Valor,L_OrigTipo,"CARTAO",L_OrigID,$A13,L_Data,">"&$O13,L_Status,"PROJETADO")) -> 0 | T13: =IF($A13="",0,SUMIFS(L_Valor,L_OrigTipo,"CARTAO",L_OrigID,$A13,L_Status,"PROJETADO",L_ParcID,"<>")) -> 0 | U13: =IF($A13="","",$L13+$S13)
A14: =IF($B14="","","CAR-"&TEXT(ROW()-4,"000000")) | D14: =IF($C14="","",IFERROR(INDEX(INS_ID,MATCH($C14,INS_NOME,0)),"?")) | J14: =IF($A14="",0,SUMIFS(L_Valor,L_OrigTipo,"CARTAO",L_OrigID,$A14,L_Status,"REALIZADO")) -> 0 | K14: =IF($A14="",0,SUMIFS(L_Valor,L_DestTipo,"CARTAO",L_DestID,$A14,L_Status,"REALIZADO")) -> 0 | L14: =IF($A14="","",$F14+$J14-$K14) | M14: =IF(OR($A14="",$E14=0),0,$L14/$E14) -> 0 | N14: =IF($A14="","",$E14-$L14) | O14: =IF($A14="","",MIN(EOMONTH(DATE(YEAR(CFG_HOJE),MONTH(CFG_HOJE)+IF(DAY(CFG_HOJE)>$H14,1,0),1),0),DATE(YEAR(CFG_HOJE),MONTH(CFG_HOJE)+IF(DAY(CFG_HOJE)>$H14,1,0),1)+$H14-1)) | P14: =IF($A14="","",EDATE($O14,-1)+1) | Q14: =IF($A14="","",MIN(EOMONTH(DATE(YEAR($O14),MONTH($O14)+IF($I14>$H14,0,1),1),0),DATE(YEAR($O14),MONTH($O14)+IF($I14>$H14,0,1),1)+$I14-1)) | R14: =IF($A14="",0,SUMIFS(L_Valor,L_OrigTipo,"CARTAO",L_OrigID,$A14,L_Data,">="&$P14,L_Data,"<="&$O14,L_Status,"REALIZADO")+SUMIFS(L_Valor,L_OrigTipo,"CARTAO",L_OrigID,$A14,L_Data,">="&$P14,L_Data,"<="&$O14,L_Status,"PROJETADO")) -> 0 | S14: =IF($A14="",0,SUMIFS(L_Valor,L_OrigTipo,"CARTAO",L_OrigID,$A14,L_Data,">"&$O14,L_Status,"PROJETADO")) -> 0 | T14: =IF($A14="",0,SUMIFS(L_Valor,L_OrigTipo,"CARTAO",L_OrigID,$A14,L_Status,"PROJETADO",L_ParcID,"<>")) -> 0 | U14: =IF($A14="","",$L14+$S14)
A15: =IF($B15="","","CAR-"&TEXT(ROW()-4,"000000")) | D15: =IF($C15="","",IFERROR(INDEX(INS_ID,MATCH($C15,INS_NOME,0)),"?")) | J15: =IF($A15="",0,SUMIFS(L_Valor,L_OrigTipo,"CARTAO",L_OrigID,$A15,L_Status,"REALIZADO")) -> 0 | K15: =IF($A15="",0,SUMIFS(L_Valor,L_DestTipo,"CARTAO",L_DestID,$A15,L_Status,"REALIZADO")) -> 0 | L15: =IF($A15="","",$F15+$J15-$K15) | M15: =IF(OR($A15="",$E15=0),0,$L15/$E15) -> 0 | N15: =IF($A15="","",$E15-$L15) | O15: =IF($A15="","",MIN(EOMONTH(DATE(YEAR(CFG_HOJE),MONTH(CFG_HOJE)+IF(DAY(CFG_HOJE)>$H15,1,0),1),0),DATE(YEAR(CFG_HOJE),MONTH(CFG_HOJE)+IF(DAY(CFG_HOJE)>$H15,1,0),1)+$H15-1)) | P15: =IF($A15="","",EDATE($O15,-1)+1) | Q15: =IF($A15="","",MIN(EOMONTH(DATE(YEAR($O15),MONTH($O15)+IF($I15>$H15,0,1),1),0),DATE(YEAR($O15),MONTH($O15)+IF($I15>$H15,0,1),1)+$I15-1)) | R15: =IF($A15="",0,SUMIFS(L_Valor,L_OrigTipo,"CARTAO",L_OrigID,$A15,L_Data,">="&$P15,L_Data,"<="&$O15,L_Status,"REALIZADO")+SUMIFS(L_Valor,L_OrigTipo,"CARTAO",L_OrigID,$A15,L_Data,">="&$P15,L_Data,"<="&$O15,L_Status,"PROJETADO")) -> 0 | S15: =IF($A15="",0,SUMIFS(L_Valor,L_OrigTipo,"CARTAO",L_OrigID,$A15,L_Data,">"&$O15,L_Status,"PROJETADO")) -> 0 | T15: =IF($A15="",0,SUMIFS(L_Valor,L_OrigTipo,"CARTAO",L_OrigID,$A15,L_Status,"PROJETADO",L_ParcID,"<>")) -> 0 | U15: =IF($A15="","",$L15+$S15)
A16: =IF($B16="","","CAR-"&TEXT(ROW()-4,"000000")) | D16: =IF($C16="","",IFERROR(INDEX(INS_ID,MATCH($C16,INS_NOME,0)),"?")) | J16: =IF($A16="",0,SUMIFS(L_Valor,L_OrigTipo,"CARTAO",L_OrigID,$A16,L_Status,"REALIZADO")) -> 0 | K16: =IF($A16="",0,SUMIFS(L_Valor,L_DestTipo,"CARTAO",L_DestID,$A16,L_Status,"REALIZADO")) -> 0 | L16: =IF($A16="","",$F16+$J16-$K16) | M16: =IF(OR($A16="",$E16=0),0,$L16/$E16) -> 0 | N16: =IF($A16="","",$E16-$L16) | O16: =IF($A16="","",MIN(EOMONTH(DATE(YEAR(CFG_HOJE),MONTH(CFG_HOJE)+IF(DAY(CFG_HOJE)>$H16,1,0),1),0),DATE(YEAR(CFG_HOJE),MONTH(CFG_HOJE)+IF(DAY(CFG_HOJE)>$H16,1,0),1)+$H16-1)) | P16: =IF($A16="","",EDATE($O16,-1)+1) | Q16: =IF($A16="","",MIN(EOMONTH(DATE(YEAR($O16),MONTH($O16)+IF($I16>$H16,0,1),1),0),DATE(YEAR($O16),MONTH($O16)+IF($I16>$H16,0,1),1)+$I16-1)) | R16: =IF($A16="",0,SUMIFS(L_Valor,L_OrigTipo,"CARTAO",L_OrigID,$A16,L_Data,">="&$P16,L_Data,"<="&$O16,L_Status,"REALIZADO")+SUMIFS(L_Valor,L_OrigTipo,"CARTAO",L_OrigID,$A16,L_Data,">="&$P16,L_Data,"<="&$O16,L_Status,"PROJETADO")) -> 0 | S16: =IF($A16="",0,SUMIFS(L_Valor,L_OrigTipo,"CARTAO",L_OrigID,$A16,L_Data,">"&$O16,L_Status,"PROJETADO")) -> 0 | T16: =IF($A16="",0,SUMIFS(L_Valor,L_OrigTipo,"CARTAO",L_OrigID,$A16,L_Status,"PROJETADO",L_ParcID,"<>")) -> 0 | U16: =IF($A16="","",$L16+$S16)
... A44: =IF($B44="","","CAR-"&TEXT(ROW()-4,"000000")) | D44: =IF($C44="","",IFERROR(INDEX(INS_ID,MATCH($C44,INS_NOME,0)),"?")) | J44: =IF($A44="",0,SUMIFS(L_Valor,L_OrigTipo,"CARTAO",L_OrigID,$A44,L_Status,"REALIZADO")) -> 0 | K44: =IF($A44="",0,SUMIFS(L_Valor,L_DestTipo,"CARTAO",L_DestID,$A44,L_Status,"REALIZADO")) -> 0 | L44: =IF($A44="","",$F44+$J44-$K44) | M44: =IF(OR($A44="",$E44=0),0,$L44/$E44) -> 0 | N44: =IF($A44="","",$E44-$L44) | O44: =IF($A44="","",MIN(EOMONTH(DATE(YEAR(CFG_HOJE),MONTH(CFG_HOJE)+IF(DAY(CFG_HOJE)>$H44,1,0),1),0),DATE(YEAR(CFG_HOJE),MONTH(CFG_HOJE)+IF(DAY(CFG_HOJE)>$H44,1,0),1)+$H44-1)) | P44: =IF($A44="","",EDATE($O44,-1)+1) | Q44: =IF($A44="","",MIN(EOMONTH(DATE(YEAR($O44),MONTH($O44)+IF($I44>$H44,0,1),1),0),DATE(YEAR($O44),MONTH($O44)+IF($I44>$H44,0,1),1)+$I44-1)) | R44: =IF($A44="",0,SUMIFS(L_Valor,L_OrigTipo,"CARTAO",L_OrigID,$A44,L_Data,">="&$P44,L_Data,"<="&$O44,L_Status,"REALIZADO")+SUMIFS(L_Valor,L_OrigTipo,"CARTAO",L_OrigID,$A44,L_Data,">="&$P44,L_Data,"<="&$O44,L_Status,"PROJETADO")) -> 0 | S44: =IF($A44="",0,SUMIFS(L_Valor,L_OrigTipo,"CARTAO",L_OrigID,$A44,L_Data,">"&$O44,L_Status,"PROJETADO")) -> 0 | T44: =IF($A44="",0,SUMIFS(L_Valor,L_OrigTipo,"CARTAO",L_OrigID,$A44,L_Status,"PROJETADO",L_ParcID,"<>")) -> 0 | U44: =IF($A44="","",$L44+$S44)

Sheet CAD_Investimentos
A1: CAD_INVESTIMENTOS - FONDOS MUTUOS, AHORRO A PLAZO E OUTROS
A2: PARA APAGAR UM REGISTRO: selecione as celulas AMARELAS da linha e pressione DELETE (limpar conteudo). NUNCA use 'Excluir linha' nem classifique (sort) esta aba: os IDs sao gerados pela posicao da linha e os vinculos seriam quebrados em silencio. Para anular um lancamento sem perder o historico use o campo Status (CANCELADO / Inativo). Para pesquisar use os filtros do cabecalho.
A4: ID_Investimento | B4: Nome | C4: Instituicao | D4: ID_Instituicao | E4: Tipo | F4: Valor_Inicial_Aplicado | G4: Data_Inicial | H4: Base_Rendimento | I4: Taxa | J4: Prazo_Meses | K4: Data_Vencimento | L4: Aportes_Realizados | M4: Resgates_Realizados | N4: Rendimento_Realizado | O4: Saldo_Atual | P4: Principal_Atual | Q4: Rendimento_No_Saldo | R4: Meses_Ate_Horizonte | S4: Rendimento_Projetado | T4: Rendimento_Estimado_Taxa | U4: Valor_Estimado_Vencimento | V4: Aportes_Projetados | W4: Resgates_Projetados | X4: Status | Y4: Observacao
A5: =IF($B5="","","INV-"&TEXT(ROW()-4,"000000")) | D5: =IF($C5="","",IFERROR(INDEX(INS_ID,MATCH($C5,INS_NOME,0)),"?")) | K5: =IF($A5="","",IF($J5>0,EDATE($G5,$J5),"")) | L5: =IF($A5="",0,SUMIFS(L_Valor,L_DestTipo,"INVESTIMENTO",L_DestID,$A5,L_Tipo,"APORTE",L_Status,"REALIZADO")) -> 0 | M5: =IF($A5="",0,SUMIFS(L_Valor,L_OrigTipo,"INVESTIMENTO",L_OrigID,$A5,L_Status,"REALIZADO")) -> 0 | N5: =IF($A5="",0,SUMIFS(L_Valor,L_DestTipo,"INVESTIMENTO",L_DestID,$A5,L_Tipo,"RENDIMENTO",L_Status,"REALIZADO")) -> 0 | O5: =IF($A5="","",$F5+$L5+$N5-$M5) | P5: =IF($A5="","",MAX(0,$F5+$L5-$M5)) | Q5: =IF($A5="","",$O5-$P5) | R5: =IF($A5="","",IF($K5="",12,MAX(0,(YEAR($K5)-YEAR(CFG_HOJE))*12+MONTH($K5)-MONTH(CFG_HOJE)))) | S5: =IF($A5="",0,SUMIFS(L_Valor,L_DestTipo,"INVESTIMENTO",L_DestID,$A5,L_Tipo,"RENDIMENTO",L_Status,"PROJETADO")) -> 0 | T5: =IF($A5="",0,IF($H5="Taxa anual",ROUND($O5*((1+$I5)^($R5/12)-1),0),IF($H5="Taxa mensal",ROUND($O5*((1+$I5)^$R5-1),0),IF($H5="Valor fixo",$I5,0)))) -> 0 | U5: =IF($A5="","",$O5+$S5+$V5-$W5) | V5: =IF($A5="",0,SUMIFS(L_Valor,L_DestTipo,"INVESTIMENTO",L_DestID,$A5,L_Tipo,"APORTE",L_Status,"PROJETADO")) -> 0 | W5: =IF($A5="",0,SUMIFS(L_Valor,L_OrigTipo,"INVESTIMENTO",L_OrigID,$A5,L_Status,"PROJETADO")) -> 0
A6: =IF($B6="","","INV-"&TEXT(ROW()-4,"000000")) | D6: =IF($C6="","",IFERROR(INDEX(INS_ID,MATCH($C6,INS_NOME,0)),"?")) | K6: =IF($A6="","",IF($J6>0,EDATE($G6,$J6),"")) | L6: =IF($A6="",0,SUMIFS(L_Valor,L_DestTipo,"INVESTIMENTO",L_DestID,$A6,L_Tipo,"APORTE",L_Status,"REALIZADO")) -> 0 | M6: =IF($A6="",0,SUMIFS(L_Valor,L_OrigTipo,"INVESTIMENTO",L_OrigID,$A6,L_Status,"REALIZADO")) -> 0 | N6: =IF($A6="",0,SUMIFS(L_Valor,L_DestTipo,"INVESTIMENTO",L_DestID,$A6,L_Tipo,"RENDIMENTO",L_Status,"REALIZADO")) -> 0 | O6: =IF($A6="","",$F6+$L6+$N6-$M6) | P6: =IF($A6="","",MAX(0,$F6+$L6-$M6)) | Q6: =IF($A6="","",$O6-$P6) | R6: =IF($A6="","",IF($K6="",12,MAX(0,(YEAR($K6)-YEAR(CFG_HOJE))*12+MONTH($K6)-MONTH(CFG_HOJE)))) | S6: =IF($A6="",0,SUMIFS(L_Valor,L_DestTipo,"INVESTIMENTO",L_DestID,$A6,L_Tipo,"RENDIMENTO",L_Status,"PROJETADO")) -> 0 | T6: =IF($A6="",0,IF($H6="Taxa anual",ROUND($O6*((1+$I6)^($R6/12)-1),0),IF($H6="Taxa mensal",ROUND($O6*((1+$I6)^$R6-1),0),IF($H6="Valor fixo",$I6,0)))) -> 0 | U6: =IF($A6="","",$O6+$S6+$V6-$W6) | V6: =IF($A6="",0,SUMIFS(L_Valor,L_DestTipo,"INVESTIMENTO",L_DestID,$A6,L_Tipo,"APORTE",L_Status,"PROJETADO")) -> 0 | W6: =IF($A6="",0,SUMIFS(L_Valor,L_OrigTipo,"INVESTIMENTO",L_OrigID,$A6,L_Status,"PROJETADO")) -> 0
A7: =IF($B7="","","INV-"&TEXT(ROW()-4,"000000")) | D7: =IF($C7="","",IFERROR(INDEX(INS_ID,MATCH($C7,INS_NOME,0)),"?")) | K7: =IF($A7="","",IF($J7>0,EDATE($G7,$J7),"")) | L7: =IF($A7="",0,SUMIFS(L_Valor,L_DestTipo,"INVESTIMENTO",L_DestID,$A7,L_Tipo,"APORTE",L_Status,"REALIZADO")) -> 0 | M7: =IF($A7="",0,SUMIFS(L_Valor,L_OrigTipo,"INVESTIMENTO",L_OrigID,$A7,L_Status,"REALIZADO")) -> 0 | N7: =IF($A7="",0,SUMIFS(L_Valor,L_DestTipo,"INVESTIMENTO",L_DestID,$A7,L_Tipo,"RENDIMENTO",L_Status,"REALIZADO")) -> 0 | O7: =IF($A7="","",$F7+$L7+$N7-$M7) | P7: =IF($A7="","",MAX(0,$F7+$L7-$M7)) | Q7: =IF($A7="","",$O7-$P7) | R7: =IF($A7="","",IF($K7="",12,MAX(0,(YEAR($K7)-YEAR(CFG_HOJE))*12+MONTH($K7)-MONTH(CFG_HOJE)))) | S7: =IF($A7="",0,SUMIFS(L_Valor,L_DestTipo,"INVESTIMENTO",L_DestID,$A7,L_Tipo,"RENDIMENTO",L_Status,"PROJETADO")) -> 0 | T7: =IF($A7="",0,IF($H7="Taxa anual",ROUND($O7*((1+$I7)^($R7/12)-1),0),IF($H7="Taxa mensal",ROUND($O7*((1+$I7)^$R7-1),0),IF($H7="Valor fixo",$I7,0)))) -> 0 | U7: =IF($A7="","",$O7+$S7+$V7-$W7) | V7: =IF($A7="",0,SUMIFS(L_Valor,L_DestTipo,"INVESTIMENTO",L_DestID,$A7,L_Tipo,"APORTE",L_Status,"PROJETADO")) -> 0 | W7: =IF($A7="",0,SUMIFS(L_Valor,L_OrigTipo,"INVESTIMENTO",L_OrigID,$A7,L_Status,"PROJETADO")) -> 0
A8: =IF($B8="","","INV-"&TEXT(ROW()-4,"000000")) | D8: =IF($C8="","",IFERROR(INDEX(INS_ID,MATCH($C8,INS_NOME,0)),"?")) | K8: =IF($A8="","",IF($J8>0,EDATE($G8,$J8),"")) | L8: =IF($A8="",0,SUMIFS(L_Valor,L_DestTipo,"INVESTIMENTO",L_DestID,$A8,L_Tipo,"APORTE",L_Status,"REALIZADO")) -> 0 | M8: =IF($A8="",0,SUMIFS(L_Valor,L_OrigTipo,"INVESTIMENTO",L_OrigID,$A8,L_Status,"REALIZADO")) -> 0 | N8: =IF($A8="",0,SUMIFS(L_Valor,L_DestTipo,"INVESTIMENTO",L_DestID,$A8,L_Tipo,"RENDIMENTO",L_Status,"REALIZADO")) -> 0 | O8: =IF($A8="","",$F8+$L8+$N8-$M8) | P8: =IF($A8="","",MAX(0,$F8+$L8-$M8)) | Q8: =IF($A8="","",$O8-$P8) | R8: =IF($A8="","",IF($K8="",12,MAX(0,(YEAR($K8)-YEAR(CFG_HOJE))*12+MONTH($K8)-MONTH(CFG_HOJE)))) | S8: =IF($A8="",0,SUMIFS(L_Valor,L_DestTipo,"INVESTIMENTO",L_DestID,$A8,L_Tipo,"RENDIMENTO",L_Status,"PROJETADO")) -> 0 | T8: =IF($A8="",0,IF($H8="Taxa anual",ROUND($O8*((1+$I8)^($R8/12)-1),0),IF($H8="Taxa mensal",ROUND($O8*((1+$I8)^$R8-1),0),IF($H8="Valor fixo",$I8,0)))) -> 0 | U8: =IF($A8="","",$O8+$S8+$V8-$W8) | V8: =IF($A8="",0,SUMIFS(L_Valor,L_DestTipo,"INVESTIMENTO",L_DestID,$A8,L_Tipo,"APORTE",L_Status,"PROJETADO")) -> 0 | W8: =IF($A8="",0,SUMIFS(L_Valor,L_OrigTipo,"INVESTIMENTO",L_OrigID,$A8,L_Status,"PROJETADO")) -> 0
A9: =IF($B9="","","INV-"&TEXT(ROW()-4,"000000")) | D9: =IF($C9="","",IFERROR(INDEX(INS_ID,MATCH($C9,INS_NOME,0)),"?")) | K9: =IF($A9="","",IF($J9>0,EDATE($G9,$J9),"")) | L9: =IF($A9="",0,SUMIFS(L_Valor,L_DestTipo,"INVESTIMENTO",L_DestID,$A9,L_Tipo,"APORTE",L_Status,"REALIZADO")) -> 0 | M9: =IF($A9="",0,SUMIFS(L_Valor,L_OrigTipo,"INVESTIMENTO",L_OrigID,$A9,L_Status,"REALIZADO")) -> 0 | N9: =IF($A9="",0,SUMIFS(L_Valor,L_DestTipo,"INVESTIMENTO",L_DestID,$A9,L_Tipo,"RENDIMENTO",L_Status,"REALIZADO")) -> 0 | O9: =IF($A9="","",$F9+$L9+$N9-$M9) | P9: =IF($A9="","",MAX(0,$F9+$L9-$M9)) | Q9: =IF($A9="","",$O9-$P9) | R9: =IF($A9="","",IF($K9="",12,MAX(0,(YEAR($K9)-YEAR(CFG_HOJE))*12+MONTH($K9)-MONTH(CFG_HOJE)))) | S9: =IF($A9="",0,SUMIFS(L_Valor,L_DestTipo,"INVESTIMENTO",L_DestID,$A9,L_Tipo,"RENDIMENTO",L_Status,"PROJETADO")) -> 0 | T9: =IF($A9="",0,IF($H9="Taxa anual",ROUND($O9*((1+$I9)^($R9/12)-1),0),IF($H9="Taxa mensal",ROUND($O9*((1+$I9)^$R9-1),0),IF($H9="Valor fixo",$I9,0)))) -> 0 | U9: =IF($A9="","",$O9+$S9+$V9-$W9) | V9: =IF($A9="",0,SUMIFS(L_Valor,L_DestTipo,"INVESTIMENTO",L_DestID,$A9,L_Tipo,"APORTE",L_Status,"PROJETADO")) -> 0 | W9: =IF($A9="",0,SUMIFS(L_Valor,L_OrigTipo,"INVESTIMENTO",L_OrigID,$A9,L_Status,"PROJETADO")) -> 0
A10: =IF($B10="","","INV-"&TEXT(ROW()-4,"000000")) | D10: =IF($C10="","",IFERROR(INDEX(INS_ID,MATCH($C10,INS_NOME,0)),"?")) | K10: =IF($A10="","",IF($J10>0,EDATE($G10,$J10),"")) | L10: =IF($A10="",0,SUMIFS(L_Valor,L_DestTipo,"INVESTIMENTO",L_DestID,$A10,L_Tipo,"APORTE",L_Status,"REALIZADO")) -> 0 | M10: =IF($A10="",0,SUMIFS(L_Valor,L_OrigTipo,"INVESTIMENTO",L_OrigID,$A10,L_Status,"REALIZADO")) -> 0 | N10: =IF($A10="",0,SUMIFS(L_Valor,L_DestTipo,"INVESTIMENTO",L_DestID,$A10,L_Tipo,"RENDIMENTO",L_Status,"REALIZADO")) -> 0 | O10: =IF($A10="","",$F10+$L10+$N10-$M10) | P10: =IF($A10="","",MAX(0,$F10+$L10-$M10)) | Q10: =IF($A10="","",$O10-$P10) | R10: =IF($A10="","",IF($K10="",12,MAX(0,(YEAR($K10)-YEAR(CFG_HOJE))*12+MONTH($K10)-MONTH(CFG_HOJE)))) | S10: =IF($A10="",0,SUMIFS(L_Valor,L_DestTipo,"INVESTIMENTO",L_DestID,$A10,L_Tipo,"RENDIMENTO",L_Status,"PROJETADO")) -> 0 | T10: =IF($A10="",0,IF($H10="Taxa anual",ROUND($O10*((1+$I10)^($R10/12)-1),0),IF($H10="Taxa mensal",ROUND($O10*((1+$I10)^$R10-1),0),IF($H10="Valor fixo",$I10,0)))) -> 0 | U10: =IF($A10="","",$O10+$S10+$V10-$W10) | V10: =IF($A10="",0,SUMIFS(L_Valor,L_DestTipo,"INVESTIMENTO",L_DestID,$A10,L_Tipo,"APORTE",L_Status,"PROJETADO")) -> 0 | W10: =IF($A10="",0,SUMIFS(L_Valor,L_OrigTipo,"INVESTIMENTO",L_OrigID,$A10,L_Status,"PROJETADO")) -> 0
A11: =IF($B11="","","INV-"&TEXT(ROW()-4,"000000")) | D11: =IF($C11="","",IFERROR(INDEX(INS_ID,MATCH($C11,INS_NOME,0)),"?")) | K11: =IF($A11="","",IF($J11>0,EDATE($G11,$J11),"")) | L11: =IF($A11="",0,SUMIFS(L_Valor,L_DestTipo,"INVESTIMENTO",L_DestID,$A11,L_Tipo,"APORTE",L_Status,"REALIZADO")) -> 0 | M11: =IF($A11="",0,SUMIFS(L_Valor,L_OrigTipo,"INVESTIMENTO",L_OrigID,$A11,L_Status,"REALIZADO")) -> 0 | N11: =IF($A11="",0,SUMIFS(L_Valor,L_DestTipo,"INVESTIMENTO",L_DestID,$A11,L_Tipo,"RENDIMENTO",L_Status,"REALIZADO")) -> 0 | O11: =IF($A11="","",$F11+$L11+$N11-$M11) | P11: =IF($A11="","",MAX(0,$F11+$L11-$M11)) | Q11: =IF($A11="","",$O11-$P11) | R11: =IF($A11="","",IF($K11="",12,MAX(0,(YEAR($K11)-YEAR(CFG_HOJE))*12+MONTH($K11)-MONTH(CFG_HOJE)))) | S11: =IF($A11="",0,SUMIFS(L_Valor,L_DestTipo,"INVESTIMENTO",L_DestID,$A11,L_Tipo,"RENDIMENTO",L_Status,"PROJETADO")) -> 0 | T11: =IF($A11="",0,IF($H11="Taxa anual",ROUND($O11*((1+$I11)^($R11/12)-1),0),IF($H11="Taxa mensal",ROUND($O11*((1+$I11)^$R11-1),0),IF($H11="Valor fixo",$I11,0)))) -> 0 | U11: =IF($A11="","",$O11+$S11+$V11-$W11) | V11: =IF($A11="",0,SUMIFS(L_Valor,L_DestTipo,"INVESTIMENTO",L_DestID,$A11,L_Tipo,"APORTE",L_Status,"PROJETADO")) -> 0 | W11: =IF($A11="",0,SUMIFS(L_Valor,L_OrigTipo,"INVESTIMENTO",L_OrigID,$A11,L_Status,"PROJETADO")) -> 0
A12: =IF($B12="","","INV-"&TEXT(ROW()-4,"000000")) | D12: =IF($C12="","",IFERROR(INDEX(INS_ID,MATCH($C12,INS_NOME,0)),"?")) | K12: =IF($A12="","",IF($J12>0,EDATE($G12,$J12),"")) | L12: =IF($A12="",0,SUMIFS(L_Valor,L_DestTipo,"INVESTIMENTO",L_DestID,$A12,L_Tipo,"APORTE",L_Status,"REALIZADO")) -> 0 | M12: =IF($A12="",0,SUMIFS(L_Valor,L_OrigTipo,"INVESTIMENTO",L_OrigID,$A12,L_Status,"REALIZADO")) -> 0 | N12: =IF($A12="",0,SUMIFS(L_Valor,L_DestTipo,"INVESTIMENTO",L_DestID,$A12,L_Tipo,"RENDIMENTO",L_Status,"REALIZADO")) -> 0 | O12: =IF($A12="","",$F12+$L12+$N12-$M12) | P12: =IF($A12="","",MAX(0,$F12+$L12-$M12)) | Q12: =IF($A12="","",$O12-$P12) | R12: =IF($A12="","",IF($K12="",12,MAX(0,(YEAR($K12)-YEAR(CFG_HOJE))*12+MONTH($K12)-MONTH(CFG_HOJE)))) | S12: =IF($A12="",0,SUMIFS(L_Valor,L_DestTipo,"INVESTIMENTO",L_DestID,$A12,L_Tipo,"RENDIMENTO",L_Status,"PROJETADO")) -> 0 | T12: =IF($A12="",0,IF($H12="Taxa anual",ROUND($O12*((1+$I12)^($R12/12)-1),0),IF($H12="Taxa mensal",ROUND($O12*((1+$I12)^$R12-1),0),IF($H12="Valor fixo",$I12,0)))) -> 0 | U12: =IF($A12="","",$O12+$S12+$V12-$W12) | V12: =IF($A12="",0,SUMIFS(L_Valor,L_DestTipo,"INVESTIMENTO",L_DestID,$A12,L_Tipo,"APORTE",L_Status,"PROJETADO")) -> 0 | W12: =IF($A12="",0,SUMIFS(L_Valor,L_OrigTipo,"INVESTIMENTO",L_OrigID,$A12,L_Status,"PROJETADO")) -> 0
A13: =IF($B13="","","INV-"&TEXT(ROW()-4,"000000")) | D13: =IF($C13="","",IFERROR(INDEX(INS_ID,MATCH($C13,INS_NOME,0)),"?")) | K13: =IF($A13="","",IF($J13>0,EDATE($G13,$J13),"")) | L13: =IF($A13="",0,SUMIFS(L_Valor,L_DestTipo,"INVESTIMENTO",L_DestID,$A13,L_Tipo,"APORTE",L_Status,"REALIZADO")) -> 0 | M13: =IF($A13="",0,SUMIFS(L_Valor,L_OrigTipo,"INVESTIMENTO",L_OrigID,$A13,L_Status,"REALIZADO")) -> 0 | N13: =IF($A13="",0,SUMIFS(L_Valor,L_DestTipo,"INVESTIMENTO",L_DestID,$A13,L_Tipo,"RENDIMENTO",L_Status,"REALIZADO")) -> 0 | O13: =IF($A13="","",$F13+$L13+$N13-$M13) | P13: =IF($A13="","",MAX(0,$F13+$L13-$M13)) | Q13: =IF($A13="","",$O13-$P13) | R13: =IF($A13="","",IF($K13="",12,MAX(0,(YEAR($K13)-YEAR(CFG_HOJE))*12+MONTH($K13)-MONTH(CFG_HOJE)))) | S13: =IF($A13="",0,SUMIFS(L_Valor,L_DestTipo,"INVESTIMENTO",L_DestID,$A13,L_Tipo,"RENDIMENTO",L_Status,"PROJETADO")) -> 0 | T13: =IF($A13="",0,IF($H13="Taxa anual",ROUND($O13*((1+$I13)^($R13/12)-1),0),IF($H13="Taxa mensal",ROUND($O13*((1+$I13)^$R13-1),0),IF($H13="Valor fixo",$I13,0)))) -> 0 | U13: =IF($A13="","",$O13+$S13+$V13-$W13) | V13: =IF($A13="",0,SUMIFS(L_Valor,L_DestTipo,"INVESTIMENTO",L_DestID,$A13,L_Tipo,"APORTE",L_Status,"PROJETADO")) -> 0 | W13: =IF($A13="",0,SUMIFS(L_Valor,L_OrigTipo,"INVESTIMENTO",L_OrigID,$A13,L_Status,"PROJETADO")) -> 0
A14: =IF($B14="","","INV-"&TEXT(ROW()-4,"000000")) | D14: =IF($C14="","",IFERROR(INDEX(INS_ID,MATCH($C14,INS_NOME,0)),"?")) | K14: =IF($A14="","",IF($J14>0,EDATE($G14,$J14),"")) | L14: =IF($A14="",0,SUMIFS(L_Valor,L_DestTipo,"INVESTIMENTO",L_DestID,$A14,L_Tipo,"APORTE",L_Status,"REALIZADO")) -> 0 | M14: =IF($A14="",0,SUMIFS(L_Valor,L_OrigTipo,"INVESTIMENTO",L_OrigID,$A14,L_Status,"REALIZADO")) -> 0 | N14: =IF($A14="",0,SUMIFS(L_Valor,L_DestTipo,"INVESTIMENTO",L_DestID,$A14,L_Tipo,"RENDIMENTO",L_Status,"REALIZADO")) -> 0 | O14: =IF($A14="","",$F14+$L14+$N14-$M14) | P14: =IF($A14="","",MAX(0,$F14+$L14-$M14)) | Q14: =IF($A14="","",$O14-$P14) | R14: =IF($A14="","",IF($K14="",12,MAX(0,(YEAR($K14)-YEAR(CFG_HOJE))*12+MONTH($K14)-MONTH(CFG_HOJE)))) | S14: =IF($A14="",0,SUMIFS(L_Valor,L_DestTipo,"INVESTIMENTO",L_DestID,$A14,L_Tipo,"RENDIMENTO",L_Status,"PROJETADO")) -> 0 | T14: =IF($A14="",0,IF($H14="Taxa anual",ROUND($O14*((1+$I14)^($R14/12)-1),0),IF($H14="Taxa mensal",ROUND($O14*((1+$I14)^$R14-1),0),IF($H14="Valor fixo",$I14,0)))) -> 0 | U14: =IF($A14="","",$O14+$S14+$V14-$W14) | V14: =IF($A14="",0,SUMIFS(L_Valor,L_DestTipo,"INVESTIMENTO",L_DestID,$A14,L_Tipo,"APORTE",L_Status,"PROJETADO")) -> 0 | W14: =IF($A14="",0,SUMIFS(L_Valor,L_OrigTipo,"INVESTIMENTO",L_OrigID,$A14,L_Status,"PROJETADO")) -> 0
A15: =IF($B15="","","INV-"&TEXT(ROW()-4,"000000")) | D15: =IF($C15="","",IFERROR(INDEX(INS_ID,MATCH($C15,INS_NOME,0)),"?")) | K15: =IF($A15="","",IF($J15>0,EDATE($G15,$J15),"")) | L15: =IF($A15="",0,SUMIFS(L_Valor,L_DestTipo,"INVESTIMENTO",L_DestID,$A15,L_Tipo,"APORTE",L_Status,"REALIZADO")) -> 0 | M15: =IF($A15="",0,SUMIFS(L_Valor,L_OrigTipo,"INVESTIMENTO",L_OrigID,$A15,L_Status,"REALIZADO")) -> 0 | N15: =IF($A15="",0,SUMIFS(L_Valor,L_DestTipo,"INVESTIMENTO",L_DestID,$A15,L_Tipo,"RENDIMENTO",L_Status,"REALIZADO")) -> 0 | O15: =IF($A15="","",$F15+$L15+$N15-$M15) | P15: =IF($A15="","",MAX(0,$F15+$L15-$M15)) | Q15: =IF($A15="","",$O15-$P15) | R15: =IF($A15="","",IF($K15="",12,MAX(0,(YEAR($K15)-YEAR(CFG_HOJE))*12+MONTH($K15)-MONTH(CFG_HOJE)))) | S15: =IF($A15="",0,SUMIFS(L_Valor,L_DestTipo,"INVESTIMENTO",L_DestID,$A15,L_Tipo,"RENDIMENTO",L_Status,"PROJETADO")) -> 0 | T15: =IF($A15="",0,IF($H15="Taxa anual",ROUND($O15*((1+$I15)^($R15/12)-1),0),IF($H15="Taxa mensal",ROUND($O15*((1+$I15)^$R15-1),0),IF($H15="Valor fixo",$I15,0)))) -> 0 | U15: =IF($A15="","",$O15+$S15+$V15-$W15) | V15: =IF($A15="",0,SUMIFS(L_Valor,L_DestTipo,"INVESTIMENTO",L_DestID,$A15,L_Tipo,"APORTE",L_Status,"PROJETADO")) -> 0 | W15: =IF($A15="",0,SUMIFS(L_Valor,L_OrigTipo,"INVESTIMENTO",L_OrigID,$A15,L_Status,"PROJETADO")) -> 0
A16: =IF($B16="","","INV-"&TEXT(ROW()-4,"000000")) | D16: =IF($C16="","",IFERROR(INDEX(INS_ID,MATCH($C16,INS_NOME,0)),"?")) | K16: =IF($A16="","",IF($J16>0,EDATE($G16,$J16),"")) | L16: =IF($A16="",0,SUMIFS(L_Valor,L_DestTipo,"INVESTIMENTO",L_DestID,$A16,L_Tipo,"APORTE",L_Status,"REALIZADO")) -> 0 | M16: =IF($A16="",0,SUMIFS(L_Valor,L_OrigTipo,"INVESTIMENTO",L_OrigID,$A16,L_Status,"REALIZADO")) -> 0 | N16: =IF($A16="",0,SUMIFS(L_Valor,L_DestTipo,"INVESTIMENTO",L_DestID,$A16,L_Tipo,"RENDIMENTO",L_Status,"REALIZADO")) -> 0 | O16: =IF($A16="","",$F16+$L16+$N16-$M16) | P16: =IF($A16="","",MAX(0,$F16+$L16-$M16)) | Q16: =IF($A16="","",$O16-$P16) | R16: =IF($A16="","",IF($K16="",12,MAX(0,(YEAR($K16)-YEAR(CFG_HOJE))*12+MONTH($K16)-MONTH(CFG_HOJE)))) | S16: =IF($A16="",0,SUMIFS(L_Valor,L_DestTipo,"INVESTIMENTO",L_DestID,$A16,L_Tipo,"RENDIMENTO",L_Status,"PROJETADO")) -> 0 | T16: =IF($A16="",0,IF($H16="Taxa anual",ROUND($O16*((1+$I16)^($R16/12)-1),0),IF($H16="Taxa mensal",ROUND($O16*((1+$I16)^$R16-1),0),IF($H16="Valor fixo",$I16,0)))) -> 0 | U16: =IF($A16="","",$O16+$S16+$V16-$W16) | V16: =IF($A16="",0,SUMIFS(L_Valor,L_DestTipo,"INVESTIMENTO",L_DestID,$A16,L_Tipo,"APORTE",L_Status,"PROJETADO")) -> 0 | W16: =IF($A16="",0,SUMIFS(L_Valor,L_OrigTipo,"INVESTIMENTO",L_OrigID,$A16,L_Status,"PROJETADO")) -> 0
... A44: =IF($B44="","","INV-"&TEXT(ROW()-4,"000000")) | D44: =IF($C44="","",IFERROR(INDEX(INS_ID,MATCH($C44,INS_NOME,0)),"?")) | K44: =IF($A44="","",IF($J44>0,EDATE($G44,$J44),"")) | L44: =IF($A44="",0,SUMIFS(L_Valor,L_DestTipo,"INVESTIMENTO",L_DestID,$A44,L_Tipo,"APORTE",L_Status,"REALIZADO")) -> 0 | M44: =IF($A44="",0,SUMIFS(L_Valor,L_OrigTipo,"INVESTIMENTO",L_OrigID,$A44,L_Status,"REALIZADO")) -> 0 | N44: =IF($A44="",0,SUMIFS(L_Valor,L_DestTipo,"INVESTIMENTO",L_DestID,$A44,L_Tipo,"RENDIMENTO",L_Status,"REALIZADO")) -> 0 | O44: =IF($A44="","",$F44+$L44+$N44-$M44) | P44: =IF($A44="","",MAX(0,$F44+$L44-$M44)) | Q44: =IF($A44="","",$O44-$P44) | R44: =IF($A44="","",IF($K44="",12,MAX(0,(YEAR($K44)-YEAR(CFG_HOJE))*12+MONTH($K44)-MONTH(CFG_HOJE)))) | S44: =IF($A44="",0,SUMIFS(L_Valor,L_DestTipo,"INVESTIMENTO",L_DestID,$A44,L_Tipo,"RENDIMENTO",L_Status,"PROJETADO")) -> 0 | T44: =IF($A44="",0,IF($H44="Taxa anual",ROUND($O44*((1+$I44)^($R44/12)-1),0),IF($H44="Taxa mensal",ROUND($O44*((1+$I44)^$R44-1),0),IF($H44="Valor fixo",$I44,0)))) -> 0 | U44: =IF($A44="","",$O44+$S44+$V44-$W44) | V44: =IF($A44="",0,SUMIFS(L_Valor,L_DestTipo,"INVESTIMENTO",L_DestID,$A44,L_Tipo,"APORTE",L_Status,"PROJETADO")) -> 0 | W44: =IF($A44="",0,SUMIFS(L_Valor,L_OrigTipo,"INVESTIMENTO",L_OrigID,$A44,L_Status,"PROJETADO")) -> 0

Sheet CAD_Categorias
A1: CAD_CATEGORIAS - CLASSIFICACAO DE RECEITAS E DESPESAS
A2: PARA APAGAR UM REGISTRO: selecione as celulas AMARELAS da linha e pressione DELETE (limpar conteudo). NUNCA use 'Excluir linha' nem classifique (sort) esta aba: os IDs sao gerados pela posicao da linha e os vinculos seriam quebrados em silencio. Para anular um lancamento sem perder o historico use o campo Status (CANCELADO / Inativo). Para pesquisar use os filtros do cabecalho.
A4: ID_Categoria | B4: Nome | C4: Tipo_Padrao | D4: Qtd_Subcategorias | E4: Realizado_Ano | F4: Projetado_Ano | G4: Status | H4: Observacao
A5: =IF($B5="","","CAT-"&TEXT(ROW()-4,"000000")) -> CAT-000001 | B5: Alimentacao | C5: DESPESA | D5: =IF($A5="","",COUNTIF(SUB_CATID,$A5)) -> 5 | E5: =IF($A5="",0,SUMIFS(L_VDesp,L_CatID,$A5,L_Ano,CFG_ANO,L_Status,"REALIZADO")+SUMIFS(L_VRec,L_CatID,$A5,L_Ano,CFG_ANO,L_Status,"REALIZADO")+SUMIFS(L_VRend,L_CatID,$A5,L_Ano,CFG_ANO,L_Status,"REALIZADO")) -> 0 | F5: =IF($A5="",0,SUMIFS(L_VDesp,L_CatID,$A5,L_Ano,CFG_ANO,L_Status,"PROJETADO")+SUMIFS(L_VRec,L_CatID,$A5,L_Ano,CFG_ANO,L_Status,"PROJETADO")+SUMIFS(L_VRend,L_CatID,$A5,L_Ano,CFG_ANO,L_Status,"PROJETADO")) -> 0 | G5: Ativo
A6: =IF($B6="","","CAT-"&TEXT(ROW()-4,"000000")) -> CAT-000002 | B6: Transporte | C6: DESPESA | D6: =IF($A6="","",COUNTIF(SUB_CATID,$A6)) -> 5 | E6: =IF($A6="",0,SUMIFS(L_VDesp,L_CatID,$A6,L_Ano,CFG_ANO,L_Status,"REALIZADO")+SUMIFS(L_VRec,L_CatID,$A6,L_Ano,CFG_ANO,L_Status,"REALIZADO")+SUMIFS(L_VRend,L_CatID,$A6,L_Ano,CFG_ANO,L_Status,"REALIZADO")) -> 0 | F6: =IF($A6="",0,SUMIFS(L_VDesp,L_CatID,$A6,L_Ano,CFG_ANO,L_Status,"PROJETADO")+SUMIFS(L_VRec,L_CatID,$A6,L_Ano,CFG_ANO,L_Status,"PROJETADO")+SUMIFS(L_VRend,L_CatID,$A6,L_Ano,CFG_ANO,L_Status,"PROJETADO")) -> 0 | G6: Ativo
A7: =IF($B7="","","CAT-"&TEXT(ROW()-4,"000000")) -> CAT-000003 | B7: Moradia | C7: DESPESA | D7: =IF($A7="","",COUNTIF(SUB_CATID,$A7)) -> 6 | E7: =IF($A7="",0,SUMIFS(L_VDesp,L_CatID,$A7,L_Ano,CFG_ANO,L_Status,"REALIZADO")+SUMIFS(L_VRec,L_CatID,$A7,L_Ano,CFG_ANO,L_Status,"REALIZADO")+SUMIFS(L_VRend,L_CatID,$A7,L_Ano,CFG_ANO,L_Status,"REALIZADO")) -> 0 | F7: =IF($A7="",0,SUMIFS(L_VDesp,L_CatID,$A7,L_Ano,CFG_ANO,L_Status,"PROJETADO")+SUMIFS(L_VRec,L_CatID,$A7,L_Ano,CFG_ANO,L_Status,"PROJETADO")+SUMIFS(L_VRend,L_CatID,$A7,L_Ano,CFG_ANO,L_Status,"PROJETADO")) -> 0 | G7: Ativo
A8: =IF($B8="","","CAT-"&TEXT(ROW()-4,"000000")) -> CAT-000004 | B8: Saude | C8: DESPESA | D8: =IF($A8="","",COUNTIF(SUB_CATID,$A8)) -> 5 | E8: =IF($A8="",0,SUMIFS(L_VDesp,L_CatID,$A8,L_Ano,CFG_ANO,L_Status,"REALIZADO")+SUMIFS(L_VRec,L_CatID,$A8,L_Ano,CFG_ANO,L_Status,"REALIZADO")+SUMIFS(L_VRend,L_CatID,$A8,L_Ano,CFG_ANO,L_Status,"REALIZADO")) -> 0 | F8: =IF($A8="",0,SUMIFS(L_VDesp,L_CatID,$A8,L_Ano,CFG_ANO,L_Status,"PROJETADO")+SUMIFS(L_VRec,L_CatID,$A8,L_Ano,CFG_ANO,L_Status,"PROJETADO")+SUMIFS(L_VRend,L_CatID,$A8,L_Ano,CFG_ANO,L_Status,"PROJETADO")) -> 0 | G8: Ativo
A9: =IF($B9="","","CAT-"&TEXT(ROW()-4,"000000")) -> CAT-000005 | B9: Educacao | C9: DESPESA | D9: =IF($A9="","",COUNTIF(SUB_CATID,$A9)) -> 4 | E9: =IF($A9="",0,SUMIFS(L_VDesp,L_CatID,$A9,L_Ano,CFG_ANO,L_Status,"REALIZADO")+SUMIFS(L_VRec,L_CatID,$A9,L_Ano,CFG_ANO,L_Status,"REALIZADO")+SUMIFS(L_VRend,L_CatID,$A9,L_Ano,CFG_ANO,L_Status,"REALIZADO")) -> 0 | F9: =IF($A9="",0,SUMIFS(L_VDesp,L_CatID,$A9,L_Ano,CFG_ANO,L_Status,"PROJETADO")+SUMIFS(L_VRec,L_CatID,$A9,L_Ano,CFG_ANO,L_Status,"PROJETADO")+SUMIFS(L_VRend,L_CatID,$A9,L_Ano,CFG_ANO,L_Status,"PROJETADO")) -> 0 | G9: Ativo
A10: =IF($B10="","","CAT-"&TEXT(ROW()-4,"000000")) -> CAT-000006 | B10: Lazer | C10: DESPESA | D10: =IF($A10="","",COUNTIF(SUB_CATID,$A10)) -> 4 | E10: =IF($A10="",0,SUMIFS(L_VDesp,L_CatID,$A10,L_Ano,CFG_ANO,L_Status,"REALIZADO")+SUMIFS(L_VRec,L_CatID,$A10,L_Ano,CFG_ANO,L_Status,"REALIZADO")+SUMIFS(L_VRend,L_CatID,$A10,L_Ano,CFG_ANO,L_Status,"REALIZADO")) -> 0 | F10: =IF($A10="",0,SUMIFS(L_VDesp,L_CatID,$A10,L_Ano,CFG_ANO,L_Status,"PROJETADO")+SUMIFS(L_VRec,L_CatID,$A10,L_Ano,CFG_ANO,L_Status,"PROJETADO")+SUMIFS(L_VRend,L_CatID,$A10,L_Ano,CFG_ANO,L_Status,"PROJETADO")) -> 0 | G10: Ativo
A11: =IF($B11="","","CAT-"&TEXT(ROW()-4,"000000")) -> CAT-000007 | B11: Compras | C11: DESPESA | D11: =IF($A11="","",COUNTIF(SUB_CATID,$A11)) -> 4 | E11: =IF($A11="",0,SUMIFS(L_VDesp,L_CatID,$A11,L_Ano,CFG_ANO,L_Status,"REALIZADO")+SUMIFS(L_VRec,L_CatID,$A11,L_Ano,CFG_ANO,L_Status,"REALIZADO")+SUMIFS(L_VRend,L_CatID,$A11,L_Ano,CFG_ANO,L_Status,"REALIZADO")) -> 0 | F11: =IF($A11="",0,SUMIFS(L_VDesp,L_CatID,$A11,L_Ano,CFG_ANO,L_Status,"PROJETADO")+SUMIFS(L_VRec,L_CatID,$A11,L_Ano,CFG_ANO,L_Status,"PROJETADO")+SUMIFS(L_VRend,L_CatID,$A11,L_Ano,CFG_ANO,L_Status,"PROJETADO")) -> 0 | G11: Ativo
A12: =IF($B12="","","CAT-"&TEXT(ROW()-4,"000000")) -> CAT-000008 | B12: Dividas e Financiamentos | C12: DESPESA | D12: =IF($A12="","",COUNTIF(SUB_CATID,$A12)) -> 4 | E12: =IF($A12="",0,SUMIFS(L_VDesp,L_CatID,$A12,L_Ano,CFG_ANO,L_Status,"REALIZADO")+SUMIFS(L_VRec,L_CatID,$A12,L_Ano,CFG_ANO,L_Status,"REALIZADO")+SUMIFS(L_VRend,L_CatID,$A12,L_Ano,CFG_ANO,L_Status,"REALIZADO")) -> 0 | F12: =IF($A12="",0,SUMIFS(L_VDesp,L_CatID,$A12,L_Ano,CFG_ANO,L_Status,"PROJETADO")+SUMIFS(L_VRec,L_CatID,$A12,L_Ano,CFG_ANO,L_Status,"PROJETADO")+SUMIFS(L_VRend,L_CatID,$A12,L_Ano,CFG_ANO,L_Status,"PROJETADO")) -> 0 | G12: Ativo
A13: =IF($B13="","","CAT-"&TEXT(ROW()-4,"000000")) -> CAT-000009 | B13: Investimentos | C13: NEUTRO | D13: =IF($A13="","",COUNTIF(SUB_CATID,$A13)) -> 3 | E13: =IF($A13="",0,SUMIFS(L_VDesp,L_CatID,$A13,L_Ano,CFG_ANO,L_Status,"REALIZADO")+SUMIFS(L_VRec,L_CatID,$A13,L_Ano,CFG_ANO,L_Status,"REALIZADO")+SUMIFS(L_VRend,L_CatID,$A13,L_Ano,CFG_ANO,L_Status,"REALIZADO")) -> 0 | F13: =IF($A13="",0,SUMIFS(L_VDesp,L_CatID,$A13,L_Ano,CFG_ANO,L_Status,"PROJETADO")+SUMIFS(L_VRec,L_CatID,$A13,L_Ano,CFG_ANO,L_Status,"PROJETADO")+SUMIFS(L_VRend,L_CatID,$A13,L_Ano,CFG_ANO,L_Status,"PROJETADO")) -> 0 | G13: Ativo
A14: =IF($B14="","","CAT-"&TEXT(ROW()-4,"000000")) -> CAT-000010 | B14: Receitas | C14: RECEITA | D14: =IF($A14="","",COUNTIF(SUB_CATID,$A14)) -> 6 | E14: =IF($A14="",0,SUMIFS(L_VDesp,L_CatID,$A14,L_Ano,CFG_ANO,L_Status,"REALIZADO")+SUMIFS(L_VRec,L_CatID,$A14,L_Ano,CFG_ANO,L_Status,"REALIZADO")+SUMIFS(L_VRend,L_CatID,$A14,L_Ano,CFG_ANO,L_Status,"REALIZADO")) -> 0 | F14: =IF($A14="",0,SUMIFS(L_VDesp,L_CatID,$A14,L_Ano,CFG_ANO,L_Status,"PROJETADO")+SUMIFS(L_VRec,L_CatID,$A14,L_Ano,CFG_ANO,L_Status,"PROJETADO")+SUMIFS(L_VRend,L_CatID,$A14,L_Ano,CFG_ANO,L_Status,"PROJETADO")) -> 0 | G14: Ativo
A15: =IF($B15="","","CAT-"&TEXT(ROW()-4,"000000")) -> CAT-000011 | B15: Impostos e Taxas | C15: DESPESA | D15: =IF($A15="","",COUNTIF(SUB_CATID,$A15)) -> 4 | E15: =IF($A15="",0,SUMIFS(L_VDesp,L_CatID,$A15,L_Ano,CFG_ANO,L_Status,"REALIZADO")+SUMIFS(L_VRec,L_CatID,$A15,L_Ano,CFG_ANO,L_Status,"REALIZADO")+SUMIFS(L_VRend,L_CatID,$A15,L_Ano,CFG_ANO,L_Status,"REALIZADO")) -> 0 | F15: =IF($A15="",0,SUMIFS(L_VDesp,L_CatID,$A15,L_Ano,CFG_ANO,L_Status,"PROJETADO")+SUMIFS(L_VRec,L_CatID,$A15,L_Ano,CFG_ANO,L_Status,"PROJETADO")+SUMIFS(L_VRend,L_CatID,$A15,L_Ano,CFG_ANO,L_Status,"PROJETADO")) -> 0 | G15: Ativo
A16: =IF($B16="","","CAT-"&TEXT(ROW()-4,"000000")) -> CAT-000012 | B16: Outros | C16: DESPESA | D16: =IF($A16="","",COUNTIF(SUB_CATID,$A16)) -> 2 | E16: =IF($A16="",0,SUMIFS(L_VDesp,L_CatID,$A16,L_Ano,CFG_ANO,L_Status,"REALIZADO")+SUMIFS(L_VRec,L_CatID,$A16,L_Ano,CFG_ANO,L_Status,"REALIZADO")+SUMIFS(L_VRend,L_CatID,$A16,L_Ano,CFG_ANO,L_Status,"REALIZADO")) -> 0 | F16: =IF($A16="",0,SUMIFS(L_VDesp,L_CatID,$A16,L_Ano,CFG_ANO,L_Status,"PROJETADO")+SUMIFS(L_VRec,L_CatID,$A16,L_Ano,CFG_ANO,L_Status,"PROJETADO")+SUMIFS(L_VRend,L_CatID,$A16,L_Ano,CFG_ANO,L_Status,"PROJETADO")) -> 0 | G16: Ativo
A17: =IF($B17="","","CAT-"&TEXT(ROW()-4,"000000")) -> CAT-000013 | B17: Transferencias | C17: NEUTRO | D17: =IF($A17="","",COUNTIF(SUB_CATID,$A17)) -> 2 | E17: =IF($A17="",0,SUMIFS(L_VDesp,L_CatID,$A17,L_Ano,CFG_ANO,L_Status,"REALIZADO")+SUMIFS(L_VRec,L_CatID,$A17,L_Ano,CFG_ANO,L_Status,"REALIZADO")+SUMIFS(L_VRend,L_CatID,$A17,L_Ano,CFG_ANO,L_Status,"REALIZADO")) -> 0 | F17: =IF($A17="",0,SUMIFS(L_VDesp,L_CatID,$A17,L_Ano,CFG_ANO,L_Status,"PROJETADO")+SUMIFS(L_VRec,L_CatID,$A17,L_Ano,CFG_ANO,L_Status,"PROJETADO")+SUMIFS(L_VRend,L_CatID,$A17,L_Ano,CFG_ANO,L_Status,"PROJETADO")) -> 0 | G17: Ativo
A18: =IF($B18="","","CAT-"&TEXT(ROW()-4,"000000")) | D18: =IF($A18="","",COUNTIF(SUB_CATID,$A18)) | E18: =IF($A18="",0,SUMIFS(L_VDesp,L_CatID,$A18,L_Ano,CFG_ANO,L_Status,"REALIZADO")+SUMIFS(L_VRec,L_CatID,$A18,L_Ano,CFG_ANO,L_Status,"REALIZADO")+SUMIFS(L_VRend,L_CatID,$A18,L_Ano,CFG_ANO,L_Status,"REALIZADO")) -> 0 | F18: =IF($A18="",0,SUMIFS(L_VDesp,L_CatID,$A18,L_Ano,CFG_ANO,L_Status,"PROJETADO")+SUMIFS(L_VRec,L_CatID,$A18,L_Ano,CFG_ANO,L_Status,"PROJETADO")+SUMIFS(L_VRend,L_CatID,$A18,L_Ano,CFG_ANO,L_Status,"PROJETADO")) -> 0
A19: =IF($B19="","","CAT-"&TEXT(ROW()-4,"000000")) | D19: =IF($A19="","",COUNTIF(SUB_CATID,$A19)) | E19: =IF($A19="",0,SUMIFS(L_VDesp,L_CatID,$A19,L_Ano,CFG_ANO,L_Status,"REALIZADO")+SUMIFS(L_VRec,L_CatID,$A19,L_Ano,CFG_ANO,L_Status,"REALIZADO")+SUMIFS(L_VRend,L_CatID,$A19,L_Ano,CFG_ANO,L_Status,"REALIZADO")) -> 0 | F19: =IF($A19="",0,SUMIFS(L_VDesp,L_CatID,$A19,L_Ano,CFG_ANO,L_Status,"PROJETADO")+SUMIFS(L_VRec,L_CatID,$A19,L_Ano,CFG_ANO,L_Status,"PROJETADO")+SUMIFS(L_VRend,L_CatID,$A19,L_Ano,CFG_ANO,L_Status,"PROJETADO")) -> 0
A20: =IF($B20="","","CAT-"&TEXT(ROW()-4,"000000")) | D20: =IF($A20="","",COUNTIF(SUB_CATID,$A20)) | E20: =IF($A20="",0,SUMIFS(L_VDesp,L_CatID,$A20,L_Ano,CFG_ANO,L_Status,"REALIZADO")+SUMIFS(L_VRec,L_CatID,$A20,L_Ano,CFG_ANO,L_Status,"REALIZADO")+SUMIFS(L_VRend,L_CatID,$A20,L_Ano,CFG_ANO,L_Status,"REALIZADO")) -> 0 | F20: =IF($A20="",0,SUMIFS(L_VDesp,L_CatID,$A20,L_Ano,CFG_ANO,L_Status,"PROJETADO")+SUMIFS(L_VRec,L_CatID,$A20,L_Ano,CFG_ANO,L_Status,"PROJETADO")+SUMIFS(L_VRend,L_CatID,$A20,L_Ano,CFG_ANO,L_Status,"PROJETADO")) -> 0
A21: =IF($B21="","","CAT-"&TEXT(ROW()-4,"000000")) | D21: =IF($A21="","",COUNTIF(SUB_CATID,$A21)) | E21: =IF($A21="",0,SUMIFS(L_VDesp,L_CatID,$A21,L_Ano,CFG_ANO,L_Status,"REALIZADO")+SUMIFS(L_VRec,L_CatID,$A21,L_Ano,CFG_ANO,L_Status,"REALIZADO")+SUMIFS(L_VRend,L_CatID,$A21,L_Ano,CFG_ANO,L_Status,"REALIZADO")) -> 0 | F21: =IF($A21="",0,SUMIFS(L_VDesp,L_CatID,$A21,L_Ano,CFG_ANO,L_Status,"PROJETADO")+SUMIFS(L_VRec,L_CatID,$A21,L_Ano,CFG_ANO,L_Status,"PROJETADO")+SUMIFS(L_VRend,L_CatID,$A21,L_Ano,CFG_ANO,L_Status,"PROJETADO")) -> 0
A22: =IF($B22="","","CAT-"&TEXT(ROW()-4,"000000")) | D22: =IF($A22="","",COUNTIF(SUB_CATID,$A22)) | E22: =IF($A22="",0,SUMIFS(L_VDesp,L_CatID,$A22,L_Ano,CFG_ANO,L_Status,"REALIZADO")+SUMIFS(L_VRec,L_CatID,$A22,L_Ano,CFG_ANO,L_Status,"REALIZADO")+SUMIFS(L_VRend,L_CatID,$A22,L_Ano,CFG_ANO,L_Status,"REALIZADO")) -> 0 | F22: =IF($A22="",0,SUMIFS(L_VDesp,L_CatID,$A22,L_Ano,CFG_ANO,L_Status,"PROJETADO")+SUMIFS(L_VRec,L_CatID,$A22,L_Ano,CFG_ANO,L_Status,"PROJETADO")+SUMIFS(L_VRend,L_CatID,$A22,L_Ano,CFG_ANO,L_Status,"PROJETADO")) -> 0
A23: =IF($B23="","","CAT-"&TEXT(ROW()-4,"000000")) | D23: =IF($A23="","",COUNTIF(SUB_CATID,$A23)) | E23: =IF($A23="",0,SUMIFS(L_VDesp,L_CatID,$A23,L_Ano,CFG_ANO,L_Status,"REALIZADO")+SUMIFS(L_VRec,L_CatID,$A23,L_Ano,CFG_ANO,L_Status,"REALIZADO")+SUMIFS(L_VRend,L_CatID,$A23,L_Ano,CFG_ANO,L_Status,"REALIZADO")) -> 0 | F23: =IF($A23="",0,SUMIFS(L_VDesp,L_CatID,$A23,L_Ano,CFG_ANO,L_Status,"PROJETADO")+SUMIFS(L_VRec,L_CatID,$A23,L_Ano,CFG_ANO,L_Status,"PROJETADO")+SUMIFS(L_VRend,L_CatID,$A23,L_Ano,CFG_ANO,L_Status,"PROJETADO")) -> 0
A24: =IF($B24="","","CAT-"&TEXT(ROW()-4,"000000")) | D24: =IF($A24="","",COUNTIF(SUB_CATID,$A24)) | E24: =IF($A24="",0,SUMIFS(L_VDesp,L_CatID,$A24,L_Ano,CFG_ANO,L_Status,"REALIZADO")+SUMIFS(L_VRec,L_CatID,$A24,L_Ano,CFG_ANO,L_Status,"REALIZADO")+SUMIFS(L_VRend,L_CatID,$A24,L_Ano,CFG_ANO,L_Status,"REALIZADO")) -> 0 | F24: =IF($A24="",0,SUMIFS(L_VDesp,L_CatID,$A24,L_Ano,CFG_ANO,L_Status,"PROJETADO")+SUMIFS(L_VRec,L_CatID,$A24,L_Ano,CFG_ANO,L_Status,"PROJETADO")+SUMIFS(L_VRend,L_CatID,$A24,L_Ano,CFG_ANO,L_Status,"PROJETADO")) -> 0
A25: =IF($B25="","","CAT-"&TEXT(ROW()-4,"000000")) | D25: =IF($A25="","",COUNTIF(SUB_CATID,$A25)) | E25: =IF($A25="",0,SUMIFS(L_VDesp,L_CatID,$A25,L_Ano,CFG_ANO,L_Status,"REALIZADO")+SUMIFS(L_VRec,L_CatID,$A25,L_Ano,CFG_ANO,L_Status,"REALIZADO")+SUMIFS(L_VRend,L_CatID,$A25,L_Ano,CFG_ANO,L_Status,"REALIZADO")) -> 0 | F25: =IF($A25="",0,SUMIFS(L_VDesp,L_CatID,$A25,L_Ano,CFG_ANO,L_Status,"PROJETADO")+SUMIFS(L_VRec,L_CatID,$A25,L_Ano,CFG_ANO,L_Status,"PROJETADO")+SUMIFS(L_VRend,L_CatID,$A25,L_Ano,CFG_ANO,L_Status,"PROJETADO")) -> 0
A26: =IF($B26="","","CAT-"&TEXT(ROW()-4,"000000")) | D26: =IF($A26="","",COUNTIF(SUB_CATID,$A26)) | E26: =IF($A26="",0,SUMIFS(L_VDesp,L_CatID,$A26,L_Ano,CFG_ANO,L_Status,"REALIZADO")+SUMIFS(L_VRec,L_CatID,$A26,L_Ano,CFG_ANO,L_Status,"REALIZADO")+SUMIFS(L_VRend,L_CatID,$A26,L_Ano,CFG_ANO,L_Status,"REALIZADO")) -> 0 | F26: =IF($A26="",0,SUMIFS(L_VDesp,L_CatID,$A26,L_Ano,CFG_ANO,L_Status,"PROJETADO")+SUMIFS(L_VRec,L_CatID,$A26,L_Ano,CFG_ANO,L_Status,"PROJETADO")+SUMIFS(L_VRend,L_CatID,$A26,L_Ano,CFG_ANO,L_Status,"PROJETADO")) -> 0
A27: =IF($B27="","","CAT-"&TEXT(ROW()-4,"000000")) | D27: =IF($A27="","",COUNTIF(SUB_CATID,$A27)) | E27: =IF($A27="",0,SUMIFS(L_VDesp,L_CatID,$A27,L_Ano,CFG_ANO,L_Status,"REALIZADO")+SUMIFS(L_VRec,L_CatID,$A27,L_Ano,CFG_ANO,L_Status,"REALIZADO")+SUMIFS(L_VRend,L_CatID,$A27,L_Ano,CFG_ANO,L_Status,"REALIZADO")) -> 0 | F27: =IF($A27="",0,SUMIFS(L_VDesp,L_CatID,$A27,L_Ano,CFG_ANO,L_Status,"PROJETADO")+SUMIFS(L_VRec,L_CatID,$A27,L_Ano,CFG_ANO,L_Status,"PROJETADO")+SUMIFS(L_VRend,L_CatID,$A27,L_Ano,CFG_ANO,L_Status,"PROJETADO")) -> 0
A28: =IF($B28="","","CAT-"&TEXT(ROW()-4,"000000")) | D28: =IF($A28="","",COUNTIF(SUB_CATID,$A28)) | E28: =IF($A28="",0,SUMIFS(L_VDesp,L_CatID,$A28,L_Ano,CFG_ANO,L_Status,"REALIZADO")+SUMIFS(L_VRec,L_CatID,$A28,L_Ano,CFG_ANO,L_Status,"REALIZADO")+SUMIFS(L_VRend,L_CatID,$A28,L_Ano,CFG_ANO,L_Status,"REALIZADO")) -> 0 | F28: =IF($A28="",0,SUMIFS(L_VDesp,L_CatID,$A28,L_Ano,CFG_ANO,L_Status,"PROJETADO")+SUMIFS(L_VRec,L_CatID,$A28,L_Ano,CFG_ANO,L_Status,"PROJETADO")+SUMIFS(L_VRend,L_CatID,$A28,L_Ano,CFG_ANO,L_Status,"PROJETADO")) -> 0
A29: =IF($B29="","","CAT-"&TEXT(ROW()-4,"000000")) | D29: =IF($A29="","",COUNTIF(SUB_CATID,$A29)) | E29: =IF($A29="",0,SUMIFS(L_VDesp,L_CatID,$A29,L_Ano,CFG_ANO,L_Status,"REALIZADO")+SUMIFS(L_VRec,L_CatID,$A29,L_Ano,CFG_ANO,L_Status,"REALIZADO")+SUMIFS(L_VRend,L_CatID,$A29,L_Ano,CFG_ANO,L_Status,"REALIZADO")) -> 0 | F29: =IF($A29="",0,SUMIFS(L_VDesp,L_CatID,$A29,L_Ano,CFG_ANO,L_Status,"PROJETADO")+SUMIFS(L_VRec,L_CatID,$A29,L_Ano,CFG_ANO,L_Status,"PROJETADO")+SUMIFS(L_VRend,L_CatID,$A29,L_Ano,CFG_ANO,L_Status,"PROJETADO")) -> 0
... A44: =IF($B44="","","CAT-"&TEXT(ROW()-4,"000000")) | D44: =IF($A44="","",COUNTIF(SUB_CATID,$A44)) | E44: =IF($A44="",0,SUMIFS(L_VDesp,L_CatID,$A44,L_Ano,CFG_ANO,L_Status,"REALIZADO")+SUMIFS(L_VRec,L_CatID,$A44,L_Ano,CFG_ANO,L_Status,"REALIZADO")+SUMIFS(L_VRend,L_CatID,$A44,L_Ano,CFG_ANO,L_Status,"REALIZADO")) -> 0 | F44: =IF($A44="",0,SUMIFS(L_VDesp,L_CatID,$A44,L_Ano,CFG_ANO,L_Status,"PROJETADO")+SUMIFS(L_VRec,L_CatID,$A44,L_Ano,CFG_ANO,L_Status,"PROJETADO")+SUMIFS(L_VRend,L_CatID,$A44,L_Ano,CFG_ANO,L_Status,"PROJETADO")) -> 0

Sheet CAD_Subcategorias
A1: CAD_SUBCATEGORIAS - DETALHAMENTO DAS CATEGORIAS
A2: PARA APAGAR UM REGISTRO: selecione as celulas AMARELAS da linha e pressione DELETE (limpar conteudo). NUNCA use 'Excluir linha' nem classifique (sort) esta aba: os IDs sao gerados pela posicao da linha e os vinculos seriam quebrados em silencio. Para anular um lancamento sem perder o historico use o campo Status (CANCELADO / Inativo). Para pesquisar use os filtros do cabecalho.
A4: ID_Subcategoria | B4: Categoria | C4: ID_Categoria | D4: Nome | E4: Realizado_Ano | F4: Projetado_Ano | G4: Ordem_Na_Categoria | H4: Status | I4: Observacao
A5: =IF($B5="","","SUB-"&TEXT(ROW()-4,"000000")) -> SUB-000001 | B5: Alimentacao | C5: =IF($B5="","",IFERROR(INDEX(CAT_ID,MATCH($B5,CAT_NOME,0)),"?")) -> CAT-000001 | D5: Supermercado | E5: =IF($A5="",0,SUMIFS(L_VDesp,L_SubID,$A5,L_Ano,CFG_ANO,L_Status,"REALIZADO")+SUMIFS(L_VRec,L_SubID,$A5,L_Ano,CFG_ANO,L_Status,"REALIZADO")+SUMIFS(L_VRend,L_SubID,$A5,L_Ano,CFG_ANO,L_Status,"REALIZADO")) -> 0 | F5: =IF($A5="",0,SUMIFS(L_VDesp,L_SubID,$A5,L_Ano,CFG_ANO,L_Status,"PROJETADO")+SUMIFS(L_VRec,L_SubID,$A5,L_Ano,CFG_ANO,L_Status,"PROJETADO")+SUMIFS(L_VRend,L_SubID,$A5,L_Ano,CFG_ANO,L_Status,"PROJETADO")) -> 0 | G5: =IF($A5="","",COUNTIFS($C$5:$C5,$C5)) -> 1 | H5: Ativo
A6: =IF($B6="","","SUB-"&TEXT(ROW()-4,"000000")) -> SUB-000002 | B6: Alimentacao | C6: =IF($B6="","",IFERROR(INDEX(CAT_ID,MATCH($B6,CAT_NOME,0)),"?")) -> CAT-000001 | D6: Restaurante | E6: =IF($A6="",0,SUMIFS(L_VDesp,L_SubID,$A6,L_Ano,CFG_ANO,L_Status,"REALIZADO")+SUMIFS(L_VRec,L_SubID,$A6,L_Ano,CFG_ANO,L_Status,"REALIZADO")+SUMIFS(L_VRend,L_SubID,$A6,L_Ano,CFG_ANO,L_Status,"REALIZADO")) -> 0 | F6: =IF($A6="",0,SUMIFS(L_VDesp,L_SubID,$A6,L_Ano,CFG_ANO,L_Status,"PROJETADO")+SUMIFS(L_VRec,L_SubID,$A6,L_Ano,CFG_ANO,L_Status,"PROJETADO")+SUMIFS(L_VRend,L_SubID,$A6,L_Ano,CFG_ANO,L_Status,"PROJETADO")) -> 0 | G6: =IF($A6="","",COUNTIFS($C$5:$C6,$C6)) -> 2 | H6: Ativo
A7: =IF($B7="","","SUB-"&TEXT(ROW()-4,"000000")) -> SUB-000003 | B7: Alimentacao | C7: =IF($B7="","",IFERROR(INDEX(CAT_ID,MATCH($B7,CAT_NOME,0)),"?")) -> CAT-000001 | D7: Delivery | E7: =IF($A7="",0,SUMIFS(L_VDesp,L_SubID,$A7,L_Ano,CFG_ANO,L_Status,"REALIZADO")+SUMIFS(L_VRec,L_SubID,$A7,L_Ano,CFG_ANO,L_Status,"REALIZADO")+SUMIFS(L_VRend,L_SubID,$A7,L_Ano,CFG_ANO,L_Status,"REALIZADO")) -> 0 | F7: =IF($A7="",0,SUMIFS(L_VDesp,L_SubID,$A7,L_Ano,CFG_ANO,L_Status,"PROJETADO")+SUMIFS(L_VRec,L_SubID,$A7,L_Ano,CFG_ANO,L_Status,"PROJETADO")+SUMIFS(L_VRend,L_SubID,$A7,L_Ano,CFG_ANO,L_Status,"PROJETADO")) -> 0 | G7: =IF($A7="","",COUNTIFS($C$5:$C7,$C7)) -> 3 | H7: Ativo
A8: =IF($B8="","","SUB-"&TEXT(ROW()-4,"000000")) -> SUB-000004 | B8: Alimentacao | C8: =IF($B8="","",IFERROR(INDEX(CAT_ID,MATCH($B8,CAT_NOME,0)),"?")) -> CAT-000001 | D8: Lanches | E8: =IF($A8="",0,SUMIFS(L_VDesp,L_SubID,$A8,L_Ano,CFG_ANO,L_Status,"REALIZADO")+SUMIFS(L_VRec,L_SubID,$A8,L_Ano,CFG_ANO,L_Status,"REALIZADO")+SUMIFS(L_VRend,L_SubID,$A8,L_Ano,CFG_ANO,L_Status,"REALIZADO")) -> 0 | F8: =IF($A8="",0,SUMIFS(L_VDesp,L_SubID,$A8,L_Ano,CFG_ANO,L_Status,"PROJETADO")+SUMIFS(L_VRec,L_SubID,$A8,L_Ano,CFG_ANO,L_Status,"PROJETADO")+SUMIFS(L_VRend,L_SubID,$A8,L_Ano,CFG_ANO,L_Status,"PROJETADO")) -> 0 | G8: =IF($A8="","",COUNTIFS($C$5:$C8,$C8)) -> 4 | H8: Ativo
A9: =IF($B9="","","SUB-"&TEXT(ROW()-4,"000000")) -> SUB-000005 | B9: Alimentacao | C9: =IF($B9="","",IFERROR(INDEX(CAT_ID,MATCH($B9,CAT_NOME,0)),"?")) -> CAT-000001 | D9: Feira | E9: =IF($A9="",0,SUMIFS(L_VDesp,L_SubID,$A9,L_Ano,CFG_ANO,L_Status,"REALIZADO")+SUMIFS(L_VRec,L_SubID,$A9,L_Ano,CFG_ANO,L_Status,"REALIZADO")+SUMIFS(L_VRend,L_SubID,$A9,L_Ano,CFG_ANO,L_Status,"REALIZADO")) -> 0 | F9: =IF($A9="",0,SUMIFS(L_VDesp,L_SubID,$A9,L_Ano,CFG_ANO,L_Status,"PROJETADO")+SUMIFS(L_VRec,L_SubID,$A9,L_Ano,CFG_ANO,L_Status,"PROJETADO")+SUMIFS(L_VRend,L_SubID,$A9,L_Ano,CFG_ANO,L_Status,"PROJETADO")) -> 0 | G9: =IF($A9="","",COUNTIFS($C$5:$C9,$C9)) -> 5 | H9: Ativo
A10: =IF($B10="","","SUB-"&TEXT(ROW()-4,"000000")) -> SUB-000006 | B10: Transporte | C10: =IF($B10="","",IFERROR(INDEX(CAT_ID,MATCH($B10,CAT_NOME,0)),"?")) -> CAT-000002 | D10: Combustivel | E10: =IF($A10="",0,SUMIFS(L_VDesp,L_SubID,$A10,L_Ano,CFG_ANO,L_Status,"REALIZADO")+SUMIFS(L_VRec,L_SubID,$A10,L_Ano,CFG_ANO,L_Status,"REALIZADO")+SUMIFS(L_VRend,L_SubID,$A10,L_Ano,CFG_ANO,L_Status,"REALIZADO")) -> 0 | F10: =IF($A10="",0,SUMIFS(L_VDesp,L_SubID,$A10,L_Ano,CFG_ANO,L_Status,"PROJETADO")+SUMIFS(L_VRec,L_SubID,$A10,L_Ano,CFG_ANO,L_Status,"PROJETADO")+SUMIFS(L_VRend,L_SubID,$A10,L_Ano,CFG_ANO,L_Status,"PROJETADO")) -> 0 | G10: =IF($A10="","",COUNTIFS($C$5:$C10,$C10)) -> 1 | H10: Ativo
A11: =IF($B11="","","SUB-"&TEXT(ROW()-4,"000000")) -> SUB-000007 | B11: Transporte | C11: =IF($B11="","",IFERROR(INDEX(CAT_ID,MATCH($B11,CAT_NOME,0)),"?")) -> CAT-000002 | D11: Uber/Taxi | E11: =IF($A11="",0,SUMIFS(L_VDesp,L_SubID,$A11,L_Ano,CFG_ANO,L_Status,"REALIZADO")+SUMIFS(L_VRec,L_SubID,$A11,L_Ano,CFG_ANO,L_Status,"REALIZADO")+SUMIFS(L_VRend,L_SubID,$A11,L_Ano,CFG_ANO,L_Status,"REALIZADO")) -> 0 | F11: =IF($A11="",0,SUMIFS(L_VDesp,L_SubID,$A11,L_Ano,CFG_ANO,L_Status,"PROJETADO")+SUMIFS(L_VRec,L_SubID,$A11,L_Ano,CFG_ANO,L_Status,"PROJETADO")+SUMIFS(L_VRend,L_SubID,$A11,L_Ano,CFG_ANO,L_Status,"PROJETADO")) -> 0 | G11: =IF($A11="","",COUNTIFS($C$5:$C11,$C11)) -> 2 | H11: Ativo
A12: =IF($B12="","","SUB-"&TEXT(ROW()-4,"000000")) -> SUB-000008 | B12: Transporte | C12: =IF($B12="","",IFERROR(INDEX(CAT_ID,MATCH($B12,CAT_NOME,0)),"?")) -> CAT-000002 | D12: Onibus | E12: =IF($A12="",0,SUMIFS(L_VDesp,L_SubID,$A12,L_Ano,CFG_ANO,L_Status,"REALIZADO")+SUMIFS(L_VRec,L_SubID,$A12,L_Ano,CFG_ANO,L_Status,"REALIZADO")+SUMIFS(L_VRend,L_SubID,$A12,L_Ano,CFG_ANO,L_Status,"REALIZADO")) -> 0 | F12: =IF($A12="",0,SUMIFS(L_VDesp,L_SubID,$A12,L_Ano,CFG_ANO,L_Status,"PROJETADO")+SUMIFS(L_VRec,L_SubID,$A12,L_Ano,CFG_ANO,L_Status,"PROJETADO")+SUMIFS(L_VRend,L_SubID,$A12,L_Ano,CFG_ANO,L_Status,"PROJETADO")) -> 0 | G12: =IF($A12="","",COUNTIFS($C$5:$C12,$C12)) -> 3 | H12: Ativo
A13: =IF($B13="","","SUB-"&TEXT(ROW()-4,"000000")) -> SUB-000009 | B13: Transporte | C13: =IF($B13="","",IFERROR(INDEX(CAT_ID,MATCH($B13,CAT_NOME,0)),"?")) -> CAT-000002 | D13: Manutencao | E13: =IF($A13="",0,SUMIFS(L_VDesp,L_SubID,$A13,L_Ano,CFG_ANO,L_Status,"REALIZADO")+SUMIFS(L_VRec,L_SubID,$A13,L_Ano,CFG_ANO,L_Status,"REALIZADO")+SUMIFS(L_VRend,L_SubID,$A13,L_Ano,CFG_ANO,L_Status,"REALIZADO")) -> 0 | F13: =IF($A13="",0,SUMIFS(L_VDesp,L_SubID,$A13,L_Ano,CFG_ANO,L_Status,"PROJETADO")+SUMIFS(L_VRec,L_SubID,$A13,L_Ano,CFG_ANO,L_Status,"PROJETADO")+SUMIFS(L_VRend,L_SubID,$A13,L_Ano,CFG_ANO,L_Status,"PROJETADO")) -> 0 | G13: =IF($A13="","",COUNTIFS($C$5:$C13,$C13)) -> 4 | H13: Ativo
A14: =IF($B14="","","SUB-"&TEXT(ROW()-4,"000000")) -> SUB-000010 | B14: Transporte | C14: =IF($B14="","",IFERROR(INDEX(CAT_ID,MATCH($B14,CAT_NOME,0)),"?")) -> CAT-000002 | D14: Seguro veicular | E14: =IF($A14="",0,SUMIFS(L_VDesp,L_SubID,$A14,L_Ano,CFG_ANO,L_Status,"REALIZADO")+SUMIFS(L_VRec,L_SubID,$A14,L_Ano,CFG_ANO,L_Status,"REALIZADO")+SUMIFS(L_VRend,L_SubID,$A14,L_Ano,CFG_ANO,L_Status,"REALIZADO")) -> 0 | F14: =IF($A14="",0,SUMIFS(L_VDesp,L_SubID,$A14,L_Ano,CFG_ANO,L_Status,"PROJETADO")+SUMIFS(L_VRec,L_SubID,$A14,L_Ano,CFG_ANO,L_Status,"PROJETADO")+SUMIFS(L_VRend,L_SubID,$A14,L_Ano,CFG_ANO,L_Status,"PROJETADO")) -> 0 | G14: =IF($A14="","",COUNTIFS($C$5:$C14,$C14)) -> 5 | H14: Ativo
A15: =IF($B15="","","SUB-"&TEXT(ROW()-4,"000000")) -> SUB-000011 | B15: Moradia | C15: =IF($B15="","",IFERROR(INDEX(CAT_ID,MATCH($B15,CAT_NOME,0)),"?")) -> CAT-000003 | D15: Aluguel | E15: =IF($A15="",0,SUMIFS(L_VDesp,L_SubID,$A15,L_Ano,CFG_ANO,L_Status,"REALIZADO")+SUMIFS(L_VRec,L_SubID,$A15,L_Ano,CFG_ANO,L_Status,"REALIZADO")+SUMIFS(L_VRend,L_SubID,$A15,L_Ano,CFG_ANO,L_Status,"REALIZADO")) -> 0 | F15: =IF($A15="",0,SUMIFS(L_VDesp,L_SubID,$A15,L_Ano,CFG_ANO,L_Status,"PROJETADO")+SUMIFS(L_VRec,L_SubID,$A15,L_Ano,CFG_ANO,L_Status,"PROJETADO")+SUMIFS(L_VRend,L_SubID,$A15,L_Ano,CFG_ANO,L_Status,"PROJETADO")) -> 0 | G15: =IF($A15="","",COUNTIFS($C$5:$C15,$C15)) -> 1 | H15: Ativo
A16: =IF($B16="","","SUB-"&TEXT(ROW()-4,"000000")) -> SUB-000012 | B16: Moradia | C16: =IF($B16="","",IFERROR(INDEX(CAT_ID,MATCH($B16,CAT_NOME,0)),"?")) -> CAT-000003 | D16: Energia (ANDE) | E16: =IF($A16="",0,SUMIFS(L_VDesp,L_SubID,$A16,L_Ano,CFG_ANO,L_Status,"REALIZADO")+SUMIFS(L_VRec,L_SubID,$A16,L_Ano,CFG_ANO,L_Status,"REALIZADO")+SUMIFS(L_VRend,L_SubID,$A16,L_Ano,CFG_ANO,L_Status,"REALIZADO")) -> 0 | F16: =IF($A16="",0,SUMIFS(L_VDesp,L_SubID,$A16,L_Ano,CFG_ANO,L_Status,"PROJETADO")+SUMIFS(L_VRec,L_SubID,$A16,L_Ano,CFG_ANO,L_Status,"PROJETADO")+SUMIFS(L_VRend,L_SubID,$A16,L_Ano,CFG_ANO,L_Status,"PROJETADO")) -> 0 | G16: =IF($A16="","",COUNTIFS($C$5:$C16,$C16)) -> 2 | H16: Ativo
... A58: =IF($B58="","","SUB-"&TEXT(ROW()-4,"000000")) -> SUB-000054 | B58: Transferencias | C58: =IF($B58="","",IFERROR(INDEX(CAT_ID,MATCH($B58,CAT_NOME,0)),"?")) -> CAT-000013 | D58: Saque/Deposito | E58: =IF($A58="",0,SUMIFS(L_VDesp,L_SubID,$A58,L_Ano,CFG_ANO,L_Status,"REALIZADO")+SUMIFS(L_VRec,L_SubID,$A58,L_Ano,CFG_ANO,L_Status,"REALIZADO")+SUMIFS(L_VRend,L_SubID,$A58,L_Ano,CFG_ANO,L_Status,"REALIZADO")) -> 0 | F58: =IF($A58="",0,SUMIFS(L_VDesp,L_SubID,$A58,L_Ano,CFG_ANO,L_Status,"PROJETADO")+SUMIFS(L_VRec,L_SubID,$A58,L_Ano,CFG_ANO,L_Status,"PROJETADO")+SUMIFS(L_VRend,L_SubID,$A58,L_Ano,CFG_ANO,L_Status,"PROJETADO")) -> 0 | G58: =IF($A58="","",COUNTIFS($C$5:$C58,$C58)) -> 2 | H58: Ativo
A59: =IF($B59="","","SUB-"&TEXT(ROW()-4,"000000")) | C59: =IF($B59="","",IFERROR(INDEX(CAT_ID,MATCH($B59,CAT_NOME,0)),"?")) | E59: =IF($A59="",0,SUMIFS(L_VDesp,L_SubID,$A59,L_Ano,CFG_ANO,L_Status,"REALIZADO")+SUMIFS(L_VRec,L_SubID,$A59,L_Ano,CFG_ANO,L_Status,"REALIZADO")+SUMIFS(L_VRend,L_SubID,$A59,L_Ano,CFG_ANO,L_Status,"REALIZADO")) -> 0 | F59: =IF($A59="",0,SUMIFS(L_VDesp,L_SubID,$A59,L_Ano,CFG_ANO,L_Status,"PROJETADO")+SUMIFS(L_VRec,L_SubID,$A59,L_Ano,CFG_ANO,L_Status,"PROJETADO")+SUMIFS(L_VRend,L_SubID,$A59,L_Ano,CFG_ANO,L_Status,"PROJETADO")) -> 0 | G59: =IF($A59="","",COUNTIFS($C$5:$C59,$C59))
A60: =IF($B60="","","SUB-"&TEXT(ROW()-4,"000000")) | C60: =IF($B60="","",IFERROR(INDEX(CAT_ID,MATCH($B60,CAT_NOME,0)),"?")) | E60: =IF($A60="",0,SUMIFS(L_VDesp,L_SubID,$A60,L_Ano,CFG_ANO,L_Status,"REALIZADO")+SUMIFS(L_VRec,L_SubID,$A60,L_Ano,CFG_ANO,L_Status,"REALIZADO")+SUMIFS(L_VRend,L_SubID,$A60,L_Ano,CFG_ANO,L_Status,"REALIZADO")) -> 0 | F60: =IF($A60="",0,SUMIFS(L_VDesp,L_SubID,$A60,L_Ano,CFG_ANO,L_Status,"PROJETADO")+SUMIFS(L_VRec,L_SubID,$A60,L_Ano,CFG_ANO,L_Status,"PROJETADO")+SUMIFS(L_VRend,L_SubID,$A60,L_Ano,CFG_ANO,L_Status,"PROJETADO")) -> 0 | G60: =IF($A60="","",COUNTIFS($C$5:$C60,$C60))
A61: =IF($B61="","","SUB-"&TEXT(ROW()-4,"000000")) | C61: =IF($B61="","",IFERROR(INDEX(CAT_ID,MATCH($B61,CAT_NOME,0)),"?")) | E61: =IF($A61="",0,SUMIFS(L_VDesp,L_SubID,$A61,L_Ano,CFG_ANO,L_Status,"REALIZADO")+SUMIFS(L_VRec,L_SubID,$A61,L_Ano,CFG_ANO,L_Status,"REALIZADO")+SUMIFS(L_VRend,L_SubID,$A61,L_Ano,CFG_ANO,L_Status,"REALIZADO")) -> 0 | F61: =IF($A61="",0,SUMIFS(L_VDesp,L_SubID,$A61,L_Ano,CFG_ANO,L_Status,"PROJETADO")+SUMIFS(L_VRec,L_SubID,$A61,L_Ano,CFG_ANO,L_Status,"PROJETADO")+SUMIFS(L_VRend,L_SubID,$A61,L_Ano,CFG_ANO,L_Status,"PROJETADO")) -> 0 | G61: =IF($A61="","",COUNTIFS($C$5:$C61,$C61))
A62: =IF($B62="","","SUB-"&TEXT(ROW()-4,"000000")) | C62: =IF($B62="","",IFERROR(INDEX(CAT_ID,MATCH($B62,CAT_NOME,0)),"?")) | E62: =IF($A62="",0,SUMIFS(L_VDesp,L_SubID,$A62,L_Ano,CFG_ANO,L_Status,"REALIZADO")+SUMIFS(L_VRec,L_SubID,$A62,L_Ano,CFG_ANO,L_Status,"REALIZADO")+SUMIFS(L_VRend,L_SubID,$A62,L_Ano,CFG_ANO,L_Status,"REALIZADO")) -> 0 | F62: =IF($A62="",0,SUMIFS(L_VDesp,L_SubID,$A62,L_Ano,CFG_ANO,L_Status,"PROJETADO")+SUMIFS(L_VRec,L_SubID,$A62,L_Ano,CFG_ANO,L_Status,"PROJETADO")+SUMIFS(L_VRend,L_SubID,$A62,L_Ano,CFG_ANO,L_Status,"PROJETADO")) -> 0 | G62: =IF($A62="","",COUNTIFS($C$5:$C62,$C62))
A63: =IF($B63="","","SUB-"&TEXT(ROW()-4,"000000")) | C63: =IF($B63="","",IFERROR(INDEX(CAT_ID,MATCH($B63,CAT_NOME,0)),"?")) | E63: =IF($A63="",0,SUMIFS(L_VDesp,L_SubID,$A63,L_Ano,CFG_ANO,L_Status,"REALIZADO")+SUMIFS(L_VRec,L_SubID,$A63,L_Ano,CFG_ANO,L_Status,"REALIZADO")+SUMIFS(L_VRend,L_SubID,$A63,L_Ano,CFG_ANO,L_Status,"REALIZADO")) -> 0 | F63: =IF($A63="",0,SUMIFS(L_VDesp,L_SubID,$A63,L_Ano,CFG_ANO,L_Status,"PROJETADO")+SUMIFS(L_VRec,L_SubID,$A63,L_Ano,CFG_ANO,L_Status,"PROJETADO")+SUMIFS(L_VRend,L_SubID,$A63,L_Ano,CFG_ANO,L_Status,"PROJETADO")) -> 0 | G63: =IF($A63="","",COUNTIFS($C$5:$C63,$C63))
A64: =IF($B64="","","SUB-"&TEXT(ROW()-4,"000000")) | C64: =IF($B64="","",IFERROR(INDEX(CAT_ID,MATCH($B64,CAT_NOME,0)),"?")) | E64: =IF($A64="",0,SUMIFS(L_VDesp,L_SubID,$A64,L_Ano,CFG_ANO,L_Status,"REALIZADO")+SUMIFS(L_VRec,L_SubID,$A64,L_Ano,CFG_ANO,L_Status,"REALIZADO")+SUMIFS(L_VRend,L_SubID,$A64,L_Ano,CFG_ANO,L_Status,"REALIZADO")) -> 0 | F64: =IF($A64="",0,SUMIFS(L_VDesp,L_SubID,$A64,L_Ano,CFG_ANO,L_Status,"PROJETADO")+SUMIFS(L_VRec,L_SubID,$A64,L_Ano,CFG_ANO,L_Status,"PROJETADO")+SUMIFS(L_VRend,L_SubID,$A64,L_Ano,CFG_ANO,L_Status,"PROJETADO")) -> 0 | G64: =IF($A64="","",COUNTIFS($C$5:$C64,$C64))
A65: =IF($B65="","","SUB-"&TEXT(ROW()-4,"000000")) | C65: =IF($B65="","",IFERROR(INDEX(CAT_ID,MATCH($B65,CAT_NOME,0)),"?")) | E65: =IF($A65="",0,SUMIFS(L_VDesp,L_SubID,$A65,L_Ano,CFG_ANO,L_Status,"REALIZADO")+SUMIFS(L_VRec,L_SubID,$A65,L_Ano,CFG_ANO,L_Status,"REALIZADO")+SUMIFS(L_VRend,L_SubID,$A65,L_Ano,CFG_ANO,L_Status,"REALIZADO")) -> 0 | F65: =IF($A65="",0,SUMIFS(L_VDesp,L_SubID,$A65,L_Ano,CFG_ANO,L_Status,"PROJETADO")+SUMIFS(L_VRec,L_SubID,$A65,L_Ano,CFG_ANO,L_Status,"PROJETADO")+SUMIFS(L_VRend,L_SubID,$A65,L_Ano,CFG_ANO,L_Status,"PROJETADO")) -> 0 | G65: =IF($A65="","",COUNTIFS($C$5:$C65,$C65))
A66: =IF($B66="","","SUB-"&TEXT(ROW()-4,"000000")) | C66: =IF($B66="","",IFERROR(INDEX(CAT_ID,MATCH($B66,CAT_NOME,0)),"?")) | E66: =IF($A66="",0,SUMIFS(L_VDesp,L_SubID,$A66,L_Ano,CFG_ANO,L_Status,"REALIZADO")+SUMIFS(L_VRec,L_SubID,$A66,L_Ano,CFG_ANO,L_Status,"REALIZADO")+SUMIFS(L_VRend,L_SubID,$A66,L_Ano,CFG_ANO,L_Status,"REALIZADO")) -> 0 | F66: =IF($A66="",0,SUMIFS(L_VDesp,L_SubID,$A66,L_Ano,CFG_ANO,L_Status,"PROJETADO")+SUMIFS(L_VRec,L_SubID,$A66,L_Ano,CFG_ANO,L_Status,"PROJETADO")+SUMIFS(L_VRend,L_SubID,$A66,L_Ano,CFG_ANO,L_Status,"PROJETADO")) -> 0 | G66: =IF($A66="","",COUNTIFS($C$5:$C66,$C66))
A67: =IF($B67="","","SUB-"&TEXT(ROW()-4,"000000")) | C67: =IF($B67="","",IFERROR(INDEX(CAT_ID,MATCH($B67,CAT_NOME,0)),"?")) | E67: =IF($A67="",0,SUMIFS(L_VDesp,L_SubID,$A67,L_Ano,CFG_ANO,L_Status,"REALIZADO")+SUMIFS(L_VRec,L_SubID,$A67,L_Ano,CFG_ANO,L_Status,"REALIZADO")+SUMIFS(L_VRend,L_SubID,$A67,L_Ano,CFG_ANO,L_Status,"REALIZADO")) -> 0 | F67: =IF($A67="",0,SUMIFS(L_VDesp,L_SubID,$A67,L_Ano,CFG_ANO,L_Status,"PROJETADO")+SUMIFS(L_VRec,L_SubID,$A67,L_Ano,CFG_ANO,L_Status,"PROJETADO")+SUMIFS(L_VRend,L_SubID,$A67,L_Ano,CFG_ANO,L_Status,"PROJETADO")) -> 0 | G67: =IF($A67="","",COUNTIFS($C$5:$C67,$C67))
A68: =IF($B68="","","SUB-"&TEXT(ROW()-4,"000000")) | C68: =IF($B68="","",IFERROR(INDEX(CAT_ID,MATCH($B68,CAT_NOME,0)),"?")) | E68: =IF($A68="",0,SUMIFS(L_VDesp,L_SubID,$A68,L_Ano,CFG_ANO,L_Status,"REALIZADO")+SUMIFS(L_VRec,L_SubID,$A68,L_Ano,CFG_ANO,L_Status,"REALIZADO")+SUMIFS(L_VRend,L_SubID,$A68,L_Ano,CFG_ANO,L_Status,"REALIZADO")) -> 0 | F68: =IF($A68="",0,SUMIFS(L_VDesp,L_SubID,$A68,L_Ano,CFG_ANO,L_Status,"PROJETADO")+SUMIFS(L_VRec,L_SubID,$A68,L_Ano,CFG_ANO,L_Status,"PROJETADO")+SUMIFS(L_VRend,L_SubID,$A68,L_Ano,CFG_ANO,L_Status,"PROJETADO")) -> 0 | G68: =IF($A68="","",COUNTIFS($C$5:$C68,$C68))
A69: =IF($B69="","","SUB-"&TEXT(ROW()-4,"000000")) | C69: =IF($B69="","",IFERROR(INDEX(CAT_ID,MATCH($B69,CAT_NOME,0)),"?")) | E69: =IF($A69="",0,SUMIFS(L_VDesp,L_SubID,$A69,L_Ano,CFG_ANO,L_Status,"REALIZADO")+SUMIFS(L_VRec,L_SubID,$A69,L_Ano,CFG_ANO,L_Status,"REALIZADO")+SUMIFS(L_VRend,L_SubID,$A69,L_Ano,CFG_ANO,L_Status,"REALIZADO")) -> 0 | F69: =IF($A69="",0,SUMIFS(L_VDesp,L_SubID,$A69,L_Ano,CFG_ANO,L_Status,"PROJETADO")+SUMIFS(L_VRec,L_SubID,$A69,L_Ano,CFG_ANO,L_Status,"PROJETADO")+SUMIFS(L_VRend,L_SubID,$A69,L_Ano,CFG_ANO,L_Status,"PROJETADO")) -> 0 | G69: =IF($A69="","",COUNTIFS($C$5:$C69,$C69))
A70: =IF($B70="","","SUB-"&TEXT(ROW()-4,"000000")) | C70: =IF($B70="","",IFERROR(INDEX(CAT_ID,MATCH($B70,CAT_NOME,0)),"?")) | E70: =IF($A70="",0,SUMIFS(L_VDesp,L_SubID,$A70,L_Ano,CFG_ANO,L_Status,"REALIZADO")+SUMIFS(L_VRec,L_SubID,$A70,L_Ano,CFG_ANO,L_Status,"REALIZADO")+SUMIFS(L_VRend,L_SubID,$A70,L_Ano,CFG_ANO,L_Status,"REALIZADO")) -> 0 | F70: =IF($A70="",0,SUMIFS(L_VDesp,L_SubID,$A70,L_Ano,CFG_ANO,L_Status,"PROJETADO")+SUMIFS(L_VRec,L_SubID,$A70,L_Ano,CFG_ANO,L_Status,"PROJETADO")+SUMIFS(L_VRend,L_SubID,$A70,L_Ano,CFG_ANO,L_Status,"PROJETADO")) -> 0 | G70: =IF($A70="","",COUNTIFS($C$5:$C70,$C70))
... A124: =IF($B124="","","SUB-"&TEXT(ROW()-4,"000000")) | C124: =IF($B124="","",IFERROR(INDEX(CAT_ID,MATCH($B124,CAT_NOME,0)),"?")) | E124: =IF($A124="",0,SUMIFS(L_VDesp,L_SubID,$A124,L_Ano,CFG_ANO,L_Status,"REALIZADO")+SUMIFS(L_VRec,L_SubID,$A124,L_Ano,CFG_ANO,L_Status,"REALIZADO")+SUMIFS(L_VRend,L_SubID,$A124,L_Ano,CFG_ANO,L_Status,"REALIZADO")) -> 0 | F124: =IF($A124="",0,SUMIFS(L_VDesp,L_SubID,$A124,L_Ano,CFG_ANO,L_Status,"PROJETADO")+SUMIFS(L_VRec,L_SubID,$A124,L_Ano,CFG_ANO,L_Status,"PROJETADO")+SUMIFS(L_VRend,L_SubID,$A124,L_Ano,CFG_ANO,L_Status,"PROJETADO")) -> 0 | G124: =IF($A124="","",COUNTIFS($C$5:$C124,$C124))

Sheet CAD_Compromissos
A1: CAD_COMPROMISSOS - PARCELAMENTOS E FINANCIAMENTOS
A2: PARA APAGAR UM REGISTRO: selecione as celulas AMARELAS da linha e pressione DELETE (limpar conteudo). NUNCA use 'Excluir linha' nem classifique (sort) esta aba: os IDs sao gerados pela posicao da linha e os vinculos seriam quebrados em silencio. Para anular um lancamento sem perder o historico use o campo Status (CANCELADO / Inativo). Para pesquisar use os filtros do cabecalho.
A4: ID_Compromisso | B4: Nome | C4: Categoria | D4: ID_Categoria | E4: Subcategoria | F4: ID_Subcategoria | G4: Qtd_Parcelas | H4: Valor_Parcela | I4: Valor_Total | J4: Data_Primeira_Parcela | K4: Dia_Vencimento | L4: Periodicidade | M4: Parcelas_Pagas_Antes | N4: Entidade_Tipo | O4: Entidade_ID | P4: Parcelas_Pagas | Q4: Parcelas_Abertas | R4: Parcelas_Atrasadas | S4: Parcelas_Projetadas | T4: Parcelas_Restantes | U4: Valor_Pago | V4: Saldo_Devedor | W4: Parcela_Atual | X4: Proximo_Vencimento | Y4: Status | Z4: Observacao
A5: =IF($B5="","","CMP-"&TEXT(ROW()-4,"000000")) | D5: =IF($B5="","",IFERROR(INDEX(CAT_ID,MATCH($C5,CAT_NOME,0)),"?")) | F5: =IF($E5="","",IFERROR(INDEX(SUB_ID,MATCH(1,INDEX((SUB_NOME=$E5)*(SUB_CATID=$D5),0),0)),"?")) | I5: =IF($A5="","",$G5*$H5) | P5: =IF($A5="",0,COUNTIFS(P_CMP,$A5,P_STATUS,"PAGA")) -> 0 | Q5: =IF($A5="",0,COUNTIFS(P_CMP,$A5,P_STATUS,"ABERTA")) -> 0 | R5: =IF($A5="",0,COUNTIFS(P_CMP,$A5,P_STATUS,"ATRASADA")) -> 0 | S5: =IF($A5="",0,COUNTIFS(P_CMP,$A5,P_STATUS,"PROJETADA")) -> 0 | T5: =IF($A5="","",$G5-$P5) | U5: =IF($A5="",0,SUMIFS(P_VALOR,P_CMP,$A5,P_STATUS,"PAGA")) -> 0 | V5: =IF($A5="","",$I5-$U5) | W5: =IF($A5="","",MIN($G5,$P5+1)&"/"&$G5) | X5: =IF($A5="","",IFERROR(INDEX(P_VENC,MATCH(1,INDEX((P_CMP=$A5)*(P_STATUS<>"PAGA")*(P_STATUS<>"CANCELADA"),0),0)),""))
A6: =IF($B6="","","CMP-"&TEXT(ROW()-4,"000000")) | D6: =IF($B6="","",IFERROR(INDEX(CAT_ID,MATCH($C6,CAT_NOME,0)),"?")) | F6: =IF($E6="","",IFERROR(INDEX(SUB_ID,MATCH(1,INDEX((SUB_NOME=$E6)*(SUB_CATID=$D6),0),0)),"?")) | I6: =IF($A6="","",$G6*$H6) | P6: =IF($A6="",0,COUNTIFS(P_CMP,$A6,P_STATUS,"PAGA")) -> 0 | Q6: =IF($A6="",0,COUNTIFS(P_CMP,$A6,P_STATUS,"ABERTA")) -> 0 | R6: =IF($A6="",0,COUNTIFS(P_CMP,$A6,P_STATUS,"ATRASADA")) -> 0 | S6: =IF($A6="",0,COUNTIFS(P_CMP,$A6,P_STATUS,"PROJETADA")) -> 0 | T6: =IF($A6="","",$G6-$P6) | U6: =IF($A6="",0,SUMIFS(P_VALOR,P_CMP,$A6,P_STATUS,"PAGA")) -> 0 | V6: =IF($A6="","",$I6-$U6) | W6: =IF($A6="","",MIN($G6,$P6+1)&"/"&$G6) | X6: =IF($A6="","",IFERROR(INDEX(P_VENC,MATCH(1,INDEX((P_CMP=$A6)*(P_STATUS<>"PAGA")*(P_STATUS<>"CANCELADA"),0),0)),""))
A7: =IF($B7="","","CMP-"&TEXT(ROW()-4,"000000")) | D7: =IF($B7="","",IFERROR(INDEX(CAT_ID,MATCH($C7,CAT_NOME,0)),"?")) | F7: =IF($E7="","",IFERROR(INDEX(SUB_ID,MATCH(1,INDEX((SUB_NOME=$E7)*(SUB_CATID=$D7),0),0)),"?")) | I7: =IF($A7="","",$G7*$H7) | P7: =IF($A7="",0,COUNTIFS(P_CMP,$A7,P_STATUS,"PAGA")) -> 0 | Q7: =IF($A7="",0,COUNTIFS(P_CMP,$A7,P_STATUS,"ABERTA")) -> 0 | R7: =IF($A7="",0,COUNTIFS(P_CMP,$A7,P_STATUS,"ATRASADA")) -> 0 | S7: =IF($A7="",0,COUNTIFS(P_CMP,$A7,P_STATUS,"PROJETADA")) -> 0 | T7: =IF($A7="","",$G7-$P7) | U7: =IF($A7="",0,SUMIFS(P_VALOR,P_CMP,$A7,P_STATUS,"PAGA")) -> 0 | V7: =IF($A7="","",$I7-$U7) | W7: =IF($A7="","",MIN($G7,$P7+1)&"/"&$G7) | X7: =IF($A7="","",IFERROR(INDEX(P_VENC,MATCH(1,INDEX((P_CMP=$A7)*(P_STATUS<>"PAGA")*(P_STATUS<>"CANCELADA"),0),0)),""))
A8: =IF($B8="","","CMP-"&TEXT(ROW()-4,"000000")) | D8: =IF($B8="","",IFERROR(INDEX(CAT_ID,MATCH($C8,CAT_NOME,0)),"?")) | F8: =IF($E8="","",IFERROR(INDEX(SUB_ID,MATCH(1,INDEX((SUB_NOME=$E8)*(SUB_CATID=$D8),0),0)),"?")) | I8: =IF($A8="","",$G8*$H8) | P8: =IF($A8="",0,COUNTIFS(P_CMP,$A8,P_STATUS,"PAGA")) -> 0 | Q8: =IF($A8="",0,COUNTIFS(P_CMP,$A8,P_STATUS,"ABERTA")) -> 0 | R8: =IF($A8="",0,COUNTIFS(P_CMP,$A8,P_STATUS,"ATRASADA")) -> 0 | S8: =IF($A8="",0,COUNTIFS(P_CMP,$A8,P_STATUS,"PROJETADA")) -> 0 | T8: =IF($A8="","",$G8-$P8) | U8: =IF($A8="",0,SUMIFS(P_VALOR,P_CMP,$A8,P_STATUS,"PAGA")) -> 0 | V8: =IF($A8="","",$I8-$U8) | W8: =IF($A8="","",MIN($G8,$P8+1)&"/"&$G8) | X8: =IF($A8="","",IFERROR(INDEX(P_VENC,MATCH(1,INDEX((P_CMP=$A8)*(P_STATUS<>"PAGA")*(P_STATUS<>"CANCELADA"),0),0)),""))
A9: =IF($B9="","","CMP-"&TEXT(ROW()-4,"000000")) | D9: =IF($B9="","",IFERROR(INDEX(CAT_ID,MATCH($C9,CAT_NOME,0)),"?")) | F9: =IF($E9="","",IFERROR(INDEX(SUB_ID,MATCH(1,INDEX((SUB_NOME=$E9)*(SUB_CATID=$D9),0),0)),"?")) | I9: =IF($A9="","",$G9*$H9) | P9: =IF($A9="",0,COUNTIFS(P_CMP,$A9,P_STATUS,"PAGA")) -> 0 | Q9: =IF($A9="",0,COUNTIFS(P_CMP,$A9,P_STATUS,"ABERTA")) -> 0 | R9: =IF($A9="",0,COUNTIFS(P_CMP,$A9,P_STATUS,"ATRASADA")) -> 0 | S9: =IF($A9="",0,COUNTIFS(P_CMP,$A9,P_STATUS,"PROJETADA")) -> 0 | T9: =IF($A9="","",$G9-$P9) | U9: =IF($A9="",0,SUMIFS(P_VALOR,P_CMP,$A9,P_STATUS,"PAGA")) -> 0 | V9: =IF($A9="","",$I9-$U9) | W9: =IF($A9="","",MIN($G9,$P9+1)&"/"&$G9) | X9: =IF($A9="","",IFERROR(INDEX(P_VENC,MATCH(1,INDEX((P_CMP=$A9)*(P_STATUS<>"PAGA")*(P_STATUS<>"CANCELADA"),0),0)),""))
A10: =IF($B10="","","CMP-"&TEXT(ROW()-4,"000000")) | D10: =IF($B10="","",IFERROR(INDEX(CAT_ID,MATCH($C10,CAT_NOME,0)),"?")) | F10: =IF($E10="","",IFERROR(INDEX(SUB_ID,MATCH(1,INDEX((SUB_NOME=$E10)*(SUB_CATID=$D10),0),0)),"?")) | I10: =IF($A10="","",$G10*$H10) | P10: =IF($A10="",0,COUNTIFS(P_CMP,$A10,P_STATUS,"PAGA")) -> 0 | Q10: =IF($A10="",0,COUNTIFS(P_CMP,$A10,P_STATUS,"ABERTA")) -> 0 | R10: =IF($A10="",0,COUNTIFS(P_CMP,$A10,P_STATUS,"ATRASADA")) -> 0 | S10: =IF($A10="",0,COUNTIFS(P_CMP,$A10,P_STATUS,"PROJETADA")) -> 0 | T10: =IF($A10="","",$G10-$P10) | U10: =IF($A10="",0,SUMIFS(P_VALOR,P_CMP,$A10,P_STATUS,"PAGA")) -> 0 | V10: =IF($A10="","",$I10-$U10) | W10: =IF($A10="","",MIN($G10,$P10+1)&"/"&$G10) | X10: =IF($A10="","",IFERROR(INDEX(P_VENC,MATCH(1,INDEX((P_CMP=$A10)*(P_STATUS<>"PAGA")*(P_STATUS<>"CANCELADA"),0),0)),""))
A11: =IF($B11="","","CMP-"&TEXT(ROW()-4,"000000")) | D11: =IF($B11="","",IFERROR(INDEX(CAT_ID,MATCH($C11,CAT_NOME,0)),"?")) | F11: =IF($E11="","",IFERROR(INDEX(SUB_ID,MATCH(1,INDEX((SUB_NOME=$E11)*(SUB_CATID=$D11),0),0)),"?")) | I11: =IF($A11="","",$G11*$H11) | P11: =IF($A11="",0,COUNTIFS(P_CMP,$A11,P_STATUS,"PAGA")) -> 0 | Q11: =IF($A11="",0,COUNTIFS(P_CMP,$A11,P_STATUS,"ABERTA")) -> 0 | R11: =IF($A11="",0,COUNTIFS(P_CMP,$A11,P_STATUS,"ATRASADA")) -> 0 | S11: =IF($A11="",0,COUNTIFS(P_CMP,$A11,P_STATUS,"PROJETADA")) -> 0 | T11: =IF($A11="","",$G11-$P11) | U11: =IF($A11="",0,SUMIFS(P_VALOR,P_CMP,$A11,P_STATUS,"PAGA")) -> 0 | V11: =IF($A11="","",$I11-$U11) | W11: =IF($A11="","",MIN($G11,$P11+1)&"/"&$G11) | X11: =IF($A11="","",IFERROR(INDEX(P_VENC,MATCH(1,INDEX((P_CMP=$A11)*(P_STATUS<>"PAGA")*(P_STATUS<>"CANCELADA"),0),0)),""))
A12: =IF($B12="","","CMP-"&TEXT(ROW()-4,"000000")) | D12: =IF($B12="","",IFERROR(INDEX(CAT_ID,MATCH($C12,CAT_NOME,0)),"?")) | F12: =IF($E12="","",IFERROR(INDEX(SUB_ID,MATCH(1,INDEX((SUB_NOME=$E12)*(SUB_CATID=$D12),0),0)),"?")) | I12: =IF($A12="","",$G12*$H12) | P12: =IF($A12="",0,COUNTIFS(P_CMP,$A12,P_STATUS,"PAGA")) -> 0 | Q12: =IF($A12="",0,COUNTIFS(P_CMP,$A12,P_STATUS,"ABERTA")) -> 0 | R12: =IF($A12="",0,COUNTIFS(P_CMP,$A12,P_STATUS,"ATRASADA")) -> 0 | S12: =IF($A12="",0,COUNTIFS(P_CMP,$A12,P_STATUS,"PROJETADA")) -> 0 | T12: =IF($A12="","",$G12-$P12) | U12: =IF($A12="",0,SUMIFS(P_VALOR,P_CMP,$A12,P_STATUS,"PAGA")) -> 0 | V12: =IF($A12="","",$I12-$U12) | W12: =IF($A12="","",MIN($G12,$P12+1)&"/"&$G12) | X12: =IF($A12="","",IFERROR(INDEX(P_VENC,MATCH(1,INDEX((P_CMP=$A12)*(P_STATUS<>"PAGA")*(P_STATUS<>"CANCELADA"),0),0)),""))
A13: =IF($B13="","","CMP-"&TEXT(ROW()-4,"000000")) | D13: =IF($B13="","",IFERROR(INDEX(CAT_ID,MATCH($C13,CAT_NOME,0)),"?")) | F13: =IF($E13="","",IFERROR(INDEX(SUB_ID,MATCH(1,INDEX((SUB_NOME=$E13)*(SUB_CATID=$D13),0),0)),"?")) | I13: =IF($A13="","",$G13*$H13) | P13: =IF($A13="",0,COUNTIFS(P_CMP,$A13,P_STATUS,"PAGA")) -> 0 | Q13: =IF($A13="",0,COUNTIFS(P_CMP,$A13,P_STATUS,"ABERTA")) -> 0 | R13: =IF($A13="",0,COUNTIFS(P_CMP,$A13,P_STATUS,"ATRASADA")) -> 0 | S13: =IF($A13="",0,COUNTIFS(P_CMP,$A13,P_STATUS,"PROJETADA")) -> 0 | T13: =IF($A13="","",$G13-$P13) | U13: =IF($A13="",0,SUMIFS(P_VALOR,P_CMP,$A13,P_STATUS,"PAGA")) -> 0 | V13: =IF($A13="","",$I13-$U13) | W13: =IF($A13="","",MIN($G13,$P13+1)&"/"&$G13) | X13: =IF($A13="","",IFERROR(INDEX(P_VENC,MATCH(1,INDEX((P_CMP=$A13)*(P_STATUS<>"PAGA")*(P_STATUS<>"CANCELADA"),0),0)),""))
A14: =IF($B14="","","CMP-"&TEXT(ROW()-4,"000000")) | D14: =IF($B14="","",IFERROR(INDEX(CAT_ID,MATCH($C14,CAT_NOME,0)),"?")) | F14: =IF($E14="","",IFERROR(INDEX(SUB_ID,MATCH(1,INDEX((SUB_NOME=$E14)*(SUB_CATID=$D14),0),0)),"?")) | I14: =IF($A14="","",$G14*$H14) | P14: =IF($A14="",0,COUNTIFS(P_CMP,$A14,P_STATUS,"PAGA")) -> 0 | Q14: =IF($A14="",0,COUNTIFS(P_CMP,$A14,P_STATUS,"ABERTA")) -> 0 | R14: =IF($A14="",0,COUNTIFS(P_CMP,$A14,P_STATUS,"ATRASADA")) -> 0 | S14: =IF($A14="",0,COUNTIFS(P_CMP,$A14,P_STATUS,"PROJETADA")) -> 0 | T14: =IF($A14="","",$G14-$P14) | U14: =IF($A14="",0,SUMIFS(P_VALOR,P_CMP,$A14,P_STATUS,"PAGA")) -> 0 | V14: =IF($A14="","",$I14-$U14) | W14: =IF($A14="","",MIN($G14,$P14+1)&"/"&$G14) | X14: =IF($A14="","",IFERROR(INDEX(P_VENC,MATCH(1,INDEX((P_CMP=$A14)*(P_STATUS<>"PAGA")*(P_STATUS<>"CANCELADA"),0),0)),""))
A15: =IF($B15="","","CMP-"&TEXT(ROW()-4,"000000")) | D15: =IF($B15="","",IFERROR(INDEX(CAT_ID,MATCH($C15,CAT_NOME,0)),"?")) | F15: =IF($E15="","",IFERROR(INDEX(SUB_ID,MATCH(1,INDEX((SUB_NOME=$E15)*(SUB_CATID=$D15),0),0)),"?")) | I15: =IF($A15="","",$G15*$H15) | P15: =IF($A15="",0,COUNTIFS(P_CMP,$A15,P_STATUS,"PAGA")) -> 0 | Q15: =IF($A15="",0,COUNTIFS(P_CMP,$A15,P_STATUS,"ABERTA")) -> 0 | R15: =IF($A15="",0,COUNTIFS(P_CMP,$A15,P_STATUS,"ATRASADA")) -> 0 | S15: =IF($A15="",0,COUNTIFS(P_CMP,$A15,P_STATUS,"PROJETADA")) -> 0 | T15: =IF($A15="","",$G15-$P15) | U15: =IF($A15="",0,SUMIFS(P_VALOR,P_CMP,$A15,P_STATUS,"PAGA")) -> 0 | V15: =IF($A15="","",$I15-$U15) | W15: =IF($A15="","",MIN($G15,$P15+1)&"/"&$G15) | X15: =IF($A15="","",IFERROR(INDEX(P_VENC,MATCH(1,INDEX((P_CMP=$A15)*(P_STATUS<>"PAGA")*(P_STATUS<>"CANCELADA"),0),0)),""))
A16: =IF($B16="","","CMP-"&TEXT(ROW()-4,"000000")) | D16: =IF($B16="","",IFERROR(INDEX(CAT_ID,MATCH($C16,CAT_NOME,0)),"?")) | F16: =IF($E16="","",IFERROR(INDEX(SUB_ID,MATCH(1,INDEX((SUB_NOME=$E16)*(SUB_CATID=$D16),0),0)),"?")) | I16: =IF($A16="","",$G16*$H16) | P16: =IF($A16="",0,COUNTIFS(P_CMP,$A16,P_STATUS,"PAGA")) -> 0 | Q16: =IF($A16="",0,COUNTIFS(P_CMP,$A16,P_STATUS,"ABERTA")) -> 0 | R16: =IF($A16="",0,COUNTIFS(P_CMP,$A16,P_STATUS,"ATRASADA")) -> 0 | S16: =IF($A16="",0,COUNTIFS(P_CMP,$A16,P_STATUS,"PROJETADA")) -> 0 | T16: =IF($A16="","",$G16-$P16) | U16: =IF($A16="",0,SUMIFS(P_VALOR,P_CMP,$A16,P_STATUS,"PAGA")) -> 0 | V16: =IF($A16="","",$I16-$U16) | W16: =IF($A16="","",MIN($G16,$P16+1)&"/"&$G16) | X16: =IF($A16="","",IFERROR(INDEX(P_VENC,MATCH(1,INDEX((P_CMP=$A16)*(P_STATUS<>"PAGA")*(P_STATUS<>"CANCELADA"),0),0)),""))
... A44: =IF($B44="","","CMP-"&TEXT(ROW()-4,"000000")) | D44: =IF($B44="","",IFERROR(INDEX(CAT_ID,MATCH($C44,CAT_NOME,0)),"?")) | F44: =IF($E44="","",IFERROR(INDEX(SUB_ID,MATCH(1,INDEX((SUB_NOME=$E44)*(SUB_CATID=$D44),0),0)),"?")) | I44: =IF($A44="","",$G44*$H44) | P44: =IF($A44="",0,COUNTIFS(P_CMP,$A44,P_STATUS,"PAGA")) -> 0 | Q44: =IF($A44="",0,COUNTIFS(P_CMP,$A44,P_STATUS,"ABERTA")) -> 0 | R44: =IF($A44="",0,COUNTIFS(P_CMP,$A44,P_STATUS,"ATRASADA")) -> 0 | S44: =IF($A44="",0,COUNTIFS(P_CMP,$A44,P_STATUS,"PROJETADA")) -> 0 | T44: =IF($A44="","",$G44-$P44) | U44: =IF($A44="",0,SUMIFS(P_VALOR,P_CMP,$A44,P_STATUS,"PAGA")) -> 0 | V44: =IF($A44="","",$I44-$U44) | W44: =IF($A44="","",MIN($G44,$P44+1)&"/"&$G44) | X44: =IF($A44="","",IFERROR(INDEX(P_VENC,MATCH(1,INDEX((P_CMP=$A44)*(P_STATUS<>"PAGA")*(P_STATUS<>"CANCELADA"),0),0)),""))

Sheet CAD_Metas
A1: CAD_METAS - METAS FINANCEIRAS (RESERVA LOGICA)
A2: PARA APAGAR UM REGISTRO: selecione as celulas AMARELAS da linha e pressione DELETE (limpar conteudo). NUNCA use 'Excluir linha' nem classifique (sort) esta aba: os IDs sao gerados pela posicao da linha e os vinculos seriam quebrados em silencio. Para anular um lancamento sem perder o historico use o campo Status (CANCELADO / Inativo). Para pesquisar use os filtros do cabecalho.
A4: ID_Meta | B4: Nome | C4: Valor_Objetivo | D4: Data_Prazo | E4: Conta_Vinculada_ID | F4: Investimento_Vinculado_ID | G4: Considerar_No_Fluxo | H4: Valor_Reservado | I4: Pct_Concluido | J4: Valor_Faltante | K4: Meses_Restantes | L4: Aporte_Mensal_Necessario | M4: Status | N4: Data_Conclusao | O4: Situacao | P4: Conta_Vinculada_Nome | Q4: Observacao
A5: =IF($B5="","","MET-"&TEXT(ROW()-4,"000000")) | H5: =IF($A5="",0,SUMIFS(MM_VALSINAL,MM_META,$A5)) -> 0 | I5: =IF(OR($A5="",$C5=0),0,$H5/$C5) -> 0 | J5: =IF($A5="","",MAX(0,$C5-$H5)) | K5: =IF(OR($A5="",$D5=""),0,MAX(0,(YEAR($D5)-YEAR(CFG_HOJE))*12+MONTH($D5)-MONTH(CFG_HOJE))) -> 0 | L5: =IF($A5="","",IF($K5<=0,$J5,ROUND($J5/$K5,0))) | O5: =IF($A5="","",IF($M5="Cancelada","CANCELADA",IF($M5="Concluida","CONCLUIDA",IF($H5>=$C5,"OBJETIVO ATINGIDO",IF($D5<CFG_HOJE,"PRAZO VENCIDO",IF($K5<=3,"EM RISCO","EM DIA")))))) | P5: =IF($E5="","",IFERROR(INDEX(C_NOME,MATCH($E5,C_ID,0)),"?"))
A6: =IF($B6="","","MET-"&TEXT(ROW()-4,"000000")) | H6: =IF($A6="",0,SUMIFS(MM_VALSINAL,MM_META,$A6)) -> 0 | I6: =IF(OR($A6="",$C6=0),0,$H6/$C6) -> 0 | J6: =IF($A6="","",MAX(0,$C6-$H6)) | K6: =IF(OR($A6="",$D6=""),0,MAX(0,(YEAR($D6)-YEAR(CFG_HOJE))*12+MONTH($D6)-MONTH(CFG_HOJE))) -> 0 | L6: =IF($A6="","",IF($K6<=0,$J6,ROUND($J6/$K6,0))) | O6: =IF($A6="","",IF($M6="Cancelada","CANCELADA",IF($M6="Concluida","CONCLUIDA",IF($H6>=$C6,"OBJETIVO ATINGIDO",IF($D6<CFG_HOJE,"PRAZO VENCIDO",IF($K6<=3,"EM RISCO","EM DIA")))))) | P6: =IF($E6="","",IFERROR(INDEX(C_NOME,MATCH($E6,C_ID,0)),"?"))
A7: =IF($B7="","","MET-"&TEXT(ROW()-4,"000000")) | H7: =IF($A7="",0,SUMIFS(MM_VALSINAL,MM_META,$A7)) -> 0 | I7: =IF(OR($A7="",$C7=0),0,$H7/$C7) -> 0 | J7: =IF($A7="","",MAX(0,$C7-$H7)) | K7: =IF(OR($A7="",$D7=""),0,MAX(0,(YEAR($D7)-YEAR(CFG_HOJE))*12+MONTH($D7)-MONTH(CFG_HOJE))) -> 0 | L7: =IF($A7="","",IF($K7<=0,$J7,ROUND($J7/$K7,0))) | O7: =IF($A7="","",IF($M7="Cancelada","CANCELADA",IF($M7="Concluida","CONCLUIDA",IF($H7>=$C7,"OBJETIVO ATINGIDO",IF($D7<CFG_HOJE,"PRAZO VENCIDO",IF($K7<=3,"EM RISCO","EM DIA")))))) | P7: =IF($E7="","",IFERROR(INDEX(C_NOME,MATCH($E7,C_ID,0)),"?"))
A8: =IF($B8="","","MET-"&TEXT(ROW()-4,"000000")) | H8: =IF($A8="",0,SUMIFS(MM_VALSINAL,MM_META,$A8)) -> 0 | I8: =IF(OR($A8="",$C8=0),0,$H8/$C8) -> 0 | J8: =IF($A8="","",MAX(0,$C8-$H8)) | K8: =IF(OR($A8="",$D8=""),0,MAX(0,(YEAR($D8)-YEAR(CFG_HOJE))*12+MONTH($D8)-MONTH(CFG_HOJE))) -> 0 | L8: =IF($A8="","",IF($K8<=0,$J8,ROUND($J8/$K8,0))) | O8: =IF($A8="","",IF($M8="Cancelada","CANCELADA",IF($M8="Concluida","CONCLUIDA",IF($H8>=$C8,"OBJETIVO ATINGIDO",IF($D8<CFG_HOJE,"PRAZO VENCIDO",IF($K8<=3,"EM RISCO","EM DIA")))))) | P8: =IF($E8="","",IFERROR(INDEX(C_NOME,MATCH($E8,C_ID,0)),"?"))
A9: =IF($B9="","","MET-"&TEXT(ROW()-4,"000000")) | H9: =IF($A9="",0,SUMIFS(MM_VALSINAL,MM_META,$A9)) -> 0 | I9: =IF(OR($A9="",$C9=0),0,$H9/$C9) -> 0 | J9: =IF($A9="","",MAX(0,$C9-$H9)) | K9: =IF(OR($A9="",$D9=""),0,MAX(0,(YEAR($D9)-YEAR(CFG_HOJE))*12+MONTH($D9)-MONTH(CFG_HOJE))) -> 0 | L9: =IF($A9="","",IF($K9<=0,$J9,ROUND($J9/$K9,0))) | O9: =IF($A9="","",IF($M9="Cancelada","CANCELADA",IF($M9="Concluida","CONCLUIDA",IF($H9>=$C9,"OBJETIVO ATINGIDO",IF($D9<CFG_HOJE,"PRAZO VENCIDO",IF($K9<=3,"EM RISCO","EM DIA")))))) | P9: =IF($E9="","",IFERROR(INDEX(C_NOME,MATCH($E9,C_ID,0)),"?"))
A10: =IF($B10="","","MET-"&TEXT(ROW()-4,"000000")) | H10: =IF($A10="",0,SUMIFS(MM_VALSINAL,MM_META,$A10)) -> 0 | I10: =IF(OR($A10="",$C10=0),0,$H10/$C10) -> 0 | J10: =IF($A10="","",MAX(0,$C10-$H10)) | K10: =IF(OR($A10="",$D10=""),0,MAX(0,(YEAR($D10)-YEAR(CFG_HOJE))*12+MONTH($D10)-MONTH(CFG_HOJE))) -> 0 | L10: =IF($A10="","",IF($K10<=0,$J10,ROUND($J10/$K10,0))) | O10: =IF($A10="","",IF($M10="Cancelada","CANCELADA",IF($M10="Concluida","CONCLUIDA",IF($H10>=$C10,"OBJETIVO ATINGIDO",IF($D10<CFG_HOJE,"PRAZO VENCIDO",IF($K10<=3,"EM RISCO","EM DIA")))))) | P10: =IF($E10="","",IFERROR(INDEX(C_NOME,MATCH($E10,C_ID,0)),"?"))
A11: =IF($B11="","","MET-"&TEXT(ROW()-4,"000000")) | H11: =IF($A11="",0,SUMIFS(MM_VALSINAL,MM_META,$A11)) -> 0 | I11: =IF(OR($A11="",$C11=0),0,$H11/$C11) -> 0 | J11: =IF($A11="","",MAX(0,$C11-$H11)) | K11: =IF(OR($A11="",$D11=""),0,MAX(0,(YEAR($D11)-YEAR(CFG_HOJE))*12+MONTH($D11)-MONTH(CFG_HOJE))) -> 0 | L11: =IF($A11="","",IF($K11<=0,$J11,ROUND($J11/$K11,0))) | O11: =IF($A11="","",IF($M11="Cancelada","CANCELADA",IF($M11="Concluida","CONCLUIDA",IF($H11>=$C11,"OBJETIVO ATINGIDO",IF($D11<CFG_HOJE,"PRAZO VENCIDO",IF($K11<=3,"EM RISCO","EM DIA")))))) | P11: =IF($E11="","",IFERROR(INDEX(C_NOME,MATCH($E11,C_ID,0)),"?"))
A12: =IF($B12="","","MET-"&TEXT(ROW()-4,"000000")) | H12: =IF($A12="",0,SUMIFS(MM_VALSINAL,MM_META,$A12)) -> 0 | I12: =IF(OR($A12="",$C12=0),0,$H12/$C12) -> 0 | J12: =IF($A12="","",MAX(0,$C12-$H12)) | K12: =IF(OR($A12="",$D12=""),0,MAX(0,(YEAR($D12)-YEAR(CFG_HOJE))*12+MONTH($D12)-MONTH(CFG_HOJE))) -> 0 | L12: =IF($A12="","",IF($K12<=0,$J12,ROUND($J12/$K12,0))) | O12: =IF($A12="","",IF($M12="Cancelada","CANCELADA",IF($M12="Concluida","CONCLUIDA",IF($H12>=$C12,"OBJETIVO ATINGIDO",IF($D12<CFG_HOJE,"PRAZO VENCIDO",IF($K12<=3,"EM RISCO","EM DIA")))))) | P12: =IF($E12="","",IFERROR(INDEX(C_NOME,MATCH($E12,C_ID,0)),"?"))
A13: =IF($B13="","","MET-"&TEXT(ROW()-4,"000000")) | H13: =IF($A13="",0,SUMIFS(MM_VALSINAL,MM_META,$A13)) -> 0 | I13: =IF(OR($A13="",$C13=0),0,$H13/$C13) -> 0 | J13: =IF($A13="","",MAX(0,$C13-$H13)) | K13: =IF(OR($A13="",$D13=""),0,MAX(0,(YEAR($D13)-YEAR(CFG_HOJE))*12+MONTH($D13)-MONTH(CFG_HOJE))) -> 0 | L13: =IF($A13="","",IF($K13<=0,$J13,ROUND($J13/$K13,0))) | O13: =IF($A13="","",IF($M13="Cancelada","CANCELADA",IF($M13="Concluida","CONCLUIDA",IF($H13>=$C13,"OBJETIVO ATINGIDO",IF($D13<CFG_HOJE,"PRAZO VENCIDO",IF($K13<=3,"EM RISCO","EM DIA")))))) | P13: =IF($E13="","",IFERROR(INDEX(C_NOME,MATCH($E13,C_ID,0)),"?"))
A14: =IF($B14="","","MET-"&TEXT(ROW()-4,"000000")) | H14: =IF($A14="",0,SUMIFS(MM_VALSINAL,MM_META,$A14)) -> 0 | I14: =IF(OR($A14="",$C14=0),0,$H14/$C14) -> 0 | J14: =IF($A14="","",MAX(0,$C14-$H14)) | K14: =IF(OR($A14="",$D14=""),0,MAX(0,(YEAR($D14)-YEAR(CFG_HOJE))*12+MONTH($D14)-MONTH(CFG_HOJE))) -> 0 | L14: =IF($A14="","",IF($K14<=0,$J14,ROUND($J14/$K14,0))) | O14: =IF($A14="","",IF($M14="Cancelada","CANCELADA",IF($M14="Concluida","CONCLUIDA",IF($H14>=$C14,"OBJETIVO ATINGIDO",IF($D14<CFG_HOJE,"PRAZO VENCIDO",IF($K14<=3,"EM RISCO","EM DIA")))))) | P14: =IF($E14="","",IFERROR(INDEX(C_NOME,MATCH($E14,C_ID,0)),"?"))
A15: =IF($B15="","","MET-"&TEXT(ROW()-4,"000000")) | H15: =IF($A15="",0,SUMIFS(MM_VALSINAL,MM_META,$A15)) -> 0 | I15: =IF(OR($A15="",$C15=0),0,$H15/$C15) -> 0 | J15: =IF($A15="","",MAX(0,$C15-$H15)) | K15: =IF(OR($A15="",$D15=""),0,MAX(0,(YEAR($D15)-YEAR(CFG_HOJE))*12+MONTH($D15)-MONTH(CFG_HOJE))) -> 0 | L15: =IF($A15="","",IF($K15<=0,$J15,ROUND($J15/$K15,0))) | O15: =IF($A15="","",IF($M15="Cancelada","CANCELADA",IF($M15="Concluida","CONCLUIDA",IF($H15>=$C15,"OBJETIVO ATINGIDO",IF($D15<CFG_HOJE,"PRAZO VENCIDO",IF($K15<=3,"EM RISCO","EM DIA")))))) | P15: =IF($E15="","",IFERROR(INDEX(C_NOME,MATCH($E15,C_ID,0)),"?"))
A16: =IF($B16="","","MET-"&TEXT(ROW()-4,"000000")) | H16: =IF($A16="",0,SUMIFS(MM_VALSINAL,MM_META,$A16)) -> 0 | I16: =IF(OR($A16="",$C16=0),0,$H16/$C16) -> 0 | J16: =IF($A16="","",MAX(0,$C16-$H16)) | K16: =IF(OR($A16="",$D16=""),0,MAX(0,(YEAR($D16)-YEAR(CFG_HOJE))*12+MONTH($D16)-MONTH(CFG_HOJE))) -> 0 | L16: =IF($A16="","",IF($K16<=0,$J16,ROUND($J16/$K16,0))) | O16: =IF($A16="","",IF($M16="Cancelada","CANCELADA",IF($M16="Concluida","CONCLUIDA",IF($H16>=$C16,"OBJETIVO ATINGIDO",IF($D16<CFG_HOJE,"PRAZO VENCIDO",IF($K16<=3,"EM RISCO","EM DIA")))))) | P16: =IF($E16="","",IFERROR(INDEX(C_NOME,MATCH($E16,C_ID,0)),"?"))
... A44: =IF($B44="","","MET-"&TEXT(ROW()-4,"000000")) | H44: =IF($A44="",0,SUMIFS(MM_VALSINAL,MM_META,$A44)) -> 0 | I44: =IF(OR($A44="",$C44=0),0,$H44/$C44) -> 0 | J44: =IF($A44="","",MAX(0,$C44-$H44)) | K44: =IF(OR($A44="",$D44=""),0,MAX(0,(YEAR($D44)-YEAR(CFG_HOJE))*12+MONTH($D44)-MONTH(CFG_HOJE))) -> 0 | L44: =IF($A44="","",IF($K44<=0,$J44,ROUND($J44/$K44,0))) | O44: =IF($A44="","",IF($M44="Cancelada","CANCELADA",IF($M44="Concluida","CONCLUIDA",IF($H44>=$C44,"OBJETIVO ATINGIDO",IF($D44<CFG_HOJE,"PRAZO VENCIDO",IF($K44<=3,"EM RISCO","EM DIA")))))) | P44: =IF($E44="","",IFERROR(INDEX(C_NOME,MATCH($E44,C_ID,0)),"?"))

Sheet CAD_Recorrencias
A1: CAD_RECORRENCIAS - LANCAMENTOS REPETITIVOS
A2: PARA APAGAR UM REGISTRO: selecione as celulas AMARELAS da linha e pressione DELETE (limpar conteudo). NUNCA use 'Excluir linha' nem classifique (sort) esta aba: os IDs sao gerados pela posicao da linha e os vinculos seriam quebrados em silencio. Para anular um lancamento sem perder o historico use o campo Status (CANCELADO / Inativo). Para pesquisar use os filtros do cabecalho.
A4: ID_Recorrencia | B4: Descricao | C4: Tipo_Operacao | D4: Valor | E4: Periodicidade | F4: Dia | G4: Data_Inicio | H4: Qtd_Ocorrencias | I4: Data_Fim_Prevista | J4: Categoria_ID | K4: Subcategoria_ID | L4: Origem_Tipo | M4: Origem_ID | N4: Destino_Tipo | O4: Destino_ID | P4: Forma_Pagamento | Q4: Status | R4: Lanc_Gerados | S4: Lanc_Realizados | T4: Lanc_Projetados | U4: Proxima_Ocorrencia | V4: Observacao
A5: =IF($B5="","","REC-"&TEXT(ROW()-4,"000000")) | I5: =IF(OR($A5="",$H5=0),"",IF(IF($E5="Mensal",1,IF($E5="Bimestral",2,IF($E5="Trimestral",3,IF($E5="Semestral",6,IF($E5="Anual",12,0)))))>0,EDATE($G5,($H5-1)*IF($E5="Mensal",1,IF($E5="Bimestral",2,IF($E5="Trimestral",3,IF($E5="Semestral",6,IF($E5="Anual",12,0)))))),IF(IF($E5="Diario",1,IF($E5="Semanal",7,IF($E5="Quinzenal",15,0)))>0,$G5+($H5-1)*IF($E5="Diario",1,IF($E5="Semanal",7,IF($E5="Quinzenal",15,0))),""))) | R5: =IF($A5="",0,COUNTIFS(L_RecID,$A5)) -> 0 | S5: =IF($A5="",0,COUNTIFS(L_RecID,$A5,L_Status,"REALIZADO")) -> 0 | T5: =IF($A5="",0,COUNTIFS(L_RecID,$A5,L_Status,"PROJETADO")) -> 0 | U5: =IF($A5="","",IFERROR(INDEX(L_Data,MATCH(1,INDEX((L_RecID=$A5)*(L_Status="PROJETADO"),0),0)),""))
A6: =IF($B6="","","REC-"&TEXT(ROW()-4,"000000")) | I6: =IF(OR($A6="",$H6=0),"",IF(IF($E6="Mensal",1,IF($E6="Bimestral",2,IF($E6="Trimestral",3,IF($E6="Semestral",6,IF($E6="Anual",12,0)))))>0,EDATE($G6,($H6-1)*IF($E6="Mensal",1,IF($E6="Bimestral",2,IF($E6="Trimestral",3,IF($E6="Semestral",6,IF($E6="Anual",12,0)))))),IF(IF($E6="Diario",1,IF($E6="Semanal",7,IF($E6="Quinzenal",15,0)))>0,$G6+($H6-1)*IF($E6="Diario",1,IF($E6="Semanal",7,IF($E6="Quinzenal",15,0))),""))) | R6: =IF($A6="",0,COUNTIFS(L_RecID,$A6)) -> 0 | S6: =IF($A6="",0,COUNTIFS(L_RecID,$A6,L_Status,"REALIZADO")) -> 0 | T6: =IF($A6="",0,COUNTIFS(L_RecID,$A6,L_Status,"PROJETADO")) -> 0 | U6: =IF($A6="","",IFERROR(INDEX(L_Data,MATCH(1,INDEX((L_RecID=$A6)*(L_Status="PROJETADO"),0),0)),""))
A7: =IF($B7="","","REC-"&TEXT(ROW()-4,"000000")) | I7: =IF(OR($A7="",$H7=0),"",IF(IF($E7="Mensal",1,IF($E7="Bimestral",2,IF($E7="Trimestral",3,IF($E7="Semestral",6,IF($E7="Anual",12,0)))))>0,EDATE($G7,($H7-1)*IF($E7="Mensal",1,IF($E7="Bimestral",2,IF($E7="Trimestral",3,IF($E7="Semestral",6,IF($E7="Anual",12,0)))))),IF(IF($E7="Diario",1,IF($E7="Semanal",7,IF($E7="Quinzenal",15,0)))>0,$G7+($H7-1)*IF($E7="Diario",1,IF($E7="Semanal",7,IF($E7="Quinzenal",15,0))),""))) | R7: =IF($A7="",0,COUNTIFS(L_RecID,$A7)) -> 0 | S7: =IF($A7="",0,COUNTIFS(L_RecID,$A7,L_Status,"REALIZADO")) -> 0 | T7: =IF($A7="",0,COUNTIFS(L_RecID,$A7,L_Status,"PROJETADO")) -> 0 | U7: =IF($A7="","",IFERROR(INDEX(L_Data,MATCH(1,INDEX((L_RecID=$A7)*(L_Status="PROJETADO"),0),0)),""))
A8: =IF($B8="","","REC-"&TEXT(ROW()-4,"000000")) | I8: =IF(OR($A8="",$H8=0),"",IF(IF($E8="Mensal",1,IF($E8="Bimestral",2,IF($E8="Trimestral",3,IF($E8="Semestral",6,IF($E8="Anual",12,0)))))>0,EDATE($G8,($H8-1)*IF($E8="Mensal",1,IF($E8="Bimestral",2,IF($E8="Trimestral",3,IF($E8="Semestral",6,IF($E8="Anual",12,0)))))),IF(IF($E8="Diario",1,IF($E8="Semanal",7,IF($E8="Quinzenal",15,0)))>0,$G8+($H8-1)*IF($E8="Diario",1,IF($E8="Semanal",7,IF($E8="Quinzenal",15,0))),""))) | R8: =IF($A8="",0,COUNTIFS(L_RecID,$A8)) -> 0 | S8: =IF($A8="",0,COUNTIFS(L_RecID,$A8,L_Status,"REALIZADO")) -> 0 | T8: =IF($A8="",0,COUNTIFS(L_RecID,$A8,L_Status,"PROJETADO")) -> 0 | U8: =IF($A8="","",IFERROR(INDEX(L_Data,MATCH(1,INDEX((L_RecID=$A8)*(L_Status="PROJETADO"),0),0)),""))
A9: =IF($B9="","","REC-"&TEXT(ROW()-4,"000000")) | I9: =IF(OR($A9="",$H9=0),"",IF(IF($E9="Mensal",1,IF($E9="Bimestral",2,IF($E9="Trimestral",3,IF($E9="Semestral",6,IF($E9="Anual",12,0)))))>0,EDATE($G9,($H9-1)*IF($E9="Mensal",1,IF($E9="Bimestral",2,IF($E9="Trimestral",3,IF($E9="Semestral",6,IF($E9="Anual",12,0)))))),IF(IF($E9="Diario",1,IF($E9="Semanal",7,IF($E9="Quinzenal",15,0)))>0,$G9+($H9-1)*IF($E9="Diario",1,IF($E9="Semanal",7,IF($E9="Quinzenal",15,0))),""))) | R9: =IF($A9="",0,COUNTIFS(L_RecID,$A9)) -> 0 | S9: =IF($A9="",0,COUNTIFS(L_RecID,$A9,L_Status,"REALIZADO")) -> 0 | T9: =IF($A9="",0,COUNTIFS(L_RecID,$A9,L_Status,"PROJETADO")) -> 0 | U9: =IF($A9="","",IFERROR(INDEX(L_Data,MATCH(1,INDEX((L_RecID=$A9)*(L_Status="PROJETADO"),0),0)),""))
A10: =IF($B10="","","REC-"&TEXT(ROW()-4,"000000")) | I10: =IF(OR($A10="",$H10=0),"",IF(IF($E10="Mensal",1,IF($E10="Bimestral",2,IF($E10="Trimestral",3,IF($E10="Semestral",6,IF($E10="Anual",12,0)))))>0,EDATE($G10,($H10-1)*IF($E10="Mensal",1,IF($E10="Bimestral",2,IF($E10="Trimestral",3,IF($E10="Semestral",6,IF($E10="Anual",12,0)))))),IF(IF($E10="Diario",1,IF($E10="Semanal",7,IF($E10="Quinzenal",15,0)))>0,$G10+($H10-1)*IF($E10="Diario",1,IF($E10="Semanal",7,IF($E10="Quinzenal",15,0))),""))) | R10: =IF($A10="",0,COUNTIFS(L_RecID,$A10)) -> 0 | S10: =IF($A10="",0,COUNTIFS(L_RecID,$A10,L_Status,"REALIZADO")) -> 0 | T10: =IF($A10="",0,COUNTIFS(L_RecID,$A10,L_Status,"PROJETADO")) -> 0 | U10: =IF($A10="","",IFERROR(INDEX(L_Data,MATCH(1,INDEX((L_RecID=$A10)*(L_Status="PROJETADO"),0),0)),""))
A11: =IF($B11="","","REC-"&TEXT(ROW()-4,"000000")) | I11: =IF(OR($A11="",$H11=0),"",IF(IF($E11="Mensal",1,IF($E11="Bimestral",2,IF($E11="Trimestral",3,IF($E11="Semestral",6,IF($E11="Anual",12,0)))))>0,EDATE($G11,($H11-1)*IF($E11="Mensal",1,IF($E11="Bimestral",2,IF($E11="Trimestral",3,IF($E11="Semestral",6,IF($E11="Anual",12,0)))))),IF(IF($E11="Diario",1,IF($E11="Semanal",7,IF($E11="Quinzenal",15,0)))>0,$G11+($H11-1)*IF($E11="Diario",1,IF($E11="Semanal",7,IF($E11="Quinzenal",15,0))),""))) | R11: =IF($A11="",0,COUNTIFS(L_RecID,$A11)) -> 0 | S11: =IF($A11="",0,COUNTIFS(L_RecID,$A11,L_Status,"REALIZADO")) -> 0 | T11: =IF($A11="",0,COUNTIFS(L_RecID,$A11,L_Status,"PROJETADO")) -> 0 | U11: =IF($A11="","",IFERROR(INDEX(L_Data,MATCH(1,INDEX((L_RecID=$A11)*(L_Status="PROJETADO"),0),0)),""))
A12: =IF($B12="","","REC-"&TEXT(ROW()-4,"000000")) | I12: =IF(OR($A12="",$H12=0),"",IF(IF($E12="Mensal",1,IF($E12="Bimestral",2,IF($E12="Trimestral",3,IF($E12="Semestral",6,IF($E12="Anual",12,0)))))>0,EDATE($G12,($H12-1)*IF($E12="Mensal",1,IF($E12="Bimestral",2,IF($E12="Trimestral",3,IF($E12="Semestral",6,IF($E12="Anual",12,0)))))),IF(IF($E12="Diario",1,IF($E12="Semanal",7,IF($E12="Quinzenal",15,0)))>0,$G12+($H12-1)*IF($E12="Diario",1,IF($E12="Semanal",7,IF($E12="Quinzenal",15,0))),""))) | R12: =IF($A12="",0,COUNTIFS(L_RecID,$A12)) -> 0 | S12: =IF($A12="",0,COUNTIFS(L_RecID,$A12,L_Status,"REALIZADO")) -> 0 | T12: =IF($A12="",0,COUNTIFS(L_RecID,$A12,L_Status,"PROJETADO")) -> 0 | U12: =IF($A12="","",IFERROR(INDEX(L_Data,MATCH(1,INDEX((L_RecID=$A12)*(L_Status="PROJETADO"),0),0)),""))
A13: =IF($B13="","","REC-"&TEXT(ROW()-4,"000000")) | I13: =IF(OR($A13="",$H13=0),"",IF(IF($E13="Mensal",1,IF($E13="Bimestral",2,IF($E13="Trimestral",3,IF($E13="Semestral",6,IF($E13="Anual",12,0)))))>0,EDATE($G13,($H13-1)*IF($E13="Mensal",1,IF($E13="Bimestral",2,IF($E13="Trimestral",3,IF($E13="Semestral",6,IF($E13="Anual",12,0)))))),IF(IF($E13="Diario",1,IF($E13="Semanal",7,IF($E13="Quinzenal",15,0)))>0,$G13+($H13-1)*IF($E13="Diario",1,IF($E13="Semanal",7,IF($E13="Quinzenal",15,0))),""))) | R13: =IF($A13="",0,COUNTIFS(L_RecID,$A13)) -> 0 | S13: =IF($A13="",0,COUNTIFS(L_RecID,$A13,L_Status,"REALIZADO")) -> 0 | T13: =IF($A13="",0,COUNTIFS(L_RecID,$A13,L_Status,"PROJETADO")) -> 0 | U13: =IF($A13="","",IFERROR(INDEX(L_Data,MATCH(1,INDEX((L_RecID=$A13)*(L_Status="PROJETADO"),0),0)),""))
A14: =IF($B14="","","REC-"&TEXT(ROW()-4,"000000")) | I14: =IF(OR($A14="",$H14=0),"",IF(IF($E14="Mensal",1,IF($E14="Bimestral",2,IF($E14="Trimestral",3,IF($E14="Semestral",6,IF($E14="Anual",12,0)))))>0,EDATE($G14,($H14-1)*IF($E14="Mensal",1,IF($E14="Bimestral",2,IF($E14="Trimestral",3,IF($E14="Semestral",6,IF($E14="Anual",12,0)))))),IF(IF($E14="Diario",1,IF($E14="Semanal",7,IF($E14="Quinzenal",15,0)))>0,$G14+($H14-1)*IF($E14="Diario",1,IF($E14="Semanal",7,IF($E14="Quinzenal",15,0))),""))) | R14: =IF($A14="",0,COUNTIFS(L_RecID,$A14)) -> 0 | S14: =IF($A14="",0,COUNTIFS(L_RecID,$A14,L_Status,"REALIZADO")) -> 0 | T14: =IF($A14="",0,COUNTIFS(L_RecID,$A14,L_Status,"PROJETADO")) -> 0 | U14: =IF($A14="","",IFERROR(INDEX(L_Data,MATCH(1,INDEX((L_RecID=$A14)*(L_Status="PROJETADO"),0),0)),""))
A15: =IF($B15="","","REC-"&TEXT(ROW()-4,"000000")) | I15: =IF(OR($A15="",$H15=0),"",IF(IF($E15="Mensal",1,IF($E15="Bimestral",2,IF($E15="Trimestral",3,IF($E15="Semestral",6,IF($E15="Anual",12,0)))))>0,EDATE($G15,($H15-1)*IF($E15="Mensal",1,IF($E15="Bimestral",2,IF($E15="Trimestral",3,IF($E15="Semestral",6,IF($E15="Anual",12,0)))))),IF(IF($E15="Diario",1,IF($E15="Semanal",7,IF($E15="Quinzenal",15,0)))>0,$G15+($H15-1)*IF($E15="Diario",1,IF($E15="Semanal",7,IF($E15="Quinzenal",15,0))),""))) | R15: =IF($A15="",0,COUNTIFS(L_RecID,$A15)) -> 0 | S15: =IF($A15="",0,COUNTIFS(L_RecID,$A15,L_Status,"REALIZADO")) -> 0 | T15: =IF($A15="",0,COUNTIFS(L_RecID,$A15,L_Status,"PROJETADO")) -> 0 | U15: =IF($A15="","",IFERROR(INDEX(L_Data,MATCH(1,INDEX((L_RecID=$A15)*(L_Status="PROJETADO"),0),0)),""))
A16: =IF($B16="","","REC-"&TEXT(ROW()-4,"000000")) | I16: =IF(OR($A16="",$H16=0),"",IF(IF($E16="Mensal",1,IF($E16="Bimestral",2,IF($E16="Trimestral",3,IF($E16="Semestral",6,IF($E16="Anual",12,0)))))>0,EDATE($G16,($H16-1)*IF($E16="Mensal",1,IF($E16="Bimestral",2,IF($E16="Trimestral",3,IF($E16="Semestral",6,IF($E16="Anual",12,0)))))),IF(IF($E16="Diario",1,IF($E16="Semanal",7,IF($E16="Quinzenal",15,0)))>0,$G16+($H16-1)*IF($E16="Diario",1,IF($E16="Semanal",7,IF($E16="Quinzenal",15,0))),""))) | R16: =IF($A16="",0,COUNTIFS(L_RecID,$A16)) -> 0 | S16: =IF($A16="",0,COUNTIFS(L_RecID,$A16,L_Status,"REALIZADO")) -> 0 | T16: =IF($A16="",0,COUNTIFS(L_RecID,$A16,L_Status,"PROJETADO")) -> 0 | U16: =IF($A16="","",IFERROR(INDEX(L_Data,MATCH(1,INDEX((L_RecID=$A16)*(L_Status="PROJETADO"),0),0)),""))
... A44: =IF($B44="","","REC-"&TEXT(ROW()-4,"000000")) | I44: =IF(OR($A44="",$H44=0),"",IF(IF($E44="Mensal",1,IF($E44="Bimestral",2,IF($E44="Trimestral",3,IF($E44="Semestral",6,IF($E44="Anual",12,0)))))>0,EDATE($G44,($H44-1)*IF($E44="Mensal",1,IF($E44="Bimestral",2,IF($E44="Trimestral",3,IF($E44="Semestral",6,IF($E44="Anual",12,0)))))),IF(IF($E44="Diario",1,IF($E44="Semanal",7,IF($E44="Quinzenal",15,0)))>0,$G44+($H44-1)*IF($E44="Diario",1,IF($E44="Semanal",7,IF($E44="Quinzenal",15,0))),""))) | R44: =IF($A44="",0,COUNTIFS(L_RecID,$A44)) -> 0 | S44: =IF($A44="",0,COUNTIFS(L_RecID,$A44,L_Status,"REALIZADO")) -> 0 | T44: =IF($A44="",0,COUNTIFS(L_RecID,$A44,L_Status,"PROJETADO")) -> 0 | U44: =IF($A44="","",IFERROR(INDEX(L_Data,MATCH(1,INDEX((L_RecID=$A44)*(L_Status="PROJETADO"),0),0)),""))

Sheet CAD_Bens
A1: CAD_BENS - ATIVOS NAO FINANCEIROS (COMPLEMENTO DO PATRIMONIO)
A2: PARA APAGAR UM REGISTRO: selecione as celulas AMARELAS da linha e pressione DELETE (limpar conteudo). NUNCA use 'Excluir linha' nem classifique (sort) esta aba: os IDs sao gerados pela posicao da linha e os vinculos seriam quebrados em silencio. Para anular um lancamento sem perder o historico use o campo Status (CANCELADO / Inativo). Para pesquisar use os filtros do cabecalho.
A4: ID_Bem | B4: Nome | C4: Tipo | D4: Valor_Atual | E4: Data_Aquisicao | F4: ID_Compromisso_Vinculado | G4: Saldo_Devedor_Vinculado | H4: Valor_Liquido | I4: Status | J4: Observacao
A5: =IF($B5="","","BEM-"&TEXT(ROW()-4,"000000")) | G5: =IF($A5="",0,IF($F5="",0,IFERROR(INDEX(CM_DEVEDOR,MATCH($F5,CM_ID,0)),0))) -> 0 | H5: =IF($A5="","",$D5-$G5)
A6: =IF($B6="","","BEM-"&TEXT(ROW()-4,"000000")) | G6: =IF($A6="",0,IF($F6="",0,IFERROR(INDEX(CM_DEVEDOR,MATCH($F6,CM_ID,0)),0))) -> 0 | H6: =IF($A6="","",$D6-$G6)
A7: =IF($B7="","","BEM-"&TEXT(ROW()-4,"000000")) | G7: =IF($A7="",0,IF($F7="",0,IFERROR(INDEX(CM_DEVEDOR,MATCH($F7,CM_ID,0)),0))) -> 0 | H7: =IF($A7="","",$D7-$G7)
A8: =IF($B8="","","BEM-"&TEXT(ROW()-4,"000000")) | G8: =IF($A8="",0,IF($F8="",0,IFERROR(INDEX(CM_DEVEDOR,MATCH($F8,CM_ID,0)),0))) -> 0 | H8: =IF($A8="","",$D8-$G8)
A9: =IF($B9="","","BEM-"&TEXT(ROW()-4,"000000")) | G9: =IF($A9="",0,IF($F9="",0,IFERROR(INDEX(CM_DEVEDOR,MATCH($F9,CM_ID,0)),0))) -> 0 | H9: =IF($A9="","",$D9-$G9)
A10: =IF($B10="","","BEM-"&TEXT(ROW()-4,"000000")) | G10: =IF($A10="",0,IF($F10="",0,IFERROR(INDEX(CM_DEVEDOR,MATCH($F10,CM_ID,0)),0))) -> 0 | H10: =IF($A10="","",$D10-$G10)
A11: =IF($B11="","","BEM-"&TEXT(ROW()-4,"000000")) | G11: =IF($A11="",0,IF($F11="",0,IFERROR(INDEX(CM_DEVEDOR,MATCH($F11,CM_ID,0)),0))) -> 0 | H11: =IF($A11="","",$D11-$G11)
A12: =IF($B12="","","BEM-"&TEXT(ROW()-4,"000000")) | G12: =IF($A12="",0,IF($F12="",0,IFERROR(INDEX(CM_DEVEDOR,MATCH($F12,CM_ID,0)),0))) -> 0 | H12: =IF($A12="","",$D12-$G12)
A13: =IF($B13="","","BEM-"&TEXT(ROW()-4,"000000")) | G13: =IF($A13="",0,IF($F13="",0,IFERROR(INDEX(CM_DEVEDOR,MATCH($F13,CM_ID,0)),0))) -> 0 | H13: =IF($A13="","",$D13-$G13)
A14: =IF($B14="","","BEM-"&TEXT(ROW()-4,"000000")) | G14: =IF($A14="",0,IF($F14="",0,IFERROR(INDEX(CM_DEVEDOR,MATCH($F14,CM_ID,0)),0))) -> 0 | H14: =IF($A14="","",$D14-$G14)
A15: =IF($B15="","","BEM-"&TEXT(ROW()-4,"000000")) | G15: =IF($A15="",0,IF($F15="",0,IFERROR(INDEX(CM_DEVEDOR,MATCH($F15,CM_ID,0)),0))) -> 0 | H15: =IF($A15="","",$D15-$G15)
A16: =IF($B16="","","BEM-"&TEXT(ROW()-4,"000000")) | G16: =IF($A16="",0,IF($F16="",0,IFERROR(INDEX(CM_DEVEDOR,MATCH($F16,CM_ID,0)),0))) -> 0 | H16: =IF($A16="","",$D16-$G16)
... A44: =IF($B44="","","BEM-"&TEXT(ROW()-4,"000000")) | G44: =IF($A44="",0,IF($F44="",0,IFERROR(INDEX(CM_DEVEDOR,MATCH($F44,CM_ID,0)),0))) -> 0 | H44: =IF($A44="","",$D44-$G44)

Sheet FLUXO_CAIXA
A1: FLUXO_CAIXA - ENTRADAS E SAIDAS DE CAIXA
A2: Somente movimentos que atravessam uma CONTA. Transferencias entre contas proprias nao aparecem como entrada nem como saida (nao ha duplicidade). Compra no cartao so vira saida de caixa quando a fatura e paga.
A4: Mes inicial da grade | B4: =EOMONTH(CFG_INICIO,0)+1 -> 46023 | D4: Reservas de metas consideradas no fluxo | F4: =IF(CFG_RESERVA_FLUXO="SIM",SUMIFS(M_RESERV,M_FLUXO,"SIM",M_STATUS,"Ativa"),0) -> 0
A6: 1. FLUXO DE CAIXA MENSAL (REALIZADO + PROJETADO)
A7: Competencia | B7: Data_Inicio | C7: Data_Fim | D7: Saldo_Inicial | E7: Entradas_Realizadas | F7: Saidas_Realizadas | G7: Liquido_Realizado | H7: Entradas_Projetadas | I7: Saidas_Projetadas | J7: Liquido_Projetado | K7: Saldo_Final | L7: Reservado_Metas | M7: Saldo_Livre
A8: =YEAR($B8)*100+MONTH($B8) -> 202601 | B8: =EDATE($B$4,0) -> 46023 | C8: =EOMONTH($B8,0) -> 46053 | D8: =SUM(C_SALDOINI)+SUMIFS(L_Ent,L_Data,"<"&$B8,L_Status,"REALIZADO")-SUMIFS(L_Sai,L_Data,"<"&$B8,L_Status,"REALIZADO")+SUMIFS(L_Ent,L_Data,"<"&$B8,L_Status,"PROJETADO")-SUMIFS(L_Sai,L_Data,"<"&$B8,L_Status,"PROJETADO") -> 0 | E8: =SUMIFS(L_Ent,L_Data,">="&$B8,L_Data,"<="&$C8,L_Status,"REALIZADO") -> 0 | F8: =SUMIFS(L_Sai,L_Data,">="&$B8,L_Data,"<="&$C8,L_Status,"REALIZADO") -> 0 | G8: =$E8-$F8 -> 0 | H8: =SUMIFS(L_Ent,L_Data,">="&$B8,L_Data,"<="&$C8,L_Status,"PROJETADO") -> 0 | I8: =SUMIFS(L_Sai,L_Data,">="&$B8,L_Data,"<="&$C8,L_Status,"PROJETADO") -> 0 | J8: =$H8-$I8 -> 0 | K8: =$D8+$G8+$J8 -> 0 | L8: =$F$4 -> 0 | M8: =$K8-$L8 -> 0
A9: =YEAR($B9)*100+MONTH($B9) -> 202602 | B9: =EDATE($B$4,1) -> 46054 | C9: =EOMONTH($B9,0) -> 46081 | D9: =$K8 -> 0 | E9: =SUMIFS(L_Ent,L_Data,">="&$B9,L_Data,"<="&$C9,L_Status,"REALIZADO") -> 0 | F9: =SUMIFS(L_Sai,L_Data,">="&$B9,L_Data,"<="&$C9,L_Status,"REALIZADO") -> 0 | G9: =$E9-$F9 -> 0 | H9: =SUMIFS(L_Ent,L_Data,">="&$B9,L_Data,"<="&$C9,L_Status,"PROJETADO") -> 0 | I9: =SUMIFS(L_Sai,L_Data,">="&$B9,L_Data,"<="&$C9,L_Status,"PROJETADO") -> 0 | J9: =$H9-$I9 -> 0 | K9: =$D9+$G9+$J9 -> 0 | L9: =$F$4 -> 0 | M9: =$K9-$L9 -> 0
A10: =YEAR($B10)*100+MONTH($B10) -> 202603 | B10: =EDATE($B$4,2) -> 46082 | C10: =EOMONTH($B10,0) -> 46112 | D10: =$K9 -> 0 | E10: =SUMIFS(L_Ent,L_Data,">="&$B10,L_Data,"<="&$C10,L_Status,"REALIZADO") -> 0 | F10: =SUMIFS(L_Sai,L_Data,">="&$B10,L_Data,"<="&$C10,L_Status,"REALIZADO") -> 0 | G10: =$E10-$F10 -> 0 | H10: =SUMIFS(L_Ent,L_Data,">="&$B10,L_Data,"<="&$C10,L_Status,"PROJETADO") -> 0 | I10: =SUMIFS(L_Sai,L_Data,">="&$B10,L_Data,"<="&$C10,L_Status,"PROJETADO") -> 0 | J10: =$H10-$I10 -> 0 | K10: =$D10+$G10+$J10 -> 0 | L10: =$F$4 -> 0 | M10: =$K10-$L10 -> 0
A11: =YEAR($B11)*100+MONTH($B11) -> 202604 | B11: =EDATE($B$4,3) -> 46113 | C11: =EOMONTH($B11,0) -> 46142 | D11: =$K10 -> 0 | E11: =SUMIFS(L_Ent,L_Data,">="&$B11,L_Data,"<="&$C11,L_Status,"REALIZADO") -> 0 | F11: =SUMIFS(L_Sai,L_Data,">="&$B11,L_Data,"<="&$C11,L_Status,"REALIZADO") -> 0 | G11: =$E11-$F11 -> 0 | H11: =SUMIFS(L_Ent,L_Data,">="&$B11,L_Data,"<="&$C11,L_Status,"PROJETADO") -> 0 | I11: =SUMIFS(L_Sai,L_Data,">="&$B11,L_Data,"<="&$C11,L_Status,"PROJETADO") -> 0 | J11: =$H11-$I11 -> 0 | K11: =$D11+$G11+$J11 -> 0 | L11: =$F$4 -> 0 | M11: =$K11-$L11 -> 0
A12: =YEAR($B12)*100+MONTH($B12) -> 202605 | B12: =EDATE($B$4,4) -> 46143 | C12: =EOMONTH($B12,0) -> 46173 | D12: =$K11 -> 0 | E12: =SUMIFS(L_Ent,L_Data,">="&$B12,L_Data,"<="&$C12,L_Status,"REALIZADO") -> 0 | F12: =SUMIFS(L_Sai,L_Data,">="&$B12,L_Data,"<="&$C12,L_Status,"REALIZADO") -> 0 | G12: =$E12-$F12 -> 0 | H12: =SUMIFS(L_Ent,L_Data,">="&$B12,L_Data,"<="&$C12,L_Status,"PROJETADO") -> 0 | I12: =SUMIFS(L_Sai,L_Data,">="&$B12,L_Data,"<="&$C12,L_Status,"PROJETADO") -> 0 | J12: =$H12-$I12 -> 0 | K12: =$D12+$G12+$J12 -> 0 | L12: =$F$4 -> 0 | M12: =$K12-$L12 -> 0
A13: =YEAR($B13)*100+MONTH($B13) -> 202606 | B13: =EDATE($B$4,5) -> 46174 | C13: =EOMONTH($B13,0) -> 46203 | D13: =$K12 -> 0 | E13: =SUMIFS(L_Ent,L_Data,">="&$B13,L_Data,"<="&$C13,L_Status,"REALIZADO") -> 0 | F13: =SUMIFS(L_Sai,L_Data,">="&$B13,L_Data,"<="&$C13,L_Status,"REALIZADO") -> 0 | G13: =$E13-$F13 -> 0 | H13: =SUMIFS(L_Ent,L_Data,">="&$B13,L_Data,"<="&$C13,L_Status,"PROJETADO") -> 0 | I13: =SUMIFS(L_Sai,L_Data,">="&$B13,L_Data,"<="&$C13,L_Status,"PROJETADO") -> 0 | J13: =$H13-$I13 -> 0 | K13: =$D13+$G13+$J13 -> 0 | L13: =$F$4 -> 0 | M13: =$K13-$L13 -> 0
A14: =YEAR($B14)*100+MONTH($B14) -> 202607 | B14: =EDATE($B$4,6) -> 46204 | C14: =EOMONTH($B14,0) -> 46234 | D14: =$K13 -> 0 | E14: =SUMIFS(L_Ent,L_Data,">="&$B14,L_Data,"<="&$C14,L_Status,"REALIZADO") -> 0 | F14: =SUMIFS(L_Sai,L_Data,">="&$B14,L_Data,"<="&$C14,L_Status,"REALIZADO") -> 0 | G14: =$E14-$F14 -> 0 | H14: =SUMIFS(L_Ent,L_Data,">="&$B14,L_Data,"<="&$C14,L_Status,"PROJETADO") -> 0 | I14: =SUMIFS(L_Sai,L_Data,">="&$B14,L_Data,"<="&$C14,L_Status,"PROJETADO") -> 0 | J14: =$H14-$I14 -> 0 | K14: =$D14+$G14+$J14 -> 0 | L14: =$F$4 -> 0 | M14: =$K14-$L14 -> 0
A15: =YEAR($B15)*100+MONTH($B15) -> 202608 | B15: =EDATE($B$4,7) -> 46235 | C15: =EOMONTH($B15,0) -> 46265 | D15: =$K14 -> 0 | E15: =SUMIFS(L_Ent,L_Data,">="&$B15,L_Data,"<="&$C15,L_Status,"REALIZADO") -> 0 | F15: =SUMIFS(L_Sai,L_Data,">="&$B15,L_Data,"<="&$C15,L_Status,"REALIZADO") -> 0 | G15: =$E15-$F15 -> 0 | H15: =SUMIFS(L_Ent,L_Data,">="&$B15,L_Data,"<="&$C15,L_Status,"PROJETADO") -> 0 | I15: =SUMIFS(L_Sai,L_Data,">="&$B15,L_Data,"<="&$C15,L_Status,"PROJETADO") -> 0 | J15: =$H15-$I15 -> 0 | K15: =$D15+$G15+$J15 -> 0 | L15: =$F$4 -> 0 | M15: =$K15-$L15 -> 0
A16: =YEAR($B16)*100+MONTH($B16) -> 202609 | B16: =EDATE($B$4,8) -> 46266 | C16: =EOMONTH($B16,0) -> 46295 | D16: =$K15 -> 0 | E16: =SUMIFS(L_Ent,L_Data,">="&$B16,L_Data,"<="&$C16,L_Status,"REALIZADO") -> 0 | F16: =SUMIFS(L_Sai,L_Data,">="&$B16,L_Data,"<="&$C16,L_Status,"REALIZADO") -> 0 | G16: =$E16-$F16 -> 0 | H16: =SUMIFS(L_Ent,L_Data,">="&$B16,L_Data,"<="&$C16,L_Status,"PROJETADO") -> 0 | I16: =SUMIFS(L_Sai,L_Data,">="&$B16,L_Data,"<="&$C16,L_Status,"PROJETADO") -> 0 | J16: =$H16-$I16 -> 0 | K16: =$D16+$G16+$J16 -> 0 | L16: =$F$4 -> 0 | M16: =$K16-$L16 -> 0
A17: =YEAR($B17)*100+MONTH($B17) -> 202610 | B17: =EDATE($B$4,9) -> 46296 | C17: =EOMONTH($B17,0) -> 46326 | D17: =$K16 -> 0 | E17: =SUMIFS(L_Ent,L_Data,">="&$B17,L_Data,"<="&$C17,L_Status,"REALIZADO") -> 0 | F17: =SUMIFS(L_Sai,L_Data,">="&$B17,L_Data,"<="&$C17,L_Status,"REALIZADO") -> 0 | G17: =$E17-$F17 -> 0 | H17: =SUMIFS(L_Ent,L_Data,">="&$B17,L_Data,"<="&$C17,L_Status,"PROJETADO") -> 0 | I17: =SUMIFS(L_Sai,L_Data,">="&$B17,L_Data,"<="&$C17,L_Status,"PROJETADO") -> 0 | J17: =$H17-$I17 -> 0 | K17: =$D17+$G17+$J17 -> 0 | L17: =$F$4 -> 0 | M17: =$K17-$L17 -> 0
A18: =YEAR($B18)*100+MONTH($B18) -> 202611 | B18: =EDATE($B$4,10) -> 46327 | C18: =EOMONTH($B18,0) -> 46356 | D18: =$K17 -> 0 | E18: =SUMIFS(L_Ent,L_Data,">="&$B18,L_Data,"<="&$C18,L_Status,"REALIZADO") -> 0 | F18: =SUMIFS(L_Sai,L_Data,">="&$B18,L_Data,"<="&$C18,L_Status,"REALIZADO") -> 0 | G18: =$E18-$F18 -> 0 | H18: =SUMIFS(L_Ent,L_Data,">="&$B18,L_Data,"<="&$C18,L_Status,"PROJETADO") -> 0 | I18: =SUMIFS(L_Sai,L_Data,">="&$B18,L_Data,"<="&$C18,L_Status,"PROJETADO") -> 0 | J18: =$H18-$I18 -> 0 | K18: =$D18+$G18+$J18 -> 0 | L18: =$F$4 -> 0 | M18: =$K18-$L18 -> 0
A19: =YEAR($B19)*100+MONTH($B19) -> 202612 | B19: =EDATE($B$4,11) -> 46357 | C19: =EOMONTH($B19,0) -> 46387 | D19: =$K18 -> 0 | E19: =SUMIFS(L_Ent,L_Data,">="&$B19,L_Data,"<="&$C19,L_Status,"REALIZADO") -> 0 | F19: =SUMIFS(L_Sai,L_Data,">="&$B19,L_Data,"<="&$C19,L_Status,"REALIZADO") -> 0 | G19: =$E19-$F19 -> 0 | H19: =SUMIFS(L_Ent,L_Data,">="&$B19,L_Data,"<="&$C19,L_Status,"PROJETADO") -> 0 | I19: =SUMIFS(L_Sai,L_Data,">="&$B19,L_Data,"<="&$C19,L_Status,"PROJETADO") -> 0 | J19: =$H19-$I19 -> 0 | K19: =$D19+$G19+$J19 -> 0 | L19: =$F$4 -> 0 | M19: =$K19-$L19 -> 0
A20: =YEAR($B20)*100+MONTH($B20) -> 202701 | B20: =EDATE($B$4,12) -> 46388 | C20: =EOMONTH($B20,0) -> 46418 | D20: =$K19 -> 0 | E20: =SUMIFS(L_Ent,L_Data,">="&$B20,L_Data,"<="&$C20,L_Status,"REALIZADO") -> 0 | F20: =SUMIFS(L_Sai,L_Data,">="&$B20,L_Data,"<="&$C20,L_Status,"REALIZADO") -> 0 | G20: =$E20-$F20 -> 0 | H20: =SUMIFS(L_Ent,L_Data,">="&$B20,L_Data,"<="&$C20,L_Status,"PROJETADO") -> 0 | I20: =SUMIFS(L_Sai,L_Data,">="&$B20,L_Data,"<="&$C20,L_Status,"PROJETADO") -> 0 | J20: =$H20-$I20 -> 0 | K20: =$D20+$G20+$J20 -> 0 | L20: =$F$4 -> 0 | M20: =$K20-$L20 -> 0
A21: =YEAR($B21)*100+MONTH($B21) -> 202702 | B21: =EDATE($B$4,13) -> 46419 | C21: =EOMONTH($B21,0) -> 46446 | D21: =$K20 -> 0 | E21: =SUMIFS(L_Ent,L_Data,">="&$B21,L_Data,"<="&$C21,L_Status,"REALIZADO") -> 0 | F21: =SUMIFS(L_Sai,L_Data,">="&$B21,L_Data,"<="&$C21,L_Status,"REALIZADO") -> 0 | G21: =$E21-$F21 -> 0 | H21: =SUMIFS(L_Ent,L_Data,">="&$B21,L_Data,"<="&$C21,L_Status,"PROJETADO") -> 0 | I21: =SUMIFS(L_Sai,L_Data,">="&$B21,L_Data,"<="&$C21,L_Status,"PROJETADO") -> 0 | J21: =$H21-$I21 -> 0 | K21: =$D21+$G21+$J21 -> 0 | L21: =$F$4 -> 0 | M21: =$K21-$L21 -> 0
A22: =YEAR($B22)*100+MONTH($B22) -> 202703 | B22: =EDATE($B$4,14) -> 46447 | C22: =EOMONTH($B22,0) -> 46477 | D22: =$K21 -> 0 | E22: =SUMIFS(L_Ent,L_Data,">="&$B22,L_Data,"<="&$C22,L_Status,"REALIZADO") -> 0 | F22: =SUMIFS(L_Sai,L_Data,">="&$B22,L_Data,"<="&$C22,L_Status,"REALIZADO") -> 0 | G22: =$E22-$F22 -> 0 | H22: =SUMIFS(L_Ent,L_Data,">="&$B22,L_Data,"<="&$C22,L_Status,"PROJETADO") -> 0 | I22: =SUMIFS(L_Sai,L_Data,">="&$B22,L_Data,"<="&$C22,L_Status,"PROJETADO") -> 0 | J22: =$H22-$I22 -> 0 | K22: =$D22+$G22+$J22 -> 0 | L22: =$F$4 -> 0 | M22: =$K22-$L22 -> 0
A23: =YEAR($B23)*100+MONTH($B23) -> 202704 | B23: =EDATE($B$4,15) -> 46478 | C23: =EOMONTH($B23,0) -> 46507 | D23: =$K22 -> 0 | E23: =SUMIFS(L_Ent,L_Data,">="&$B23,L_Data,"<="&$C23,L_Status,"REALIZADO") -> 0 | F23: =SUMIFS(L_Sai,L_Data,">="&$B23,L_Data,"<="&$C23,L_Status,"REALIZADO") -> 0 | G23: =$E23-$F23 -> 0 | H23: =SUMIFS(L_Ent,L_Data,">="&$B23,L_Data,"<="&$C23,L_Status,"PROJETADO") -> 0 | I23: =SUMIFS(L_Sai,L_Data,">="&$B23,L_Data,"<="&$C23,L_Status,"PROJETADO") -> 0 | J23: =$H23-$I23 -> 0 | K23: =$D23+$G23+$J23 -> 0 | L23: =$F$4 -> 0 | M23: =$K23-$L23 -> 0
A24: =YEAR($B24)*100+MONTH($B24) -> 202705 | B24: =EDATE($B$4,16) -> 46508 | C24: =EOMONTH($B24,0) -> 46538 | D24: =$K23 -> 0 | E24: =SUMIFS(L_Ent,L_Data,">="&$B24,L_Data,"<="&$C24,L_Status,"REALIZADO") -> 0 | F24: =SUMIFS(L_Sai,L_Data,">="&$B24,L_Data,"<="&$C24,L_Status,"REALIZADO") -> 0 | G24: =$E24-$F24 -> 0 | H24: =SUMIFS(L_Ent,L_Data,">="&$B24,L_Data,"<="&$C24,L_Status,"PROJETADO") -> 0 | I24: =SUMIFS(L_Sai,L_Data,">="&$B24,L_Data,"<="&$C24,L_Status,"PROJETADO") -> 0 | J24: =$H24-$I24 -> 0 | K24: =$D24+$G24+$J24 -> 0 | L24: =$F$4 -> 0 | M24: =$K24-$L24 -> 0
A25: =YEAR($B25)*100+MONTH($B25) -> 202706 | B25: =EDATE($B$4,17) -> 46539 | C25: =EOMONTH($B25,0) -> 46568 | D25: =$K24 -> 0 | E25: =SUMIFS(L_Ent,L_Data,">="&$B25,L_Data,"<="&$C25,L_Status,"REALIZADO") -> 0 | F25: =SUMIFS(L_Sai,L_Data,">="&$B25,L_Data,"<="&$C25,L_Status,"REALIZADO") -> 0 | G25: =$E25-$F25 -> 0 | H25: =SUMIFS(L_Ent,L_Data,">="&$B25,L_Data,"<="&$C25,L_Status,"PROJETADO") -> 0 | I25: =SUMIFS(L_Sai,L_Data,">="&$B25,L_Data,"<="&$C25,L_Status,"PROJETADO") -> 0 | J25: =$H25-$I25 -> 0 | K25: =$D25+$G25+$J25 -> 0 | L25: =$F$4 -> 0 | M25: =$K25-$L25 -> 0
A26: =YEAR($B26)*100+MONTH($B26) -> 202707 | B26: =EDATE($B$4,18) -> 46569 | C26: =EOMONTH($B26,0) -> 46599 | D26: =$K25 -> 0 | E26: =SUMIFS(L_Ent,L_Data,">="&$B26,L_Data,"<="&$C26,L_Status,"REALIZADO") -> 0 | F26: =SUMIFS(L_Sai,L_Data,">="&$B26,L_Data,"<="&$C26,L_Status,"REALIZADO") -> 0 | G26: =$E26-$F26 -> 0 | H26: =SUMIFS(L_Ent,L_Data,">="&$B26,L_Data,"<="&$C26,L_Status,"PROJETADO") -> 0 | I26: =SUMIFS(L_Sai,L_Data,">="&$B26,L_Data,"<="&$C26,L_Status,"PROJETADO") -> 0 | J26: =$H26-$I26 -> 0 | K26: =$D26+$G26+$J26 -> 0 | L26: =$F$4 -> 0 | M26: =$K26-$L26 -> 0
A27: =YEAR($B27)*100+MONTH($B27) -> 202708 | B27: =EDATE($B$4,19) -> 46600 | C27: =EOMONTH($B27,0) -> 46630 | D27: =$K26 -> 0 | E27: =SUMIFS(L_Ent,L_Data,">="&$B27,L_Data,"<="&$C27,L_Status,"REALIZADO") -> 0 | F27: =SUMIFS(L_Sai,L_Data,">="&$B27,L_Data,"<="&$C27,L_Status,"REALIZADO") -> 0 | G27: =$E27-$F27 -> 0 | H27: =SUMIFS(L_Ent,L_Data,">="&$B27,L_Data,"<="&$C27,L_Status,"PROJETADO") -> 0 | I27: =SUMIFS(L_Sai,L_Data,">="&$B27,L_Data,"<="&$C27,L_Status,"PROJETADO") -> 0 | J27: =$H27-$I27 -> 0 | K27: =$D27+$G27+$J27 -> 0 | L27: =$F$4 -> 0 | M27: =$K27-$L27 -> 0
A28: =YEAR($B28)*100+MONTH($B28) -> 202709 | B28: =EDATE($B$4,20) -> 46631 | C28: =EOMONTH($B28,0) -> 46660 | D28: =$K27 -> 0 | E28: =SUMIFS(L_Ent,L_Data,">="&$B28,L_Data,"<="&$C28,L_Status,"REALIZADO") -> 0 | F28: =SUMIFS(L_Sai,L_Data,">="&$B28,L_Data,"<="&$C28,L_Status,"REALIZADO") -> 0 | G28: =$E28-$F28 -> 0 | H28: =SUMIFS(L_Ent,L_Data,">="&$B28,L_Data,"<="&$C28,L_Status,"PROJETADO") -> 0 | I28: =SUMIFS(L_Sai,L_Data,">="&$B28,L_Data,"<="&$C28,L_Status,"PROJETADO") -> 0 | J28: =$H28-$I28 -> 0 | K28: =$D28+$G28+$J28 -> 0 | L28: =$F$4 -> 0 | M28: =$K28-$L28 -> 0
A29: =YEAR($B29)*100+MONTH($B29) -> 202710 | B29: =EDATE($B$4,21) -> 46661 | C29: =EOMONTH($B29,0) -> 46691 | D29: =$K28 -> 0 | E29: =SUMIFS(L_Ent,L_Data,">="&$B29,L_Data,"<="&$C29,L_Status,"REALIZADO") -> 0 | F29: =SUMIFS(L_Sai,L_Data,">="&$B29,L_Data,"<="&$C29,L_Status,"REALIZADO") -> 0 | G29: =$E29-$F29 -> 0 | H29: =SUMIFS(L_Ent,L_Data,">="&$B29,L_Data,"<="&$C29,L_Status,"PROJETADO") -> 0 | I29: =SUMIFS(L_Sai,L_Data,">="&$B29,L_Data,"<="&$C29,L_Status,"PROJETADO") -> 0 | J29: =$H29-$I29 -> 0 | K29: =$D29+$G29+$J29 -> 0 | L29: =$F$4 -> 0 | M29: =$K29-$L29 -> 0
A30: =YEAR($B30)*100+MONTH($B30) -> 202711 | B30: =EDATE($B$4,22) -> 46692 | C30: =EOMONTH($B30,0) -> 46721 | D30: =$K29 -> 0 | E30: =SUMIFS(L_Ent,L_Data,">="&$B30,L_Data,"<="&$C30,L_Status,"REALIZADO") -> 0 | F30: =SUMIFS(L_Sai,L_Data,">="&$B30,L_Data,"<="&$C30,L_Status,"REALIZADO") -> 0 | G30: =$E30-$F30 -> 0 | H30: =SUMIFS(L_Ent,L_Data,">="&$B30,L_Data,"<="&$C30,L_Status,"PROJETADO") -> 0 | I30: =SUMIFS(L_Sai,L_Data,">="&$B30,L_Data,"<="&$C30,L_Status,"PROJETADO") -> 0 | J30: =$H30-$I30 -> 0 | K30: =$D30+$G30+$J30 -> 0 | L30: =$F$4 -> 0 | M30: =$K30-$L30 -> 0
A31: =YEAR($B31)*100+MONTH($B31) -> 202712 | B31: =EDATE($B$4,23) -> 46722 | C31: =EOMONTH($B31,0) -> 46752 | D31: =$K30 -> 0 | E31: =SUMIFS(L_Ent,L_Data,">="&$B31,L_Data,"<="&$C31,L_Status,"REALIZADO") -> 0 | F31: =SUMIFS(L_Sai,L_Data,">="&$B31,L_Data,"<="&$C31,L_Status,"REALIZADO") -> 0 | G31: =$E31-$F31 -> 0 | H31: =SUMIFS(L_Ent,L_Data,">="&$B31,L_Data,"<="&$C31,L_Status,"PROJETADO") -> 0 | I31: =SUMIFS(L_Sai,L_Data,">="&$B31,L_Data,"<="&$C31,L_Status,"PROJETADO") -> 0 | J31: =$H31-$I31 -> 0 | K31: =$D31+$G31+$J31 -> 0 | L31: =$F$4 -> 0 | M31: =$K31-$L31 -> 0
A32: =YEAR($B32)*100+MONTH($B32) -> 202801 | B32: =EDATE($B$4,24) -> 46753 | C32: =EOMONTH($B32,0) -> 46783 | D32: =$K31 -> 0 | E32: =SUMIFS(L_Ent,L_Data,">="&$B32,L_Data,"<="&$C32,L_Status,"REALIZADO") -> 0 | F32: =SUMIFS(L_Sai,L_Data,">="&$B32,L_Data,"<="&$C32,L_Status,"REALIZADO") -> 0 | G32: =$E32-$F32 -> 0 | H32: =SUMIFS(L_Ent,L_Data,">="&$B32,L_Data,"<="&$C32,L_Status,"PROJETADO") -> 0 | I32: =SUMIFS(L_Sai,L_Data,">="&$B32,L_Data,"<="&$C32,L_Status,"PROJETADO") -> 0 | J32: =$H32-$I32 -> 0 | K32: =$D32+$G32+$J32 -> 0 | L32: =$F$4 -> 0 | M32: =$K32-$L32 -> 0
